Workbook

Sheet Lisez-moi
A1: Nouveaux kits SacAdo V2 : du préscolaire à la Terminale (proposition du 29 septembre 2026)
A3: Remplace le fichier « préscolaire et élémentaire » envoyé plus tôt. Rien n'est encore dans l'app : ce fichier sert à valider.
A4: 69 kits : 9 classes du préscolaire et de l'élémentaire, 4 du collège, 10 du lycée (Seconde L et S, Première et Terminale L1, L2, S1, S2).
A6: Tes consignes appliquées au préscolaire et à l'élémentaire
A7: • Craies blanches : vendues à l'unité à 25 F, 20 craies par kit (500 F au lieu de la boîte de 100 à 3 000 F). Produit à créer.
A8: • Matériel géométrique : une seule ligne du CE1 au CM2 au lieu de règle, équerre, rapporteur et compas. Au CP, la ligne est renommée.
A9: • Gourde violette (1287) à 2 500 F. Gourde ours à 3 100 F en Grande section Complet et Confort (déjà en place).
A10: • Lecture CI Kotti Kotti retiré du CI Confort. C'était le seul Kotti Kotti des kits.
A11: • Trousses Hello et gourdes : remarques de stock retirées.
A13: Collège et lycée : tes tableaux, rattachés au catalogue
A14: • Tes colonnes étaient dans l'ordre Essentiel, Confort, Complet : ici elles sont remises dans l'ordre de l'app (Essentiel < Complet < Confort).
A15: • Matériel géométrique = 1229, boîte d'instruments Marshal (1 800 F) dans toutes les gammes : elle a tout (compas compris) et coûte moins cher que les pièces séparées. Contenu à vérifier avec LPD.
... A35: À faire dans l'admin : les actions de ton côté.

Sheet Récap par kit
A1: Nouveaux kits, du préscolaire à la Terminale : prix et contrôle
A2: Prix = somme des lignes cochées de la section Principal (formules liées à l'onglet Contenu des kits). Les articles absents du catalogue ne comptent pas. Prix actuel = export de l'app du 29 septembre. Bénéfice = prix de vente moins prix d'achat, sur les seuls articles dont le prix d'achat est connu ; la dernière colonne dit combien du kit n'a pas de prix d'achat.
A4: Cycle | B4: Classe | C4: Gamme | D4: ID du kit dans l'app | E4: Prix actuel | F4: Nouveau prix | G4: Écart | H4: Articles cochés (nouveau) | I4: Articles cochés (actuel) | J4: Articles manquants au catalogue | K4: Ordre des gammes | L4: Coût d'achat (connu) | M4: Bénéfice (connu) | N4: Marge sur le connu | O4: Montant sans prix d'achat
A5: Préscolaire | B5: Petite section | C5: Essentiel | D5: 493 | E5: 1400 | F5: =SUMIFS('Contenu des kits'!$M$2:$M$1856,'Contenu des kits'!$B$2:$B$1856,B5,'Contenu des kits'!$C$2:$C$1856,C5) -> 12940 | G5: =IF(E5="","",F5-E5) -> 11540 | H5: =COUNTIFS('Contenu des kits'!$B$2:$B$1856,B5,'Contenu des kits'!$C$2:$C$1856,C5,'Contenu des kits'!$L$2:$L$1856,"Oui",'Contenu des kits'!$K$2:$K$1856,"Principal") -> 15 | I5: 2 | J5: =COUNTIFS('Contenu des kits'!$B$2:$B$1856,B5,'Contenu des kits'!$C$2:$C$1856,C5,'Contenu des kits'!$N$2:$N$1856,"MANQUE") -> 0 | K5: =IF(AND(F5<F6,F6<F7),"OK","À REVOIR") -> OK | L5: =SUMIFS('Contenu des kits'!$S$2:$S$1856,'Contenu des kits'!$B$2:$B$1856,B5,'Contenu des kits'!$C$2:$C$1856,C5) -> 5520 | M5: =SUMIFS('Contenu des kits'!$T$2:$T$1856,'Contenu des kits'!$B$2:$B$1856,B5,'Contenu des kits'!$C$2:$C$1856,C5) -> 2420 | N5: =IF(F5-O5=0,"",M5/(F5-O5)) -> 0.30478589 | O5: =SUMIFS('Contenu des kits'!$U$2:$U$1856,'Contenu des kits'!$B$2:$B$1856,B5,'Contenu des kits'!$C$2:$C$1856,C5) -> 5000
A6: Préscolaire | B6: Petite section | C6: Complet | D6: 494 | E6: 6150 | F6: =SUMIFS('Contenu des kits'!$M$2:$M$1856,'Contenu des kits'!$B$2:$B$1856,B6,'Contenu des kits'!$C$2:$C$1856,C6) -> 21500 | G6: =IF(E6="","",F6-E6) -> 15350 | H6: =COUNTIFS('Contenu des kits'!$B$2:$B$1856,B6,'Contenu des kits'!$C$2:$C$1856,C6,'Contenu des kits'!$L$2:$L$1856,"Oui",'Contenu des kits'!$K$2:$K$1856,"Principal") -> 19 | I6: 7 | J6: =COUNTIFS('Contenu des kits'!$B$2:$B$1856,B6,'Contenu des kits'!$C$2:$C$1856,C6,'Contenu des kits'!$N$2:$N$1856,"MANQUE") -> 3 | L6: =SUMIFS('Contenu des kits'!$S$2:$S$1856,'Contenu des kits'!$B$2:$B$1856,B6,'Contenu des kits'!$C$2:$C$1856,C6) -> 12090 | M6: =SUMIFS('Contenu des kits'!$T$2:$T$1856,'Contenu des kits'!$B$2:$B$1856,B6,'Contenu des kits'!$C$2:$C$1856,C6) -> 4460 | N6: =IF(F6-O6=0,"",M6/(F6-O6)) -> 0.2694864 | O6: =SUMIFS('Contenu des kits'!$U$2:$U$1856,'Contenu des kits'!$B$2:$B$1856,B6,'Contenu des kits'!$C$2:$C$1856,C6) -> 4950
A7: Préscolaire | B7: Petite section | C7: Confort | D7: 495 | E7: 15520 | F7: =SUMIFS('Contenu des kits'!$M$2:$M$1856,'Contenu des kits'!$B$2:$B$1856,B7,'Contenu des kits'!$C$2:$C$1856,C7) -> 38400 | G7: =IF(E7="","",F7-E7) -> 22880 | H7: =COUNTIFS('Contenu des kits'!$B$2:$B$1856,B7,'Contenu des kits'!$C$2:$C$1856,C7,'Contenu des kits'!$L$2:$L$1856,"Oui",'Contenu des kits'!$K$2:$K$1856,"Principal") -> 25 | I7: 10 | J7: =COUNTIFS('Contenu des kits'!$B$2:$B$1856,B7,'Contenu des kits'!$C$2:$C$1856,C7,'Contenu des kits'!$N$2:$N$1856,"MANQUE") -> 4 | L7: =SUMIFS('Contenu des kits'!$S$2:$S$1856,'Contenu des kits'!$B$2:$B$1856,B7,'Contenu des kits'!$C$2:$C$1856,C7) -> 21640 | M7: =SUMIFS('Contenu des kits'!$T$2:$T$1856,'Contenu des kits'!$B$2:$B$1856,B7,'Contenu des kits'!$C$2:$C$1856,C7) -> 6360 | N7: =IF(F7-O7=0,"",M7/(F7-O7)) -> 0.22714286 | O7: =SUMIFS('Contenu des kits'!$U$2:$U$1856,'Contenu des kits'!$B$2:$B$1856,B7,'Contenu des kits'!$C$2:$C$1856,C7) -> 10400
A9: Préscolaire | B9: Moyenne section | C9: Essentiel | D9: 496 | E9: 7800 | F9: =SUMIFS('Contenu des kits'!$M$2:$M$1856,'Contenu des kits'!$B$2:$B$1856,B9,'Contenu des kits'!$C$2:$C$1856,C9) -> 12490 | G9: =IF(E9="","",F9-E9) -> 4690 | H9: =COUNTIFS('Contenu des kits'!$B$2:$B$1856,B9,'Contenu des kits'!$C$2:$C$1856,C9,'Contenu des kits'!$L$2:$L$1856,"Oui",'Contenu des kits'!$K$2:$K$1856,"Principal") -> 15 | I9: 10 | J9: =COUNTIFS('Contenu des kits'!$B$2:$B$1856,B9,'Contenu des kits'!$C$2:$C$1856,C9,'Contenu des kits'!$N$2:$N$1856,"MANQUE") -> 0 | K9: =IF(AND(F9<F10,F10<F11),"OK","À REVOIR") -> OK | L9: =SUMIFS('Contenu des kits'!$S$2:$S$1856,'Contenu des kits'!$B$2:$B$1856,B9,'Contenu des kits'!$C$2:$C$1856,C9) -> 5870 | M9: =SUMIFS('Contenu des kits'!$T$2:$T$1856,'Contenu des kits'!$B$2:$B$1856,B9,'Contenu des kits'!$C$2:$C$1856,C9) -> 2520 | N9: =IF(F9-O9=0,"",M9/(F9-O9)) -> 0.30035757 | O9: =SUMIFS('Contenu des kits'!$U$2:$U$1856,'Contenu des kits'!$B$2:$B$1856,B9,'Contenu des kits'!$C$2:$C$1856,C9) -> 4100
A10: Préscolaire | B10: Moyenne section | C10: Complet | D10: 497 | E10: 13900 | F10: =SUMIFS('Contenu des kits'!$M$2:$M$1856,'Contenu des kits'!$B$2:$B$1856,B10,'Contenu des kits'!$C$2:$C$1856,C10) -> 19050 | G10: =IF(E10="","",F10-E10) -> 5150 | H10: =COUNTIFS('Contenu des kits'!$B$2:$B$1856,B10,'Contenu des kits'!$C$2:$C$1856,C10,'Contenu des kits'!$L$2:$L$1856,"Oui",'Contenu des kits'!$K$2:$K$1856,"Principal") -> 18 | I10: 15 | J10: =COUNTIFS('Contenu des kits'!$B$2:$B$1856,B10,'Contenu des kits'!$C$2:$C$1856,C10,'Contenu des kits'!$N$2:$N$1856,"MANQUE") -> 2 | L10: =SUMIFS('Contenu des kits'!$S$2:$S$1856,'Contenu des kits'!$B$2:$B$1856,B10,'Contenu des kits'!$C$2:$C$1856,C10) -> 10940 | M10: =SUMIFS('Contenu des kits'!$T$2:$T$1856,'Contenu des kits'!$B$2:$B$1856,B10,'Contenu des kits'!$C$2:$C$1856,C10) -> 4060 | N10: =IF(F10-O10=0,"",M10/(F10-O10)) -> 0.27066667 | O10: =SUMIFS('Contenu des kits'!$U$2:$U$1856,'Contenu des kits'!$B$2:$B$1856,B10,'Contenu des kits'!$C$2:$C$1856,C10) -> 4050
A11: Préscolaire | B11: Moyenne section | C11: Confort | D11: 498 | E11: 28470 | F11: =SUMIFS('Contenu des kits'!$M$2:$M$1856,'Contenu des kits'!$B$2:$B$1856,B11,'Contenu des kits'!$C$2:$C$1856,C11) -> 35450 | G11: =IF(E11="","",F11-E11) -> 6980 | H11: =COUNTIFS('Contenu des kits'!$B$2:$B$1856,B11,'Contenu des kits'!$C$2:$C$1856,C11,'Contenu des kits'!$L$2:$L$1856,"Oui",'Contenu des kits'!$K$2:$K$1856,"Principal") -> 23 | I11: 20 | J11: =COUNTIFS('Contenu des kits'!$B$2:$B$1856,B11,'Contenu des kits'!$C$2:$C$1856,C11,'Contenu des kits'!$N$2:$N$1856,"MANQUE") -> 4 | L11: =SUMIFS('Contenu des kits'!$S$2:$S$1856,'Contenu des kits'!$B$2:$B$1856,B11,'Contenu des kits'!$C$2:$C$1856,C11) -> 19500 | M11: =SUMIFS('Contenu des kits'!$T$2:$T$1856,'Contenu des kits'!$B$2:$B$1856,B11,'Contenu des kits'!$C$2:$C$1856,C11) -> 5650 | N11: =IF(F11-O11=0,"",M11/(F11-O11)) -> 0.22465209 | O11: =SUMIFS('Contenu des kits'!$U$2:$U$1856,'Contenu des kits'!$B$2:$B$1856,B11,'Contenu des kits'!$C$2:$C$1856,C11) -> 10300
A13: Préscolaire | B13: Grande section | C13: Essentiel | D13: 499 | E13: 8250 | F13: =SUMIFS('Contenu des kits'!$M$2:$M$1856,'Contenu des kits'!$B$2:$B$1856,B13,'Contenu des kits'!$C$2:$C$1856,C13) -> 12940 | G13: =IF(E13="","",F13-E13) -> 4690 | H13: =COUNTIFS('Contenu des kits'!$B$2:$B$1856,B13,'Contenu des kits'!$C$2:$C$1856,C13,'Contenu des kits'!$L$2:$L$1856,"Oui",'Contenu des kits'!$K$2:$K$1856,"Principal") -> 15 | I13: 10 | J13: =COUNTIFS('Contenu des kits'!$B$2:$B$1856,B13,'Contenu des kits'!$C$2:$C$1856,C13,'Contenu des kits'!$N$2:$N$1856,"MANQUE") -> 0 | K13: =IF(AND(F13<F14,F14<F15),"OK","À REVOIR") -> OK | L13: =SUMIFS('Contenu des kits'!$S$2:$S$1856,'Contenu des kits'!$B$2:$B$1856,B13,'Contenu des kits'!$C$2:$C$1856,C13) -> 6220 | M13: =SUMIFS('Contenu des kits'!$T$2:$T$1856,'Contenu des kits'!$B$2:$B$1856,B13,'Contenu des kits'!$C$2:$C$1856,C13) -> 2620 | N13: =IF(F13-O13=0,"",M13/(F13-O13)) -> 0.29638009 | O13: =SUMIFS('Contenu des kits'!$U$2:$U$1856,'Contenu des kits'!$B$2:$B$1856,B13,'Contenu des kits'!$C$2:$C$1856,C13) -> 4100
A14: Préscolaire | B14: Grande section | C14: Complet | D14: 500 | E14: 14350 | F14: =SUMIFS('Contenu des kits'!$M$2:$M$1856,'Contenu des kits'!$B$2:$B$1856,B14,'Contenu des kits'!$C$2:$C$1856,C14) -> 19500 | G14: =IF(E14="","",F14-E14) -> 5150 | H14: =COUNTIFS('Contenu des kits'!$B$2:$B$1856,B14,'Contenu des kits'!$C$2:$C$1856,C14,'Contenu des kits'!$L$2:$L$1856,"Oui",'Contenu des kits'!$K$2:$K$1856,"Principal") -> 18 | I14: 15 | J14: =COUNTIFS('Contenu des kits'!$B$2:$B$1856,B14,'Contenu des kits'!$C$2:$C$1856,C14,'Contenu des kits'!$N$2:$N$1856,"MANQUE") -> 2 | L14: =SUMIFS('Contenu des kits'!$S$2:$S$1856,'Contenu des kits'!$B$2:$B$1856,B14,'Contenu des kits'!$C$2:$C$1856,C14) -> 11290 | M14: =SUMIFS('Contenu des kits'!$T$2:$T$1856,'Contenu des kits'!$B$2:$B$1856,B14,'Contenu des kits'!$C$2:$C$1856,C14) -> 4160 | N14: =IF(F14-O14=0,"",M14/(F14-O14)) -> 0.26925566 | O14: =SUMIFS('Contenu des kits'!$U$2:$U$1856,'Contenu des kits'!$B$2:$B$1856,B14,'Contenu des kits'!$C$2:$C$1856,C14) -> 4050
A15: Préscolaire | B15: Grande section | C15: Confort | D15: 501 | E15: 28920 | F15: =SUMIFS('Contenu des kits'!$M$2:$M$1856,'Contenu des kits'!$B$2:$B$1856,B15,'Contenu des kits'!$C$2:$C$1856,C15) -> 36700 | G15: =IF(E15="","",F15-E15) -> 7780 | H15: =COUNTIFS('Contenu des kits'!$B$2:$B$1856,B15,'Contenu des kits'!$C$2:$C$1856,C15,'Contenu des kits'!$L$2:$L$1856,"Oui",'Contenu des kits'!$K$2:$K$1856,"Principal") -> 23 | I15: 20 | J15: =COUNTIFS('Contenu des kits'!$B$2:$B$1856,B15,'Contenu des kits'!$C$2:$C$1856,C15,'Contenu des kits'!$N$2:$N$1856,"MANQUE") -> 4 | L15: =SUMIFS('Contenu des kits'!$S$2:$S$1856,'Contenu des kits'!$B$2:$B$1856,B15,'Contenu des kits'!$C$2:$C$1856,C15) -> 19850 | M15: =SUMIFS('Contenu des kits'!$T$2:$T$1856,'Contenu des kits'!$B$2:$B$1856,B15,'Contenu des kits'!$C$2:$C$1856,C15) -> 5750 | N15: =IF(F15-O15=0,"",M15/(F15-O15)) -> 0.22460938 | O15: =SUMIFS('Contenu des kits'!$U$2:$U$1856,'Contenu des kits'!$B$2:$B$1856,B15,'Contenu des kits'!$C$2:$C$1856,C15) -> 11100
A17: Élémentaire | B17: CI | C17: Essentiel | D17: 1 | E17: 7750 | F17: =SUMIFS('Contenu des kits'!$M$2:$M$1856,'Contenu des kits'!$B$2:$B$1856,B17,'Contenu des kits'!$C$2:$C$1856,C17) -> 12420 | G17: =IF(E17="","",F17-E17) -> 4670 | H17: =COUNTIFS('Contenu des kits'!$B$2:$B$1856,B17,'Contenu des kits'!$C$2:$C$1856,C17,'Contenu des kits'!$L$2:$L$1856,"Oui",'Contenu des kits'!$K$2:$K$1856,"Principal") -> 17 | I17: 11 | J17: =COUNTIFS('Contenu des kits'!$B$2:$B$1856,B17,'Contenu des kits'!$C$2:$C$1856,C17,'Contenu des kits'!$N$2:$N$1856,"MANQUE") -> 0 | K17: =IF(AND(F17<F18,F18<F19),"OK","À REVOIR") -> OK | L17: =SUMIFS('Contenu des kits'!$S$2:$S$1856,'Contenu des kits'!$B$2:$B$1856,B17,'Contenu des kits'!$C$2:$C$1856,C17) -> 5700 | M17: =SUMIFS('Contenu des kits'!$T$2:$T$1856,'Contenu des kits'!$B$2:$B$1856,B17,'Contenu des kits'!$C$2:$C$1856,C17) -> 2570 | N17: =IF(F17-O17=0,"",M17/(F17-O17)) -> 0.31076179 | O17: =SUMIFS('Contenu des kits'!$U$2:$U$1856,'Contenu des kits'!$B$2:$B$1856,B17,'Contenu des kits'!$C$2:$C$1856,C17) -> 4150
A18: Élémentaire | B18: CI | C18: Complet | D18: 13 | E18: 25580 | F18: =SUMIFS('Contenu des kits'!$M$2:$M$1856,'Contenu des kits'!$B$2:$B$1856,B18,'Contenu des kits'!$C$2:$C$1856,C18) -> 27080 | G18: =IF(E18="","",F18-E18) -> 1500 | H18: =COUNTIFS('Contenu des kits'!$B$2:$B$1856,B18,'Contenu des kits'!$C$2:$C$1856,C18,'Contenu des kits'!$L$2:$L$1856,"Oui",'Contenu des kits'!$K$2:$K$1856,"Principal") -> 20 | I18: 18 | J18: =COUNTIFS('Contenu des kits'!$B$2:$B$1856,B18,'Contenu des kits'!$C$2:$C$1856,C18,'Contenu des kits'!$N$2:$N$1856,"MANQUE") -> 0 | L18: =SUMIFS('Contenu des kits'!$S$2:$S$1856,'Contenu des kits'!$B$2:$B$1856,B18,'Contenu des kits'!$C$2:$C$1856,C18) -> 16578 | M18: =SUMIFS('Contenu des kits'!$T$2:$T$1856,'Contenu des kits'!$B$2:$B$1856,B18,'Contenu des kits'!$C$2:$C$1856,C18) -> 6352 | N18: =IF(F18-O18=0,"",M18/(F18-O18)) -> 0.27701701 | O18: =SUMIFS('Contenu des kits'!$U$2:$U$1856,'Contenu des kits'!$B$2:$B$1856,B18,'Contenu des kits'!$C$2:$C$1856,C18) -> 4150
A19: Élémentaire | B19: CI | C19: Confort | D19: 7 | E19: 32360 | F19: =SUMIFS('Contenu des kits'!$M$2:$M$1856,'Contenu des kits'!$B$2:$B$1856,B19,'Contenu des kits'!$C$2:$C$1856,C19) -> 36520 | G19: =IF(E19="","",F19-E19) -> 4160 | H19: =COUNTIFS('Contenu des kits'!$B$2:$B$1856,B19,'Contenu des kits'!$C$2:$C$1856,C19,'Contenu des kits'!$L$2:$L$1856,"Oui",'Contenu des kits'!$K$2:$K$1856,"Principal") -> 23 | I19: 20 | J19: =COUNTIFS('Contenu des kits'!$B$2:$B$1856,B19,'Contenu des kits'!$C$2:$C$1856,C19,'Contenu des kits'!$N$2:$N$1856,"MANQUE") -> 0 | L19: =SUMIFS('Contenu des kits'!$S$2:$S$1856,'Contenu des kits'!$B$2:$B$1856,B19,'Contenu des kits'!$C$2:$C$1856,C19) -> 22968 | M19: =SUMIFS('Contenu des kits'!$T$2:$T$1856,'Contenu des kits'!$B$2:$B$1856,B19,'Contenu des kits'!$C$2:$C$1856,C19) -> 9402 | N19: =IF(F19-O19=0,"",M19/(F19-O19)) -> 0.29045412 | O19: =SUMIFS('Contenu des kits'!$U$2:$U$1856,'Contenu des kits'!$B$2:$B$1856,B19,'Contenu des kits'!$C$2:$C$1856,C19) -> 4150
A21: Élémentaire | B21: CP | C21: Essentiel | D21: 2 | E21: 8550 | F21: =SUMIFS('Contenu des kits'!$M$2:$M$1856,'Contenu des kits'!$B$2:$B$1856,B21,'Contenu des kits'!$C$2:$C$1856,C21) -> 15245 | G21: =IF(E21="","",F21-E21) -> 6695 | H21: =COUNTIFS('Contenu des kits'!$B$2:$B$1856,B21,'Contenu des kits'!$C$2:$C$1856,C21,'Contenu des kits'!$L$2:$L$1856,"Oui",'Contenu des kits'!$K$2:$K$1856,"Principal") -> 20 | I21: 12 | J21: =COUNTIFS('Contenu des kits'!$B$2:$B$1856,B21,'Contenu des kits'!$C$2:$C$1856,C21,'Contenu des kits'!$N$2:$N$1856,"MANQUE") -> 1 | K21: =IF(AND(F21<F22,F22<F23),"OK","À REVOIR") -> OK | L21: =SUMIFS('Contenu des kits'!$S$2:$S$1856,'Contenu des kits'!$B$2:$B$1856,B21,'Contenu des kits'!$C$2:$C$1856,C21) -> 7385 | M21: =SUMIFS('Contenu des kits'!$T$2:$T$1856,'Contenu des kits'!$B$2:$B$1856,B21,'Contenu des kits'!$C$2:$C$1856,C21) -> 3610 | N21: =IF(F21-O21=0,"",M21/(F21-O21)) -> 0.32833106 | O21: =SUMIFS('Contenu des kits'!$U$2:$U$1856,'Contenu des kits'!$B$2:$B$1856,B21,'Contenu des kits'!$C$2:$C$1856,C21) -> 4250
A22: Élémentaire | B22: CP | C22: Complet | D22: 14 | E22: 26380 | F22: =SUMIFS('Contenu des kits'!$M$2:$M$1856,'Contenu des kits'!$B$2:$B$1856,B22,'Contenu des kits'!$C$2:$C$1856,C22) -> 32445 | G22: =IF(E22="","",F22-E22) -> 6065 | H22: =COUNTIFS('Contenu des kits'!$B$2:$B$1856,B22,'Contenu des kits'!$C$2:$C$1856,C22,'Contenu des kits'!$L$2:$L$1856,"Oui",'Contenu des kits'!$K$2:$K$1856,"Principal") -> 24 | I22: 19 | J22: =COUNTIFS('Contenu des kits'!$B$2:$B$1856,B22,'Contenu des kits'!$C$2:$C$1856,C22,'Contenu des kits'!$N$2:$N$1856,"MANQUE") -> 1 | L22: =SUMIFS('Contenu des kits'!$S$2:$S$1856,'Contenu des kits'!$B$2:$B$1856,B22,'Contenu des kits'!$C$2:$C$1856,C22) -> 19463 | M22: =SUMIFS('Contenu des kits'!$T$2:$T$1856,'Contenu des kits'!$B$2:$B$1856,B22,'Contenu des kits'!$C$2:$C$1856,C22) -> 8532 | N22: =IF(F22-O22=0,"",M22/(F22-O22)) -> 0.30476871 | O22: =SUMIFS('Contenu des kits'!$U$2:$U$1856,'Contenu des kits'!$B$2:$B$1856,B22,'Contenu des kits'!$C$2:$C$1856,C22) -> 4450
A23: Élémentaire | B23: CP | C23: Confort | D23: 8 | E23: 33160 | F23: =SUMIFS('Contenu des kits'!$M$2:$M$1856,'Contenu des kits'!$B$2:$B$1856,B23,'Contenu des kits'!$C$2:$C$1856,C23) -> 50755 | G23: =IF(E23="","",F23-E23) -> 17595 | H23: =COUNTIFS('Contenu des kits'!$B$2:$B$1856,B23,'Contenu des kits'!$C$2:$C$1856,C23,'Contenu des kits'!$L$2:$L$1856,"Oui",'Contenu des kits'!$K$2:$K$1856,"Principal") -> 30 | I23: 21 | J23: =COUNTIFS('Contenu des kits'!$B$2:$B$1856,B23,'Contenu des kits'!$C$2:$C$1856,C23,'Contenu des kits'!$N$2:$N$1856,"MANQUE") -> 1 | L23: =SUMIFS('Contenu des kits'!$S$2:$S$1856,'Contenu des kits'!$B$2:$B$1856,B23,'Contenu des kits'!$C$2:$C$1856,C23) -> 31723 | M23: =SUMIFS('Contenu des kits'!$T$2:$T$1856,'Contenu des kits'!$B$2:$B$1856,B23,'Contenu des kits'!$C$2:$C$1856,C23) -> 14582 | N23: =IF(F23-O23=0,"",M23/(F23-O23)) -> 0.314912 | O23: =SUMIFS('Contenu des kits'!$U$2:$U$1856,'Contenu des kits'!$B$2:$B$1856,B23,'Contenu des kits'!$C$2:$C$1856,C23) -> 4450
A25: Élémentaire | B25: CE1 | C25: Essentiel | D25: 3 | E25: 10700 | F25: =SUMIFS('Contenu des kits'!$M$2:$M$1856,'Contenu des kits'!$B$2:$B$1856,B25,'Contenu des kits'!$C$2:$C$1856,C25) -> 15620 | G25: =IF(E25="","",F25-E25) -> 4920 | H25: =COUNTIFS('Contenu des kits'!$B$2:$B$1856,B25,'Contenu des kits'!$C$2:$C$1856,C25,'Contenu des kits'!$L$2:$L$1856,"Oui",'Contenu des kits'!$K$2:$K$1856,"Principal") -> 18 | I25: 15 | J25: =COUNTIFS('Contenu des kits'!$B$2:$B$1856,B25,'Contenu des kits'!$C$2:$C$1856,C25,'Contenu des kits'!$N$2:$N$1856,"MANQUE") -> 0 | K25: =IF(AND(F25<F26,F26<F27),"OK","À REVOIR") -> OK | L25: =SUMIFS('Contenu des kits'!$S$2:$S$1856,'Contenu des kits'!$B$2:$B$1856,B25,'Contenu des kits'!$C$2:$C$1856,C25) -> 8160 | M25: =SUMIFS('Contenu des kits'!$T$2:$T$1856,'Contenu des kits'!$B$2:$B$1856,B25,'Contenu des kits'!$C$2:$C$1856,C25) -> 2960 | N25: =IF(F25-O25=0,"",M25/(F25-O25)) -> 0.26618705 | O25: =SUMIFS('Contenu des kits'!$U$2:$U$1856,'Contenu des kits'!$B$2:$B$1856,B25,'Contenu des kits'!$C$2:$C$1856,C25) -> 4500
A26: Élémentaire | B26: CE1 | C26: Complet | D26: 15 | E26: 29650 | F26: =SUMIFS('Contenu des kits'!$M$2:$M$1856,'Contenu des kits'!$B$2:$B$1856,B26,'Contenu des kits'!$C$2:$C$1856,C26) -> 35250 | G26: =IF(E26="","",F26-E26) -> 5600 | H26: =COUNTIFS('Contenu des kits'!$B$2:$B$1856,B26,'Contenu des kits'!$C$2:$C$1856,C26,'Contenu des kits'!$L$2:$L$1856,"Oui",'Contenu des kits'!$K$2:$K$1856,"Principal") -> 22 | I26: 21 | J26: =COUNTIFS('Contenu des kits'!$B$2:$B$1856,B26,'Contenu des kits'!$C$2:$C$1856,C26,'Contenu des kits'!$N$2:$N$1856,"MANQUE") -> 0 | L26: =SUMIFS('Contenu des kits'!$S$2:$S$1856,'Contenu des kits'!$B$2:$B$1856,B26,'Contenu des kits'!$C$2:$C$1856,C26) -> 22178 | M26: =SUMIFS('Contenu des kits'!$T$2:$T$1856,'Contenu des kits'!$B$2:$B$1856,B26,'Contenu des kits'!$C$2:$C$1856,C26) -> 8722 | N26: =IF(F26-O26=0,"",M26/(F26-O26)) -> 0.28226537 | O26: =SUMIFS('Contenu des kits'!$U$2:$U$1856,'Contenu des kits'!$B$2:$B$1856,B26,'Contenu des kits'!$C$2:$C$1856,C26) -> 4350
A27: Élémentaire | B27: CE1 | C27: Confort | D27: 9 | E27: 36870 | F27: =SUMIFS('Contenu des kits'!$M$2:$M$1856,'Contenu des kits'!$B$2:$B$1856,B27,'Contenu des kits'!$C$2:$C$1856,C27) -> 44980 | G27: =IF(E27="","",F27-E27) -> 8110 | H27: =COUNTIFS('Contenu des kits'!$B$2:$B$1856,B27,'Contenu des kits'!$C$2:$C$1856,C27,'Contenu des kits'!$L$2:$L$1856,"Oui",'Contenu des kits'!$K$2:$K$1856,"Principal") -> 25 | I27: 23 | J27: =COUNTIFS('Contenu des kits'!$B$2:$B$1856,B27,'Contenu des kits'!$C$2:$C$1856,C27,'Contenu des kits'!$N$2:$N$1856,"MANQUE") -> 0 | L27: =SUMIFS('Contenu des kits'!$S$2:$S$1856,'Contenu des kits'!$B$2:$B$1856,B27,'Contenu des kits'!$C$2:$C$1856,C27) -> 28858 | M27: =SUMIFS('Contenu des kits'!$T$2:$T$1856,'Contenu des kits'!$B$2:$B$1856,B27,'Contenu des kits'!$C$2:$C$1856,C27) -> 11772 | N27: =IF(F27-O27=0,"",M27/(F27-O27)) -> 0.28973665 | O27: =SUMIFS('Contenu des kits'!$U$2:$U$1856,'Contenu des kits'!$B$2:$B$1856,B27,'Contenu des kits'!$C$2:$C$1856,C27) -> 4350
A29: Élémentaire | B29: CE2 | C29: Essentiel | D29: 4 | E29: 10700 | F29: =SUMIFS('Contenu des kits'!$M$2:$M$1856,'Contenu des kits'!$B$2:$B$1856,B29,'Contenu des kits'!$C$2:$C$1856,C29) -> 15620 | G29: =IF(E29="","",F29-E29) -> 4920 | H29: =COUNTIFS('Contenu des kits'!$B$2:$B$1856,B29,'Contenu des kits'!$C$2:$C$1856,C29,'Contenu des kits'!$L$2:$L$1856,"Oui",'Contenu des kits'!$K$2:$K$1856,"Principal") -> 18 | I29: 15 | J29: =COUNTIFS('Contenu des kits'!$B$2:$B$1856,B29,'Contenu des kits'!$C$2:$C$1856,C29,'Contenu des kits'!$N$2:$N$1856,"MANQUE") -> 0 | K29: =IF(AND(F29<F30,F30<F31),"OK","À REVOIR") -> OK | L29: =SUMIFS('Contenu des kits'!$S$2:$S$1856,'Contenu des kits'!$B$2:$B$1856,B29,'Contenu des kits'!$C$2:$C$1856,C29) -> 8160 | M29: =SUMIFS('Contenu des kits'!$T$2:$T$1856,'Contenu des kits'!$B$2:$B$1856,B29,'Contenu des kits'!$C$2:$C$1856,C29) -> 2960 | N29: =IF(F29-O29=0,"",M29/(F29-O29)) -> 0.26618705 | O29: =SUMIFS('Contenu des kits'!$U$2:$U$1856,'Contenu des kits'!$B$2:$B$1856,B29,'Contenu des kits'!$C$2:$C$1856,C29) -> 4500
A30: Élémentaire | B30: CE2 | C30: Complet | D30: 16 | E30: 29650 | F30: =SUMIFS('Contenu des kits'!$M$2:$M$1856,'Contenu des kits'!$B$2:$B$1856,B30,'Contenu des kits'!$C$2:$C$1856,C30) -> 35250 | G30: =IF(E30="","",F30-E30) -> 5600 | H30: =COUNTIFS('Contenu des kits'!$B$2:$B$1856,B30,'Contenu des kits'!$C$2:$C$1856,C30,'Contenu des kits'!$L$2:$L$1856,"Oui",'Contenu des kits'!$K$2:$K$1856,"Principal") -> 22 | I30: 21 | J30: =COUNTIFS('Contenu des kits'!$B$2:$B$1856,B30,'Contenu des kits'!$C$2:$C$1856,C30,'Contenu des kits'!$N$2:$N$1856,"MANQUE") -> 0 | L30: =SUMIFS('Contenu des kits'!$S$2:$S$1856,'Contenu des kits'!$B$2:$B$1856,B30,'Contenu des kits'!$C$2:$C$1856,C30) -> 22178 | M30: =SUMIFS('Contenu des kits'!$T$2:$T$1856,'Contenu des kits'!$B$2:$B$1856,B30,'Contenu des kits'!$C$2:$C$1856,C30) -> 8722 | N30: =IF(F30-O30=0,"",M30/(F30-O30)) -> 0.28226537 | O30: =SUMIFS('Contenu des kits'!$U$2:$U$1856,'Contenu des kits'!$B$2:$B$1856,B30,'Contenu des kits'!$C$2:$C$1856,C30) -> 4350
A31: Élémentaire | B31: CE2 | C31: Confort | D31: 10 | E31: 36870 | F31: =SUMIFS('Contenu des kits'!$M$2:$M$1856,'Contenu des kits'!$B$2:$B$1856,B31,'Contenu des kits'!$C$2:$C$1856,C31) -> 51990 | G31: =IF(E31="","",F31-E31) -> 15120 | H31: =COUNTIFS('Contenu des kits'!$B$2:$B$1856,B31,'Contenu des kits'!$C$2:$C$1856,C31,'Contenu des kits'!$L$2:$L$1856,"Oui",'Contenu des kits'!$K$2:$K$1856,"Principal") -> 27 | I31: 23 | J31: =COUNTIFS('Contenu des kits'!$B$2:$B$1856,B31,'Contenu des kits'!$C$2:$C$1856,C31,'Contenu des kits'!$N$2:$N$1856,"MANQUE") -> 0 | L31: =SUMIFS('Contenu des kits'!$S$2:$S$1856,'Contenu des kits'!$B$2:$B$1856,B31,'Contenu des kits'!$C$2:$C$1856,C31) -> 33868 | M31: =SUMIFS('Contenu des kits'!$T$2:$T$1856,'Contenu des kits'!$B$2:$B$1856,B31,'Contenu des kits'!$C$2:$C$1856,C31) -> 13772 | N31: =IF(F31-O31=0,"",M31/(F31-O31)) -> 0.2890848 | O31: =SUMIFS('Contenu des kits'!$U$2:$U$1856,'Contenu des kits'!$B$2:$B$1856,B31,'Contenu des kits'!$C$2:$C$1856,C31) -> 4350
A33: Élémentaire | B33: CM1 | C33: Essentiel | D33: 5 | E33: 12425 | F33: =SUMIFS('Contenu des kits'!$M$2:$M$1856,'Contenu des kits'!$B$2:$B$1856,B33,'Contenu des kits'!$C$2:$C$1856,C33) -> 17290 | G33: =IF(E33="","",F33-E33) -> 4865 | H33: =COUNTIFS('Contenu des kits'!$B$2:$B$1856,B33,'Contenu des kits'!$C$2:$C$1856,C33,'Contenu des kits'!$L$2:$L$1856,"Oui",'Contenu des kits'!$K$2:$K$1856,"Principal") -> 18 | I33: 17 | J33: =COUNTIFS('Contenu des kits'!$B$2:$B$1856,B33,'Contenu des kits'!$C$2:$C$1856,C33,'Contenu des kits'!$N$2:$N$1856,"MANQUE") -> 0 | K33: =IF(AND(F33<F34,F34<F35),"OK","À REVOIR") -> OK | L33: =SUMIFS('Contenu des kits'!$S$2:$S$1856,'Contenu des kits'!$B$2:$B$1856,B33,'Contenu des kits'!$C$2:$C$1856,C33) -> 9440 | M33: =SUMIFS('Contenu des kits'!$T$2:$T$1856,'Contenu des kits'!$B$2:$B$1856,B33,'Contenu des kits'!$C$2:$C$1856,C33) -> 3400 | N33: =IF(F33-O33=0,"",M33/(F33-O33)) -> 0.26479751 | O33: =SUMIFS('Contenu des kits'!$U$2:$U$1856,'Contenu des kits'!$B$2:$B$1856,B33,'Contenu des kits'!$C$2:$C$1856,C33) -> 4450
A34: Élémentaire | B34: CM1 | C34: Complet | D34: 17 | E34: 29975 | F34: =SUMIFS('Contenu des kits'!$M$2:$M$1856,'Contenu des kits'!$B$2:$B$1856,B34,'Contenu des kits'!$C$2:$C$1856,C34) -> 36850 | G34: =IF(E34="","",F34-E34) -> 6875 | H34: =COUNTIFS('Contenu des kits'!$B$2:$B$1856,B34,'Contenu des kits'!$C$2:$C$1856,C34,'Contenu des kits'!$L$2:$L$1856,"Oui",'Contenu des kits'!$K$2:$K$1856,"Principal") -> 22 | I34: 20 | J34: =COUNTIFS('Contenu des kits'!$B$2:$B$1856,B34,'Contenu des kits'!$C$2:$C$1856,C34,'Contenu des kits'!$N$2:$N$1856,"MANQUE") -> 0 | L34: =SUMIFS('Contenu des kits'!$S$2:$S$1856,'Contenu des kits'!$B$2:$B$1856,B34,'Contenu des kits'!$C$2:$C$1856,C34) -> 23168 | M34: =SUMIFS('Contenu des kits'!$T$2:$T$1856,'Contenu des kits'!$B$2:$B$1856,B34,'Contenu des kits'!$C$2:$C$1856,C34) -> 9182 | N34: =IF(F34-O34=0,"",M34/(F34-O34)) -> 0.28383308 | O34: =SUMIFS('Contenu des kits'!$U$2:$U$1856,'Contenu des kits'!$B$2:$B$1856,B34,'Contenu des kits'!$C$2:$C$1856,C34) -> 4500
A35: Élémentaire | B35: CM1 | C35: Confort | D35: 11 | E35: 37655 | F35: =SUMIFS('Contenu des kits'!$M$2:$M$1856,'Contenu des kits'!$B$2:$B$1856,B35,'Contenu des kits'!$C$2:$C$1856,C35) -> 51270 | G35: =IF(E35="","",F35-E35) -> 13615 | H35: =COUNTIFS('Contenu des kits'!$B$2:$B$1856,B35,'Contenu des kits'!$C$2:$C$1856,C35,'Contenu des kits'!$L$2:$L$1856,"Oui",'Contenu des kits'!$K$2:$K$1856,"Principal") -> 26 | I35: 22 | J35: =COUNTIFS('Contenu des kits'!$B$2:$B$1856,B35,'Contenu des kits'!$C$2:$C$1856,C35,'Contenu des kits'!$N$2:$N$1856,"MANQUE") -> 0 | L35: =SUMIFS('Contenu des kits'!$S$2:$S$1856,'Contenu des kits'!$B$2:$B$1856,B35,'Contenu des kits'!$C$2:$C$1856,C35) -> 33538 | M35: =SUMIFS('Contenu des kits'!$T$2:$T$1856,'Contenu des kits'!$B$2:$B$1856,B35,'Contenu des kits'!$C$2:$C$1856,C35) -> 13232 | N35: =IF(F35-O35=0,"",M35/(F35-O35)) -> 0.2829164 | O35: =SUMIFS('Contenu des kits'!$U$2:$U$1856,'Contenu des kits'!$B$2:$B$1856,B35,'Contenu des kits'!$C$2:$C$1856,C35) -> 4500
A37: Élémentaire | B37: CM2 | C37: Essentiel | D37: 6 | E37: 12425 | F37: =SUMIFS('Contenu des kits'!$M$2:$M$1856,'Contenu des kits'!$B$2:$B$1856,B37,'Contenu des kits'!$C$2:$C$1856,C37) -> 17290 | G37: =IF(E37="","",F37-E37) -> 4865 | H37: =COUNTIFS('Contenu des kits'!$B$2:$B$1856,B37,'Contenu des kits'!$C$2:$C$1856,C37,'Contenu des kits'!$L$2:$L$1856,"Oui",'Contenu des kits'!$K$2:$K$1856,"Principal") -> 18 | I37: 17 | J37: =COUNTIFS('Contenu des kits'!$B$2:$B$1856,B37,'Contenu des kits'!$C$2:$C$1856,C37,'Contenu des kits'!$N$2:$N$1856,"MANQUE") -> 0 | K37: =IF(AND(F37<F38,F38<F39),"OK","À REVOIR") -> OK | L37: =SUMIFS('Contenu des kits'!$S$2:$S$1856,'Contenu des kits'!$B$2:$B$1856,B37,'Contenu des kits'!$C$2:$C$1856,C37) -> 9440 | M37: =SUMIFS('Contenu des kits'!$T$2:$T$1856,'Contenu des kits'!$B$2:$B$1856,B37,'Contenu des kits'!$C$2:$C$1856,C37) -> 3400 | N37: =IF(F37-O37=0,"",M37/(F37-O37)) -> 0.26479751 | O37: =SUMIFS('Contenu des kits'!$U$2:$U$1856,'Contenu des kits'!$B$2:$B$1856,B37,'Contenu des kits'!$C$2:$C$1856,C37) -> 4450
A38: Élémentaire | B38: CM2 | C38: Complet | D38: 18 | E38: 29975 | F38: =SUMIFS('Contenu des kits'!$M$2:$M$1856,'Contenu des kits'!$B$2:$B$1856,B38,'Contenu des kits'!$C$2:$C$1856,C38) -> 41500 | G38: =IF(E38="","",F38-E38) -> 11525 | H38: =COUNTIFS('Contenu des kits'!$B$2:$B$1856,B38,'Contenu des kits'!$C$2:$C$1856,C38,'Contenu des kits'!$L$2:$L$1856,"Oui",'Contenu des kits'!$K$2:$K$1856,"Principal") -> 23 | I38: 20 | J38: =COUNTIFS('Contenu des kits'!$B$2:$B$1856,B38,'Contenu des kits'!$C$2:$C$1856,C38,'Contenu des kits'!$N$2:$N$1856,"MANQUE") -> 0 | L38: =SUMIFS('Contenu des kits'!$S$2:$S$1856,'Contenu des kits'!$B$2:$B$1856,B38,'Contenu des kits'!$C$2:$C$1856,C38) -> 26818 | M38: =SUMIFS('Contenu des kits'!$T$2:$T$1856,'Contenu des kits'!$B$2:$B$1856,B38,'Contenu des kits'!$C$2:$C$1856,C38) -> 10182 | N38: =IF(F38-O38=0,"",M38/(F38-O38)) -> 0.27518919 | O38: =SUMIFS('Contenu des kits'!$U$2:$U$1856,'Contenu des kits'!$B$2:$B$1856,B38,'Contenu des kits'!$C$2:$C$1856,C38) -> 4500
A39: Élémentaire | B39: CM2 | C39: Confort | D39: 12 | E39: 40325 | F39: =SUMIFS('Contenu des kits'!$M$2:$M$1856,'Contenu des kits'!$B$2:$B$1856,B39,'Contenu des kits'!$C$2:$C$1856,C39) -> 59160 | G39: =IF(E39="","",F39-E39) -> 18835 | H39: =COUNTIFS('Contenu des kits'!$B$2:$B$1856,B39,'Contenu des kits'!$C$2:$C$1856,C39,'Contenu des kits'!$L$2:$L$1856,"Oui",'Contenu des kits'!$K$2:$K$1856,"Principal") -> 28 | I39: 22 | J39: =COUNTIFS('Contenu des kits'!$B$2:$B$1856,B39,'Contenu des kits'!$C$2:$C$1856,C39,'Contenu des kits'!$N$2:$N$1856,"MANQUE") -> 0 | L39: =SUMIFS('Contenu des kits'!$S$2:$S$1856,'Contenu des kits'!$B$2:$B$1856,B39,'Contenu des kits'!$C$2:$C$1856,C39) -> 39428 | M39: =SUMIFS('Contenu des kits'!$T$2:$T$1856,'Contenu des kits'!$B$2:$B$1856,B39,'Contenu des kits'!$C$2:$C$1856,C39) -> 15232 | N39: =IF(F39-O39=0,"",M39/(F39-O39)) -> 0.27866813 | O39: =SUMIFS('Contenu des kits'!$U$2:$U$1856,'Contenu des kits'!$B$2:$B$1856,B39,'Contenu des kits'!$C$2:$C$1856,C39) -> 4500
A41: Collège | B41: 6e | C41: Essentiel | D41: 37 | E41: 12550 | F41: =SUMIFS('Contenu des kits'!$M$2:$M$1856,'Contenu des kits'!$B$2:$B$1856,B41,'Contenu des kits'!$C$2:$C$1856,C41) -> 15370 | G41: =IF(E41="","",F41-E41) -> 2820 | H41: =COUNTIFS('Contenu des kits'!$B$2:$B$1856,B41,'Contenu des kits'!$C$2:$C$1856,C41,'Contenu des kits'!$L$2:$L$1856,"Oui",'Contenu des kits'!$K$2:$K$1856,"Principal") -> 15 | I41: 13 | J41: =COUNTIFS('Contenu des kits'!$B$2:$B$1856,B41,'Contenu des kits'!$C$2:$C$1856,C41,'Contenu des kits'!$N$2:$N$1856,"MANQUE") -> 3 | K41: =IF(AND(F41<F42,F42<F43),"OK","À REVOIR") -> OK | L41: =SUMIFS('Contenu des kits'!$S$2:$S$1856,'Contenu des kits'!$B$2:$B$1856,B41,'Contenu des kits'!$C$2:$C$1856,C41) -> 5870 | M41: =SUMIFS('Contenu des kits'!$T$2:$T$1856,'Contenu des kits'!$B$2:$B$1856,B41,'Contenu des kits'!$C$2:$C$1856,C41) -> 3100 | N41: =IF(F41-O41=0,"",M41/(F41-O41)) -> 0.34559643 | O41: =SUMIFS('Contenu des kits'!$U$2:$U$1856,'Contenu des kits'!$B$2:$B$1856,B41,'Contenu des kits'!$C$2:$C$1856,C41) -> 6400
A42: Collège | B42: 6e | C42: Complet | D42: 38 | E42: 32950 | F42: =SUMIFS('Contenu des kits'!$M$2:$M$1856,'Contenu des kits'!$B$2:$B$1856,B42,'Contenu des kits'!$C$2:$C$1856,C42) -> 55670 | G42: =IF(E42="","",F42-E42) -> 22720 | H42: =COUNTIFS('Contenu des kits'!$B$2:$B$1856,B42,'Contenu des kits'!$C$2:$C$1856,C42,'Contenu des kits'!$L$2:$L$1856,"Oui",'Contenu des kits'!$K$2:$K$1856,"Principal") -> 28 | I42: 19 | J42: =COUNTIFS('Contenu des kits'!$B$2:$B$1856,B42,'Contenu des kits'!$C$2:$C$1856,C42,'Contenu des kits'!$N$2:$N$1856,"MANQUE") -> 3 | L42: =SUMIFS('Contenu des kits'!$S$2:$S$1856,'Contenu des kits'!$B$2:$B$1856,B42,'Contenu des kits'!$C$2:$C$1856,C42) -> 35580 | M42: =SUMIFS('Contenu des kits'!$T$2:$T$1856,'Contenu des kits'!$B$2:$B$1856,B42,'Contenu des kits'!$C$2:$C$1856,C42) -> 11690 | N42: =IF(F42-O42=0,"",M42/(F42-O42)) -> 0.24730273 | O42: =SUMIFS('Contenu des kits'!$U$2:$U$1856,'Contenu des kits'!$B$2:$B$1856,B42,'Contenu des kits'!$C$2:$C$1856,C42) -> 8400
A43: Collège | B43: 6e | C43: Confort | D43: 39 | E43: 59980 | F43: =SUMIFS('Contenu des kits'!$M$2:$M$1856,'Contenu des kits'!$B$2:$B$1856,B43,'Contenu des kits'!$C$2:$C$1856,C43) -> 63530 | G43: =IF(E43="","",F43-E43) -> 3550 | H43: =COUNTIFS('Contenu des kits'!$B$2:$B$1856,B43,'Contenu des kits'!$C$2:$C$1856,C43,'Contenu des kits'!$L$2:$L$1856,"Oui",'Contenu des kits'!$K$2:$K$1856,"Principal") -> 30 | I43: 26 | J43: =COUNTIFS('Contenu des kits'!$B$2:$B$1856,B43,'Contenu des kits'!$C$2:$C$1856,C43,'Contenu des kits'!$N$2:$N$1856,"MANQUE") -> 4 | L43: =SUMIFS('Contenu des kits'!$S$2:$S$1856,'Contenu des kits'!$B$2:$B$1856,B43,'Contenu des kits'!$C$2:$C$1856,C43) -> 41240 | M43: =SUMIFS('Contenu des kits'!$T$2:$T$1856,'Contenu des kits'!$B$2:$B$1856,B43,'Contenu des kits'!$C$2:$C$1856,C43) -> 13890 | N43: =IF(F43-O43=0,"",M43/(F43-O43)) -> 0.25194994 | O43: =SUMIFS('Contenu des kits'!$U$2:$U$1856,'Contenu des kits'!$B$2:$B$1856,B43,'Contenu des kits'!$C$2:$C$1856,C43) -> 8400
A45: Collège | B45: 5e | C45: Essentiel | D45: 40 | E45: 12550 | F45: =SUMIFS('Contenu des kits'!$M$2:$M$1856,'Contenu des kits'!$B$2:$B$1856,B45,'Contenu des kits'!$C$2:$C$1856,C45) -> 16170 | G45: =IF(E45="","",F45-E45) -> 3620 | H45: =COUNTIFS('Contenu des kits'!$B$2:$B$1856,B45,'Contenu des kits'!$C$2:$C$1856,C45,'Contenu des kits'!$L$2:$L$1856,"Oui",'Contenu des kits'!$K$2:$K$1856,"Principal") -> 16 | I45: 13 | J45: =COUNTIFS('Contenu des kits'!$B$2:$B$1856,B45,'Contenu des kits'!$C$2:$C$1856,C45,'Contenu des kits'!$N$2:$N$1856,"MANQUE") -> 1 | K45: =IF(AND(F45<F46,F46<F47),"OK","À REVOIR") -> OK | L45: =SUMIFS('Contenu des kits'!$S$2:$S$1856,'Contenu des kits'!$B$2:$B$1856,B45,'Contenu des kits'!$C$2:$C$1856,C45) -> 5470 | M45: =SUMIFS('Contenu des kits'!$T$2:$T$1856,'Contenu des kits'!$B$2:$B$1856,B45,'Contenu des kits'!$C$2:$C$1856,C45) -> 3000 | N45: =IF(F45-O45=0,"",M45/(F45-O45)) -> 0.35419126 | O45: =SUMIFS('Contenu des kits'!$U$2:$U$1856,'Contenu des kits'!$B$2:$B$1856,B45,'Contenu des kits'!$C$2:$C$1856,C45) -> 7700
A46: Collège | B46: 5e | C46: Complet | D46: 41 | E46: 29050 | F46: =SUMIFS('Contenu des kits'!$M$2:$M$1856,'Contenu des kits'!$B$2:$B$1856,B46,'Contenu des kits'!$C$2:$C$1856,C46) -> 65430 | G46: =IF(E46="","",F46-E46) -> 36380 | H46: =COUNTIFS('Contenu des kits'!$B$2:$B$1856,B46,'Contenu des kits'!$C$2:$C$1856,C46,'Contenu des kits'!$L$2:$L$1856,"Oui",'Contenu des kits'!$K$2:$K$1856,"Principal") -> 31 | I46: 18 | J46: =COUNTIFS('Contenu des kits'!$B$2:$B$1856,B46,'Contenu des kits'!$C$2:$C$1856,C46,'Contenu des kits'!$N$2:$N$1856,"MANQUE") -> 1 | L46: =SUMIFS('Contenu des kits'!$S$2:$S$1856,'Contenu des kits'!$B$2:$B$1856,B46,'Contenu des kits'!$C$2:$C$1856,C46) -> 43340 | M46: =SUMIFS('Contenu des kits'!$T$2:$T$1856,'Contenu des kits'!$B$2:$B$1856,B46,'Contenu des kits'!$C$2:$C$1856,C46) -> 14190 | N46: =IF(F46-O46=0,"",M46/(F46-O46)) -> 0.24665392 | O46: =SUMIFS('Contenu des kits'!$U$2:$U$1856,'Contenu des kits'!$B$2:$B$1856,B46,'Contenu des kits'!$C$2:$C$1856,C46) -> 7900
A47: Collège | B47: 5e | C47: Confort | D47: 42 | E47: 60080 | F47: =SUMIFS('Contenu des kits'!$M$2:$M$1856,'Contenu des kits'!$B$2:$B$1856,B47,'Contenu des kits'!$C$2:$C$1856,C47) -> 80290 | G47: =IF(E47="","",F47-E47) -> 20210 | H47: =COUNTIFS('Contenu des kits'!$B$2:$B$1856,B47,'Contenu des kits'!$C$2:$C$1856,C47,'Contenu des kits'!$L$2:$L$1856,"Oui",'Contenu des kits'!$K$2:$K$1856,"Principal") -> 35 | I47: 26 | J47: =COUNTIFS('Contenu des kits'!$B$2:$B$1856,B47,'Contenu des kits'!$C$2:$C$1856,C47,'Contenu des kits'!$N$2:$N$1856,"MANQUE") -> 2 | L47: =SUMIFS('Contenu des kits'!$S$2:$S$1856,'Contenu des kits'!$B$2:$B$1856,B47,'Contenu des kits'!$C$2:$C$1856,C47) -> 54000 | M47: =SUMIFS('Contenu des kits'!$T$2:$T$1856,'Contenu des kits'!$B$2:$B$1856,B47,'Contenu des kits'!$C$2:$C$1856,C47) -> 18390 | N47: =IF(F47-O47=0,"",M47/(F47-O47)) -> 0.25404061 | O47: =SUMIFS('Contenu des kits'!$U$2:$U$1856,'Contenu des kits'!$B$2:$B$1856,B47,'Contenu des kits'!$C$2:$C$1856,C47) -> 7900
A49: Collège | B49: 4e | C49: Essentiel | D49: 43 | E49: 13000 | F49: =SUMIFS('Contenu des kits'!$M$2:$M$1856,'Contenu des kits'!$B$2:$B$1856,B49,'Contenu des kits'!$C$2:$C$1856,C49) -> 16720 | G49: =IF(E49="","",F49-E49) -> 3720 | H49: =COUNTIFS('Contenu des kits'!$B$2:$B$1856,B49,'Contenu des kits'!$C$2:$C$1856,C49,'Contenu des kits'!$L$2:$L$1856,"Oui",'Contenu des kits'!$K$2:$K$1856,"Principal") -> 16 | I49: 13 | J49: =COUNTIFS('Contenu des kits'!$B$2:$B$1856,B49,'Contenu des kits'!$C$2:$C$1856,C49,'Contenu des kits'!$N$2:$N$1856,"MANQUE") -> 1 | K49: =IF(AND(F49<F50,F50<F51),"OK","À REVOIR") -> OK | L49: =SUMIFS('Contenu des kits'!$S$2:$S$1856,'Contenu des kits'!$B$2:$B$1856,B49,'Contenu des kits'!$C$2:$C$1856,C49) -> 7020 | M49: =SUMIFS('Contenu des kits'!$T$2:$T$1856,'Contenu des kits'!$B$2:$B$1856,B49,'Contenu des kits'!$C$2:$C$1856,C49) -> 3400 | N49: =IF(F49-O49=0,"",M49/(F49-O49)) -> 0.32629559 | O49: =SUMIFS('Contenu des kits'!$U$2:$U$1856,'Contenu des kits'!$B$2:$B$1856,B49,'Contenu des kits'!$C$2:$C$1856,C49) -> 6300
A50: Collège | B50: 4e | C50: Complet | D50: 44 | E50: 37500 | F50: =SUMIFS('Contenu des kits'!$M$2:$M$1856,'Contenu des kits'!$B$2:$B$1856,B50,'Contenu des kits'!$C$2:$C$1856,C50) -> 74730 | G50: =IF(E50="","",F50-E50) -> 37230 | H50: =COUNTIFS('Contenu des kits'!$B$2:$B$1856,B50,'Contenu des kits'!$C$2:$C$1856,C50,'Contenu des kits'!$L$2:$L$1856,"Oui",'Contenu des kits'!$K$2:$K$1856,"Principal") -> 33 | I50: 19 | J50: =COUNTIFS('Contenu des kits'!$B$2:$B$1856,B50,'Contenu des kits'!$C$2:$C$1856,C50,'Contenu des kits'!$N$2:$N$1856,"MANQUE") -> 2 | L50: =SUMIFS('Contenu des kits'!$S$2:$S$1856,'Contenu des kits'!$B$2:$B$1856,B50,'Contenu des kits'!$C$2:$C$1856,C50) -> 51040 | M50: =SUMIFS('Contenu des kits'!$T$2:$T$1856,'Contenu des kits'!$B$2:$B$1856,B50,'Contenu des kits'!$C$2:$C$1856,C50) -> 16290 | N50: =IF(F50-O50=0,"",M50/(F50-O50)) -> 0.24194267 | O50: =SUMIFS('Contenu des kits'!$U$2:$U$1856,'Contenu des kits'!$B$2:$B$1856,B50,'Contenu des kits'!$C$2:$C$1856,C50) -> 7400
A51: Collège | B51: 4e | C51: Confort | D51: 45 | E51: 75520 | F51: =SUMIFS('Contenu des kits'!$M$2:$M$1856,'Contenu des kits'!$B$2:$B$1856,B51,'Contenu des kits'!$C$2:$C$1856,C51) -> 89620 | G51: =IF(E51="","",F51-E51) -> 14100 | H51: =COUNTIFS('Contenu des kits'!$B$2:$B$1856,B51,'Contenu des kits'!$C$2:$C$1856,C51,'Contenu des kits'!$L$2:$L$1856,"Oui",'Contenu des kits'!$K$2:$K$1856,"Principal") -> 37 | I51: 29 | J51: =COUNTIFS('Contenu des kits'!$B$2:$B$1856,B51,'Contenu des kits'!$C$2:$C$1856,C51,'Contenu des kits'!$N$2:$N$1856,"MANQUE") -> 4 | L51: =SUMIFS('Contenu des kits'!$S$2:$S$1856,'Contenu des kits'!$B$2:$B$1856,B51,'Contenu des kits'!$C$2:$C$1856,C51) -> 61730 | M51: =SUMIFS('Contenu des kits'!$T$2:$T$1856,'Contenu des kits'!$B$2:$B$1856,B51,'Contenu des kits'!$C$2:$C$1856,C51) -> 20490 | N51: =IF(F51-O51=0,"",M51/(F51-O51)) -> 0.24920944 | O51: =SUMIFS('Contenu des kits'!$U$2:$U$1856,'Contenu des kits'!$B$2:$B$1856,B51,'Contenu des kits'!$C$2:$C$1856,C51) -> 7400
A53: Collège | B53: 3e | C53: Essentiel | D53: 46 | E53: 13000 | F53: =SUMIFS('Contenu des kits'!$M$2:$M$1856,'Contenu des kits'!$B$2:$B$1856,B53,'Contenu des kits'!$C$2:$C$1856,C53) -> 17570 | G53: =IF(E53="","",F53-E53) -> 4570 | H53: =COUNTIFS('Contenu des kits'!$B$2:$B$1856,B53,'Contenu des kits'!$C$2:$C$1856,C53,'Contenu des kits'!$L$2:$L$1856,"Oui",'Contenu des kits'!$K$2:$K$1856,"Principal") -> 16 | I53: 13 | J53: =COUNTIFS('Contenu des kits'!$B$2:$B$1856,B53,'Contenu des kits'!$C$2:$C$1856,C53,'Contenu des kits'!$N$2:$N$1856,"MANQUE") -> 2 | K53: =IF(AND(F53<F54,F54<F55),"OK","À REVOIR") -> OK | L53: =SUMIFS('Contenu des kits'!$S$2:$S$1856,'Contenu des kits'!$B$2:$B$1856,B53,'Contenu des kits'!$C$2:$C$1856,C53) -> 7070 | M53: =SUMIFS('Contenu des kits'!$T$2:$T$1856,'Contenu des kits'!$B$2:$B$1856,B53,'Contenu des kits'!$C$2:$C$1856,C53) -> 3400 | N53: =IF(F53-O53=0,"",M53/(F53-O53)) -> 0.32473734 | O53: =SUMIFS('Contenu des kits'!$U$2:$U$1856,'Contenu des kits'!$B$2:$B$1856,B53,'Contenu des kits'!$C$2:$C$1856,C53) -> 7100
A54: Collège | B54: 3e | C54: Complet | D54: 47 | E54: 40300 | F54: =SUMIFS('Contenu des kits'!$M$2:$M$1856,'Contenu des kits'!$B$2:$B$1856,B54,'Contenu des kits'!$C$2:$C$1856,C54) -> 85810 | G54: =IF(E54="","",F54-E54) -> 45510 | H54: =COUNTIFS('Contenu des kits'!$B$2:$B$1856,B54,'Contenu des kits'!$C$2:$C$1856,C54,'Contenu des kits'!$L$2:$L$1856,"Oui",'Contenu des kits'!$K$2:$K$1856,"Principal") -> 34 | I54: 20 | J54: =COUNTIFS('Contenu des kits'!$B$2:$B$1856,B54,'Contenu des kits'!$C$2:$C$1856,C54,'Contenu des kits'!$N$2:$N$1856,"MANQUE") -> 3 | L54: =SUMIFS('Contenu des kits'!$S$2:$S$1856,'Contenu des kits'!$B$2:$B$1856,B54,'Contenu des kits'!$C$2:$C$1856,C54) -> 60520 | M54: =SUMIFS('Contenu des kits'!$T$2:$T$1856,'Contenu des kits'!$B$2:$B$1856,B54,'Contenu des kits'!$C$2:$C$1856,C54) -> 18890 | N54: =IF(F54-O54=0,"",M54/(F54-O54)) -> 0.23787936 | O54: =SUMIFS('Contenu des kits'!$U$2:$U$1856,'Contenu des kits'!$B$2:$B$1856,B54,'Contenu des kits'!$C$2:$C$1856,C54) -> 6400
A55: Collège | B55: 3e | C55: Confort | D55: 48 | E55: 92420 | F55: =SUMIFS('Contenu des kits'!$M$2:$M$1856,'Contenu des kits'!$B$2:$B$1856,B55,'Contenu des kits'!$C$2:$C$1856,C55) -> 112670 | G55: =IF(E55="","",F55-E55) -> 20250 | H55: =COUNTIFS('Contenu des kits'!$B$2:$B$1856,B55,'Contenu des kits'!$C$2:$C$1856,C55,'Contenu des kits'!$L$2:$L$1856,"Oui",'Contenu des kits'!$K$2:$K$1856,"Principal") -> 39 | I55: 32 | J55: =COUNTIFS('Contenu des kits'!$B$2:$B$1856,B55,'Contenu des kits'!$C$2:$C$1856,C55,'Contenu des kits'!$N$2:$N$1856,"MANQUE") -> 4 | L55: =SUMIFS('Contenu des kits'!$S$2:$S$1856,'Contenu des kits'!$B$2:$B$1856,B55,'Contenu des kits'!$C$2:$C$1856,C55) -> 81180 | M55: =SUMIFS('Contenu des kits'!$T$2:$T$1856,'Contenu des kits'!$B$2:$B$1856,B55,'Contenu des kits'!$C$2:$C$1856,C55) -> 25090 | N55: =IF(F55-O55=0,"",M55/(F55-O55)) -> 0.23609673 | O55: =SUMIFS('Contenu des kits'!$U$2:$U$1856,'Contenu des kits'!$B$2:$B$1856,B55,'Contenu des kits'!$C$2:$C$1856,C55) -> 6400
A57: Lycée | B57: Seconde L | C57: Essentiel | D57: 49 | E57: 8350 | F57: =SUMIFS('Contenu des kits'!$M$2:$M$1856,'Contenu des kits'!$B$2:$B$1856,B57,'Contenu des kits'!$C$2:$C$1856,C57) -> 14470 | G57: =IF(E57="","",F57-E57) -> 6120 | H57: =COUNTIFS('Contenu des kits'!$B$2:$B$1856,B57,'Contenu des kits'!$C$2:$C$1856,C57,'Contenu des kits'!$L$2:$L$1856,"Oui",'Contenu des kits'!$K$2:$K$1856,"Principal") -> 15 | I57: 10 | J57: =COUNTIFS('Contenu des kits'!$B$2:$B$1856,B57,'Contenu des kits'!$C$2:$C$1856,C57,'Contenu des kits'!$N$2:$N$1856,"MANQUE") -> 1 | K57: =IF(AND(F57<F58,F58<F59),"OK","À REVOIR") -> OK | L57: =SUMIFS('Contenu des kits'!$S$2:$S$1856,'Contenu des kits'!$B$2:$B$1856,B57,'Contenu des kits'!$C$2:$C$1856,C57) -> 3820 | M57: =SUMIFS('Contenu des kits'!$T$2:$T$1856,'Contenu des kits'!$B$2:$B$1856,B57,'Contenu des kits'!$C$2:$C$1856,C57) -> 1150 | N57: =IF(F57-O57=0,"",M57/(F57-O57)) -> 0.23138833 | O57: =SUMIFS('Contenu des kits'!$U$2:$U$1856,'Contenu des kits'!$B$2:$B$1856,B57,'Contenu des kits'!$C$2:$C$1856,C57) -> 9500
A58: Lycée | B58: Seconde L | C58: Complet | D58: 50 | E58: 21700 | F58: =SUMIFS('Contenu des kits'!$M$2:$M$1856,'Contenu des kits'!$B$2:$B$1856,B58,'Contenu des kits'!$C$2:$C$1856,C58) -> 42850 | G58: =IF(E58="","",F58-E58) -> 21150 | H58: =COUNTIFS('Contenu des kits'!$B$2:$B$1856,B58,'Contenu des kits'!$C$2:$C$1856,C58,'Contenu des kits'!$L$2:$L$1856,"Oui",'Contenu des kits'!$K$2:$K$1856,"Principal") -> 23 | I58: 13 | J58: =COUNTIFS('Contenu des kits'!$B$2:$B$1856,B58,'Contenu des kits'!$C$2:$C$1856,C58,'Contenu des kits'!$N$2:$N$1856,"MANQUE") -> 3 | L58: =SUMIFS('Contenu des kits'!$S$2:$S$1856,'Contenu des kits'!$B$2:$B$1856,B58,'Contenu des kits'!$C$2:$C$1856,C58) -> 27760 | M58: =SUMIFS('Contenu des kits'!$T$2:$T$1856,'Contenu des kits'!$B$2:$B$1856,B58,'Contenu des kits'!$C$2:$C$1856,C58) -> 8190 | N58: =IF(F58-O58=0,"",M58/(F58-O58)) -> 0.22781641 | O58: =SUMIFS('Contenu des kits'!$U$2:$U$1856,'Contenu des kits'!$B$2:$B$1856,B58,'Contenu des kits'!$C$2:$C$1856,C58) -> 6900
A59: Lycée | B59: Seconde L | C59: Confort | D59: 51 | E59: 36770 | F59: =SUMIFS('Contenu des kits'!$M$2:$M$1856,'Contenu des kits'!$B$2:$B$1856,B59,'Contenu des kits'!$C$2:$C$1856,C59) -> 49200 | G59: =IF(E59="","",F59-E59) -> 12430 | H59: =COUNTIFS('Contenu des kits'!$B$2:$B$1856,B59,'Contenu des kits'!$C$2:$C$1856,C59,'Contenu des kits'!$L$2:$L$1856,"Oui",'Contenu des kits'!$K$2:$K$1856,"Principal") -> 25 | I59: 18 | J59: =COUNTIFS('Contenu des kits'!$B$2:$B$1856,B59,'Contenu des kits'!$C$2:$C$1856,C59,'Contenu des kits'!$N$2:$N$1856,"MANQUE") -> 3 | L59: =SUMIFS('Contenu des kits'!$S$2:$S$1856,'Contenu des kits'!$B$2:$B$1856,B59,'Contenu des kits'!$C$2:$C$1856,C59) -> 32210 | M59: =SUMIFS('Contenu des kits'!$T$2:$T$1856,'Contenu des kits'!$B$2:$B$1856,B59,'Contenu des kits'!$C$2:$C$1856,C59) -> 10090 | N59: =IF(F59-O59=0,"",M59/(F59-O59)) -> 0.23853428 | O59: =SUMIFS('Contenu des kits'!$U$2:$U$1856,'Contenu des kits'!$B$2:$B$1856,B59,'Contenu des kits'!$C$2:$C$1856,C59) -> 6900
A61: Lycée | B61: Seconde S | C61: Essentiel | D61: 52 | E61: 14950 | F61: =SUMIFS('Contenu des kits'!$M$2:$M$1856,'Contenu des kits'!$B$2:$B$1856,B61,'Contenu des kits'!$C$2:$C$1856,C61) -> 20970 | G61: =IF(E61="","",F61-E61) -> 6020 | H61: =COUNTIFS('Contenu des kits'!$B$2:$B$1856,B61,'Contenu des kits'!$C$2:$C$1856,C61,'Contenu des kits'!$L$2:$L$1856,"Oui",'Contenu des kits'!$K$2:$K$1856,"Principal") -> 16 | I61: 13 | J61: =COUNTIFS('Contenu des kits'!$B$2:$B$1856,B61,'Contenu des kits'!$C$2:$C$1856,C61,'Contenu des kits'!$N$2:$N$1856,"MANQUE") -> 4 | K61: =IF(AND(F61<F62,F62<F63),"OK","À REVOIR") -> OK | L61: =SUMIFS('Contenu des kits'!$S$2:$S$1856,'Contenu des kits'!$B$2:$B$1856,B61,'Contenu des kits'!$C$2:$C$1856,C61) -> 7870 | M61: =SUMIFS('Contenu des kits'!$T$2:$T$1856,'Contenu des kits'!$B$2:$B$1856,B61,'Contenu des kits'!$C$2:$C$1856,C61) -> 2300 | N61: =IF(F61-O61=0,"",M61/(F61-O61)) -> 0.22615536 | O61: =SUMIFS('Contenu des kits'!$U$2:$U$1856,'Contenu des kits'!$B$2:$B$1856,B61,'Contenu des kits'!$C$2:$C$1856,C61) -> 10800
A62: Lycée | B62: Seconde S | C62: Complet | D62: 53 | E62: 33350 | F62: =SUMIFS('Contenu des kits'!$M$2:$M$1856,'Contenu des kits'!$B$2:$B$1856,B62,'Contenu des kits'!$C$2:$C$1856,C62) -> 63860 | G62: =IF(E62="","",F62-E62) -> 30510 | H62: =COUNTIFS('Contenu des kits'!$B$2:$B$1856,B62,'Contenu des kits'!$C$2:$C$1856,C62,'Contenu des kits'!$L$2:$L$1856,"Oui",'Contenu des kits'!$K$2:$K$1856,"Principal") -> 27 | I62: 15 | J62: =COUNTIFS('Contenu des kits'!$B$2:$B$1856,B62,'Contenu des kits'!$C$2:$C$1856,C62,'Contenu des kits'!$N$2:$N$1856,"MANQUE") -> 6 | L62: =SUMIFS('Contenu des kits'!$S$2:$S$1856,'Contenu des kits'!$B$2:$B$1856,B62,'Contenu des kits'!$C$2:$C$1856,C62) -> 43920 | M62: =SUMIFS('Contenu des kits'!$T$2:$T$1856,'Contenu des kits'!$B$2:$B$1856,B62,'Contenu des kits'!$C$2:$C$1856,C62) -> 12640 | N62: =IF(F62-O62=0,"",M62/(F62-O62)) -> 0.22347949 | O62: =SUMIFS('Contenu des kits'!$U$2:$U$1856,'Contenu des kits'!$B$2:$B$1856,B62,'Contenu des kits'!$C$2:$C$1856,C62) -> 7300
A63: Lycée | B63: Seconde S | C63: Confort | D63: 54 | E63: 92970 | F63: =SUMIFS('Contenu des kits'!$M$2:$M$1856,'Contenu des kits'!$B$2:$B$1856,B63,'Contenu des kits'!$C$2:$C$1856,C63) -> 93120 | G63: =IF(E63="","",F63-E63) -> 150 | H63: =COUNTIFS('Contenu des kits'!$B$2:$B$1856,B63,'Contenu des kits'!$C$2:$C$1856,C63,'Contenu des kits'!$L$2:$L$1856,"Oui",'Contenu des kits'!$K$2:$K$1856,"Principal") -> 30 | I63: 25 | J63: =COUNTIFS('Contenu des kits'!$B$2:$B$1856,B63,'Contenu des kits'!$C$2:$C$1856,C63,'Contenu des kits'!$N$2:$N$1856,"MANQUE") -> 9 | L63: =SUMIFS('Contenu des kits'!$S$2:$S$1856,'Contenu des kits'!$B$2:$B$1856,B63,'Contenu des kits'!$C$2:$C$1856,C63) -> 67030 | M63: =SUMIFS('Contenu des kits'!$T$2:$T$1856,'Contenu des kits'!$B$2:$B$1856,B63,'Contenu des kits'!$C$2:$C$1856,C63) -> 18790 | N63: =IF(F63-O63=0,"",M63/(F63-O63)) -> 0.21894663 | O63: =SUMIFS('Contenu des kits'!$U$2:$U$1856,'Contenu des kits'!$B$2:$B$1856,B63,'Contenu des kits'!$C$2:$C$1856,C63) -> 7300
A65: Lycée | B65: Première L1 | C65: Essentiel | D65: 511 | E65: 7950 | F65: =SUMIFS('Contenu des kits'!$M$2:$M$1856,'Contenu des kits'!$B$2:$B$1856,B65,'Contenu des kits'!$C$2:$C$1856,C65) -> 14470 | G65: =IF(E65="","",F65-E65) -> 6520 | H65: =COUNTIFS('Contenu des kits'!$B$2:$B$1856,B65,'Contenu des kits'!$C$2:$C$1856,C65,'Contenu des kits'!$L$2:$L$1856,"Oui",'Contenu des kits'!$K$2:$K$1856,"Principal") -> 15 | I65: 10 | J65: =COUNTIFS('Contenu des kits'!$B$2:$B$1856,B65,'Contenu des kits'!$C$2:$C$1856,C65,'Contenu des kits'!$N$2:$N$1856,"MANQUE") -> 0 | K65: =IF(AND(F65<F66,F66<F67),"OK","À REVOIR") -> OK | L65: =SUMIFS('Contenu des kits'!$S$2:$S$1856,'Contenu des kits'!$B$2:$B$1856,B65,'Contenu des kits'!$C$2:$C$1856,C65) -> 3820 | M65: =SUMIFS('Contenu des kits'!$T$2:$T$1856,'Contenu des kits'!$B$2:$B$1856,B65,'Contenu des kits'!$C$2:$C$1856,C65) -> 1150 | N65: =IF(F65-O65=0,"",M65/(F65-O65)) -> 0.23138833 | O65: =SUMIFS('Contenu des kits'!$U$2:$U$1856,'Contenu des kits'!$B$2:$B$1856,B65,'Contenu des kits'!$C$2:$C$1856,C65) -> 9500
A66: Lycée | B66: Première L1 | C66: Complet | D66: 512 | E66: 23400 | F66: =SUMIFS('Contenu des kits'!$M$2:$M$1856,'Contenu des kits'!$B$2:$B$1856,B66,'Contenu des kits'!$C$2:$C$1856,C66) -> 48050 | G66: =IF(E66="","",F66-E66) -> 24650 | H66: =COUNTIFS('Contenu des kits'!$B$2:$B$1856,B66,'Contenu des kits'!$C$2:$C$1856,C66,'Contenu des kits'!$L$2:$L$1856,"Oui",'Contenu des kits'!$K$2:$K$1856,"Principal") -> 25 | I66: 14 | J66: =COUNTIFS('Contenu des kits'!$B$2:$B$1856,B66,'Contenu des kits'!$C$2:$C$1856,C66,'Contenu des kits'!$N$2:$N$1856,"MANQUE") -> 1 | L66: =SUMIFS('Contenu des kits'!$S$2:$S$1856,'Contenu des kits'!$B$2:$B$1856,B66,'Contenu des kits'!$C$2:$C$1856,C66) -> 30960 | M66: =SUMIFS('Contenu des kits'!$T$2:$T$1856,'Contenu des kits'!$B$2:$B$1856,B66,'Contenu des kits'!$C$2:$C$1856,C66) -> 10190 | N66: =IF(F66-O66=0,"",M66/(F66-O66)) -> 0.24763062 | O66: =SUMIFS('Contenu des kits'!$U$2:$U$1856,'Contenu des kits'!$B$2:$B$1856,B66,'Contenu des kits'!$C$2:$C$1856,C66) -> 6900
A67: Lycée | B67: Première L1 | C67: Confort | D67: 513 | E67: 42670 | F67: =SUMIFS('Contenu des kits'!$M$2:$M$1856,'Contenu des kits'!$B$2:$B$1856,B67,'Contenu des kits'!$C$2:$C$1856,C67) -> 57200 | G67: =IF(E67="","",F67-E67) -> 14530 | H67: =COUNTIFS('Contenu des kits'!$B$2:$B$1856,B67,'Contenu des kits'!$C$2:$C$1856,C67,'Contenu des kits'!$L$2:$L$1856,"Oui",'Contenu des kits'!$K$2:$K$1856,"Principal") -> 28 | I67: 20 | J67: =COUNTIFS('Contenu des kits'!$B$2:$B$1856,B67,'Contenu des kits'!$C$2:$C$1856,C67,'Contenu des kits'!$N$2:$N$1856,"MANQUE") -> 2 | L67: =SUMIFS('Contenu des kits'!$S$2:$S$1856,'Contenu des kits'!$B$2:$B$1856,B67,'Contenu des kits'!$C$2:$C$1856,C67) -> 37210 | M67: =SUMIFS('Contenu des kits'!$T$2:$T$1856,'Contenu des kits'!$B$2:$B$1856,B67,'Contenu des kits'!$C$2:$C$1856,C67) -> 13090 | N67: =IF(F67-O67=0,"",M67/(F67-O67)) -> 0.26023857 | O67: =SUMIFS('Contenu des kits'!$U$2:$U$1856,'Contenu des kits'!$B$2:$B$1856,B67,'Contenu des kits'!$C$2:$C$1856,C67) -> 6900
A69: Lycée | B69: Première L2 | C69: Essentiel | D69: 514 | E69: 7450 | F69: =SUMIFS('Contenu des kits'!$M$2:$M$1856,'Contenu des kits'!$B$2:$B$1856,B69,'Contenu des kits'!$C$2:$C$1856,C69) -> 14470 | G69: =IF(E69="","",F69-E69) -> 7020 | H69: =COUNTIFS('Contenu des kits'!$B$2:$B$1856,B69,'Contenu des kits'!$C$2:$C$1856,C69,'Contenu des kits'!$L$2:$L$1856,"Oui",'Contenu des kits'!$K$2:$K$1856,"Principal") -> 15 | I69: 10 | J69: =COUNTIFS('Contenu des kits'!$B$2:$B$1856,B69,'Contenu des kits'!$C$2:$C$1856,C69,'Contenu des kits'!$N$2:$N$1856,"MANQUE") -> 0 | K69: =IF(AND(F69<F70,F70<F71),"OK","À REVOIR") -> OK | L69: =SUMIFS('Contenu des kits'!$S$2:$S$1856,'Contenu des kits'!$B$2:$B$1856,B69,'Contenu des kits'!$C$2:$C$1856,C69) -> 3820 | M69: =SUMIFS('Contenu des kits'!$T$2:$T$1856,'Contenu des kits'!$B$2:$B$1856,B69,'Contenu des kits'!$C$2:$C$1856,C69) -> 1150 | N69: =IF(F69-O69=0,"",M69/(F69-O69)) -> 0.23138833 | O69: =SUMIFS('Contenu des kits'!$U$2:$U$1856,'Contenu des kits'!$B$2:$B$1856,B69,'Contenu des kits'!$C$2:$C$1856,C69) -> 9500
A70: Lycée | B70: Première L2 | C70: Complet | D70: 515 | E70: 21800 | F70: =SUMIFS('Contenu des kits'!$M$2:$M$1856,'Contenu des kits'!$B$2:$B$1856,B70,'Contenu des kits'!$C$2:$C$1856,C70) -> 48050 | G70: =IF(E70="","",F70-E70) -> 26250 | H70: =COUNTIFS('Contenu des kits'!$B$2:$B$1856,B70,'Contenu des kits'!$C$2:$C$1856,C70,'Contenu des kits'!$L$2:$L$1856,"Oui",'Contenu des kits'!$K$2:$K$1856,"Principal") -> 25 | I70: 14 | J70: =COUNTIFS('Contenu des kits'!$B$2:$B$1856,B70,'Contenu des kits'!$C$2:$C$1856,C70,'Contenu des kits'!$N$2:$N$1856,"MANQUE") -> 1 | L70: =SUMIFS('Contenu des kits'!$S$2:$S$1856,'Contenu des kits'!$B$2:$B$1856,B70,'Contenu des kits'!$C$2:$C$1856,C70) -> 30960 | M70: =SUMIFS('Contenu des kits'!$T$2:$T$1856,'Contenu des kits'!$B$2:$B$1856,B70,'Contenu des kits'!$C$2:$C$1856,C70) -> 10190 | N70: =IF(F70-O70=0,"",M70/(F70-O70)) -> 0.24763062 | O70: =SUMIFS('Contenu des kits'!$U$2:$U$1856,'Contenu des kits'!$B$2:$B$1856,B70,'Contenu des kits'!$C$2:$C$1856,C70) -> 6900
A71: Lycée | B71: Première L2 | C71: Confort | D71: 516 | E71: 41070 | F71: =SUMIFS('Contenu des kits'!$M$2:$M$1856,'Contenu des kits'!$B$2:$B$1856,B71,'Contenu des kits'!$C$2:$C$1856,C71) -> 57200 | G71: =IF(E71="","",F71-E71) -> 16130 | H71: =COUNTIFS('Contenu des kits'!$B$2:$B$1856,B71,'Contenu des kits'!$C$2:$C$1856,C71,'Contenu des kits'!$L$2:$L$1856,"Oui",'Contenu des kits'!$K$2:$K$1856,"Principal") -> 28 | I71: 20 | J71: =COUNTIFS('Contenu des kits'!$B$2:$B$1856,B71,'Contenu des kits'!$C$2:$C$1856,C71,'Contenu des kits'!$N$2:$N$1856,"MANQUE") -> 2 | L71: =SUMIFS('Contenu des kits'!$S$2:$S$1856,'Contenu des kits'!$B$2:$B$1856,B71,'Contenu des kits'!$C$2:$C$1856,C71) -> 37210 | M71: =SUMIFS('Contenu des kits'!$T$2:$T$1856,'Contenu des kits'!$B$2:$B$1856,B71,'Contenu des kits'!$C$2:$C$1856,C71) -> 13090 | N71: =IF(F71-O71=0,"",M71/(F71-O71)) -> 0.26023857 | O71: =SUMIFS('Contenu des kits'!$U$2:$U$1856,'Contenu des kits'!$B$2:$B$1856,B71,'Contenu des kits'!$C$2:$C$1856,C71) -> 6900
A73: Lycée | B73: Première S1 | C73: Essentiel | D73: 154 | E73: 14900 | F73: =SUMIFS('Contenu des kits'!$M$2:$M$1856,'Contenu des kits'!$B$2:$B$1856,B73,'Contenu des kits'!$C$2:$C$1856,C73) -> 20970 | G73: =IF(E73="","",F73-E73) -> 6070 | H73: =COUNTIFS('Contenu des kits'!$B$2:$B$1856,B73,'Contenu des kits'!$C$2:$C$1856,C73,'Contenu des kits'!$L$2:$L$1856,"Oui",'Contenu des kits'!$K$2:$K$1856,"Principal") -> 16 | I73: 13 | J73: =COUNTIFS('Contenu des kits'!$B$2:$B$1856,B73,'Contenu des kits'!$C$2:$C$1856,C73,'Contenu des kits'!$N$2:$N$1856,"MANQUE") -> 0 | K73: =IF(AND(F73<F74,F74<F75),"OK","À REVOIR") -> OK | L73: =SUMIFS('Contenu des kits'!$S$2:$S$1856,'Contenu des kits'!$B$2:$B$1856,B73,'Contenu des kits'!$C$2:$C$1856,C73) -> 7870 | M73: =SUMIFS('Contenu des kits'!$T$2:$T$1856,'Contenu des kits'!$B$2:$B$1856,B73,'Contenu des kits'!$C$2:$C$1856,C73) -> 2300 | N73: =IF(F73-O73=0,"",M73/(F73-O73)) -> 0.22615536 | O73: =SUMIFS('Contenu des kits'!$U$2:$U$1856,'Contenu des kits'!$B$2:$B$1856,B73,'Contenu des kits'!$C$2:$C$1856,C73) -> 10800
A74: Lycée | B74: Première S1 | C74: Complet | D74: 155 | E74: 35300 | F74: =SUMIFS('Contenu des kits'!$M$2:$M$1856,'Contenu des kits'!$B$2:$B$1856,B74,'Contenu des kits'!$C$2:$C$1856,C74) -> 134750 | G74: =IF(E74="","",F74-E74) -> 99450 | H74: =COUNTIFS('Contenu des kits'!$B$2:$B$1856,B74,'Contenu des kits'!$C$2:$C$1856,C74,'Contenu des kits'!$L$2:$L$1856,"Oui",'Contenu des kits'!$K$2:$K$1856,"Principal") -> 31 | I74: 16 | J74: =COUNTIFS('Contenu des kits'!$B$2:$B$1856,B74,'Contenu des kits'!$C$2:$C$1856,C74,'Contenu des kits'!$N$2:$N$1856,"MANQUE") -> 2 | L74: =SUMIFS('Contenu des kits'!$S$2:$S$1856,'Contenu des kits'!$B$2:$B$1856,B74,'Contenu des kits'!$C$2:$C$1856,C74) -> 100210 | M74: =SUMIFS('Contenu des kits'!$T$2:$T$1856,'Contenu des kits'!$B$2:$B$1856,B74,'Contenu des kits'!$C$2:$C$1856,C74) -> 27240 | N74: =IF(F74-O74=0,"",M74/(F74-O74)) -> 0.21373087 | O74: =SUMIFS('Contenu des kits'!$U$2:$U$1856,'Contenu des kits'!$B$2:$B$1856,B74,'Contenu des kits'!$C$2:$C$1856,C74) -> 7300
A75: Lycée | B75: Première S1 | C75: Confort | D75: 156 | E75: 83460 | F75: =SUMIFS('Contenu des kits'!$M$2:$M$1856,'Contenu des kits'!$B$2:$B$1856,B75,'Contenu des kits'!$C$2:$C$1856,C75) -> 135350 | G75: =IF(E75="","",F75-E75) -> 51890 | H75: =COUNTIFS('Contenu des kits'!$B$2:$B$1856,B75,'Contenu des kits'!$C$2:$C$1856,C75,'Contenu des kits'!$L$2:$L$1856,"Oui",'Contenu des kits'!$K$2:$K$1856,"Principal") -> 31 | I75: 25 | J75: =COUNTIFS('Contenu des kits'!$B$2:$B$1856,B75,'Contenu des kits'!$C$2:$C$1856,C75,'Contenu des kits'!$N$2:$N$1856,"MANQUE") -> 2 | L75: =SUMIFS('Contenu des kits'!$S$2:$S$1856,'Contenu des kits'!$B$2:$B$1856,B75,'Contenu des kits'!$C$2:$C$1856,C75) -> 100660 | M75: =SUMIFS('Contenu des kits'!$T$2:$T$1856,'Contenu des kits'!$B$2:$B$1856,B75,'Contenu des kits'!$C$2:$C$1856,C75) -> 27390 | N75: =IF(F75-O75=0,"",M75/(F75-O75)) -> 0.21390082 | O75: =SUMIFS('Contenu des kits'!$U$2:$U$1856,'Contenu des kits'!$B$2:$B$1856,B75,'Contenu des kits'!$C$2:$C$1856,C75) -> 7300
A77: Lycée | B77: Première S2 | C77: Essentiel | D77: 157 | E77: 13600 | F77: =SUMIFS('Contenu des kits'!$M$2:$M$1856,'Contenu des kits'!$B$2:$B$1856,B77,'Contenu des kits'!$C$2:$C$1856,C77) -> 20970 | G77: =IF(E77="","",F77-E77) -> 7370 | H77: =COUNTIFS('Contenu des kits'!$B$2:$B$1856,B77,'Contenu des kits'!$C$2:$C$1856,C77,'Contenu des kits'!$L$2:$L$1856,"Oui",'Contenu des kits'!$K$2:$K$1856,"Principal") -> 16 | I77: 13 | J77: =COUNTIFS('Contenu des kits'!$B$2:$B$1856,B77,'Contenu des kits'!$C$2:$C$1856,C77,'Contenu des kits'!$N$2:$N$1856,"MANQUE") -> 0 | K77: =IF(AND(F77<F78,F78<F79),"OK","À REVOIR") -> OK | L77: =SUMIFS('Contenu des kits'!$S$2:$S$1856,'Contenu des kits'!$B$2:$B$1856,B77,'Contenu des kits'!$C$2:$C$1856,C77) -> 7870 | M77: =SUMIFS('Contenu des kits'!$T$2:$T$1856,'Contenu des kits'!$B$2:$B$1856,B77,'Contenu des kits'!$C$2:$C$1856,C77) -> 2300 | N77: =IF(F77-O77=0,"",M77/(F77-O77)) -> 0.22615536 | O77: =SUMIFS('Contenu des kits'!$U$2:$U$1856,'Contenu des kits'!$B$2:$B$1856,B77,'Contenu des kits'!$C$2:$C$1856,C77) -> 10800
A78: Lycée | B78: Première S2 | C78: Complet | D78: 158 | E78: 33000 | F78: =SUMIFS('Contenu des kits'!$M$2:$M$1856,'Contenu des kits'!$B$2:$B$1856,B78,'Contenu des kits'!$C$2:$C$1856,C78) -> 69190 | G78: =IF(E78="","",F78-E78) -> 36190 | H78: =COUNTIFS('Contenu des kits'!$B$2:$B$1856,B78,'Contenu des kits'!$C$2:$C$1856,C78,'Contenu des kits'!$L$2:$L$1856,"Oui",'Contenu des kits'!$K$2:$K$1856,"Principal") -> 28 | I78: 16 | J78: =COUNTIFS('Contenu des kits'!$B$2:$B$1856,B78,'Contenu des kits'!$C$2:$C$1856,C78,'Contenu des kits'!$N$2:$N$1856,"MANQUE") -> 2 | L78: =SUMIFS('Contenu des kits'!$S$2:$S$1856,'Contenu des kits'!$B$2:$B$1856,B78,'Contenu des kits'!$C$2:$C$1856,C78) -> 47650 | M78: =SUMIFS('Contenu des kits'!$T$2:$T$1856,'Contenu des kits'!$B$2:$B$1856,B78,'Contenu des kits'!$C$2:$C$1856,C78) -> 14240 | N78: =IF(F78-O78=0,"",M78/(F78-O78)) -> 0.23008564 | O78: =SUMIFS('Contenu des kits'!$U$2:$U$1856,'Contenu des kits'!$B$2:$B$1856,B78,'Contenu des kits'!$C$2:$C$1856,C78) -> 7300
A79: Lycée | B79: Première S2 | C79: Confort | D79: 159 | E79: 72160 | F79: =SUMIFS('Contenu des kits'!$M$2:$M$1856,'Contenu des kits'!$B$2:$B$1856,B79,'Contenu des kits'!$C$2:$C$1856,C79) -> 132790 | G79: =IF(E79="","",F79-E79) -> 60630 | H79: =COUNTIFS('Contenu des kits'!$B$2:$B$1856,B79,'Contenu des kits'!$C$2:$C$1856,C79,'Contenu des kits'!$L$2:$L$1856,"Oui",'Contenu des kits'!$K$2:$K$1856,"Principal") -> 33 | I79: 25 | J79: =COUNTIFS('Contenu des kits'!$B$2:$B$1856,B79,'Contenu des kits'!$C$2:$C$1856,C79,'Contenu des kits'!$N$2:$N$1856,"MANQUE") -> 2 | L79: =SUMIFS('Contenu des kits'!$S$2:$S$1856,'Contenu des kits'!$B$2:$B$1856,B79,'Contenu des kits'!$C$2:$C$1856,C79) -> 98500 | M79: =SUMIFS('Contenu des kits'!$T$2:$T$1856,'Contenu des kits'!$B$2:$B$1856,B79,'Contenu des kits'!$C$2:$C$1856,C79) -> 26990 | N79: =IF(F79-O79=0,"",M79/(F79-O79)) -> 0.2150769 | O79: =SUMIFS('Contenu des kits'!$U$2:$U$1856,'Contenu des kits'!$B$2:$B$1856,B79,'Contenu des kits'!$C$2:$C$1856,C79) -> 7300
A81: Lycée | B81: Terminale L1 | C81: Essentiel | D81: 532 | E81: 9350 | F81: =SUMIFS('Contenu des kits'!$M$2:$M$1856,'Contenu des kits'!$B$2:$B$1856,B81,'Contenu des kits'!$C$2:$C$1856,C81) -> 14470 | G81: =IF(E81="","",F81-E81) -> 5120 | H81: =COUNTIFS('Contenu des kits'!$B$2:$B$1856,B81,'Contenu des kits'!$C$2:$C$1856,C81,'Contenu des kits'!$L$2:$L$1856,"Oui",'Contenu des kits'!$K$2:$K$1856,"Principal") -> 15 | I81: 10 | J81: =COUNTIFS('Contenu des kits'!$B$2:$B$1856,B81,'Contenu des kits'!$C$2:$C$1856,C81,'Contenu des kits'!$N$2:$N$1856,"MANQUE") -> 1 | K81: =IF(AND(F81<F82,F82<F83),"OK","À REVOIR") -> OK | L81: =SUMIFS('Contenu des kits'!$S$2:$S$1856,'Contenu des kits'!$B$2:$B$1856,B81,'Contenu des kits'!$C$2:$C$1856,C81) -> 3820 | M81: =SUMIFS('Contenu des kits'!$T$2:$T$1856,'Contenu des kits'!$B$2:$B$1856,B81,'Contenu des kits'!$C$2:$C$1856,C81) -> 1150 | N81: =IF(F81-O81=0,"",M81/(F81-O81)) -> 0.23138833 | O81: =SUMIFS('Contenu des kits'!$U$2:$U$1856,'Contenu des kits'!$B$2:$B$1856,B81,'Contenu des kits'!$C$2:$C$1856,C81) -> 9500
A82: Lycée | B82: Terminale L1 | C82: Complet | D82: 533 | E82: 25900 | F82: =SUMIFS('Contenu des kits'!$M$2:$M$1856,'Contenu des kits'!$B$2:$B$1856,B82,'Contenu des kits'!$C$2:$C$1856,C82) -> 41750 | G82: =IF(E82="","",F82-E82) -> 15850 | H82: =COUNTIFS('Contenu des kits'!$B$2:$B$1856,B82,'Contenu des kits'!$C$2:$C$1856,C82,'Contenu des kits'!$L$2:$L$1856,"Oui",'Contenu des kits'!$K$2:$K$1856,"Principal") -> 23 | I82: 14 | J82: =COUNTIFS('Contenu des kits'!$B$2:$B$1856,B82,'Contenu des kits'!$C$2:$C$1856,C82,'Contenu des kits'!$N$2:$N$1856,"MANQUE") -> 2 | L82: =SUMIFS('Contenu des kits'!$S$2:$S$1856,'Contenu des kits'!$B$2:$B$1856,B82,'Contenu des kits'!$C$2:$C$1856,C82) -> 26660 | M82: =SUMIFS('Contenu des kits'!$T$2:$T$1856,'Contenu des kits'!$B$2:$B$1856,B82,'Contenu des kits'!$C$2:$C$1856,C82) -> 8190 | N82: =IF(F82-O82=0,"",M82/(F82-O82)) -> 0.23500717 | O82: =SUMIFS('Contenu des kits'!$U$2:$U$1856,'Contenu des kits'!$B$2:$B$1856,B82,'Contenu des kits'!$C$2:$C$1856,C82) -> 6900
A83: Lycée | B83: Terminale L1 | C83: Confort | D83: 534 | E83: 44670 | F83: =SUMIFS('Contenu des kits'!$M$2:$M$1856,'Contenu des kits'!$B$2:$B$1856,B83,'Contenu des kits'!$C$2:$C$1856,C83) -> 50900 | G83: =IF(E83="","",F83-E83) -> 6230 | H83: =COUNTIFS('Contenu des kits'!$B$2:$B$1856,B83,'Contenu des kits'!$C$2:$C$1856,C83,'Contenu des kits'!$L$2:$L$1856,"Oui",'Contenu des kits'!$K$2:$K$1856,"Principal") -> 26 | I83: 20 | J83: =COUNTIFS('Contenu des kits'!$B$2:$B$1856,B83,'Contenu des kits'!$C$2:$C$1856,C83,'Contenu des kits'!$N$2:$N$1856,"MANQUE") -> 3 | L83: =SUMIFS('Contenu des kits'!$S$2:$S$1856,'Contenu des kits'!$B$2:$B$1856,B83,'Contenu des kits'!$C$2:$C$1856,C83) -> 32910 | M83: =SUMIFS('Contenu des kits'!$T$2:$T$1856,'Contenu des kits'!$B$2:$B$1856,B83,'Contenu des kits'!$C$2:$C$1856,C83) -> 11090 | N83: =IF(F83-O83=0,"",M83/(F83-O83)) -> 0.25204545 | O83: =SUMIFS('Contenu des kits'!$U$2:$U$1856,'Contenu des kits'!$B$2:$B$1856,B83,'Contenu des kits'!$C$2:$C$1856,C83) -> 6900
A85: Lycée | B85: Terminale L2 | C85: Essentiel | D85: 535 | E85: 8850 | F85: =SUMIFS('Contenu des kits'!$M$2:$M$1856,'Contenu des kits'!$B$2:$B$1856,B85,'Contenu des kits'!$C$2:$C$1856,C85) -> 14470 | G85: =IF(E85="","",F85-E85) -> 5620 | H85: =COUNTIFS('Contenu des kits'!$B$2:$B$1856,B85,'Contenu des kits'!$C$2:$C$1856,C85,'Contenu des kits'!$L$2:$L$1856,"Oui",'Contenu des kits'!$K$2:$K$1856,"Principal") -> 15 | I85: 10 | J85: =COUNTIFS('Contenu des kits'!$B$2:$B$1856,B85,'Contenu des kits'!$C$2:$C$1856,C85,'Contenu des kits'!$N$2:$N$1856,"MANQUE") -> 1 | K85: =IF(AND(F85<F86,F86<F87),"OK","À REVOIR") -> OK | L85: =SUMIFS('Contenu des kits'!$S$2:$S$1856,'Contenu des kits'!$B$2:$B$1856,B85,'Contenu des kits'!$C$2:$C$1856,C85) -> 3820 | M85: =SUMIFS('Contenu des kits'!$T$2:$T$1856,'Contenu des kits'!$B$2:$B$1856,B85,'Contenu des kits'!$C$2:$C$1856,C85) -> 1150 | N85: =IF(F85-O85=0,"",M85/(F85-O85)) -> 0.23138833 | O85: =SUMIFS('Contenu des kits'!$U$2:$U$1856,'Contenu des kits'!$B$2:$B$1856,B85,'Contenu des kits'!$C$2:$C$1856,C85) -> 9500
A86: Lycée | B86: Terminale L2 | C86: Complet | D86: 536 | E86: 24300 | F86: =SUMIFS('Contenu des kits'!$M$2:$M$1856,'Contenu des kits'!$B$2:$B$1856,B86,'Contenu des kits'!$C$2:$C$1856,C86) -> 41750 | G86: =IF(E86="","",F86-E86) -> 17450 | H86: =COUNTIFS('Contenu des kits'!$B$2:$B$1856,B86,'Contenu des kits'!$C$2:$C$1856,C86,'Contenu des kits'!$L$2:$L$1856,"Oui",'Contenu des kits'!$K$2:$K$1856,"Principal") -> 23 | I86: 14 | J86: =COUNTIFS('Contenu des kits'!$B$2:$B$1856,B86,'Contenu des kits'!$C$2:$C$1856,C86,'Contenu des kits'!$N$2:$N$1856,"MANQUE") -> 2 | L86: =SUMIFS('Contenu des kits'!$S$2:$S$1856,'Contenu des kits'!$B$2:$B$1856,B86,'Contenu des kits'!$C$2:$C$1856,C86) -> 26660 | M86: =SUMIFS('Contenu des kits'!$T$2:$T$1856,'Contenu des kits'!$B$2:$B$1856,B86,'Contenu des kits'!$C$2:$C$1856,C86) -> 8190 | N86: =IF(F86-O86=0,"",M86/(F86-O86)) -> 0.23500717 | O86: =SUMIFS('Contenu des kits'!$U$2:$U$1856,'Contenu des kits'!$B$2:$B$1856,B86,'Contenu des kits'!$C$2:$C$1856,C86) -> 6900
A87: Lycée | B87: Terminale L2 | C87: Confort | D87: 537 | E87: 43070 | F87: =SUMIFS('Contenu des kits'!$M$2:$M$1856,'Contenu des kits'!$B$2:$B$1856,B87,'Contenu des kits'!$C$2:$C$1856,C87) -> 50900 | G87: =IF(E87="","",F87-E87) -> 7830 | H87: =COUNTIFS('Contenu des kits'!$B$2:$B$1856,B87,'Contenu des kits'!$C$2:$C$1856,C87,'Contenu des kits'!$L$2:$L$1856,"Oui",'Contenu des kits'!$K$2:$K$1856,"Principal") -> 26 | I87: 20 | J87: =COUNTIFS('Contenu des kits'!$B$2:$B$1856,B87,'Contenu des kits'!$C$2:$C$1856,C87,'Contenu des kits'!$N$2:$N$1856,"MANQUE") -> 3 | L87: =SUMIFS('Contenu des kits'!$S$2:$S$1856,'Contenu des kits'!$B$2:$B$1856,B87,'Contenu des kits'!$C$2:$C$1856,C87) -> 32910 | M87: =SUMIFS('Contenu des kits'!$T$2:$T$1856,'Contenu des kits'!$B$2:$B$1856,B87,'Contenu des kits'!$C$2:$C$1856,C87) -> 11090 | N87: =IF(F87-O87=0,"",M87/(F87-O87)) -> 0.25204545 | O87: =SUMIFS('Contenu des kits'!$U$2:$U$1856,'Contenu des kits'!$B$2:$B$1856,B87,'Contenu des kits'!$C$2:$C$1856,C87) -> 6900
A89: Lycée | B89: Terminale S1 | C89: Essentiel | D89: 163 | E89: 15800 | F89: =SUMIFS('Contenu des kits'!$M$2:$M$1856,'Contenu des kits'!$B$2:$B$1856,B89,'Contenu des kits'!$C$2:$C$1856,C89) -> 20970 | G89: =IF(E89="","",F89-E89) -> 5170 | H89: =COUNTIFS('Contenu des kits'!$B$2:$B$1856,B89,'Contenu des kits'!$C$2:$C$1856,C89,'Contenu des kits'!$L$2:$L$1856,"Oui",'Contenu des kits'!$K$2:$K$1856,"Principal") -> 16 | I89: 13 | J89: =COUNTIFS('Contenu des kits'!$B$2:$B$1856,B89,'Contenu des kits'!$C$2:$C$1856,C89,'Contenu des kits'!$N$2:$N$1856,"MANQUE") -> 1 | K89: =IF(AND(F89<F90,F90<F91),"OK","À REVOIR") -> OK | L89: =SUMIFS('Contenu des kits'!$S$2:$S$1856,'Contenu des kits'!$B$2:$B$1856,B89,'Contenu des kits'!$C$2:$C$1856,C89) -> 7870 | M89: =SUMIFS('Contenu des kits'!$T$2:$T$1856,'Contenu des kits'!$B$2:$B$1856,B89,'Contenu des kits'!$C$2:$C$1856,C89) -> 2300 | N89: =IF(F89-O89=0,"",M89/(F89-O89)) -> 0.22615536 | O89: =SUMIFS('Contenu des kits'!$U$2:$U$1856,'Contenu des kits'!$B$2:$B$1856,B89,'Contenu des kits'!$C$2:$C$1856,C89) -> 10800
A90: Lycée | B90: Terminale S1 | C90: Complet | D90: 164 | E90: 34100 | F90: =SUMIFS('Contenu des kits'!$M$2:$M$1856,'Contenu des kits'!$B$2:$B$1856,B90,'Contenu des kits'!$C$2:$C$1856,C90) -> 166150 | G90: =IF(E90="","",F90-E90) -> 132050 | H90: =COUNTIFS('Contenu des kits'!$B$2:$B$1856,B90,'Contenu des kits'!$C$2:$C$1856,C90,'Contenu des kits'!$L$2:$L$1856,"Oui",'Contenu des kits'!$K$2:$K$1856,"Principal") -> 30 | I90: 15 | J90: =COUNTIFS('Contenu des kits'!$B$2:$B$1856,B90,'Contenu des kits'!$C$2:$C$1856,C90,'Contenu des kits'!$N$2:$N$1856,"MANQUE") -> 3 | L90: =SUMIFS('Contenu des kits'!$S$2:$S$1856,'Contenu des kits'!$B$2:$B$1856,B90,'Contenu des kits'!$C$2:$C$1856,C90) -> 126210 | M90: =SUMIFS('Contenu des kits'!$T$2:$T$1856,'Contenu des kits'!$B$2:$B$1856,B90,'Contenu des kits'!$C$2:$C$1856,C90) -> 32640 | N90: =IF(F90-O90=0,"",M90/(F90-O90)) -> 0.20547686 | O90: =SUMIFS('Contenu des kits'!$U$2:$U$1856,'Contenu des kits'!$B$2:$B$1856,B90,'Contenu des kits'!$C$2:$C$1856,C90) -> 7300
A91: Lycée | B91: Terminale S1 | C91: Confort | D91: 165 | E91: 68760 | F91: =SUMIFS('Contenu des kits'!$M$2:$M$1856,'Contenu des kits'!$B$2:$B$1856,B91,'Contenu des kits'!$C$2:$C$1856,C91) -> 166750 | G91: =IF(E91="","",F91-E91) -> 97990 | H91: =COUNTIFS('Contenu des kits'!$B$2:$B$1856,B91,'Contenu des kits'!$C$2:$C$1856,C91,'Contenu des kits'!$L$2:$L$1856,"Oui",'Contenu des kits'!$K$2:$K$1856,"Principal") -> 30 | I91: 23 | J91: =COUNTIFS('Contenu des kits'!$B$2:$B$1856,B91,'Contenu des kits'!$C$2:$C$1856,C91,'Contenu des kits'!$N$2:$N$1856,"MANQUE") -> 3 | L91: =SUMIFS('Contenu des kits'!$S$2:$S$1856,'Contenu des kits'!$B$2:$B$1856,B91,'Contenu des kits'!$C$2:$C$1856,C91) -> 126660 | M91: =SUMIFS('Contenu des kits'!$T$2:$T$1856,'Contenu des kits'!$B$2:$B$1856,B91,'Contenu des kits'!$C$2:$C$1856,C91) -> 32790 | N91: =IF(F91-O91=0,"",M91/(F91-O91)) -> 0.2056444 | O91: =SUMIFS('Contenu des kits'!$U$2:$U$1856,'Contenu des kits'!$B$2:$B$1856,B91,'Contenu des kits'!$C$2:$C$1856,C91) -> 7300
A93: Lycée | B93: Terminale S2 | C93: Essentiel | D93: 166 | E93: 14500 | F93: =SUMIFS('Contenu des kits'!$M$2:$M$1856,'Contenu des kits'!$B$2:$B$1856,B93,'Contenu des kits'!$C$2:$C$1856,C93) -> 20970 | G93: =IF(E93="","",F93-E93) -> 6470 | H93: =COUNTIFS('Contenu des kits'!$B$2:$B$1856,B93,'Contenu des kits'!$C$2:$C$1856,C93,'Contenu des kits'!$L$2:$L$1856,"Oui",'Contenu des kits'!$K$2:$K$1856,"Principal") -> 16 | I93: 13 | J93: =COUNTIFS('Contenu des kits'!$B$2:$B$1856,B93,'Contenu des kits'!$C$2:$C$1856,C93,'Contenu des kits'!$N$2:$N$1856,"MANQUE") -> 3 | K93: =IF(AND(F93<F94,F94<F95),"OK","À REVOIR") -> OK | L93: =SUMIFS('Contenu des kits'!$S$2:$S$1856,'Contenu des kits'!$B$2:$B$1856,B93,'Contenu des kits'!$C$2:$C$1856,C93) -> 7870 | M93: =SUMIFS('Contenu des kits'!$T$2:$T$1856,'Contenu des kits'!$B$2:$B$1856,B93,'Contenu des kits'!$C$2:$C$1856,C93) -> 2300 | N93: =IF(F93-O93=0,"",M93/(F93-O93)) -> 0.22615536 | O93: =SUMIFS('Contenu des kits'!$U$2:$U$1856,'Contenu des kits'!$B$2:$B$1856,B93,'Contenu des kits'!$C$2:$C$1856,C93) -> 10800
A94: Lycée | B94: Terminale S2 | C94: Complet | D94: 167 | E94: 31800 | F94: =SUMIFS('Contenu des kits'!$M$2:$M$1856,'Contenu des kits'!$B$2:$B$1856,B94,'Contenu des kits'!$C$2:$C$1856,C94) -> 70870 | G94: =IF(E94="","",F94-E94) -> 39070 | H94: =COUNTIFS('Contenu des kits'!$B$2:$B$1856,B94,'Contenu des kits'!$C$2:$C$1856,C94,'Contenu des kits'!$L$2:$L$1856,"Oui",'Contenu des kits'!$K$2:$K$1856,"Principal") -> 26 | I94: 15 | J94: =COUNTIFS('Contenu des kits'!$B$2:$B$1856,B94,'Contenu des kits'!$C$2:$C$1856,C94,'Contenu des kits'!$N$2:$N$1856,"MANQUE") -> 5 | L94: =SUMIFS('Contenu des kits'!$S$2:$S$1856,'Contenu des kits'!$B$2:$B$1856,B94,'Contenu des kits'!$C$2:$C$1856,C94) -> 49930 | M94: =SUMIFS('Contenu des kits'!$T$2:$T$1856,'Contenu des kits'!$B$2:$B$1856,B94,'Contenu des kits'!$C$2:$C$1856,C94) -> 13640 | N94: =IF(F94-O94=0,"",M94/(F94-O94)) -> 0.21456662 | O94: =SUMIFS('Contenu des kits'!$U$2:$U$1856,'Contenu des kits'!$B$2:$B$1856,B94,'Contenu des kits'!$C$2:$C$1856,C94) -> 7300
A95: Lycée | B95: Terminale S2 | C95: Confort | D95: 168 | E95: 76460 | F95: =SUMIFS('Contenu des kits'!$M$2:$M$1856,'Contenu des kits'!$B$2:$B$1856,B95,'Contenu des kits'!$C$2:$C$1856,C95) -> 71470 | G95: =IF(E95="","",F95-E95) -> -4990 | H95: =COUNTIFS('Contenu des kits'!$B$2:$B$1856,B95,'Contenu des kits'!$C$2:$C$1856,C95,'Contenu des kits'!$L$2:$L$1856,"Oui",'Contenu des kits'!$K$2:$K$1856,"Principal") -> 26 | I95: 24 | J95: =COUNTIFS('Contenu des kits'!$B$2:$B$1856,B95,'Contenu des kits'!$C$2:$C$1856,C95,'Contenu des kits'!$N$2:$N$1856,"MANQUE") -> 6 | L95: =SUMIFS('Contenu des kits'!$S$2:$S$1856,'Contenu des kits'!$B$2:$B$1856,B95,'Contenu des kits'!$C$2:$C$1856,C95) -> 50380 | M95: =SUMIFS('Contenu des kits'!$T$2:$T$1856,'Contenu des kits'!$B$2:$B$1856,B95,'Contenu des kits'!$C$2:$C$1856,C95) -> 13790 | N95: =IF(F95-O95=0,"",M95/(F95-O95)) -> 0.21489793 | O95: =SUMIFS('Contenu des kits'!$U$2:$U$1856,'Contenu des kits'!$B$2:$B$1856,B95,'Contenu des kits'!$C$2:$C$1856,C95) -> 7300

Sheet Par classe
A1: Composition par classe (quantités par gamme)
A2: « — » = pas dans la gamme. Rouge = pas au catalogue, jaune = à confirmer, bleu = remplacement, violet = produit à créer. (L) = livre proposé mais décoché en Essentiel ; (opt) = option décochée.
A4: PETITE SECTION
A5: Fourniture | B5: Essentiel | C5: Complet | D5: Confort | E5: Produit Essentiel | F5: Produit Complet | G5: Produit Confort | H5: Statut
A6: Cahier de travaux pratiques 100 pages | B6: 1 | C6: 1 | D6: 1 | E6: 1728 · Cahier de travaux pratiques MyFriend 100 pages · 900 F | F6: 1728 · Cahier de travaux pratiques MyFriend 100 pages · 900 F | G6: 1728 · Cahier de travaux pratiques MyFriend 100 pages · 900 F
A7: Cahier de travaux pratiques 200 pages | B7: 1 | C7: 1 | D7: 1 | E7: 1729 · Cahier de travaux pratiques MyFriend 200 pages · 1 300 F | F7: 1729 · Cahier de travaux pratiques MyFriend 200 pages · 1 300 F | G7: 1729 · Cahier de travaux pratiques MyFriend 200 pages · 1 300 F
A8: Cahier de dessin | B8: 1 | C8: 1 | D8: 1 | E8: 1572 · Cahier de dessin L'écolier 32 pages · 250 F | F8: 1286 · Cahier de dessin TPG · 550 F | G8: 1286 · Cahier de dessin TPG · 550 F
A9: Ardoise blanche avec feutre | B9: 1 | C9: 1 | D9: 1 | E9: 33 · Ardoise blanche + feutre effaçable · 1 200 F | F9: 33 · Ardoise blanche + feutre effaçable · 1 200 F | G9: 33 · Ardoise blanche + feutre effaçable · 1 200 F
A10: Feutres pour ardoise | B10: 2 | C10: 2 | D10: 2 | E10: 1698 · Marqueur tableau blanc BEIYUE B-105 · 400 F | F10: 1698 · Marqueur tableau blanc BEIYUE B-105 · 400 F | G10: 1698 · Marqueur tableau blanc BEIYUE B-105 · 400 F
A11: Effaceur d'ardoise | B11: 1 | C11: 1 | D11: 1 | E11: 1244 · Brosse tableau blanc magnetique RX T-29 · 400 F | F11: 1244 · Brosse tableau blanc magnetique RX T-29 · 400 F | G11: 1244 · Brosse tableau blanc magnetique RX T-29 · 400 F
A12: Crayon à papier HB | B12: 2 | C12: 2 | D12: 4 | E12: 1571 · Crayon papier couleur du Senegal - a l unite · 75 F | F12: 1571 · Crayon papier couleur du Senegal - a l unite · 75 F | G12: 1571 · Crayon papier couleur du Senegal - a l unite · 75 F
A13: Gomme | B13: 1 | C13: 1 | D13: 1 | E13: 9 · Gomme blanche · 150 F | F13: 1181 · Gomme Staedtler Mars Plastic · 250 F | G13: 1181 · Gomme Staedtler Mars Plastic · 250 F
A14: Taille-crayon avec réservoir | B14: 1 | C14: 1 | D14: 1 | E14: 1587 · Tailla Crayon 1 Trou + Réservoir Clean – MAPED · 500 F | F14: 1587 · Tailla Crayon 1 Trou + Réservoir Clean – MAPED · 500 F | G14: 1587 · Tailla Crayon 1 Trou + Réservoir Clean – MAPED · 500 F
A15: Crayons de couleur | B15: 1 | C15: 1 | D15: 1 | E15: 1589 · Crayon Couleur BTE X12 – MAPED · 900 F | F15: 1589 · Crayon Couleur BTE X12 – MAPED · 900 F | G15: 1594 · Crayons de Couleur Boite de 24 Nightfall – MAPED · 1 600 F
A16: Bâtons de colle | B16: 2 | C16: 2 | D16: 4 | E16: 1173 · Baton de colle Dolphin Stick Glue · 570 F | F16: 1604 · Bâton de colle 20 g – GIOTTO · 700 F | G16: 1604 · Bâton de colle 20 g – GIOTTO · 700 F
A17: Ciseaux à bouts ronds | B17: 1 | C17: 1 | D17: 1 | E17: 1250 · Ciseaux scolaires bouts ronds · 250 F | F17: 1586 · Ciseaux 13cm Security Stop – MAPED · 900 F | G17: 1586 · Ciseaux 13cm Security Stop – MAPED · 900 F
... A20: Gourde | B20: 1 | C20: 1 | D20: 1 | E20: 1287 · Gourde Drink violette · 2 500 F | F20: 1193 · Gourde enfant motif ours Naughty Bear · 3 100 F | G20: 1193 · Gourde enfant motif ours Naughty Bear · 3 100 F
A21: Cartable | B21: 1 (opt) | C21: 1 (opt) | D21: 1 | E21: 1252 · Cartable Kam Rad Cute Capybaras · 6 500 F | F21: 1252 · Cartable Kam Rad Cute Capybaras · 6 500 F | G21: 1252 · Cartable Kam Rad Cute Capybaras · 6 500 F
A22: Feutres de couleur | B22: — | C22: 1 | D22: 2 | F22: 1204 · Feutres Giotto Turbo Color 12 couleurs · 1 300 F | G22: 1204 · Feutres Giotto Turbo Color 12 couleurs · 1 300 F
A23: Pâte à modeler | B23: — | C23: 1 | D23: 1 | F23: pas au catalogue | G23: pas au catalogue | H23: MANQUE
A24: Tablier de peinture | B24: — | C24: 1 | D24: 1 | F24: pas au catalogue | G24: pas au catalogue | H24: MANQUE
A25: Gommettes | B25: — | C25: 1 | D25: 1 | F25: pas au catalogue | G25: pas au catalogue | H25: MANQUE
A26: Règle 20 cm | B26: — | C26: 1 | D26: 1 | F26: 1183 · Regle plastique transparente 20 cm · 100 F | G26: 1183 · Regle plastique transparente 20 cm · 100 F
A27: Mon cahier de lecture, Petite section | B27: — | C27: 1 | D27: 1 | F27: 1231 · Mon cahier de lecture - Petite Section · 3 250 F | G27: 1231 · Mon cahier de lecture - Petite Section · 3 250 F
A28: Deuxième trousse Hello | B28: — | C28: 1 | D28: 1 | F28: 1708 · Trousse Hello pingouin menthe · 2 000 F | G28: 1708 · Trousse Hello pingouin menthe · 2 000 F
A29: Craies de cire | B29: — | C29: — | D29: 1 | G29: 1230 · Craies grasses Giotto Cera 24 · 1 300 F
A30: Bloc de dessin blanc A4 | B30: — | C30: — | D30: 1 | G30: 31 · Bloc de dessin A4 (50 feuilles) · 1 500 F | H30: SUBSTITUT
A31: Papier Canson couleur | B31: — | C31: — | D31: 1 | G31: pas au catalogue | H31: MANQUE
A32: Peinture gouache | B32: — | C32: — | D32: 1 | G32: 29 · Set peinture gouache (12 couleurs) · 2 800 F
A33: Pinceaux | B33: — | C33: — | D33: 1 | G33: 30 · Pinceaux assortis (lot de 5) · 1 000 F
A34: Éponge pour la peinture | B34: — | C34: — | D34: 1 | G34: 1202 · Boîte à éponge · 250 F
A35: Prix du kit | B35: ='Récap par kit'!F5 -> 12940 | C35: ='Récap par kit'!F6 -> 21500 | D35: ='Récap par kit'!F7 -> 38400
A37: MOYENNE SECTION
A38: Fourniture | B38: Essentiel | C38: Complet | D38: Confort | E38: Produit Essentiel | F38: Produit Complet | G38: Produit Confort | H38: Statut
A39: Cahier 96 pages petit format | B39: 1 | C39: 1 | D39: 1 | E39: 1618 · Cahier 96 pages petit format – 56g – seyès calligraphe · 450 F | F39: 1618 · Cahier 96 pages petit format – 56g – seyès calligraphe · 450 F | G39: 1618 · Cahier 96 pages petit format – 56g – seyès calligraphe · 450 F
A40: Cahier de travaux pratiques 200 pages | B40: 1 | C40: 1 | D40: 1 | E40: 1729 · Cahier de travaux pratiques MyFriend 200 pages · 1 300 F | F40: 1729 · Cahier de travaux pratiques MyFriend 200 pages · 1 300 F | G40: 1729 · Cahier de travaux pratiques MyFriend 200 pages · 1 300 F
A41: Cahier de dessin | B41: 1 | C41: 1 | D41: 1 | E41: 1572 · Cahier de dessin L'écolier 32 pages · 250 F | F41: 1286 · Cahier de dessin TPG · 550 F | G41: 1286 · Cahier de dessin TPG · 550 F
A42: Ardoise blanche avec feutre | B42: 1 | C42: 1 | D42: 1 | E42: 33 · Ardoise blanche + feutre effaçable · 1 200 F | F42: 33 · Ardoise blanche + feutre effaçable · 1 200 F | G42: 33 · Ardoise blanche + feutre effaçable · 1 200 F
A43: Feutres pour ardoise | B43: 2 | C43: 2 | D43: 4 | E43: 1698 · Marqueur tableau blanc BEIYUE B-105 · 400 F | F43: 1698 · Marqueur tableau blanc BEIYUE B-105 · 400 F | G43: 1698 · Marqueur tableau blanc BEIYUE B-105 · 400 F
A44: Effaceur d'ardoise | B44: 1 | C44: 1 | D44: 1 | E44: 1244 · Brosse tableau blanc magnetique RX T-29 · 400 F | F44: 1244 · Brosse tableau blanc magnetique RX T-29 · 400 F | G44: 1244 · Brosse tableau blanc magnetique RX T-29 · 400 F
A45: Crayon à papier HB | B45: 2 | C45: 2 | D45: 4 | E45: 1571 · Crayon papier couleur du Senegal - a l unite · 75 F | F45: 1571 · Crayon papier couleur du Senegal - a l unite · 75 F | G45: 1571 · Crayon papier couleur du Senegal - a l unite · 75 F
A46: Gomme | B46: 1 | C46: 1 | D46: 2 | E46: 9 · Gomme blanche · 150 F | F46: 1181 · Gomme Staedtler Mars Plastic · 250 F | G46: 1181 · Gomme Staedtler Mars Plastic · 250 F
A47: Taille-crayon avec réservoir | B47: 1 | C47: 1 | D47: 1 | E47: 1587 · Tailla Crayon 1 Trou + Réservoir Clean – MAPED · 500 F | F47: 1587 · Tailla Crayon 1 Trou + Réservoir Clean – MAPED · 500 F | G47: 1587 · Tailla Crayon 1 Trou + Réservoir Clean – MAPED · 500 F
A48: Crayons de couleur | B48: 1 | C48: 1 | D48: 1 | E48: 1589 · Crayon Couleur BTE X12 – MAPED · 900 F | F48: 1589 · Crayon Couleur BTE X12 – MAPED · 900 F | G48: 1594 · Crayons de Couleur Boite de 24 Nightfall – MAPED · 1 600 F
A49: Bâtons de colle | B49: 2 | C49: 2 | D49: 4 | E49: 1173 · Baton de colle Dolphin Stick Glue · 570 F | F49: 1604 · Bâton de colle 20 g – GIOTTO · 700 F | G49: 1604 · Bâton de colle 20 g – GIOTTO · 700 F
A50: Ciseaux à bouts ronds | B50: 1 | C50: 1 | D50: 1 | E50: 1250 · Ciseaux scolaires bouts ronds · 250 F | F50: 1586 · Ciseaux 13cm Security Stop – MAPED · 900 F | G50: 1586 · Ciseaux 13cm Security Stop – MAPED · 900 F
... A53: Gourde | B53: 1 | C53: 1 | D53: 1 | E53: 1287 · Gourde Drink violette · 2 500 F | F53: 1193 · Gourde enfant motif ours Naughty Bear · 3 100 F | G53: 1193 · Gourde enfant motif ours Naughty Bear · 3 100 F
A54: Cartable | B54: 1 (opt) | C54: 1 (opt) | D54: 1 | E54: 1252 · Cartable Kam Rad Cute Capybaras · 6 500 F | F54: 1252 · Cartable Kam Rad Cute Capybaras · 6 500 F | G54: 1252 · Cartable Kam Rad Cute Capybaras · 6 500 F
A55: Feutres de couleur | B55: — | C55: 1 | D55: 1 | F55: 1204 · Feutres Giotto Turbo Color 12 couleurs · 1 300 F | G55: 1204 · Feutres Giotto Turbo Color 12 couleurs · 1 300 F
A56: Pâte à modeler | B56: — | C56: 1 | D56: 1 | F56: pas au catalogue | G56: pas au catalogue | H56: MANQUE
A57: Tablier de peinture | B57: — | C57: 1 | D57: 1 | F57: pas au catalogue | G57: pas au catalogue | H57: MANQUE
A58: Règle 20 cm | B58: — | C58: 1 | D58: 1 | F58: 1183 · Regle plastique transparente 20 cm · 100 F | G58: 1183 · Regle plastique transparente 20 cm · 100 F
A59: J'apprends les maths, Moyenne section | B59: — | C59: 1 | D59: 1 | F59: 1232 · J apprends les maths - Moyenne Section · 3 250 F | G59: 1232 · J apprends les maths - Moyenne Section · 3 250 F
A60: Craies de cire | B60: — | C60: — | D60: 1 | G60: 1230 · Craies grasses Giotto Cera 24 · 1 300 F
A61: Gommettes | B61: — | C61: — | D61: 1 | G61: pas au catalogue | H61: MANQUE
A62: Bloc de dessin blanc A4 | B62: — | C62: — | D62: 1 | G62: 31 · Bloc de dessin A4 (50 feuilles) · 1 500 F | H62: SUBSTITUT
A63: Papier Canson couleur | B63: — | C63: — | D63: 1 | G63: pas au catalogue | H63: MANQUE
A64: Peinture gouache | B64: — | C64: — | D64: 1 | G64: 29 · Set peinture gouache (12 couleurs) · 2 800 F
A65: Pinceaux | B65: — | C65: — | D65: 1 | G65: 30 · Pinceaux assortis (lot de 5) · 1 000 F
A66: Prix du kit | B66: ='Récap par kit'!F9 -> 12490 | C66: ='Récap par kit'!F10 -> 19050 | D66: ='Récap par kit'!F11 -> 35450
A68: GRANDE SECTION
A69: Fourniture | B69: Essentiel | C69: Complet | D69: Confort | E69: Produit Essentiel | F69: Produit Complet | G69: Produit Confort | H69: Statut
A70: Cahier 96 pages petit format | B70: 2 | C70: 2 | D70: 2 | E70: 1618 · Cahier 96 pages petit format – 56g – seyès calligraphe · 450 F | F70: 1618 · Cahier 96 pages petit format – 56g – seyès calligraphe · 450 F | G70: 1618 · Cahier 96 pages petit format – 56g – seyès calligraphe · 450 F
A71: Cahier de travaux pratiques 200 pages | B71: 1 | C71: 1 | D71: 1 | E71: 1729 · Cahier de travaux pratiques MyFriend 200 pages · 1 300 F | F71: 1729 · Cahier de travaux pratiques MyFriend 200 pages · 1 300 F | G71: 1729 · Cahier de travaux pratiques MyFriend 200 pages · 1 300 F
A72: Cahier de dessin | B72: 1 | C72: 1 | D72: 1 | E72: 1572 · Cahier de dessin L'écolier 32 pages · 250 F | F72: 1286 · Cahier de dessin TPG · 550 F | G72: 1286 · Cahier de dessin TPG · 550 F
A73: Ardoise blanche avec feutre | B73: 1 | C73: 1 | D73: 1 | E73: 33 · Ardoise blanche + feutre effaçable · 1 200 F | F73: 33 · Ardoise blanche + feutre effaçable · 1 200 F | G73: 33 · Ardoise blanche + feutre effaçable · 1 200 F
A74: Feutres pour ardoise | B74: 2 | C74: 2 | D74: 6 | E74: 1698 · Marqueur tableau blanc BEIYUE B-105 · 400 F | F74: 1698 · Marqueur tableau blanc BEIYUE B-105 · 400 F | G74: 1698 · Marqueur tableau blanc BEIYUE B-105 · 400 F
A75: Effaceur d'ardoise | B75: 1 | C75: 1 | D75: 1 | E75: 1244 · Brosse tableau blanc magnetique RX T-29 · 400 F | F75: 1244 · Brosse tableau blanc magnetique RX T-29 · 400 F | G75: 1244 · Brosse tableau blanc magnetique RX T-29 · 400 F
A76: Crayon à papier HB | B76: 2 | C76: 2 | D76: 4 | E76: 1571 · Crayon papier couleur du Senegal - a l unite · 75 F | F76: 1571 · Crayon papier couleur du Senegal - a l unite · 75 F | G76: 1571 · Crayon papier couleur du Senegal - a l unite · 75 F
A77: Gomme | B77: 1 | C77: 1 | D77: 2 | E77: 9 · Gomme blanche · 150 F | F77: 1181 · Gomme Staedtler Mars Plastic · 250 F | G77: 1181 · Gomme Staedtler Mars Plastic · 250 F
A78: Taille-crayon avec réservoir | B78: 1 | C78: 1 | D78: 1 | E78: 1587 · Tailla Crayon 1 Trou + Réservoir Clean – MAPED · 500 F | F78: 1587 · Tailla Crayon 1 Trou + Réservoir Clean – MAPED · 500 F | G78: 1587 · Tailla Crayon 1 Trou + Réservoir Clean – MAPED · 500 F
A79: Crayons de couleur | B79: 1 | C79: 1 | D79: 1 | E79: 1589 · Crayon Couleur BTE X12 – MAPED · 900 F | F79: 1589 · Crayon Couleur BTE X12 – MAPED · 900 F | G79: 1594 · Crayons de Couleur Boite de 24 Nightfall – MAPED · 1 600 F
A80: Bâtons de colle | B80: 2 | C80: 2 | D80: 4 | E80: 1173 · Baton de colle Dolphin Stick Glue · 570 F | F80: 1604 · Bâton de colle 20 g – GIOTTO · 700 F | G80: 1604 · Bâton de colle 20 g – GIOTTO · 700 F
A81: Ciseaux à bouts ronds | B81: 1 | C81: 1 | D81: 1 | E81: 1250 · Ciseaux scolaires bouts ronds · 250 F | F81: 1586 · Ciseaux 13cm Security Stop – MAPED · 900 F | G81: 1586 · Ciseaux 13cm Security Stop – MAPED · 900 F
... A84: Gourde | B84: 1 | C84: 1 | D84: 1 | E84: 1287 · Gourde Drink violette · 2 500 F | F84: 1193 · Gourde enfant motif ours Naughty Bear · 3 100 F | G84: 1193 · Gourde enfant motif ours Naughty Bear · 3 100 F
A85: Cartable | B85: 1 (opt) | C85: 1 (opt) | D85: 1 | E85: 1252 · Cartable Kam Rad Cute Capybaras · 6 500 F | F85: 1252 · Cartable Kam Rad Cute Capybaras · 6 500 F | G85: 1252 · Cartable Kam Rad Cute Capybaras · 6 500 F
A86: Feutres de couleur | B86: — | C86: 1 | D86: 1 | F86: 1204 · Feutres Giotto Turbo Color 12 couleurs · 1 300 F | G86: 1204 · Feutres Giotto Turbo Color 12 couleurs · 1 300 F
A87: Pâte à modeler | B87: — | C87: 1 | D87: 1 | F87: pas au catalogue | G87: pas au catalogue | H87: MANQUE
A88: Tablier de peinture | B88: — | C88: 1 | D88: 1 | F88: pas au catalogue | G88: pas au catalogue | H88: MANQUE
A89: Règle 20 cm | B89: — | C89: 1 | D89: 1 | F89: 1183 · Regle plastique transparente 20 cm · 100 F | G89: 1183 · Regle plastique transparente 20 cm · 100 F
A90: J'apprends à écrire les chiffres | B90: — | C90: 1 | D90: 1 | F90: 1220 · Mon cahier d ecriture - J apprends a ecrire les chiffres · 3 250 F | G90: 1220 · Mon cahier d ecriture - J apprends a ecrire les chiffres · 3 250 F
A91: Craies de cire | B91: — | C91: — | D91: 1 | G91: 1230 · Craies grasses Giotto Cera 24 · 1 300 F
A92: Gommettes | B92: — | C92: — | D92: 1 | G92: pas au catalogue | H92: MANQUE
A93: Bloc de dessin blanc A4 | B93: — | C93: — | D93: 1 | G93: 31 · Bloc de dessin A4 (50 feuilles) · 1 500 F | H93: SUBSTITUT
A94: Papier Canson couleur | B94: — | C94: — | D94: 1 | G94: pas au catalogue | H94: MANQUE
A95: Peinture gouache | B95: — | C95: — | D95: 1 | G95: 29 · Set peinture gouache (12 couleurs) · 2 800 F
A96: Pinceaux | B96: — | C96: — | D96: 1 | G96: 30 · Pinceaux assortis (lot de 5) · 1 000 F
A97: Prix du kit | B97: ='Récap par kit'!F13 -> 12940 | C97: ='Récap par kit'!F14 -> 19500 | D97: ='Récap par kit'!F15 -> 36700
A99: CI
A100: Fourniture | B100: Essentiel | C100: Complet | D100: Confort | E100: Produit Essentiel | F100: Produit Complet | G100: Produit Confort | H100: Statut
A101: Cahier 48 pages | B101: 6 | C101: 6 | D101: 6 | E101: 1575 · Cahier L'écolier 48 pages · 275 F | F101: 1575 · Cahier L'écolier 48 pages · 275 F | G101: 1575 · Cahier L'écolier 48 pages · 275 F
A102: Cahier de dessin | B102: 1 | C102: 1 | D102: 1 | E102: 1572 · Cahier de dessin L'écolier 32 pages · 250 F | F102: 1286 · Cahier de dessin TPG · 550 F | G102: 1286 · Cahier de dessin TPG · 550 F
A103: Protège-cahiers | B103: 7 | C103: 7 | D103: 7 | E103: 1277 · Protège-cahiers couleurs · 150 F | F103: 1277 · Protège-cahiers couleurs · 150 F | G103: 1277 · Protège-cahiers couleurs · 150 F
A104: Crayon à papier HB | B104: 2 | C104: — | D104: — | E104: 1571 · Crayon papier couleur du Senegal - a l unite · 75 F
A105: Stylo bleu | B105: 1 | C105: 2 | D105: 2 | E105: 1635 · Stylo à bille tops 505m Schneider (Couleur: Bleu) · 100 F | F105: 1635 · Stylo à bille tops 505m Schneider (Couleur: Bleu) · 100 F | G105: 1635 · Stylo à bille tops 505m Schneider (Couleur: Bleu) · 100 F
A106: Gomme | B106: 1 | C106: 2 | D106: 2 | E106: 9 · Gomme blanche · 150 F | F106: 1181 · Gomme Staedtler Mars Plastic · 250 F | G106: 1181 · Gomme Staedtler Mars Plastic · 250 F
A107: Taille-crayon | B107: 1 | C107: — | D107: — | E107: 10 · Taille-crayon métallique · 200 F
A108: Règle 20 cm | B108: 1 | C108: 1 | D108: 1 | E108: 1183 · Regle plastique transparente 20 cm · 100 F | F108: 1183 · Regle plastique transparente 20 cm · 100 F | G108: 1183 · Regle plastique transparente 20 cm · 100 F
A109: Crayons de couleur | B109: 1 | C109: 1 | D109: 1 | E109: 1589 · Crayon Couleur BTE X12 – MAPED · 900 F | F109: 1589 · Crayon Couleur BTE X12 – MAPED · 900 F | G109: 1594 · Crayons de Couleur Boite de 24 Nightfall – MAPED · 1 600 F
A110: Bâton de colle | B110: 1 | C110: 2 | D110: 2 | E110: 1173 · Baton de colle Dolphin Stick Glue · 570 F | F110: 1604 · Bâton de colle 20 g – GIOTTO · 700 F | G110: 1604 · Bâton de colle 20 g – GIOTTO · 700 F
...

Sheet Contenu des kits
A1: Cycle | B1: Classe | C1: Gamme | D1: Ordre | E1: Groupe d'affichage | F1: Libellé (vu par le client) | G1: ID produit | H1: Produit au catalogue | I1: Quantité | J1: Prix unitaire | K1: Section | L1: Coché | M1: Total ligne | N1: Statut | O1: Note | P1: Fournisseur | Q1: Délai | R1: Prix d'achat | S1: Coût ligne | T1: Bénéfice ligne | U1: Montant sans prix d'achat
A2: Préscolaire | B2: Petite section | C2: Essentiel | D2: 1 | E2: Cahiers | F2: Cahier de travaux pratiques 100 pages | G2: 1728 | H2: Cahier de travaux pratiques MyFriend 100 pages | I2: 1 | J2: 900 | K2: Principal | L2: Oui | M2: =IF(AND(L2="Oui",K2="Principal"),I2*J2,0) -> 900 | N2: OK | O2: Cahier de graphisme | P2: LPD | Q2: 24h | S2: =IF(AND(L2="Oui",K2="Principal",R2<>""),I2*R2,0) -> 0 | T2: =IF(R2<>"",M2-S2,0) -> 0 | U2: =IF(R2="",M2,0) -> 900
A3: Préscolaire | B3: Petite section | C3: Essentiel | D3: 2 | E3: Cahiers | F3: Cahier de travaux pratiques 200 pages | G3: 1729 | H3: Cahier de travaux pratiques MyFriend 200 pages | I3: 1 | J3: 1300 | K3: Principal | L3: Oui | M3: =IF(AND(L3="Oui",K3="Principal"),I3*J3,0) -> 1300 | N3: OK | O3: Cahier de vie | P3: LPD | Q3: 24h | S3: =IF(AND(L3="Oui",K3="Principal",R3<>""),I3*R3,0) -> 0 | T3: =IF(R3<>"",M3-S3,0) -> 0 | U3: =IF(R3="",M3,0) -> 1300
A4: Préscolaire | B4: Petite section | C4: Essentiel | D4: 3 | E4: Art & dessin | F4: Cahier de dessin | G4: 1572 | H4: Cahier de dessin L'écolier 32 pages | I4: 1 | J4: 250 | K4: Principal | L4: Oui | M4: =IF(AND(L4="Oui",K4="Principal"),I4*J4,0) -> 250 | N4: OK | P4: Papex | Q4: 6j | R4: 150 | S4: =IF(AND(L4="Oui",K4="Principal",R4<>""),I4*R4,0) -> 150 | T4: =IF(R4<>"",M4-S4,0) -> 100 | U4: =IF(R4="",M4,0) -> 0
A5: Préscolaire | B5: Petite section | C5: Essentiel | D5: 4 | E5: Ardoise | F5: Ardoise blanche avec feutre | G5: 33 | H5: Ardoise blanche + feutre effaçable | I5: 1 | J5: 1200 | K5: Principal | L5: Oui | M5: =IF(AND(L5="Oui",K5="Principal"),I5*J5,0) -> 1200 | N5: OK | P5: SacAdo | Q5: 24h | S5: =IF(AND(L5="Oui",K5="Principal",R5<>""),I5*R5,0) -> 0 | T5: =IF(R5<>"",M5-S5,0) -> 0 | U5: =IF(R5="",M5,0) -> 1200
A6: Préscolaire | B6: Petite section | C6: Essentiel | D6: 5 | E6: Ardoise | F6: Feutres pour ardoise | G6: 1698 | H6: Marqueur tableau blanc BEIYUE B-105 | I6: 2 | J6: 400 | K6: Principal | L6: Oui | M6: =IF(AND(L6="Oui",K6="Principal"),I6*J6,0) -> 800 | N6: OK | P6: Cissé & Frères | Q6: 6j | S6: =IF(AND(L6="Oui",K6="Principal",R6<>""),I6*R6,0) -> 0 | T6: =IF(R6<>"",M6-S6,0) -> 0 | U6: =IF(R6="",M6,0) -> 800
A7: Préscolaire | B7: Petite section | C7: Essentiel | D7: 6 | E7: Ardoise | F7: Effaceur d'ardoise | G7: 1244 | H7: Brosse tableau blanc magnetique RX T-29 | I7: 1 | J7: 400 | K7: Principal | L7: Oui | M7: =IF(AND(L7="Oui",K7="Principal"),I7*J7,0) -> 400 | N7: OK | P7: LPD | Q7: 6j | R7: 130 | S7: =IF(AND(L7="Oui",K7="Principal",R7<>""),I7*R7,0) -> 130 | T7: =IF(R7<>"",M7-S7,0) -> 270 | U7: =IF(R7="",M7,0) -> 0
A8: Préscolaire | B8: Petite section | C8: Essentiel | D8: 7 | E8: Écriture | F8: Crayon à papier HB | G8: 1571 | H8: Crayon papier couleur du Senegal - a l unite | I8: 2 | J8: 75 | K8: Principal | L8: Oui | M8: =IF(AND(L8="Oui",K8="Principal"),I8*J8,0) -> 150 | N8: OK | P8: LPD | Q8: 6j | S8: =IF(AND(L8="Oui",K8="Principal",R8<>""),I8*R8,0) -> 0 | T8: =IF(R8<>"",M8-S8,0) -> 0 | U8: =IF(R8="",M8,0) -> 150
A9: Préscolaire | B9: Petite section | C9: Essentiel | D9: 8 | E9: Petit matériel | F9: Gomme | G9: 9 | H9: Gomme blanche | I9: 1 | J9: 150 | K9: Principal | L9: Oui | M9: =IF(AND(L9="Oui",K9="Principal"),I9*J9,0) -> 150 | N9: OK | P9: SacAdo | Q9: 24h | S9: =IF(AND(L9="Oui",K9="Principal",R9<>""),I9*R9,0) -> 0 | T9: =IF(R9<>"",M9-S9,0) -> 0 | U9: =IF(R9="",M9,0) -> 150
A10: Préscolaire | B10: Petite section | C10: Essentiel | D10: 9 | E10: Petit matériel | F10: Taille-crayon avec réservoir | G10: 1587 | H10: Tailla Crayon 1 Trou + Réservoir Clean – MAPED | I10: 1 | J10: 500 | K10: Principal | L10: Oui | M10: =IF(AND(L10="Oui",K10="Principal"),I10*J10,0) -> 500 | N10: OK | P10: Papex | Q10: 6j | R10: 350 | S10: =IF(AND(L10="Oui",K10="Principal",R10<>""),I10*R10,0) -> 350 | T10: =IF(R10<>"",M10-S10,0) -> 150 | U10: =IF(R10="",M10,0) -> 0
A11: Préscolaire | B11: Petite section | C11: Essentiel | D11: 10 | E11: Art & dessin | F11: Crayons de couleur | G11: 1589 | H11: Crayon Couleur BTE X12 – MAPED | I11: 1 | J11: 900 | K11: Principal | L11: Oui | M11: =IF(AND(L11="Oui",K11="Principal"),I11*J11,0) -> 900 | N11: OK | P11: Papex | Q11: 6j | R11: 650 | S11: =IF(AND(L11="Oui",K11="Principal",R11<>""),I11*R11,0) -> 650 | T11: =IF(R11<>"",M11-S11,0) -> 250 | U11: =IF(R11="",M11,0) -> 0
A12: Préscolaire | B12: Petite section | C12: Essentiel | D12: 11 | E12: Petit matériel | F12: Bâtons de colle | G12: 1173 | H12: Baton de colle Dolphin Stick Glue | I12: 2 | J12: 570 | K12: Principal | L12: Oui | M12: =IF(AND(L12="Oui",K12="Principal"),I12*J12,0) -> 1140 | N12: OK | P12: LPD | Q12: 6j | R12: 420 | S12: =IF(AND(L12="Oui",K12="Principal",R12<>""),I12*R12,0) -> 840 | T12: =IF(R12<>"",M12-S12,0) -> 300 | U12: =IF(R12="",M12,0) -> 0
A13: Préscolaire | B13: Petite section | C13: Essentiel | D13: 12 | E13: Petit matériel | F13: Ciseaux à bouts ronds | G13: 1250 | H13: Ciseaux scolaires bouts ronds | I13: 1 | J13: 250 | K13: Principal | L13: Oui | M13: =IF(AND(L13="Oui",K13="Principal"),I13*J13,0) -> 250 | N13: OK | P13: LPD | Q13: 6j | R13: 100 | S13: =IF(AND(L13="Oui",K13="Principal",R13<>""),I13*R13,0) -> 100 | T13: =IF(R13<>"",M13-S13,0) -> 150 | U13: =IF(R13="",M13,0) -> 0
A14: Préscolaire | B14: Petite section | C14: Essentiel | D14: 13 | E14: Rangement | F14: Pochette à élastique | G14: 1625 | H14: Chemise. 3 rabats élastiques + étiquettes 4,5/10ème assorties | I14: 1 | J14: 500 | K14: Principal | L14: Oui | M14: =IF(AND(L14="Oui",K14="Principal"),I14*J14,0) -> 500 | N14: OK | P14: Papex | Q14: 6j | S14: =IF(AND(L14="Oui",K14="Principal",R14<>""),I14*R14,0) -> 0 | T14: =IF(R14<>"",M14-S14,0) -> 0 | U14: =IF(R14="",M14,0) -> 500
A15: Préscolaire | B15: Petite section | C15: Essentiel | D15: 14 | E15: Accessoires | F15: Trousse Hello | G15: 1706 | H15: Trousse Hello monstre vert | I15: 1 | J15: 2000 | K15: Principal | L15: Oui | M15: =IF(AND(L15="Oui",K15="Principal"),I15*J15,0) -> 2000 | N15: OK | P15: Cissé & Frères | Q15: 6j | R15: 1500 | S15: =IF(AND(L15="Oui",K15="Principal",R15<>""),I15*R15,0) -> 1500 | T15: =IF(R15<>"",M15-S15,0) -> 500 | U15: =IF(R15="",M15,0) -> 0
A16: Préscolaire | B16: Petite section | C16: Essentiel | D16: 15 | E16: Accessoires | F16: Gourde | G16: 1287 | H16: Gourde Drink violette | I16: 1 | J16: 2500 | K16: Principal | L16: Oui | M16: =IF(AND(L16="Oui",K16="Principal"),I16*J16,0) -> 2500 | N16: OK | O16: Nouveau prix : 2 500 F (ancien 2 000 F), à changer dans l'admin | P16: LPD | Q16: 6j | R16: 1800 | S16: =IF(AND(L16="Oui",K16="Principal",R16<>""),I16*R16,0) -> 1800 | T16: =IF(R16<>"",M16-S16,0) -> 700 | U16: =IF(R16="",M16,0) -> 0
A17: Préscolaire | B17: Petite section | C17: Essentiel | D17: 16 | E17: Option | F17: Cartable | G17: 1252 | H17: Cartable Kam Rad Cute Capybaras | I17: 1 | J17: 6500 | K17: Option | L17: Non | M17: =IF(AND(L17="Oui",K17="Principal"),I17*J17,0) -> 0 | N17: OK | P17: LPD | Q17: 6j | R17: 6000 | S17: =IF(AND(L17="Oui",K17="Principal",R17<>""),I17*R17,0) -> 0 | T17: =IF(R17<>"",M17-S17,0) -> 0 | U17: =IF(R17="",M17,0) -> 0
A18: Préscolaire | B18: Petite section | C18: Complet | D18: 1 | E18: Cahiers | F18: Cahier de travaux pratiques 100 pages | G18: 1728 | H18: Cahier de travaux pratiques MyFriend 100 pages | I18: 1 | J18: 900 | K18: Principal | L18: Oui | M18: =IF(AND(L18="Oui",K18="Principal"),I18*J18,0) -> 900 | N18: OK | O18: Cahier de graphisme | P18: LPD | Q18: 24h | S18: =IF(AND(L18="Oui",K18="Principal",R18<>""),I18*R18,0) -> 0 | T18: =IF(R18<>"",M18-S18,0) -> 0 | U18: =IF(R18="",M18,0) -> 900
A19: Préscolaire | B19: Petite section | C19: Complet | D19: 2 | E19: Cahiers | F19: Cahier de travaux pratiques 200 pages | G19: 1729 | H19: Cahier de travaux pratiques MyFriend 200 pages | I19: 1 | J19: 1300 | K19: Principal | L19: Oui | M19: =IF(AND(L19="Oui",K19="Principal"),I19*J19,0) -> 1300 | N19: OK | O19: Cahier de vie | P19: LPD | Q19: 24h | S19: =IF(AND(L19="Oui",K19="Principal",R19<>""),I19*R19,0) -> 0 | T19: =IF(R19<>"",M19-S19,0) -> 0 | U19: =IF(R19="",M19,0) -> 1300
A20: Préscolaire | B20: Petite section | C20: Complet | D20: 3 | E20: Art & dessin | F20: Cahier de dessin | G20: 1286 | H20: Cahier de dessin TPG | I20: 1 | J20: 550 | K20: Principal | L20: Oui | M20: =IF(AND(L20="Oui",K20="Principal"),I20*J20,0) -> 550 | N20: OK | P20: LPD | Q20: 6j | R20: 450 | S20: =IF(AND(L20="Oui",K20="Principal",R20<>""),I20*R20,0) -> 450 | T20: =IF(R20<>"",M20-S20,0) -> 100 | U20: =IF(R20="",M20,0) -> 0
A21: Préscolaire | B21: Petite section | C21: Complet | D21: 4 | E21: Ardoise | F21: Ardoise blanche avec feutre | G21: 33 | H21: Ardoise blanche + feutre effaçable | I21: 1 | J21: 1200 | K21: Principal | L21: Oui | M21: =IF(AND(L21="Oui",K21="Principal"),I21*J21,0) -> 1200 | N21: OK | P21: SacAdo | Q21: 24h | S21: =IF(AND(L21="Oui",K21="Principal",R21<>""),I21*R21,0) -> 0 | T21: =IF(R21<>"",M21-S21,0) -> 0 | U21: =IF(R21="",M21,0) -> 1200
A22: Préscolaire | B22: Petite section | C22: Complet | D22: 5 | E22: Ardoise | F22: Feutres pour ardoise | G22: 1698 | H22: Marqueur tableau blanc BEIYUE B-105 | I22: 2 | J22: 400 | K22: Principal | L22: Oui | M22: =IF(AND(L22="Oui",K22="Principal"),I22*J22,0) -> 800 | N22: OK | P22: Cissé & Frères | Q22: 6j | S22: =IF(AND(L22="Oui",K22="Principal",R22<>""),I22*R22,0) -> 0 | T22: =IF(R22<>"",M22-S22,0) -> 0 | U22: =IF(R22="",M22,0) -> 800
A23: Préscolaire | B23: Petite section | C23: Complet | D23: 6 | E23: Ardoise | F23: Effaceur d'ardoise | G23: 1244 | H23: Brosse tableau blanc magnetique RX T-29 | I23: 1 | J23: 400 | K23: Principal | L23: Oui | M23: =IF(AND(L23="Oui",K23="Principal"),I23*J23,0) -> 400 | N23: OK | P23: LPD | Q23: 6j | R23: 130 | S23: =IF(AND(L23="Oui",K23="Principal",R23<>""),I23*R23,0) -> 130 | T23: =IF(R23<>"",M23-S23,0) -> 270 | U23: =IF(R23="",M23,0) -> 0
A24: Préscolaire | B24: Petite section | C24: Complet | D24: 7 | E24: Écriture | F24: Crayon à papier HB | G24: 1571 | H24: Crayon papier couleur du Senegal - a l unite | I24: 2 | J24: 75 | K24: Principal | L24: Oui | M24: =IF(AND(L24="Oui",K24="Principal"),I24*J24,0) -> 150 | N24: OK | P24: LPD | Q24: 6j | S24: =IF(AND(L24="Oui",K24="Principal",R24<>""),I24*R24,0) -> 0 | T24: =IF(R24<>"",M24-S24,0) -> 0 | U24: =IF(R24="",M24,0) -> 150
A25: Préscolaire | B25: Petite section | C25: Complet | D25: 8 | E25: Petit matériel | F25: Gomme | G25: 1181 | H25: Gomme Staedtler Mars Plastic | I25: 1 | J25: 250 | K25: Principal | L25: Oui | M25: =IF(AND(L25="Oui",K25="Principal"),I25*J25,0) -> 250 | N25: OK | P25: LPD | Q25: 6j | R25: 110 | S25: =IF(AND(L25="Oui",K25="Principal",R25<>""),I25*R25,0) -> 110 | T25: =IF(R25<>"",M25-S25,0) -> 140 | U25: =IF(R25="",M25,0) -> 0
A26: Préscolaire | B26: Petite section | C26: Complet | D26: 9 | E26: Petit matériel | F26: Taille-crayon avec réservoir | G26: 1587 | H26: Tailla Crayon 1 Trou + Réservoir Clean – MAPED | I26: 1 | J26: 500 | K26: Principal | L26: Oui | M26: =IF(AND(L26="Oui",K26="Principal"),I26*J26,0) -> 500 | N26: OK | P26: Papex | Q26: 6j | R26: 350 | S26: =IF(AND(L26="Oui",K26="Principal",R26<>""),I26*R26,0) -> 350 | T26: =IF(R26<>"",M26-S26,0) -> 150 | U26: =IF(R26="",M26,0) -> 0
A27: Préscolaire | B27: Petite section | C27: Complet | D27: 10 | E27: Art & dessin | F27: Crayons de couleur | G27: 1589 | H27: Crayon Couleur BTE X12 – MAPED | I27: 1 | J27: 900 | K27: Principal | L27: Oui | M27: =IF(AND(L27="Oui",K27="Principal"),I27*J27,0) -> 900 | N27: OK | P27: Papex | Q27: 6j | R27: 650 | S27: =IF(AND(L27="Oui",K27="Principal",R27<>""),I27*R27,0) -> 650 | T27: =IF(R27<>"",M27-S27,0) -> 250 | U27: =IF(R27="",M27,0) -> 0
A28: Préscolaire | B28: Petite section | C28: Complet | D28: 11 | E28: Petit matériel | F28: Bâtons de colle | G28: 1604 | H28: Bâton de colle 20 g – GIOTTO | I28: 2 | J28: 700 | K28: Principal | L28: Oui | M28: =IF(AND(L28="Oui",K28="Principal"),I28*J28,0) -> 1400 | N28: OK | P28: Papex | Q28: 6j | R28: 400 | S28: =IF(AND(L28="Oui",K28="Principal",R28<>""),I28*R28,0) -> 800 | T28: =IF(R28<>"",M28-S28,0) -> 600 | U28: =IF(R28="",M28,0) -> 0
A29: Préscolaire | B29: Petite section | C29: Complet | D29: 12 | E29: Petit matériel | F29: Ciseaux à bouts ronds | G29: 1586 | H29: Ciseaux 13cm Security Stop – MAPED | I29: 1 | J29: 900 | K29: Principal | L29: Oui | M29: =IF(AND(L29="Oui",K29="Principal"),I29*J29,0) -> 900 | N29: OK | P29: Papex | Q29: 6j | R29: 650 | S29: =IF(AND(L29="Oui",K29="Principal",R29<>""),I29*R29,0) -> 650 | T29: =IF(R29<>"",M29-S29,0) -> 250 | U29: =IF(R29="",M29,0) -> 0
A30: Préscolaire | B30: Petite section | C30: Complet | D30: 13 | E30: Rangement | F30: Pochette à élastique | G30: 1625 | H30: Chemise. 3 rabats élastiques + étiquettes 4,5/10ème assorties | I30: 1 | J30: 500 | K30: Principal | L30: Oui | M30: =IF(AND(L30="Oui",K30="Principal"),I30*J30,0) -> 500 | N30: OK | P30: Papex | Q30: 6j | S30: =IF(AND(L30="Oui",K30="Principal",R30<>""),I30*R30,0) -> 0 | T30: =IF(R30<>"",M30-S30,0) -> 0 | U30: =IF(R30="",M30,0) -> 500
A31: Préscolaire | B31: Petite section | C31: Complet | D31: 14 | E31: Art & dessin | F31: Feutres de couleur | G31: 1204 | H31: Feutres Giotto Turbo Color 12 couleurs | I31: 1 | J31: 1300 | K31: Principal | L31: Oui | M31: =IF(AND(L31="Oui",K31="Principal"),I31*J31,0) -> 1300 | N31: OK | P31: LPD | Q31: 6j | R31: 1000 | S31: =IF(AND(L31="Oui",K31="Principal",R31<>""),I31*R31,0) -> 1000 | T31: =IF(R31<>"",M31-S31,0) -> 300 | U31: =IF(R31="",M31,0) -> 0
A32: Préscolaire | B32: Petite section | C32: Complet | D32: 15 | E32: Art & dessin | F32: Pâte à modeler | H32: — pas au catalogue — | I32: 1 | J32: 0 | K32: Principal | L32: Non | M32: =IF(AND(L32="Oui",K32="Principal"),I32*J32,0) -> 0 | N32: MANQUE | O32: Pas au catalogue | S32: =IF(AND(L32="Oui",K32="Principal",R32<>""),I32*R32,0) -> 0 | T32: =IF(R32<>"",M32-S32,0) -> 0 | U32: =IF(R32="",M32,0) -> 0
A33: Préscolaire | B33: Petite section | C33: Complet | D33: 16 | E33: Art & dessin | F33: Tablier de peinture | H33: — pas au catalogue — | I33: 1 | J33: 0 | K33: Principal | L33: Non | M33: =IF(AND(L33="Oui",K33="Principal"),I33*J33,0) -> 0 | N33: MANQUE | O33: Pas au catalogue | S33: =IF(AND(L33="Oui",K33="Principal",R33<>""),I33*R33,0) -> 0 | T33: =IF(R33<>"",M33-S33,0) -> 0 | U33: =IF(R33="",M33,0) -> 0
A34: Préscolaire | B34: Petite section | C34: Complet | D34: 17 | E34: Art & dessin | F34: Gommettes | H34: — pas au catalogue — | I34: 1 | J34: 0 | K34: Principal | L34: Non | M34: =IF(AND(L34="Oui",K34="Principal"),I34*J34,0) -> 0 | N34: MANQUE | O34: Pas au catalogue | S34: =IF(AND(L34="Oui",K34="Principal",R34<>""),I34*R34,0) -> 0 | T34: =IF(R34<>"",M34-S34,0) -> 0 | U34: =IF(R34="",M34,0) -> 0
A35: Préscolaire | B35: Petite section | C35: Complet | D35: 18 | E35: Petit matériel | F35: Règle 20 cm | G35: 1183 | H35: Regle plastique transparente 20 cm | I35: 1 | J35: 100 | K35: Principal | L35: Oui | M35: =IF(AND(L35="Oui",K35="Principal"),I35*J35,0) -> 100 | N35: OK | P35: LPD | Q35: 6j | S35: =IF(AND(L35="Oui",K35="Principal",R35<>""),I35*R35,0) -> 0 | T35: =IF(R35<>"",M35-S35,0) -> 0 | U35: =IF(R35="",M35,0) -> 100
A36: Préscolaire | B36: Petite section | C36: Complet | D36: 19 | E36: Parascolaire | F36: Mon cahier de lecture, Petite section | G36: 1231 | H36: Mon cahier de lecture - Petite Section | I36: 1 | J36: 3250 | K36: Principal | L36: Oui | M36: =IF(AND(L36="Oui",K36="Principal"),I36*J36,0) -> 3250 | N36: OK | O36: Cahier d'activités de la section | P36: LPD | Q36: 6j | R36: 2550 | S36: =IF(AND(L36="Oui",K36="Principal",R36<>""),I36*R36,0) -> 2550 | T36: =IF(R36<>"",M36-S36,0) -> 700 | U36: =IF(R36="",M36,0) -> 0
A37: Préscolaire | B37: Petite section | C37: Complet | D37: 20 | E37: Accessoires | F37: Trousse Hello | G37: 1706 | H37: Trousse Hello monstre vert | I37: 1 | J37: 2000 | K37: Principal | L37: Oui | M37: =IF(AND(L37="Oui",K37="Principal"),I37*J37,0) -> 2000 | N37: OK | P37: Cissé & Frères | Q37: 6j | R37: 1500 | S37: =IF(AND(L37="Oui",K37="Principal",R37<>""),I37*R37,0) -> 1500 | T37: =IF(R37<>"",M37-S37,0) -> 500 | U37: =IF(R37="",M37,0) -> 0
A38: Préscolaire | B38: Petite section | C38: Complet | D38: 21 | E38: Accessoires | F38: Deuxième trousse Hello | G38: 1708 | H38: Trousse Hello pingouin menthe | I38: 1 | J38: 2000 | K38: Principal | L38: Oui | M38: =IF(AND(L38="Oui",K38="Principal"),I38*J38,0) -> 2000 | N38: OK | P38: Cissé & Frères | Q38: 6j | R38: 1500 | S38: =IF(AND(L38="Oui",K38="Principal",R38<>""),I38*R38,0) -> 1500 | T38: =IF(R38<>"",M38-S38,0) -> 500 | U38: =IF(R38="",M38,0) -> 0
A39: Préscolaire | B39: Petite section | C39: Complet | D39: 22 | E39: Accessoires | F39: Gourde | G39: 1193 | H39: Gourde enfant motif ours Naughty Bear | I39: 1 | J39: 3100 | K39: Principal | L39: Oui | M39: =IF(AND(L39="Oui",K39="Principal"),I39*J39,0) -> 3100 | N39: OK | P39: LPD | Q39: 6j | R39: 2400 | S39: =IF(AND(L39="Oui",K39="Principal",R39<>""),I39*R39,0) -> 2400 | T39: =IF(R39<>"",M39-S39,0) -> 700 | U39: =IF(R39="",M39,0) -> 0
A40: Préscolaire | B40: Petite section | C40: Complet | D40: 23 | E40: Option | F40: Cartable | G40: 1252 | H40: Cartable Kam Rad Cute Capybaras | I40: 1 | J40: 6500 | K40: Option | L40: Non | M40: =IF(AND(L40="Oui",K40="Principal"),I40*J40,0) -> 0 | N40: OK | P40: LPD | Q40: 6j | R40: 6000 | S40: =IF(AND(L40="Oui",K40="Principal",R40<>""),I40*R40,0) -> 0 | T40: =IF(R40<>"",M40-S40,0) -> 0 | U40: =IF(R40="",M40,0) -> 0
A41: Préscolaire | B41: Petite section | C41: Confort | D41: 1 | E41: Cahiers | F41: Cahier de travaux pratiques 100 pages | G41: 1728 | H41: Cahier de travaux pratiques MyFriend 100 pages | I41: 1 | J41: 900 | K41: Principal | L41: Oui | M41: =IF(AND(L41="Oui",K41="Principal"),I41*J41,0) -> 900 | N41: OK | O41: Cahier de graphisme | P41: LPD | Q41: 24h | S41: =IF(AND(L41="Oui",K41="Principal",R41<>""),I41*R41,0) -> 0 | T41: =IF(R41<>"",M41-S41,0) -> 0 | U41: =IF(R41="",M41,0) -> 900
A42: Préscolaire | B42: Petite section | C42: Confort | D42: 2 | E42: Cahiers | F42: Cahier de travaux pratiques 200 pages | G42: 1729 | H42: Cahier de travaux pratiques MyFriend 200 pages | I42: 1 | J42: 1300 | K42: Principal | L42: Oui | M42: =IF(AND(L42="Oui",K42="Principal"),I42*J42,0) -> 1300 | N42: OK | O42: Cahier de vie | P42: LPD | Q42: 24h | S42: =IF(AND(L42="Oui",K42="Principal",R42<>""),I42*R42,0) -> 0 | T42: =IF(R42<>"",M42-S42,0) -> 0 | U42: =IF(R42="",M42,0) -> 1300
A43: Préscolaire | B43: Petite section | C43: Confort | D43: 3 | E43: Art & dessin | F43: Cahier de dessin | G43: 1286 | H43: Cahier de dessin TPG | I43: 1 | J43: 550 | K43: Principal | L43: Oui | M43: =IF(AND(L43="Oui",K43="Principal"),I43*J43,0) -> 550 | N43: OK | P43: LPD | Q43: 6j | R43: 450 | S43: =IF(AND(L43="Oui",K43="Principal",R43<>""),I43*R43,0) -> 450 | T43: =IF(R43<>"",M43-S43,0) -> 100 | U43: =IF(R43="",M43,0) -> 0
A44: Préscolaire | B44: Petite section | C44: Confort | D44: 4 | E44: Ardoise | F44: Ardoise blanche avec feutre | G44: 33 | H44: Ardoise blanche + feutre effaçable | I44: 1 | J44: 1200 | K44: Principal | L44: Oui | M44: =IF(AND(L44="Oui",K44="Principal"),I44*J44,0) -> 1200 | N44: OK | P44: SacAdo | Q44: 24h | S44: =IF(AND(L44="Oui",K44="Principal",R44<>""),I44*R44,0) -> 0 | T44: =IF(R44<>"",M44-S44,0) -> 0 | U44: =IF(R44="",M44,0) -> 1200
A45: Préscolaire | B45: Petite section | C45: Confort | D45: 5 | E45: Ardoise | F45: Feutres pour ardoise | G45: 1698 | H45: Marqueur tableau blanc BEIYUE B-105 | I45: 2 | J45: 400 | K45: Principal | L45: Oui | M45: =IF(AND(L45="Oui",K45="Principal"),I45*J45,0) -> 800 | N45: OK | P45: Cissé & Frères | Q45: 6j | S45: =IF(AND(L45="Oui",K45="Principal",R45<>""),I45*R45,0) -> 0 | T45: =IF(R45<>"",M45-S45,0) -> 0 | U45: =IF(R45="",M45,0) -> 800
A46: Préscolaire | B46: Petite section | C46: Confort | D46: 6 | E46: Ardoise | F46: Effaceur d'ardoise | G46: 1244 | H46: Brosse tableau blanc magnetique RX T-29 | I46: 1 | J46: 400 | K46: Principal | L46: Oui | M46: =IF(AND(L46="Oui",K46="Principal"),I46*J46,0) -> 400 | N46: OK | P46: LPD | Q46: 6j | R46: 130 | S46: =IF(AND(L46="Oui",K46="Principal",R46<>""),I46*R46,0) -> 130 | T46: =IF(R46<>"",M46-S46,0) -> 270 | U46: =IF(R46="",M46,0) -> 0
A47: Préscolaire | B47: Petite section | C47: Confort | D47: 7 | E47: Écriture | F47: Crayon à papier HB | G47: 1571 | H47: Crayon papier couleur du Senegal - a l unite | I47: 4 | J47: 75 | K47: Principal | L47: Oui | M47: =IF(AND(L47="Oui",K47="Principal"),I47*J47,0) -> 300 | N47: OK | P47: LPD | Q47: 6j | S47: =IF(AND(L47="Oui",K47="Principal",R47<>""),I47*R47,0) -> 0 | T47: =IF(R47<>"",M47-S47,0) -> 0 | U47: =IF(R47="",M47,0) -> 300
A48: Préscolaire | B48: Petite section | C48: Confort | D48: 8 | E48: Petit matériel | F48: Gomme | G48: 1181 | H48: Gomme Staedtler Mars Plastic | I48: 1 | J48: 250 | K48: Principal | L48: Oui | M48: =IF(AND(L48="Oui",K48="Principal"),I48*J48,0) -> 250 | N48: OK | P48: LPD | Q48: 6j | R48: 110 | S48: =IF(AND(L48="Oui",K48="Principal",R48<>""),I48*R48,0) -> 110 | T48: =IF(R48<>"",M48-S48,0) -> 140 | U48: =IF(R48="",M48,0) -> 0
A49: Préscolaire | B49: Petite section | C49: Confort | D49: 9 | E49: Petit matériel | F49: Taille-crayon avec réservoir | G49: 1587 | H49: Tailla Crayon 1 Trou + Réservoir Clean – MAPED | I49: 1 | J49: 500 | K49: Principal | L49: Oui | M49: =IF(AND(L49="Oui",K49="Principal"),I49*J49,0) -> 500 | N49: OK | P49: Papex | Q49: 6j | R49: 350 | S49: =IF(AND(L49="Oui",K49="Principal",R49<>""),I49*R49,0) -> 350 | T49: =IF(R49<>"",M49-S49,0) -> 150 | U49: =IF(R49="",M49,0) -> 0
A50: Préscolaire | B50: Petite section | C50: Confort | D50: 10 | E50: Art & dessin | F50: Crayons de couleur | G50: 1594 | H50: Crayons de Couleur Boite de 24 Nightfall – MAPED | I50: 1 | J50: 1600 | K50: Principal | L50: Oui | M50: =IF(AND(L50="Oui",K50="Principal"),I50*J50,0) -> 1600 | N50: OK | P50: Papex | Q50: 6j | R50: 1300 | S50: =IF(AND(L50="Oui",K50="Principal",R50<>""),I50*R50,0) -> 1300 | T50: =IF(R50<>"",M50-S50,0) -> 300 | U50: =IF(R50="",M50,0) -> 0
A51: Préscolaire | B51: Petite section | C51: Confort | D51: 11 | E51: Petit matériel | F51: Bâtons de colle | G51: 1604 | H51: Bâton de colle 20 g – GIOTTO | I51: 4 | J51: 700 | K51: Principal | L51: Oui | M51: =IF(AND(L51="Oui",K51="Principal"),I51*J51,0) -> 2800 | N51: OK | P51: Papex | Q51: 6j | R51: 400 | S51: =IF(AND(L51="Oui",K51="Principal",R51<>""),I51*R51,0) -> 1600 | T51: =IF(R51<>"",M51-S51,0) -> 1200 | U51: =IF(R51="",M51,0) -> 0
A52: Préscolaire | B52: Petite section | C52: Confort | D52: 12 | E52: Petit matériel | F52: Ciseaux à bouts ronds | G52: 1586 | H52: Ciseaux 13cm Security Stop – MAPED | I52: 1 | J52: 900 | K52: Principal | L52: Oui | M52: =IF(AND(L52="Oui",K52="Principal"),I52*J52,0) -> 900 | N52: OK | P52: Papex | Q52: 6j | R52: 650 | S52: =IF(AND(L52="Oui",K52="Principal",R52<>""),I52*R52,0) -> 650 | T52: =IF(R52<>"",M52-S52,0) -> 250 | U52: =IF(R52="",M52,0) -> 0
A53: Préscolaire | B53: Petite section | C53: Confort | D53: 13 | E53: Rangement | F53: Pochette à élastique | G53: 1625 | H53: Chemise. 3 rabats élastiques + étiquettes 4,5/10ème assorties | I53: 1 | J53: 500 | K53: Principal | L53: Oui | M53: =IF(AND(L53="Oui",K53="Principal"),I53*J53,0) -> 500 | N53: OK | P53: Papex | Q53: 6j | S53: =IF(AND(L53="Oui",K53="Principal",R53<>""),I53*R53,0) -> 0 | T53: =IF(R53<>"",M53-S53,0) -> 0 | U53: =IF(R53="",M53,0) -> 500
A54: Préscolaire | B54: Petite section | C54: Confort | D54: 14 | E54: Art & dessin | F54: Feutres de couleur | G54: 1204 | H54: Feutres Giotto Turbo Color 12 couleurs | I54: 2 | J54: 1300 | K54: Principal | L54: Oui | M54: =IF(AND(L54="Oui",K54="Principal"),I54*J54,0) -> 2600 | N54: OK | P54: LPD | Q54: 6j | R54: 1000 | S54: =IF(AND(L54="Oui",K54="Principal",R54<>""),I54*R54,0) -> 2000 | T54: =IF(R54<>"",M54-S54,0) -> 600 | U54: =IF(R54="",M54,0) -> 0
A55: Préscolaire | B55: Petite section | C55: Confort | D55: 15 | E55: Art & dessin | F55: Pâte à modeler | H55: — pas au catalogue — | I55: 1 | J55: 0 | K55: Principal | L55: Non | M55: =IF(AND(L55="Oui",K55="Principal"),I55*J55,0) -> 0 | N55: MANQUE | O55: Pas au catalogue | S55: =IF(AND(L55="Oui",K55="Principal",R55<>""),I55*R55,0) -> 0 | T55: =IF(R55<>"",M55-S55,0) -> 0 | U55: =IF(R55="",M55,0) -> 0
A56: Préscolaire | B56: Petite section | C56: Confort | D56: 16 | E56: Art & dessin | F56: Tablier de peinture | H56: — pas au catalogue — | I56: 1 | J56: 0 | K56: Principal | L56: Non | M56: =IF(AND(L56="Oui",K56="Principal"),I56*J56,0) -> 0 | N56: MANQUE | O56: Pas au catalogue | S56: =IF(AND(L56="Oui",K56="Principal",R56<>""),I56*R56,0) -> 0 | T56: =IF(R56<>"",M56-S56,0) -> 0 | U56: =IF(R56="",M56,0) -> 0
A57: Préscolaire | B57: Petite section | C57: Confort | D57: 17 | E57: Art & dessin | F57: Gommettes | H57: — pas au catalogue — | I57: 1 | J57: 0 | K57: Principal | L57: Non | M57: =IF(AND(L57="Oui",K57="Principal"),I57*J57,0) -> 0 | N57: MANQUE | O57: Pas au catalogue | S57: =IF(AND(L57="Oui",K57="Principal",R57<>""),I57*R57,0) -> 0 | T57: =IF(R57<>"",M57-S57,0) -> 0 | U57: =IF(R57="",M57,0) -> 0
A58: Préscolaire | B58: Petite section | C58: Confort | D58: 18 | E58: Petit matériel | F58: Règle 20 cm | G58: 1183 | H58: Regle plastique transparente 20 cm | I58: 1 | J58: 100 | K58: Principal | L58: Oui | M58: =IF(AND(L58="Oui",K58="Principal"),I58*J58,0) -> 100 | N58: OK | P58: LPD | Q58: 6j | S58: =IF(AND(L58="Oui",K58="Principal",R58<>""),I58*R58,0) -> 0 | T58: =IF(R58<>"",M58-S58,0) -> 0 | U58: =IF(R58="",M58,0) -> 100
A59: Préscolaire | B59: Petite section | C59: Confort | D59: 19 | E59: Parascolaire | F59: Mon cahier de lecture, Petite section | G59: 1231 | H59: Mon cahier de lecture - Petite Section | I59: 1 | J59: 3250 | K59: Principal | L59: Oui | M59: =IF(AND(L59="Oui",K59="Principal"),I59*J59,0) -> 3250 | N59: OK | O59: Cahier d'activités de la section | P59: LPD | Q59: 6j | R59: 2550 | S59: =IF(AND(L59="Oui",K59="Principal",R59<>""),I59*R59,0) -> 2550 | T59: =IF(R59<>"",M59-S59,0) -> 700 | U59: =IF(R59="",M59,0) -> 0
A60: Préscolaire | B60: Petite section | C60: Confort | D60: 20 | E60: Art & dessin | F60: Craies de cire | G60: 1230 | H60: Craies grasses Giotto Cera 24 | I60: 1 | J60: 1300 | K60: Principal | L60: Oui | M60: =IF(AND(L60="Oui",K60="Principal"),I60*J60,0) -> 1300 | N60: OK | P60: LPD | Q60: 6j | R60: 1000 | S60: =IF(AND(L60="Oui",K60="Principal",R60<>""),I60*R60,0) -> 1000 | T60: =IF(R60<>"",M60-S60,0) -> 300 | U60: =IF(R60="",M60,0) -> 0
A61: Préscolaire | B61: Petite section | C61: Confort | D61: 21 | E61: Art & dessin | F61: Bloc de dessin blanc A4 | G61: 31 | H61: Bloc de dessin A4 (50 feuilles) | I61: 1 | J61: 1500 | K61: Principal | L61: Oui | M61: =IF(AND(L61="Oui",K61="Principal"),I61*J61,0) -> 1500 | N61: SUBSTITUT | O61: Remplace la pochette Canson blanc | P61: SacAdo | Q61: 24h | S61: =IF(AND(L61="Oui",K61="Principal",R61<>""),I61*R61,0) -> 0 | T61: =IF(R61<>"",M61-S61,0) -> 0 | U61: =IF(R61="",M61,0) -> 1500
A62: Préscolaire | B62: Petite section | C62: Confort | D62: 22 | E62: Art & dessin | F62: Papier Canson couleur | H62: — pas au catalogue — | I62: 1 | J62: 0 | K62: Principal | L62: Non | M62: =IF(AND(L62="Oui",K62="Principal"),I62*J62,0) -> 0 | N62: MANQUE | O62: Pas au catalogue | S62: =IF(AND(L62="Oui",K62="Principal",R62<>""),I62*R62,0) -> 0 | T62: =IF(R62<>"",M62-S62,0) -> 0 | U62: =IF(R62="",M62,0) -> 0
A63: Préscolaire | B63: Petite section | C63: Confort | D63: 23 | E63: Art & dessin | F63: Peinture gouache | G63: 29 | H63: Set peinture gouache (12 couleurs) | I63: 1 | J63: 2800 | K63: Principal | L63: Oui | M63: =IF(AND(L63="Oui",K63="Principal"),I63*J63,0) -> 2800 | N63: OK | P63: SacAdo | Q63: 24h | S63: =IF(AND(L63="Oui",K63="Principal",R63<>""),I63*R63,0) -> 0 | T63: =IF(R63<>"",M63-S63,0) -> 0 | U63: =IF(R63="",M63,0) -> 2800
A64: Préscolaire | B64: Petite section | C64: Confort | D64: 24 | E64: Art & dessin | F64: Pinceaux | G64: 30 | H64: Pinceaux assortis (lot de 5) | I64: 1 | J64: 1000 | K64: Principal | L64: Oui | M64: =IF(AND(L64="Oui",K64="Principal"),I64*J64,0) -> 1000 | N64: OK | P64: SacAdo | Q64: 24h | S64: =IF(AND(L64="Oui",K64="Principal",R64<>""),I64*R64,0) -> 0 | T64: =IF(R64<>"",M64-S64,0) -> 0 | U64: =IF(R64="",M64,0) -> 1000
A65: Préscolaire | B65: Petite section | C65: Confort | D65: 25 | E65: Art & dessin | F65: Éponge pour la peinture | G65: 1202 | H65: Boîte à éponge | I65: 1 | J65: 250 | K65: Principal | L65: Oui | M65: =IF(AND(L65="Oui",K65="Principal"),I65*J65,0) -> 250 | N65: OK | P65: LPD | Q65: 6j | R65: 100 | S65: =IF(AND(L65="Oui",K65="Principal",R65<>""),I65*R65,0) -> 100 | T65: =IF(R65<>"",M65-S65,0) -> 150 | U65: =IF(R65="",M65,0) -> 0
A66: Préscolaire | B66: Petite section | C66: Confort | D66: 26 | E66: Accessoires | F66: Trousse Hello | G66: 1706 | H66: Trousse Hello monstre vert | I66: 1 | J66: 2000 | K66: Principal | L66: Oui | M66: =IF(AND(L66="Oui",K66="Principal"),I66*J66,0) -> 2000 | N66: OK | P66: Cissé & Frères | Q66: 6j | R66: 1500 | S66: =IF(AND(L66="Oui",K66="Principal",R66<>""),I66*R66,0) -> 1500 | T66: =IF(R66<>"",M66-S66,0) -> 500 | U66: =IF(R66="",M66,0) -> 0
A67: Préscolaire | B67: Petite section | C67: Confort | D67: 27 | E67: Accessoires | F67: Deuxième trousse Hello | G67: 1708 | H67: Trousse Hello pingouin menthe | I67: 1 | J67: 2000 | K67: Principal | L67: Oui | M67: =IF(AND(L67="Oui",K67="Principal"),I67*J67,0) -> 2000 | N67: OK | P67: Cissé & Frères | Q67: 6j | R67: 1500 | S67: =IF(AND(L67="Oui",K67="Principal",R67<>""),I67*R67,0) -> 1500 | T67: =IF(R67<>"",M67-S67,0) -> 500 | U67: =IF(R67="",M67,0) -> 0
A68: Préscolaire | B68: Petite section | C68: Confort | D68: 28 | E68: Accessoires | F68: Gourde | G68: 1193 | H68: Gourde enfant motif ours Naughty Bear | I68: 1 | J68: 3100 | K68: Principal | L68: Oui | M68: =IF(AND(L68="Oui",K68="Principal"),I68*J68,0) -> 3100 | N68: OK | P68: LPD | Q68: 6j | R68: 2400 | S68: =IF(AND(L68="Oui",K68="Principal",R68<>""),I68*R68,0) -> 2400 | T68: =IF(R68<>"",M68-S68,0) -> 700 | U68: =IF(R68="",M68,0) -> 0
A69: Préscolaire | B69: Petite section | C69: Confort | D69: 29 | E69: Accessoires | F69: Cartable | G69: 1252 | H69: Cartable Kam Rad Cute Capybaras | I69: 1 | J69: 6500 | K69: Principal | L69: Oui | M69: =IF(AND(L69="Oui",K69="Principal"),I69*J69,0) -> 6500 | N69: OK | P69: LPD | Q69: 6j | R69: 6000 | S69: =IF(AND(L69="Oui",K69="Principal",R69<>""),I69*R69,0) -> 6000 | T69: =IF(R69<>"",M69-S69,0) -> 500 | U69: =IF(R69="",M69,0) -> 0
A70: Préscolaire | B70: Moyenne section | C70: Essentiel | D70: 1 | E70: Cahiers | F70: Cahier 96 pages petit format | G70: 1618 | H70: Cahier 96 pages petit format – 56g – seyès calligraphe | I70: 1 | J70: 450 | K70: Principal | L70: Oui | M70: =IF(AND(L70="Oui",K70="Principal"),I70*J70,0) -> 450 | N70: OK | O70: Graphisme / écriture | P70: Papex | Q70: 6j | R70: 350 | S70: =IF(AND(L70="Oui",K70="Principal",R70<>""),I70*R70,0) -> 350 | T70: =IF(R70<>"",M70-S70,0) -> 100 | U70: =IF(R70="",M70,0) -> 0
A71: Préscolaire | B71: Moyenne section | C71: Essentiel | D71: 2 | E71: Cahiers | F71: Cahier de travaux pratiques 200 pages | G71: 1729 | H71: Cahier de travaux pratiques MyFriend 200 pages | I71: 1 | J71: 1300 | K71: Principal | L71: Oui | M71: =IF(AND(L71="Oui",K71="Principal"),I71*J71,0) -> 1300 | N71: OK | O71: Cahier de vie | P71: LPD | Q71: 24h | S71: =IF(AND(L71="Oui",K71="Principal",R71<>""),I71*R71,0) -> 0 | T71: =IF(R71<>"",M71-S71,0) -> 0 | U71: =IF(R71="",M71,0) -> 1300
A72: Préscolaire | B72: Moyenne section | C72: Essentiel | D72: 3 | E72: Art & dessin | F72: Cahier de dessin | G72: 1572 | H72: Cahier de dessin L'écolier 32 pages | I72: 1 | J72: 250 | K72: Principal | L72: Oui | M72: =IF(AND(L72="Oui",K72="Principal"),I72*J72,0) -> 250 | N72: OK | P72: Papex | Q72: 6j | R72: 150 | S72: =IF(AND(L72="Oui",K72="Principal",R72<>""),I72*R72,0) -> 150 | T72: =IF(R72<>"",M72-S72,0) -> 100 | U72: =IF(R72="",M72,0) -> 0
A73: Préscolaire | B73: Moyenne section | C73: Essentiel | D73: 4 | E73: Ardoise | F73: Ardoise blanche avec feutre | G73: 33 | H73: Ardoise blanche + feutre effaçable | I73: 1 | J73: 1200 | K73: Principal | L73: Oui | M73: =IF(AND(L73="Oui",K73="Principal"),I73*J73,0) -> 1200 | N73: OK | P73: SacAdo | Q73: 24h | S73: =IF(AND(L73="Oui",K73="Principal",R73<>""),I73*R73,0) -> 0 | T73: =IF(R73<>"",M73-S73,0) -> 0 | U73: =IF(R73="",M73,0) -> 1200
A74: Préscolaire | B74: Moyenne section | C74: Essentiel | D74: 5 | E74: Ardoise | F74: Feutres pour ardoise | G74: 1698 | H74: Marqueur tableau blanc BEIYUE B-105 | I74: 2 | J74: 400 | K74: Principal | L74: Oui | M74: =IF(AND(L74="Oui",K74="Principal"),I74*J74,0) -> 800 | N74: OK | P74: Cissé & Frères | Q74: 6j | S74: =IF(AND(L74="Oui",K74="Principal",R74<>""),I74*R74,0) -> 0 | T74: =IF(R74<>"",M74-S74,0) -> 0 | U74: =IF(R74="",M74,0) -> 800
A75: Préscolaire | B75: Moyenne section | C75: Essentiel | D75: 6 | E75: Ardoise | F75: Effaceur d'ardoise | G75: 1244 | H75: Brosse tableau blanc magnetique RX T-29 | I75: 1 | J75: 400 | K75: Principal | L75: Oui | M75: =IF(AND(L75="Oui",K75="Principal"),I75*J75,0) -> 400 | N75: OK | P75: LPD | Q75: 6j | R75: 130 | S75: =IF(AND(L75="Oui",K75="Principal",R75<>""),I75*R75,0) -> 130 | T75: =IF(R75<>"",M75-S75,0) -> 270 | U75: =IF(R75="",M75,0) -> 0
A76: Préscolaire | B76: Moyenne section | C76: Essentiel | D76: 7 | E76: Écriture | F76: Crayon à papier HB | G76: 1571 | H76: Crayon papier couleur du Senegal - a l unite | I76: 2 | J76: 75 | K76: Principal | L76: Oui | M76: =IF(AND(L76="Oui",K76="Principal"),I76*J76,0) -> 150 | N76: OK | P76: LPD | Q76: 6j | S76: =IF(AND(L76="Oui",K76="Principal",R76<>""),I76*R76,0) -> 0 | T76: =IF(R76<>"",M76-S76,0) -> 0 | U76: =IF(R76="",M76,0) -> 150
A77: Préscolaire | B77: Moyenne section | C77: Essentiel | D77: 8 | E77: Petit matériel | F77: Gomme | G77: 9 | H77: Gomme blanche | I77: 1 | J77: 150 | K77: Principal | L77: Oui | M77: =IF(AND(L77="Oui",K77="Principal"),I77*J77,0) -> 150 | N77: OK | P77: SacAdo | Q77: 24h | S77: =IF(AND(L77="Oui",K77="Principal",R77<>""),I77*R77,0) -> 0 | T77: =IF(R77<>"",M77-S77,0) -> 0 | U77: =IF(R77="",M77,0) -> 150
A78: Préscolaire | B78: Moyenne section | C78: Essentiel | D78: 9 | E78: Petit matériel | F78: Taille-crayon avec réservoir | G78: 1587 | H78: Tailla Crayon 1 Trou + Réservoir Clean – MAPED | I78: 1 | J78: 500 | K78: Principal | L78: Oui | M78: =IF(AND(L78="Oui",K78="Principal"),I78*J78,0) -> 500 | N78: OK | P78: Papex | Q78: 6j | R78: 350 | S78: =IF(AND(L78="Oui",K78="Principal",R78<>""),I78*R78,0) -> 350 | T78: =IF(R78<>"",M78-S78,0) -> 150 | U78: =IF(R78="",M78,0) -> 0
A79: Préscolaire | B79: Moyenne section | C79: Essentiel | D79: 10 | E79: Art & dessin | F79: Crayons de couleur | G79: 1589 | H79: Crayon Couleur BTE X12 – MAPED | I79: 1 | J79: 900 | K79: Principal | L79: Oui | M79: =IF(AND(L79="Oui",K79="Principal"),I79*J79,0) -> 900 | N79: OK | P79: Papex | Q79: 6j | R79: 650 | S79: =IF(AND(L79="Oui",K79="Principal",R79<>""),I79*R79,0) -> 650 | T79: =IF(R79<>"",M79-S79,0) -> 250 | U79: =IF(R79="",M79,0) -> 0
A80: Préscolaire | B80: Moyenne section | C80: Essentiel | D80: 11 | E80: Petit matériel | F80: Bâtons de colle | G80: 1173 | H80: Baton de colle Dolphin Stick Glue | I80: 2 | J80: 570 | K80: Principal | L80: Oui | M80: =IF(AND(L80="Oui",K80="Principal"),I80*J80,0) -> 1140 | N80: OK | P80: LPD | Q80: 6j | R80: 420 | S80: =IF(AND(L80="Oui",K80="Principal",R80<>""),I80*R80,0) -> 840 | T80: =IF(R80<>"",M80-S80,0) -> 300 | U80: =IF(R80="",M80,0) -> 0
A81: Préscolaire | B81: Moyenne section | C81: Essentiel | D81: 12 | E81: Petit matériel | F81: Ciseaux à bouts ronds | G81: 1250 | H81: Ciseaux scolaires bouts ronds | I81: 1 | J81: 250 | K81: Principal | L81: Oui | M81: =IF(AND(L81="Oui",K81="Principal"),I81*J81,0) -> 250 | N81: OK | P81: LPD | Q81: 6j | R81: 100 | S81: =IF(AND(L81="Oui",K81="Principal",R81<>""),I81*R81,0) -> 100 | T81: =IF(R81<>"",M81-S81,0) -> 150 | U81: =IF(R81="",M81,0) -> 0
A82: Préscolaire | B82: Moyenne section | C82: Essentiel | D82: 13 | E82: Rangement | F82: Pochette à élastique | G82: 1625 | H82: Chemise. 3 rabats élastiques + étiquettes 4,5/10ème assorties | I82: 1 | J82: 500 | K82: Principal | L82: Oui | M82: =IF(AND(L82="Oui",K82="Principal"),I82*J82,0) -> 500 | N82: OK | P82: Papex | Q82: 6j | S82: =IF(AND(L82="Oui",K82="Principal",R82<>""),I82*R82,0) -> 0 | T82: =IF(R82<>"",M82-S82,0) -> 0 | U82: =IF(R82="",M82,0) -> 500
A83: Préscolaire | B83: Moyenne section | C83: Essentiel | D83: 14 | E83: Accessoires | F83: Trousse Hello | G83: 1706 | H83: Trousse Hello monstre vert | I83: 1 | J83: 2000 | K83: Principal | L83: Oui | M83: =IF(AND(L83="Oui",K83="Principal"),I83*J83,0) -> 2000 | N83: OK | P83: Cissé & Frères | Q83: 6j | R83: 1500 | S83: =IF(AND(L83="Oui",K83="Principal",R83<>""),I83*R83,0) -> 1500 | T83: =IF(R83<>"",M83-S83,0) -> 500 | U83: =IF(R83="",M83,0) -> 0
A84: Préscolaire | B84: Moyenne section | C84: Essentiel | D84: 15 | E84: Accessoires | F84: Gourde | G84: 1287 | H84: Gourde Drink violette | I84: 1 | J84: 2500 | K84: Principal | L84: Oui | M84: =IF(AND(L84="Oui",K84="Principal"),I84*J84,0) -> 2500 | N84: OK | O84: Nouveau prix : 2 500 F (ancien 2 000 F), à changer dans l'admin | P84: LPD | Q84: 6j | R84: 1800 | S84: =IF(AND(L84="Oui",K84="Principal",R84<>""),I84*R84,0) -> 1800 | T84: =IF(R84<>"",M84-S84,0) -> 700 | U84: =IF(R84="",M84,0) -> 0
A85: Préscolaire | B85: Moyenne section | C85: Essentiel | D85: 16 | E85: Option | F85: Cartable | G85: 1252 | H85: Cartable Kam Rad Cute Capybaras | I85: 1 | J85: 6500 | K85: Option | L85: Non | M85: =IF(AND(L85="Oui",K85="Principal"),I85*J85,0) -> 0 | N85: OK | P85: LPD | Q85: 6j | R85: 6000 | S85: =IF(AND(L85="Oui",K85="Principal",R85<>""),I85*R85,0) -> 0 | T85: =IF(R85<>"",M85-S85,0) -> 0 | U85: =IF(R85="",M85,0) -> 0
A86: Préscolaire | B86: Moyenne section | C86: Complet | D86: 1 | E86: Cahiers | F86: Cahier 96 pages petit format | G86: 1618 | H86: Cahier 96 pages petit format – 56g – seyès calligraphe | I86: 1 | J86: 450 | K86: Principal | L86: Oui | M86: =IF(AND(L86="Oui",K86="Principal"),I86*J86,0) -> 450 | N86: OK | O86: Graphisme / écriture | P86: Papex | Q86: 6j | R86: 350 | S86: =IF(AND(L86="Oui",K86="Principal",R86<>""),I86*R86,0) -> 350 | T86: =IF(R86<>"",M86-S86,0) -> 100 | U86: =IF(R86="",M86,0) -> 0
A87: Préscolaire | B87: Moyenne section | C87: Complet | D87: 2 | E87: Cahiers | F87: Cahier de travaux pratiques 200 pages | G87: 1729 | H87: Cahier de travaux pratiques MyFriend 200 pages | I87: 1 | J87: 1300 | K87: Principal | L87: Oui | M87: =IF(AND(L87="Oui",K87="Principal"),I87*J87,0) -> 1300 | N87: OK | O87: Cahier de vie | P87: LPD | Q87: 24h | S87: =IF(AND(L87="Oui",K87="Principal",R87<>""),I87*R87,0) -> 0 | T87: =IF(R87<>"",M87-S87,0) -> 0 | U87: =IF(R87="",M87,0) -> 1300
A88: Préscolaire | B88: Moyenne section | C88: Complet | D88: 3 | E88: Art & dessin | F88: Cahier de dessin | G88: 1286 | H88: Cahier de dessin TPG | I88: 1 | J88: 550 | K88: Principal | L88: Oui | M88: =IF(AND(L88="Oui",K88="Principal"),I88*J88,0) -> 550 | N88: OK | P88: LPD | Q88: 6j | R88: 450 | S88: =IF(AND(L88="Oui",K88="Principal",R88<>""),I88*R88,0) -> 450 | T88: =IF(R88<>"",M88-S88,0) -> 100 | U88: =IF(R88="",M88,0) -> 0
A89: Préscolaire | B89: Moyenne section | C89: Complet | D89: 4 | E89: Ardoise | F89: Ardoise blanche avec feutre | G89: 33 | H89: Ardoise blanche + feutre effaçable | I89: 1 | J89: 1200 | K89: Principal | L89: Oui | M89: =IF(AND(L89="Oui",K89="Principal"),I89*J89,0) -> 1200 | N89: OK | P89: SacAdo | Q89: 24h | S89: =IF(AND(L89="Oui",K89="Principal",R89<>""),I89*R89,0) -> 0 | T89: =IF(R89<>"",M89-S89,0) -> 0 | U89: =IF(R89="",M89,0) -> 1200
A90: Préscolaire | B90: Moyenne section | C90: Complet | D90: 5 | E90: Ardoise | F90: Feutres pour ardoise | G90: 1698 | H90: Marqueur tableau blanc BEIYUE B-105 | I90: 2 | J90: 400 | K90: Principal | L90: Oui | M90: =IF(AND(L90="Oui",K90="Principal"),I90*J90,0) -> 800 | N90: OK | P90: Cissé & Frères | Q90: 6j | S90: =IF(AND(L90="Oui",K90="Principal",R90<>""),I90*R90,0) -> 0 | T90: =IF(R90<>"",M90-S90,0) -> 0 | U90: =IF(R90="",M90,0) -> 800
A91: Préscolaire | B91: Moyenne section | C91: Complet | D91: 6 | E91: Ardoise | F91: Effaceur d'ardoise | G91: 1244 | H91: Brosse tableau blanc magnetique RX T-29 | I91: 1 | J91: 400 | K91: Principal | L91: Oui | M91: =IF(AND(L91="Oui",K91="Principal"),I91*J91,0) -> 400 | N91: OK | P91: LPD | Q91: 6j | R91: 130 | S91: =IF(AND(L91="Oui",K91="Principal",R91<>""),I91*R91,0) -> 130 | T91: =IF(R91<>"",M91-S91,0) -> 270 | U91: =IF(R91="",M91,0) -> 0
A92: Préscolaire | B92: Moyenne section | C92: Complet | D92: 7 | E92: Écriture | F92: Crayon à papier HB | G92: 1571 | H92: Crayon papier couleur du Senegal - a l unite | I92: 2 | J92: 75 | K92: Principal | L92: Oui | M92: =IF(AND(L92="Oui",K92="Principal"),I92*J92,0) -> 150 | N92: OK | P92: LPD | Q92: 6j | S92: =IF(AND(L92="Oui",K92="Principal",R92<>""),I92*R92,0) -> 0 | T92: =IF(R92<>"",M92-S92,0) -> 0 | U92: =IF(R92="",M92,0) -> 150
A93: Préscolaire | B93: Moyenne section | C93: Complet | D93: 8 | E93: Petit matériel | F93: Gomme | G93: 1181 | H93: Gomme Staedtler Mars Plastic | I93: 1 | J93: 250 | K93: Principal | L93: Oui | M93: =IF(AND(L93="Oui",K93="Principal"),I93*J93,0) -> 250 | N93: OK | P93: LPD | Q93: 6j | R93: 110 | S93: =IF(AND(L93="Oui",K93="Principal",R93<>""),I93*R93,0) -> 110 | T93: =IF(R93<>"",M93-S93,0) -> 140 | U93: =IF(R93="",M93,0) -> 0
A94: Préscolaire | B94: Moyenne section | C94: Complet | D94: 9 | E94: Petit matériel | F94: Taille-crayon avec réservoir | G94: 1587 | H94: Tailla Crayon 1 Trou + Réservoir Clean – MAPED | I94: 1 | J94: 500 | K94: Principal | L94: Oui | M94: =IF(AND(L94="Oui",K94="Principal"),I94*J94,0) -> 500 | N94: OK | P94: Papex | Q94: 6j | R94: 350 | S94: =IF(AND(L94="Oui",K94="Principal",R94<>""),I94*R94,0) -> 350 | T94: =IF(R94<>"",M94-S94,0) -> 150 | U94: =IF(R94="",M94,0) -> 0
A95: Préscolaire | B95: Moyenne section | C95: Complet | D95: 10 | E95: Art & dessin | F95: Crayons de couleur | G95: 1589 | H95: Crayon Couleur BTE X12 – MAPED | I95: 1 | J95: 900 | K95: Principal | L95: Oui | M95: =IF(AND(L95="Oui",K95="Principal"),I95*J95,0) -> 900 | N95: OK | P95: Papex | Q95: 6j | R95: 650 | S95: =IF(AND(L95="Oui",K95="Principal",R95<>""),I95*R95,0) -> 650 | T95: =IF(R95<>"",M95-S95,0) -> 250 | U95: =IF(R95="",M95,0) -> 0
A96: Préscolaire | B96: Moyenne section | C96: Complet | D96: 11 | E96: Petit matériel | F96: Bâtons de colle | G96: 1604 | H96: Bâton de colle 20 g – GIOTTO | I96: 2 | J96: 700 | K96: Principal | L96: Oui | M96: =IF(AND(L96="Oui",K96="Principal"),I96*J96,0) -> 1400 | N96: OK | P96: Papex | Q96: 6j | R96: 400 | S96: =IF(AND(L96="Oui",K96="Principal",R96<>""),I96*R96,0) -> 800 | T96: =IF(R96<>"",M96-S96,0) -> 600 | U96: =IF(R96="",M96,0) -> 0
A97: Préscolaire | B97: Moyenne section | C97: Complet | D97: 12 | E97: Petit matériel | F97: Ciseaux à bouts ronds | G97: 1586 | H97: Ciseaux 13cm Security Stop – MAPED | I97: 1 | J97: 900 | K97: Principal | L97: Oui | M97: =IF(AND(L97="Oui",K97="Principal"),I97*J97,0) -> 900 | N97: OK | P97: Papex | Q97: 6j | R97: 650 | S97: =IF(AND(L97="Oui",K97="Principal",R97<>""),I97*R97,0) -> 650 | T97: =IF(R97<>"",M97-S97,0) -> 250 | U97: =IF(R97="",M97,0) -> 0
A98: Préscolaire | B98: Moyenne section | C98: Complet | D98: 13 | E98: Rangement | F98: Pochette à élastique | G98: 1625 | H98: Chemise. 3 rabats élastiques + étiquettes 4,5/10ème assorties | I98: 1 | J98: 500 | K98: Principal | L98: Oui | M98: =IF(AND(L98="Oui",K98="Principal"),I98*J98,0) -> 500 | N98: OK | P98: Papex | Q98: 6j | S98: =IF(AND(L98="Oui",K98="Principal",R98<>""),I98*R98,0) -> 0 | T98: =IF(R98<>"",M98-S98,0) -> 0 | U98: =IF(R98="",M98,0) -> 500
A99: Préscolaire | B99: Moyenne section | C99: Complet | D99: 14 | E99: Art & dessin | F99: Feutres de couleur | G99: 1204 | H99: Feutres Giotto Turbo Color 12 couleurs | I99: 1 | J99: 1300 | K99: Principal | L99: Oui | M99: =IF(AND(L99="Oui",K99="Principal"),I99*J99,0) -> 1300 | N99: OK | P99: LPD | Q99: 6j | R99: 1000 | S99: =IF(AND(L99="Oui",K99="Principal",R99<>""),I99*R99,0) -> 1000 | T99: =IF(R99<>"",M99-S99,0) -> 300 | U99: =IF(R99="",M99,0) -> 0
A100: Préscolaire | B100: Moyenne section | C100: Complet | D100: 15 | E100: Art & dessin | F100: Pâte à modeler | H100: — pas au catalogue — | I100: 1 | J100: 0 | K100: Principal | L100: Non | M100: =IF(AND(L100="Oui",K100="Principal"),I100*J100,0) -> 0 | N100: MANQUE | O100: Pas au catalogue | S100: =IF(AND(L100="Oui",K100="Principal",R100<>""),I100*R100,0) -> 0 | T100: =IF(R100<>"",M100-S100,0) -> 0 | U100: =IF(R100="",M100,0) -> 0
...

Sheet À sourcer
A1: À sourcer, à créer et à vérifier
A3: Articles de tes listes absents du catalogue
A4: Article | B4: Classes et gammes concernées | C4: Nombre de kits | D4: Ce qu'il faut chercher | E4: Ce que j'ai mis en attendant
A5: Papier millimétré | B5: 4e (Complet, Confort); 3e (Complet, Confort); Seconde L (Complet, Confort); Seconde S (Complet, Confort); Première L1 (Complet, Confort); Première L2 (Complet, Confort); Première S1 (Complet, Confort); Première S2 (Complet, Confort); Terminale L1 (Complet, Confort); Terminale L2 (Complet, Confort); Terminale S1 (Complet, Confort); Terminale S2 (Complet, Confort) | C5: 24 | D5: Pochette de papier millimétré A4 (10 à 20 feuilles) | E5: Ligne affichée, non comptée
A6: Copies simples | B6: Seconde L (Complet, Confort); Seconde S (Complet, Confort); Première S1 (Complet, Confort); Première S2 (Complet, Confort); Terminale S1 (Complet, Confort); Terminale S2 (Complet, Confort) | C6: 12 | D6: Paquet de copies simples grand format (feuilles perforées seyès) | E6: Ligne affichée, non comptée
A7: Pâte à modeler | B7: Petite section (Complet, Confort); Moyenne section (Complet, Confort); Grande section (Complet, Confort) | C7: 6 | D7: Boîte de pâte à modeler enfant (6 à 12 couleurs), 500 à 1 500 F | E7: Ligne affichée, non comptée
A8: Tablier de peinture | B8: Petite section (Complet, Confort); Moyenne section (Complet, Confort); Grande section (Complet, Confort) | C8: 6 | D8: Tablier enfant imperméable à manches, taille 3-6 ans | E8: Ligne affichée, non comptée
A9: Phèdre (Racine) | B9: Seconde L; Seconde S | C9: 6 | D9: Édition classique de poche (Larousse, Hatier, Folio) | E9: Ligne affichée, non comptée
A10: Chants d'ombre (Léopold Sédar Senghor) | B10: Terminale L1; Terminale L2 | C10: 6 | D10: Édition Seuil (Points poésie) | E10: Ligne affichée, non comptée
A11: Gommettes | B11: Petite section (Complet, Confort); Moyenne section (Confort); Grande section (Confort) | C11: 4 | D11: Pochette de gommettes (formes géométriques de couleur) | E11: Ligne affichée, non comptée
A12: Les Misérables (Victor Hugo) | B12: Première L1 (Confort); Première L2 (Confort); Terminale L1 (Confort); Terminale L2 (Confort) | C12: 4 | D12: Édition de poche abrégée ou intégrale (Folio, Livre de poche, Hachette classiques) | E12: Ligne affichée, non comptée
A13: Papier Canson couleur | B13: Petite section (Confort); Moyenne section (Confort); Grande section (Confort) | C13: 3 | D13: Pochette de papier Canson couleur A4 (10 à 12 feuilles) | E13: Ligne affichée, non comptée
A14: Cahier double ligne (écriture) | B14: CP | C14: 3 | D14: Cahier d'écriture double ligne petit format (CP) | E14: Ligne affichée, non comptée
A15: Le Français en 6e (EDICEF) | B15: 6e | C15: 3 | D15: Chez LPD, comme les éditions 5e et 3e | E15: Ligne affichée, non comptée
A16: Keep in Touch 6e, Student's Book | B16: 6e | C16: 3 | D16: Chez LPD, comme les éditions 3e et 4e | E16: Ligne affichée, non comptée
... A35: Livre de cours et exercices TS2 (Cheikh Tidiane Seck) | B35: Terminale S2 (Confort) | C35: 1 | D35: Librairies de Dakar (auteur Cheikh Tidiane Seck) | E35: Ligne affichée, non comptée
A37: Produits à créer dans l'admin (déjà comptés dans les prix)
A38: Produit | B38: Classes et gammes concernées | C38: Nombre de kits | D38: Fiche à créer | E38: Code provisoire
A39: Craie blanche Giotto Robercolor (à l'unité) | B39: CI; CP; CE1; CE2; CM1; CM2 | C39: 18 | D39: Vendeur LPD, prix 25 F l'unité, même photo que la boîte 1299. 20 craies par kit, du CI au CM2. | E39: CRAIE-U
A40: Je me débrouille en anglais (John Smith) | B40: Seconde L (Confort); Première L1 (Confort); Première L2 (Confort); Terminale L1 (Confort); Terminale L2 (Confort) | C40: 5 | D40: Vendeur LPD, prix d'achat 2 000 F, prix de vente 3 000 F, catégorie Livres et annales, photo fournie (WebP). | E40: ANGLAIS-JMD
A41: Dictionnaire Larousse de français de poche, 60 000 mots | B41: Seconde L (Confort); Première L1 (Confort); Première L2 (Confort); Terminale L1 (Confort); Terminale L2 (Confort) | C41: 5 | D41: Prix d'achat 2 000 F, prix de vente 2 750 F, catégorie Livres et annales, photo fournie (WebP). Remplace Le Robert 1682 dans les kits. | E41: LAROUSSE-60
A43: Au catalogue mais à vérifier
A44: Produit | B44: Classes et gammes concernées | C44: Nombre de kits | D44: Pourquoi | E44: Produit mis
A45: Matériel géométrique | B45: CE1; CE2; CM1; CM2; 6e; 5e; 4e; 3e; Seconde L; Seconde S; Première L1; Première L2; Première S1; Première S2; Terminale L1; Terminale L2; Terminale S1; Terminale S2 | C45: 54 | D45: Boîte complète (compas, rapporteur, équerres, règle) : vérifier le contenu exact avec LPD | E45: 1229 · Boite instruments Marshal Mathematical Instruments · 1 800 F
A46: Porte-vues | B46: Seconde L (Complet, Confort); Seconde S (Complet, Confort); Première L1 (Complet, Confort); Première L2 (Complet, Confort); Première S1 (Complet, Confort); Première S2 (Complet, Confort); Terminale L1 (Complet, Confort); Terminale L2 (Complet, Confort); Terminale S1 (Complet, Confort); Terminale S2 (Complet, Confort) | C46: 20 | D46: Ta liste demande 40 vues : nombre de vues non indiqué sur la fiche | E46: 1269 · Protege-documents porte-vues couleurs · 1 150 F
A47: Cahier de textes | B47: 6e; 5e; 4e; 3e | C47: 12 | D47: « Journal de classe » = cahier de textes : vérifier le format | E47: 1271 · Mon journal de classe pratique · 1 150 F
A48: Papier à dessin | B48: 6e (Complet, Confort); 5e (Complet, Confort); 4e (Complet, Confort); 3e (Complet, Confort) | C48: 8 | D48: Remplace la pochette Canson (pas au catalogue) | E48: 31 · Bloc de dessin A4 (50 feuilles) · 1 500 F
A49: Physique-Chimie 1ère S (Korka Diallo) | B49: Première S1; Première S2 | C49: 6 | D49: Fiche au nom de Sidy Mohamed Ndiaye (collection Atomic) : vérifier | E49: 51 · PHYSIQUE CHIMIE PREMIERE S · 8 000 F
A50: SVT 1ère S (Korka Diallo) | B50: Première S1; Première S2 (Confort) | C50: 4 | D50: « SVT Première S1 S2 L », collection Adansonia : vérifier | E50: 54 · SVT PREMIERE S1 S2 L · 15 000 F
A51: Bloc de dessin blanc A4 | B51: Petite section (Confort); Moyenne section (Confort); Grande section (Confort) | C51: 3 | D51: Remplace la pochette Canson blanc | E51: 31 · Bloc de dessin A4 (50 feuilles) · 1 500 F
A52: Langue et communication CI (Ami et Rémi) | B52: CI | C52: 3 | D52: Ta liste dit « Livre de lecture Ami et Rémi CI » : c'est le seul Ami et Rémi CI au catalogue | E52: 1391 · Langue et Communication Ami et Rémi CI · 3 900 F
A53: Langue et communication CM2 (Didactikos) | B53: CM2 | C53: 3 | D53: Produit en attente de modération : à approuver dans l'admin | E53: 1509 · Langue et communication C.M.2 · 5 000 F
A54: Mathématiques 1ère S (Korka Diallo) | B54: Première S1 | C54: 3 | D54: Maths 1S1, Cracks en maths (existe aussi Kaamile 1S1 à 20 000 F, 46) | E54: 47 · MATHS 1S1 (CRACKS EN MATHS) · 15 000 F
A55: Maths Terminale S1 (Korka Diallo) | B55: Terminale S1 | C55: 3 | D55: Kaamile de maths TS1 TS3 à 35 000 F : vérifier que c'est bien ce livre | E55: 58 · KAAMILE DE MATHS - TS1 TS3 · 35 000 F
A56: SVT Terminale S1 (Korka Diallo) | B56: Terminale S1 | C56: 3 | D56: « SVT Terminale S1 S2 » sans auteur : vérifier | E56: 69 · SVT TERMINALE S1 S2 (tout le programme, S et L) · 15 000 F
... A67: Fascicule d'exercices SVT 1ère | B67: Première S2 (Confort) | C67: 1 | D67: « SVT Première : cours et exercices » (Mamadou Senghor) | E67: 55 · SVT PREMIERE : COURS ET EXERCICES (NON CORRIGES) · 12 000 F
A69: Produits sans prix d'achat (bénéfice non calculé)
A70: Produit | B70: Classes et gammes concernées | C70: Nombre de kits | D70: Prix d'achat à renseigner | E70: Prix de vente
A71: 19 · Trousse scolaire double compartiment | B71: CI; CP; CE1; CE2; CM1; CM2; 6e; 5e; 4e; 3e; Seconde L; Seconde S; Première L1; Première L2; Première S1; Première S2; Terminale L1; Terminale L2; Terminale S1; Terminale S2 | C71: 60 | D71: Vide dans l'export | E71: 2 500 F
A72: 1 · Cahier 96 pages grand format | B72: 6e; 5e; 4e; 3e; Seconde L; Seconde S; Première L1; Première L2; Première S1; Première S2; Terminale L1; Terminale L2; Terminale S1; Terminale S2 | C72: 42 | D72: Vide dans l'export | E72: 500 F
A73: 8 · Crayons à papier HB (lot de 3) | B73: CI (Complet, Confort); CP (Complet, Confort); CE1 (Complet, Confort); CE2 (Complet, Confort); CM1 (Complet, Confort); CM2 (Complet, Confort); 6e (Complet, Confort); 5e (Complet, Confort); 4e (Complet, Confort); 3e (Complet, Confort); Seconde L (Complet, Confort); Seconde S (Complet, Confort); Première L1 (Complet, Confort); Première L2 (Complet, Confort); Première S1 (Complet, Confort); Première S2 (Complet, Confort); Terminale L1 (Complet, Confort); Terminale L2 (Complet, Confort); Terminale S1 (Complet, Confort); Terminale S2 (Complet, Confort) | C73: 40 | D73: Vide dans l'export | E73: 500 F
A74: 1728 · Cahier de travaux pratiques MyFriend 100 pages | B74: Petite section; 6e; 5e; 4e; 3e; Seconde L; Première L1; Première L2; Terminale L1; Terminale L2 | C74: 30 | D74: Vide dans l'export | E74: 900 F
A75: 1571 · Crayon papier couleur du Senegal - a l unite | B75: Petite section; Moyenne section; Grande section; CI (Essentiel); CP (Essentiel); CE1 (Essentiel); CE2 (Essentiel); CM1 (Essentiel); CM2 (Essentiel); 6e (Essentiel); 5e (Essentiel); 4e (Essentiel); 3e (Essentiel); Seconde L (Essentiel); Seconde S (Essentiel); Première L1 (Essentiel); Première L2 (Essentiel); Première S1 (Essentiel); Première S2 (Essentiel); Terminale L1 (Essentiel); Terminale L2 (Essentiel); Terminale S1 (Essentiel); Terminale S2 (Essentiel) | C75: 29 | D75: Vide dans l'export | E75: 75 F
A76: 1729 · Cahier de travaux pratiques MyFriend 200 pages | B76: Petite section; Moyenne section; Grande section; Seconde S; Première S1; Première S2; Terminale S1; Terminale S2 | C76: 24 | D76: Vide dans l'export | E76: 1 300 F
A77: 9 · Gomme blanche | B77: Petite section (Essentiel); Moyenne section (Essentiel); Grande section (Essentiel); CI (Essentiel); CP (Essentiel); CE1 (Essentiel); CE2 (Essentiel); CM1 (Essentiel); CM2 (Essentiel); 6e (Essentiel); 5e (Essentiel); 4e (Essentiel); 3e (Essentiel); Seconde L (Essentiel); Seconde S (Essentiel); Première L1 (Essentiel); Première L2 (Essentiel); Première S1 (Essentiel); Première S2 (Essentiel); Terminale L1 (Essentiel); Terminale L2 (Essentiel); Terminale S1 (Essentiel); Terminale S2 (Essentiel) | C77: 23 | D77: Vide dans l'export | E77: 150 F
A78: 1683 · Intercalaires carte Exacompta 6 positions | B78: Seconde L (Complet, Confort); Seconde S (Complet, Confort); Première L1 (Complet, Confort); Première L2 (Complet, Confort); Première S1 (Complet, Confort); Première S2 (Complet, Confort); Terminale L1 (Complet, Confort); Terminale L2 (Complet, Confort); Terminale S1 (Complet, Confort); Terminale S2 (Complet, Confort) | C78: 20 | D78: Vide dans l'export | E78: 1 000 F
A79: 1277 · Protège-cahiers couleurs | B79: CI; CP; CE1; CE2; CM1; CM2 | C79: 18 | D79: Achat plus cher que la vente dans l'export : à vérifier | E79: 150 F
A80: 1625 · Chemise. 3 rabats élastiques + étiquettes 4,5/10ème assorties | B80: Petite section; Moyenne section; Grande section; 6e (Complet, Confort); 5e (Complet, Confort); 4e (Complet, Confort); 3e (Complet, Confort) | C80: 17 | D80: Vide dans l'export | E80: 500 F
A81: 10 · Taille-crayon métallique | B81: CI (Essentiel); CE1 (Essentiel); CE2 (Essentiel); 6e (Essentiel); 5e (Essentiel); 4e (Essentiel); 3e (Essentiel); Seconde L (Essentiel); Seconde S (Essentiel); Première L1 (Essentiel); Première L2 (Essentiel); Première S1 (Essentiel); Première S2 (Essentiel); Terminale L1 (Essentiel); Terminale L2 (Essentiel); Terminale S1 (Essentiel); Terminale S2 (Essentiel) | C81: 17 | D81: Vide dans l'export | E81: 200 F
A82: 2 · Cahier 192 pages grand format | B82: 5e (Essentiel); 4e (Essentiel); 3e (Essentiel); Seconde L (Essentiel); Seconde S (Essentiel); Première L1 (Essentiel); Première L2 (Essentiel); Première S1 (Essentiel); Première S2 (Essentiel); Terminale L1 (Essentiel); Terminale L2 (Essentiel); Terminale S1 (Essentiel); Terminale S2 (Essentiel) | C82: 13 | D82: Vide dans l'export | E82: 900 F
... A88: 30 · Pinceaux assortis (lot de 5) | B88: Petite section (Confort); Moyenne section (Confort); Grande section (Confort) | C88: 3 | D88: Vide dans l'export | E88: 1 000 F
A90: Stock à surveiller
A91: Produit | B91: Classes et gammes concernées | C91: Nombre de kits | D91: Stock actuel | E91: Risque
A92: 1727 · Casio fx-991ES Plus | B92: 6e (Complet, Confort); 5e (Complet, Confort); 4e (Complet, Confort); 3e (Complet, Confort); Seconde S; Première S1; Première S2; Terminale S1; Terminale S2 | C92: 23 | D92: 14 | E92: Au lycée elle est dans les 3 gammes : le stock part vite. À réapprovisionner avant la rentrée.

Sheet À faire dans l'admin
A1: À faire dans l'admin (avant ou pendant l'import)
A3: 1. Créer « Craie blanche Giotto Robercolor (à l'unité) » : vendeur LPD, 25 F, photo de la boîte 1299. Code provisoire CRAIE-U.
A4: 2. Créer « Je me débrouille en anglais » (John Smith) : vendeur LPD, achat 2 000 F, vente 3 000 F, photo prod-je-me-debrouille-en-anglais.webp. Code provisoire ANGLAIS-JMD.
A5: 3. Créer « Dictionnaire Larousse de français de poche, 60 000 mots » : achat 2 000 F, vente 2 750 F, photo prod-dictionnaire-larousse-poche.webp. Code provisoire LAROUSSE-60.
A6: 4. Changer le prix de 1287 « Gourde Drink violette » : 2 500 F (au lieu de 2 000 F).
A7: 5. Renseigner le prix d'achat des produits qui n'en ont pas (cahiers SacAdo 1 et 2, trousse 19, cahiers TP MyFriend 1728 et 1729, gomme 9, taille-crayon 10, crayons 8, etc. : liste dans « À sourcer »).
A8: 6. Corriger le prix d'achat de 1277 Protège-cahiers (650 F pour une vente à 150 F) et de 1183 Règle 20 cm (150 F pour une vente à 100 F) : probablement le prix d'un lot.
A9: 7. Masquer les 9 kits de la série T, encore publiés dans l'export : 502, 503, 504 (Seconde T), 517, 518, 519 (Première T), 538, 539, 540 (Terminale T).
A10: 8. Approuver le produit 1509 « Langue et communication C.M.2 » (toujours en attente de modération).
A11: 9. Réapprovisionner la Casio fx-991ES 1727 (stock 14) : elle est maintenant dans 23 kits.
A12: 10. Première S1 / S2 : ton premier tableau de Première est mis en S2 et celui avec les 3 concours généraux en S1. À inverser si c'est l'inverse.
A13: 11. Tes tableaux « 1ère L » et « Tle L » sont appliqués à L1 et L2 (Première L et Terminale L sont masqués). Les autres séries (STEG, SA, LA, L-AR, S1A, S2A) ne changent pas.
