Workbook

Sheet Lisez-moi
A1: Kits SacAdo : du CI à la Terminale (L, S1, S2, STEG)
A2: Version 10 du 26/09/2026. Même contenu que kits.json.
A4: Les trois gammes, de la moins chère à la plus chère
A5: Essentiel : les fournitures indispensables, avec l'article correct le moins cher. Les livres du Complet sont affichés en dessous, décochés : le client peut les ajouter.
A6: Complet : toute la liste en fournitures de meilleure qualité (Calligraphe, Maped), plus les œuvres au programme, et au primaire les manuels Didactikos de la liste. Calculatrice scientifique générique. Collège, lycée et STEG : un protège-cahier par cahier.
A7: Confort : le Complet, plus les manuels scolaires (collège et lycée), la Casio fx-92 à la place de la calculatrice générique, stylo 4 couleurs, correcteur, et des livres en plus : œuvres « bon à avoir » en L, La Clé des Cracks et parascolaire scientifique en 3e et en S (éditions S1 ou S2 selon la série).
A8: Dans chaque kit, chaque produit peut être décoché (colonne « Coché par défaut »). Sac en option décochée. Pas d'ebook pour l'instant.
A10: À faire avant publication
A11: 1. Reporter dans Articles l'ID et le prix de l'app pour les copies doubles et les deux Calligraphe grand format (lignes A-CREER).
A12: 2. Livres Korka Diallo (lignes CDC) : titres et prix réels du catalogue Korka depuis le 26/09.
A13: 3. Corriger les prix signalés dans la feuille Écarts Edushop (lignes orange).
A15: Séries techniques
... A29: Feuilles de classe : ID et quantité (en bleu) modifiables. Statut vente : « Fixé », « Estimé », « À trancher », « À fournir ». Statut achat : « Confirmé », « Estimé », « Inconnu ».

Sheet Récap
A1: Classe | B1: Gamme | C1: Nb de lignes | D1: Nb de cahiers | E1: Total vente (FCFA) | F1: Coût de revient connu (FCFA) | G1: Marge sur coût connu (FCFA) | H1: Part du PV estimée | I1: Statut | J1: Nb de manquants | K1: Essentiel + livres cochés (FCFA)
A2: CI | B2: Essentiel | C2: =COUNTA(CI!C6:C12) -> 7 | D2: =CI!H18 -> 2 | E2: =CI!H14 -> 4225 | F2: =CI!H15 -> 1600 | G2: =CI!H17 -> 750 | H2: =CI!H19 -> 0.34319527 | I2: =CI!H20 -> Coût incomplet : 4 ligne(s) sans prix d'achat | J2: 1 | K2: =CI!H26 -> 15895
A3: CI | B3: Complet | C3: =COUNTA(CI!C33:C42) -> 10 | D3: =CI!H48 -> 2 | E3: =CI!H44 -> 18995 | F3: =CI!H45 -> 12570 | G3: =CI!H47 -> 4650 | H3: =CI!H49 -> 0.084232693 | I3: =CI!H50 -> Coût incomplet : 3 ligne(s) sans prix d'achat | J3: 1
A4: CI | B4: Confort | C4: =COUNTA(CI!C57:C68) -> 12 | D4: =CI!H74 -> 2 | E4: =CI!H70 -> 24575 | F4: =CI!H71 -> 16150 | G4: =CI!H73 -> 6650 | H4: =CI!H75 -> 0.065106816 | I4: =CI!H76 -> Coût incomplet : 3 ligne(s) sans prix d'achat | J4: 1
A5: CP | B5: Essentiel | C5: =COUNTA(CP!C6:C12) -> 7 | D5: =CP!H18 -> 2 | E5: =CP!H14 -> 4000 | F5: =CP!H15 -> 2600 | G5: =CP!H17 -> 1000 | H5: =CP!H19 -> 0.45 | I5: =CP!H20 -> Coût incomplet : 3 ligne(s) sans prix d'achat | J5: 0 | K5: =CP!H26 -> 15670
A6: CP | B6: Complet | C6: =COUNTA(CP!C33:C42) -> 10 | D6: =CP!H48 -> 2 | E6: =CP!H44 -> 19920 | F6: =CP!H45 -> 14670 | G6: =CP!H47 -> 4950 | H6: =CP!H49 -> 0.17068273 | I6: =CP!H50 -> Coût incomplet : 2 ligne(s) sans prix d'achat | J6: 0
A7: CP | B7: Confort | C7: =COUNTA(CP!C57:C68) -> 12 | D7: =CP!H74 -> 2 | E7: =CP!H70 -> 25500 | F7: =CP!H71 -> 18250 | G7: =CP!H73 -> 6950 | H7: =CP!H75 -> 0.13333333 | I7: =CP!H76 -> Coût incomplet : 2 ligne(s) sans prix d'achat | J7: 0
A8: CE1 | B8: Essentiel | C8: =COUNTA(CE1!C6:C13) -> 8 | D8: =CE1!H19 -> 4 | E8: =CE1!H15 -> 5025 | F8: =CE1!H16 -> 3410 | G8: =CE1!H18 -> 1340 | H8: =CE1!H20 -> 0.35820896 | I8: =CE1!H21 -> Coût incomplet : 3 ligne(s) sans prix d'achat | J8: 0 | K8: =CE1!H27 -> 17025
A9: CE1 | B9: Complet | C9: =COUNTA(CE1!C34:C44) -> 11 | D9: =CE1!H50 -> 4 | E9: =CE1!H46 -> 21425 | F9: =CE1!H47 -> 16010 | G9: =CE1!H49 -> 5140 | H9: =CE1!H51 -> 0.15869312 | I9: =CE1!H52 -> Coût incomplet : 3 ligne(s) sans prix d'achat | J9: 0
A10: CE1 | B10: Confort | C10: =COUNTA(CE1!C59:C71) -> 13 | D10: =CE1!H77 -> 4 | E10: =CE1!H73 -> 27445 | F10: =CE1!H74 -> 20030 | G10: =CE1!H76 -> 7140 | H10: =CE1!H78 -> 0.12388413 | I10: =CE1!H79 -> Coût incomplet : 3 ligne(s) sans prix d'achat | J10: 0
A11: CE2 | B11: Essentiel | C11: =COUNTA(CE2!C6:C13) -> 8 | D11: =CE2!H19 -> 4 | E11: =CE2!H15 -> 5025 | F11: =CE2!H16 -> 3410 | G11: =CE2!H18 -> 1340 | H11: =CE2!H20 -> 0.35820896 | I11: =CE2!H21 -> Coût incomplet : 3 ligne(s) sans prix d'achat | J11: 0 | K11: =CE2!H27 -> 17025
A12: CE2 | B12: Complet | C12: =COUNTA(CE2!C34:C44) -> 11 | D12: =CE2!H50 -> 4 | E12: =CE2!H46 -> 21425 | F12: =CE2!H47 -> 16010 | G12: =CE2!H49 -> 5140 | H12: =CE2!H51 -> 0.15869312 | I12: =CE2!H52 -> Coût incomplet : 3 ligne(s) sans prix d'achat | J12: 0
A13: CE2 | B13: Confort | C13: =COUNTA(CE2!C59:C71) -> 13 | D13: =CE2!H77 -> 4 | E13: =CE2!H73 -> 27445 | F13: =CE2!H74 -> 20030 | G13: =CE2!H76 -> 7140 | H13: =CE2!H78 -> 0.12388413 | I13: =CE2!H79 -> Coût incomplet : 3 ligne(s) sans prix d'achat | J13: 0
A14: CM1 | B14: Essentiel | C14: =COUNTA(CM1!C6:C13) -> 8 | D14: =CM1!H19 -> 4 | E14: =CM1!H15 -> 5025 | F14: =CM1!H16 -> 3410 | G14: =CM1!H18 -> 1340 | H14: =CM1!H20 -> 0.35820896 | I14: =CM1!H21 -> Coût incomplet : 3 ligne(s) sans prix d'achat | J14: 0 | K14: =CM1!H27 -> 17025
A15: CM1 | B15: Complet | C15: =COUNTA(CM1!C34:C44) -> 11 | D15: =CM1!H50 -> 4 | E15: =CM1!H46 -> 21425 | F15: =CM1!H47 -> 16010 | G15: =CM1!H49 -> 5140 | H15: =CM1!H51 -> 0.15869312 | I15: =CM1!H52 -> Coût incomplet : 3 ligne(s) sans prix d'achat | J15: 0
A16: CM1 | B16: Confort | C16: =COUNTA(CM1!C59:C71) -> 13 | D16: =CM1!H77 -> 4 | E16: =CM1!H73 -> 27905 | F16: =CM1!H74 -> 20490 | G16: =CM1!H76 -> 7140 | H16: =CM1!H78 -> 0.12184196 | I16: =CM1!H79 -> Coût incomplet : 3 ligne(s) sans prix d'achat | J16: 0
A17: CM2 | B17: Essentiel | C17: =COUNTA(CM2!C6:C13) -> 8 | D17: =CM2!H19 -> 4 | E17: =CM2!H15 -> 5025 | F17: =CM2!H16 -> 3410 | G17: =CM2!H18 -> 1340 | H17: =CM2!H20 -> 0.35820896 | I17: =CM2!H21 -> Coût incomplet : 3 ligne(s) sans prix d'achat | J17: 0 | K17: =CM2!H27 -> 17025
A18: CM2 | B18: Complet | C18: =COUNTA(CM2!C34:C44) -> 11 | D18: =CM2!H50 -> 4 | E18: =CM2!H46 -> 21425 | F18: =CM2!H47 -> 16010 | G18: =CM2!H49 -> 5140 | H18: =CM2!H51 -> 0.15869312 | I18: =CM2!H52 -> Coût incomplet : 3 ligne(s) sans prix d'achat | J18: 0
A19: CM2 | B19: Confort | C19: =COUNTA(CM2!C59:C71) -> 13 | D19: =CM2!H77 -> 4 | E19: =CM2!H73 -> 30575 | F19: =CM2!H74 -> 23160 | G19: =CM2!H76 -> 7140 | H19: =CM2!H78 -> 0.11120196 | I19: =CM2!H79 -> Coût incomplet : 3 ligne(s) sans prix d'achat | J19: 0
A20: 6e | B20: Essentiel | C20: =COUNTA(6e!C6:C26) -> 21 | D20: =6e!H32 -> 11 | E20: =6e!H28 -> 11550 | F20: =6e!H29 -> 8135 | G20: =6e!H31 -> 2940 | H20: =6e!H33 -> 0.56926407 | I20: =6e!H34 -> Coût incomplet : 2 ligne(s) sans prix d'achat | J20: 0 | K20: =6e!H38 -> 15050
A21: 6e | B21: Complet | C21: =COUNTA(6e!C45:C70) -> 26 | D21: =6e!H76 -> 11 | E21: =6e!H72 -> 29625 | F21: =6e!H73 -> 22160 | G21: =6e!H75 -> 4890 | H21: =6e!H77 -> 0.27004219 | I21: =6e!H78 -> Total incomplet : 1 prix de vente à fournir | J21: 2
A22: 6e | B22: Confort | C22: =COUNTA(6e!C86:C121) -> 36 | D22: =6e!H127 -> 11 | E22: =6e!H123 -> 61855 | F22: =6e!H124 -> 46340 | G22: =6e!H126 -> 12940 | H22: =6e!H128 -> 0.12933473 | I22: =6e!H129 -> Total incomplet : 1 prix de vente à fournir | J22: 5
A23: 5e | B23: Essentiel | C23: =COUNTA(5e!C6:C26) -> 21 | D23: =5e!H32 -> 11 | E23: =5e!H28 -> 11550 | F23: =5e!H29 -> 8135 | G23: =5e!H31 -> 2940 | H23: =5e!H33 -> 0.56926407 | I23: =5e!H34 -> Coût incomplet : 2 ligne(s) sans prix d'achat | J23: 0 | K23: =5e!H38 -> 15050
A24: 5e | B24: Complet | C24: =COUNTA(5e!C45:C70) -> 26 | D24: =5e!H76 -> 11 | E24: =5e!H72 -> 29625 | F24: =5e!H73 -> 22160 | G24: =5e!H75 -> 4890 | H24: =5e!H77 -> 0.27004219 | I24: =5e!H78 -> Total incomplet : 1 prix de vente à fournir | J24: 2
A25: 5e | B25: Confort | C25: =COUNTA(5e!C86:C123) -> 38 | D25: =5e!H129 -> 11 | E25: =5e!H125 -> 68655 | F25: =5e!H126 -> 51140 | G25: =5e!H128 -> 14940 | H25: =5e!H130 -> 0.11652465 | I25: =5e!H131 -> Total incomplet : 1 prix de vente à fournir | J25: 3
A26: 4e | B26: Essentiel | C26: =COUNTA(4e!C6:C28) -> 23 | D26: =4e!H34 -> 13 | E26: =4e!H30 -> 14025 | F26: =4e!H31 -> 10110 | G26: =4e!H33 -> 3440 | H26: =4e!H35 -> 0.44919786 | I26: =4e!H36 -> Coût incomplet : 2 ligne(s) sans prix d'achat | J26: 0 | K26: =4e!H40 -> 17525
A27: 4e | B27: Complet | C27: =COUNTA(4e!C47:C74) -> 28 | D27: =4e!H80 -> 13 | E27: =4e!H76 -> 33125 | F27: =4e!H77 -> 24860 | G27: =4e!H79 -> 5390 | H27: =4e!H81 -> 0.24150943 | I27: =4e!H82 -> Total incomplet : 1 prix de vente à fournir | J27: 3
A28: 4e | B28: Confort | C28: =COUNTA(4e!C91:C130) -> 40 | D28: =4e!H136 -> 13 | E28: =4e!H132 -> 79445 | F28: =4e!H133 -> 60430 | G28: =4e!H135 -> 16140 | H28: =4e!H137 -> 0.1006986 | I28: =4e!H138 -> Total incomplet : 1 prix de vente à fournir | J28: 5
A29: 3e | B29: Essentiel | C29: =COUNTA(3e!C6:C29) -> 24 | D29: =3e!H35 -> 13 | E29: =3e!H31 -> 14075 | F29: =3e!H32 -> 10160 | G29: =3e!H34 -> 3440 | H29: =3e!H36 -> 0.48312611 | I29: =3e!H37 -> Coût incomplet : 2 ligne(s) sans prix d'achat | J29: 0 | K29: =3e!H42 -> 20375
A30: 3e | B30: Complet | C30: =COUNTA(3e!C49:C78) -> 30 | D30: =3e!H84 -> 13 | E30: =3e!H80 -> 36675 | F30: =3e!H81 -> 27510 | G30: =3e!H83 -> 6440 | H30: =3e!H85 -> 0.21813224 | I30: =3e!H86 -> Total incomplet : 1 prix de vente à fournir | J30: 2
A31: 3e | B31: Confort | C31: =COUNTA(3e!C94:C138) -> 45 | D31: =3e!H144 -> 13 | E31: =3e!H140 -> 101095 | F31: =3e!H141 -> 77580 | G31: =3e!H143 -> 20790 | H31: =3e!H145 -> 0.079133488 | I31: =3e!H146 -> Total incomplet : 1 prix de vente à fournir | J31: 4
A32: 2nde L | B32: Essentiel | C32: =COUNTA('2nde L'!C6:C28) -> 23 | D32: ='2nde L'!H34 -> 13 | E32: ='2nde L'!H30 -> 13925 | F32: ='2nde L'!H31 -> 10110 | G32: ='2nde L'!H33 -> 3340 | H32: ='2nde L'!H35 -> 0.56014363 | I32: ='2nde L'!H36 -> Coût incomplet : 2 ligne(s) sans prix d'achat | J32: 0 | K32: ='2nde L'!H40 -> 17825
A33: 2nde L | B33: Complet | C33: =COUNTA('2nde L'!C47:C75) -> 29 | D33: ='2nde L'!H81 -> 13 | E33: ='2nde L'!H77 -> 36675 | F33: ='2nde L'!H78 -> 28560 | G33: ='2nde L'!H80 -> 6540 | H33: ='2nde L'!H82 -> 0.21813224 | I33: ='2nde L'!H83 -> Total incomplet : 1 prix de vente à fournir | J33: 2
A34: 2nde L | B34: Confort | C34: =COUNTA('2nde L'!C91:C126) -> 36 | D34: ='2nde L'!H132 -> 13 | E34: ='2nde L'!H128 -> 64725 | F34: ='2nde L'!H129 -> 50360 | G34: ='2nde L'!H131 -> 12790 | H34: ='2nde L'!H133 -> 0.12359985 | I34: ='2nde L'!H134 -> Total incomplet : 1 prix de vente à fournir | J34: 4
A35: 2nde S | B35: Essentiel | C35: =COUNTA('2nde S'!C6:C26) -> 21 | D35: ='2nde S'!H32 -> 12 | E35: ='2nde S'!H28 -> 13525 | F35: ='2nde S'!H29 -> 9810 | G35: ='2nde S'!H31 -> 3240 | H35: ='2nde S'!H33 -> 0.61367837 | I35: ='2nde S'!H34 -> Coût incomplet : 2 ligne(s) sans prix d'achat | J35: 0 | K35: ='2nde S'!H38 -> 17425
A36: 2nde S | B36: Complet | C36: =COUNTA('2nde S'!C45:C71) -> 27 | D36: ='2nde S'!H77 -> 12 | E36: ='2nde S'!H73 -> 36225 | F36: ='2nde S'!H74 -> 28260 | G36: ='2nde S'!H76 -> 6690 | H36: ='2nde S'!H78 -> 0.22084196 | I36: ='2nde S'!H79 -> Total incomplet : 1 prix de vente à fournir | J36: 3
A37: 2nde S | B37: Confort | C37: =COUNTA('2nde S'!C88:C122) -> 35 | D37: ='2nde S'!H128 -> 12 | E37: ='2nde S'!H124 -> 93675 | F37: ='2nde S'!H125 -> 74460 | G37: ='2nde S'!H127 -> 17940 | H37: ='2nde S'!H129 -> 0.085401655 | I37: ='2nde S'!H130 -> Total incomplet : 1 prix de vente à fournir | J37: 3
A38: 1re L | B38: Essentiel | C38: =COUNTA('1re L'!C6:C28) -> 23 | D38: ='1re L'!H34 -> 12 | E38: ='1re L'!H30 -> 13425 | F38: ='1re L'!H31 -> 9710 | G38: ='1re L'!H33 -> 3240 | H38: ='1re L'!H35 -> 0.54376164 | I38: ='1re L'!H36 -> Coût incomplet : 2 ligne(s) sans prix d'achat | J38: 0 | K38: ='1re L'!H42 -> 21825
A39: 1re L | B39: Complet | C39: =COUNTA('1re L'!C49:C79) -> 31 | D39: ='1re L'!H85 -> 12 | E39: ='1re L'!H81 -> 39825 | F39: ='1re L'!H82 -> 30060 | G39: ='1re L'!H84 -> 8190 | H39: ='1re L'!H86 -> 0.20087884 | I39: ='1re L'!H87 -> Total incomplet : 1 prix de vente à fournir | J39: 2
A40: 1re L | B40: Confort | C40: =COUNTA('1re L'!C95:C131) -> 37 | D40: ='1re L'!H137 -> 12 | E40: ='1re L'!H133 -> 65615 | F40: ='1re L'!H134 -> 50600 | G40: ='1re L'!H136 -> 13440 | H40: ='1re L'!H138 -> 0.12192334 | I40: ='1re L'!H139 -> Total incomplet : 1 prix de vente à fournir | J40: 3
A41: 1re S1 | B41: Essentiel | C41: =COUNTA('1re S1'!C6:C27) -> 22 | D41: ='1re S1'!H33 -> 11 | E41: ='1re S1'!H29 -> 12975 | F41: ='1re S1'!H30 -> 9360 | G41: ='1re S1'!H32 -> 3140 | H41: ='1re S1'!H34 -> 0.56262042 | I41: ='1re S1'!H35 -> Coût incomplet : 2 ligne(s) sans prix d'achat | J41: 0 | K41: ='1re S1'!H41 -> 21375
A42: 1re S1 | B42: Complet | C42: =COUNTA('1re S1'!C48:C77) -> 30 | D42: ='1re S1'!H83 -> 11 | E42: ='1re S1'!H79 -> 38925 | F42: ='1re S1'!H80 -> 29410 | G42: ='1re S1'!H82 -> 8090 | H42: ='1re S1'!H84 -> 0.20552344 | I42: ='1re S1'!H85 -> Total incomplet : 1 prix de vente à fournir | J42: 3
A43: 1re S1 | B43: Confort | C43: =COUNTA('1re S1'!C94:C129) -> 36 | D43: ='1re S1'!H135 -> 11 | E43: ='1re S1'!H131 -> 80715 | F43: ='1re S1'!H132 -> 63350 | G43: ='1re S1'!H134 -> 15940 | H43: ='1re S1'!H136 -> 0.099114167 | I43: ='1re S1'!H137 -> Total incomplet : 1 prix de vente à fournir | J43: 3
A44: 1re S2 | B44: Essentiel | C44: =COUNTA('1re S2'!C6:C27) -> 22 | D44: ='1re S2'!H33 -> 11 | E44: ='1re S2'!H29 -> 12975 | F44: ='1re S2'!H30 -> 9360 | G44: ='1re S2'!H32 -> 3140 | H44: ='1re S2'!H34 -> 0.56262042 | I44: ='1re S2'!H35 -> Coût incomplet : 2 ligne(s) sans prix d'achat | J44: 0 | K44: ='1re S2'!H41 -> 21375
A45: 1re S2 | B45: Complet | C45: =COUNTA('1re S2'!C48:C77) -> 30 | D45: ='1re S2'!H83 -> 11 | E45: ='1re S2'!H79 -> 38925 | F45: ='1re S2'!H80 -> 29410 | G45: ='1re S2'!H82 -> 8090 | H45: ='1re S2'!H84 -> 0.20552344 | I45: ='1re S2'!H85 -> Total incomplet : 1 prix de vente à fournir | J45: 3
A46: 1re S2 | B46: Confort | C46: =COUNTA('1re S2'!C94:C129) -> 36 | D46: ='1re S2'!H135 -> 11 | E46: ='1re S2'!H131 -> 71715 | F46: ='1re S2'!H132 -> 56150 | G46: ='1re S2'!H134 -> 14140 | H46: ='1re S2'!H136 -> 0.11155267 | I46: ='1re S2'!H137 -> Total incomplet : 1 prix de vente à fournir | J46: 3
A47: Tle L | B47: Essentiel | C47: =COUNTA('Tle L'!C6:C29) -> 24 | D47: ='Tle L'!H35 -> 13 | E47: ='Tle L'!H31 -> 13925 | F47: ='Tle L'!H32 -> 10110 | G47: ='Tle L'!H34 -> 3340 | H47: ='Tle L'!H36 -> 0.56014363 | I47: ='Tle L'!H37 -> Coût incomplet : 2 ligne(s) sans prix d'achat | J47: 0 | K47: ='Tle L'!H43 -> 22325
A48: Tle L | B48: Complet | C48: =COUNTA('Tle L'!C50:C81) -> 32 | D48: ='Tle L'!H87 -> 13 | E48: ='Tle L'!H83 -> 41475 | F48: ='Tle L'!H84 -> 31560 | G48: ='Tle L'!H86 -> 8340 | H48: ='Tle L'!H88 -> 0.19288728 | I48: ='Tle L'!H89 -> Total incomplet : 1 prix de vente à fournir | J48: 5
A49: Tle L | B49: Confort | C49: =COUNTA('Tle L'!C100:C137) -> 38 | D49: ='Tle L'!H143 -> 13 | E49: ='Tle L'!H139 -> 66765 | F49: ='Tle L'!H140 -> 52000 | G49: ='Tle L'!H142 -> 13190 | H49: ='Tle L'!H144 -> 0.11982326 | I49: ='Tle L'!H145 -> Total incomplet : 1 prix de vente à fournir | J49: 8
A50: Tle S1 | B50: Essentiel | C50: =COUNTA('Tle S1'!C6:C28) -> 23 | D50: ='Tle S1'!H34 -> 13 | E50: ='Tle S1'!H30 -> 13975 | F50: ='Tle S1'!H31 -> 10160 | G50: ='Tle S1'!H33 -> 3340 | H50: ='Tle S1'!H35 -> 0.59391771 | I50: ='Tle S1'!H36 -> Coût incomplet : 2 ligne(s) sans prix d'achat | J50: 0 | K50: ='Tle S1'!H41 -> 19575
A51: Tle S1 | B51: Complet | C51: =COUNTA('Tle S1'!C48:C77) -> 30 | D51: ='Tle S1'!H83 -> 13 | E51: ='Tle S1'!H79 -> 39425 | F51: ='Tle S1'!H80 -> 30610 | G51: ='Tle S1'!H82 -> 7390 | H51: ='Tle S1'!H84 -> 0.20291693 | I51: ='Tle S1'!H85 -> Total incomplet : 1 prix de vente à fournir | J51: 5
A52: Tle S1 | B52: Confort | C52: =COUNTA('Tle S1'!C96:C131) -> 36 | D52: ='Tle S1'!H137 -> 13 | E52: ='Tle S1'!H133 -> 71215 | F52: ='Tle S1'!H134 -> 56550 | G52: ='Tle S1'!H136 -> 13240 | H52: ='Tle S1'!H138 -> 0.11233588 | I52: ='Tle S1'!H139 -> Total incomplet : 1 prix de vente à fournir | J52: 6
A53: Tle S2 | B53: Essentiel | C53: =COUNTA('Tle S2'!C6:C28) -> 23 | D53: ='Tle S2'!H34 -> 13 | E53: ='Tle S2'!H30 -> 13975 | F53: ='Tle S2'!H31 -> 10160 | G53: ='Tle S2'!H33 -> 3340 | H53: ='Tle S2'!H35 -> 0.59391771 | I53: ='Tle S2'!H36 -> Coût incomplet : 2 ligne(s) sans prix d'achat | J53: 0 | K53: ='Tle S2'!H41 -> 19575
A54: Tle S2 | B54: Complet | C54: =COUNTA('Tle S2'!C48:C77) -> 30 | D54: ='Tle S2'!H83 -> 13 | E54: ='Tle S2'!H79 -> 39425 | F54: ='Tle S2'!H80 -> 30610 | G54: ='Tle S2'!H82 -> 7390 | H54: ='Tle S2'!H84 -> 0.20291693 | I54: ='Tle S2'!H85 -> Total incomplet : 1 prix de vente à fournir | J54: 5
A55: Tle S2 | B55: Confort | C55: =COUNTA('Tle S2'!C96:C132) -> 37 | D55: ='Tle S2'!H138 -> 13 | E55: ='Tle S2'!H134 -> 81215 | F55: ='Tle S2'!H135 -> 64550 | G55: ='Tle S2'!H137 -> 15240 | H55: ='Tle S2'!H139 -> 0.098503971 | I55: ='Tle S2'!H140 -> Total incomplet : 1 prix de vente à fournir | J55: 6
A56: 2nde STEG | B56: Essentiel | C56: =COUNTA('2nde STEG'!C6:C30) -> 25 | D56: ='2nde STEG'!H36 -> 14 | E56: ='2nde STEG'!H32 -> 14425 | F56: ='2nde STEG'!H33 -> 10510 | G56: ='2nde STEG'!H35 -> 3440 | H56: ='2nde STEG'!H37 -> 0.57538995 | I56: ='2nde STEG'!H38 -> Coût incomplet : 2 ligne(s) sans prix d'achat | J56: 0 | K56: ='2nde STEG'!H42 -> 18325
A57: 2nde STEG | B57: Complet | C57: =COUNTA('2nde STEG'!C49:C79) -> 31 | D57: ='2nde STEG'!H85 -> 14 | E57: ='2nde STEG'!H81 -> 37725 | F57: ='2nde STEG'!H82 -> 29660 | G57: ='2nde STEG'!H84 -> 6190 | H57: ='2nde STEG'!H86 -> 0.21206097 | I57: ='2nde STEG'!H87 -> Total incomplet : 1 prix de vente à fournir | J57: 2
A58: 2nde STEG | B58: Confort | C58: =COUNTA('2nde STEG'!C95:C129) -> 35 | D58: ='2nde STEG'!H135 -> 14 | E58: ='2nde STEG'!H131 -> 52675 | F58: ='2nde STEG'!H132 -> 41360 | G58: ='2nde STEG'!H134 -> 9440 | H58: ='2nde STEG'!H136 -> 0.1518747 | I58: ='2nde STEG'!H137 -> Total incomplet : 1 prix de vente à fournir | J58: 2
A59: 1re STEG | B59: Essentiel | C59: =COUNTA('1re STEG'!C6:C30) -> 25 | D59: ='1re STEG'!H36 -> 14 | E59: ='1re STEG'!H32 -> 14425 | F59: ='1re STEG'!H33 -> 10510 | G59: ='1re STEG'!H35 -> 3440 | H59: ='1re STEG'!H37 -> 0.57538995 | I59: ='1re STEG'!H38 -> Coût incomplet : 2 ligne(s) sans prix d'achat | J59: 0 | K59: ='1re STEG'!H44 -> 22825
A60: 1re STEG | B60: Complet | C60: =COUNTA('1re STEG'!C51:C83) -> 33 | D60: ='1re STEG'!H89 -> 14 | E60: ='1re STEG'!H85 -> 42225 | F60: ='1re STEG'!H86 -> 32160 | G60: ='1re STEG'!H88 -> 8190 | H60: ='1re STEG'!H90 -> 0.18946122 | I60: ='1re STEG'!H91 -> Total incomplet : 1 prix de vente à fournir | J60: 2
A61: 1re STEG | B61: Confort | C61: =COUNTA('1re STEG'!C99:C135) -> 37 | D61: ='1re STEG'!H141 -> 14 | E61: ='1re STEG'!H137 -> 58575 | F61: ='1re STEG'!H138 -> 45260 | G61: ='1re STEG'!H140 -> 11440 | H61: ='1re STEG'!H142 -> 0.13657704 | I61: ='1re STEG'!H143 -> Total incomplet : 1 prix de vente à fournir | J61: 2
A62: Tle STEG | B62: Essentiel | C62: =COUNTA('Tle STEG'!C6:C31) -> 26 | D62: ='Tle STEG'!H37 -> 15 | E62: ='Tle STEG'!H33 -> 14925 | F62: ='Tle STEG'!H34 -> 10910 | G62: ='Tle STEG'!H36 -> 3540 | H62: ='Tle STEG'!H38 -> 0.58961474 | I62: ='Tle STEG'!H39 -> Coût incomplet : 2 ligne(s) sans prix d'achat | J62: 0 | K62: ='Tle STEG'!H44 -> 20525
A63: Tle STEG | B63: Complet | C63: =COUNTA('Tle STEG'!C51:C83) -> 33 | D63: ='Tle STEG'!H89 -> 15 | E63: ='Tle STEG'!H85 -> 41075 | F63: ='Tle STEG'!H86 -> 31860 | G63: ='Tle STEG'!H88 -> 7340 | H63: ='Tle STEG'!H90 -> 0.19476567 | I63: ='Tle STEG'!H91 -> Total incomplet : 1 prix de vente à fournir | J63: 2
A64: Tle STEG | B64: Confort | C64: =COUNTA('Tle STEG'!C99:C135) -> 37 | D64: ='Tle STEG'!H141 -> 15 | E64: ='Tle STEG'!H137 -> 56725 | F64: ='Tle STEG'!H138 -> 44260 | G64: ='Tle STEG'!H140 -> 10590 | H64: ='Tle STEG'!H142 -> 0.14103129 | I64: ='Tle STEG'!H143 -> Total incomplet : 1 prix de vente à fournir | J64: 2

Sheet Manquants
A1: Priorité | B1: Article manquant | C1: Classes et gammes concernées | D1: Pourquoi | E1: Où chercher
A2: Haute | B2: Copies doubles (A-CREER-03), Calligraphe 192 p GF (A-CREER-01), Calligraphe 96 p GF (A-CREER-02) | C2: Collège, lycée, STEG | D2: Rattachés aux produits de l'app lors de l'intégration. Copies doubles : 1 300 / 1 800 | E2: Intégration
A3: Info | B3: Livres Korka Diallo | C3: Confort 3e, 2nde S, 1re S1 et S2, Tle L, S1 et S2 | D3: Faits le 26/09 avec le catalogue Korka (prix public). Pas de physique-chimie de Terminale S1 au bon prix (le Sakho est à 38 000 F), pas de SVT en Première et Terminale S2 pour ne pas doubler le manuel Didactikos | E3: —
A4: Haute | B4: Format exact du L'écolier 192 p (SAC-005) | C4: Essentiel collège, lycée, STEG | D4: S'il est en petit format, l'Essentiel n'a aucun grand format. Edushop vend un 192 p à 500 F en 17x22 | E4: Papex
A5: Haute | B5: Le Vieux Nègre et la Médaille (Oyono) | C5: Complet 5e | D5: Seule œuvre de 5e de ta liste absente | E5: LPD
A6: Haute | B6: Phèdre (Racine) | C6: Complet Seconde | D6: Dans 3 listes sur 4 | E6: LPD
A7: Haute | B7: La Tragédie du roi Christophe (Césaire) | C7: Complet Première | D7: Dans 2 listes et ta liste | E7: LPD
A8: Haute | B8: Les Soleils des Indépendances (Kourouma) | C8: Complet Terminale | D8: Dans les 4 listes de Terminale | E8: LPD
A9: Haute | B9: L'Exil d'Albouri (Ndao), Antigone (Anouilh) | C9: Complet Terminale | D9: Chacun dans 2 listes | E9: LPD
A10: Moyenne | B10: Kandia physique-chimie (Seconde S, Première S, Terminale S) | C10: Complet lycée S | D10: Demandé par les deux lycées | E10: LPD, Clairafrique
A11: Moyenne | B11: Le Français en 6e, en Seconde, en 1re et Terminale (Edicef) | C11: Complet 6e et lycée | D11: Demandés par toutes les écoles ; seuls 5e et 3e sont au catalogue | E11: LPD
A12: Moyenne | B12: Cahier de TP (grand format) | C12: Collège et lycée (HG, SVT) | D12: Sainte-Marie et ton exemple de 3e le demandent. Edushop le vend 1 000 à 2 000 F | E12: Papex, LPD
... A19: Info | B19: CIAM (maths lycée) | C19: Lycée | D19: Pas disponible chez tes fournisseurs : retiré. La Clé des Cracks sert de ressource en maths | E19: —

Sheet Exclus
A1: Article des listes | B1: Pourquoi il n'est pas dans les kits
A2: Mouchoirs, sous-main, étiquettes | B2: Pas du matériel scolaire à proprement parler
A3: Blouse de laboratoire, tenue d'EPS, baskets, maillot, lunettes de piscine | B3: Textile et sport : hors papeterie
A4: Clé USB 16 Go | B4: Utile mais hors catalogue et hors papeterie ; à proposer à part si un fournisseur en a
A5: Flûte à bec, cahier de musique | B5: Demandés seulement par les écoles privées ; à garder d'une année sur l'autre
A6: Gouaches, pinceaux, canson, feutres d'arts plastiques | B6: Arts plastiques souvent « à facturer » par l'école ; LPD a de quoi faire un pack à part
A7: Globe, planisphère, gabarit carte de France | B7: Matériel de classe ou très spécifique à une école
A8: Cahiers de latin, d'allemand, d'arabe, de catéchèse et d'éthique | B8: Options propres à certaines écoles : à proposer en ajout, pas dans le kit de base
A9: Fascicules et livres vendus par l'école (HG, espagnol, arabe, Cambridge, livres religieux) | B9: Vendus uniquement par l'établissement
A10: Protège-cahiers dans l'Essentiel et au primaire | B10: Depuis le 26/09, ils sont dans le Complet et le Confort du collège, du lycée et de la STEG (1 par cahier, 150 F). Pas dans l'Essentiel ni au primaire : la liste Dar El-Hadith ne les demande pas
A11: Trousse | B11: Utile, mais chaque trousse est un modèle différent, et les kits ne proposent pas de choix : à vendre à côté, comme le sac

Sheet Écarts Edushop
A1: ID SacAdo | B1: Notre article | C1: Notre PV (FCFA) | D1: Statut vente / achat | E1: Produit Edushop (n°) | F1: Prix Edushop (FCFA) | G1: Écart | H1: Verdict | I1: Comparable ?
A2: S053 | B2: =INDEX(Articles!$C$2:$C$148,MATCH(A2,Articles!$A$2:$A$148,0)) -> Éponge | C2: =INDEX(Articles!$G$2:$G$148,MATCH(A2,Articles!$A$2:$A$148,0)) -> 1500 | D2: =INDEX(Articles!$H$2:$H$148,MATCH(A2,Articles!$A$2:$A$148,0))&" / "&INDEX(Articles!$F$2:$F$148,MATCH(A2,Articles!$A$2:$A$148,0)) -> Fixé / Inconnu | E2: Éponge (69) | F2: 200 | G2: =(C2-F2)/F2 -> 6.5 | H2: =IF(G2>=0.5,"Nous : beaucoup plus cher",IF(G2<=-0.35,"Nous : beaucoup moins cher",IF(ABS(G2)>=0.25,"Écart moyen","Aligné"))) -> Nous : beaucoup plus cher | I2: Oui, même produit
A3: S109 | B3: =INDEX(Articles!$C$2:$C$148,MATCH(A3,Articles!$A$2:$A$148,0)) -> Protège-cahier couleur petit format (à l'unité) | C3: =INDEX(Articles!$G$2:$G$148,MATCH(A3,Articles!$A$2:$A$148,0)) -> 150 | D3: =INDEX(Articles!$H$2:$H$148,MATCH(A3,Articles!$A$2:$A$148,0))&" / "&INDEX(Articles!$F$2:$F$148,MATCH(A3,Articles!$A$2:$A$148,0)) -> Fixé / Inconnu | E3: Protège-cahier (107 à 112) | F3: 100 | G3: =(C3-F3)/F3 -> 0.5 | H3: =IF(G3>=0.5,"Nous : beaucoup plus cher",IF(G3<=-0.35,"Nous : beaucoup moins cher",IF(ABS(G3)>=0.25,"Écart moyen","Aligné"))) -> Nous : beaucoup plus cher | I3: Oui, même produit
A4: CIS-ardoise | B4: =INDEX(Articles!$C$2:$C$148,MATCH(A4,Articles!$A$2:$A$148,0)) -> Ardoise quadrillée avec poignée | C4: =INDEX(Articles!$G$2:$G$148,MATCH(A4,Articles!$A$2:$A$148,0)) -> 2500 | D4: =INDEX(Articles!$H$2:$H$148,MATCH(A4,Articles!$A$2:$A$148,0))&" / "&INDEX(Articles!$F$2:$F$148,MATCH(A4,Articles!$A$2:$A$148,0)) -> Fixé / Confirmé | E4: Ardoise effaçable MM quadrillée (52) | F4: 700 | G4: =(C4-F4)/F4 -> 2.5714286 | H4: =IF(G4>=0.5,"Nous : beaucoup plus cher",IF(G4<=-0.35,"Nous : beaucoup moins cher",IF(ABS(G4)>=0.25,"Écart moyen","Aligné"))) -> Nous : beaucoup plus cher | I4: Proche : la nôtre a une poignée
A5: S086 | B5: =INDEX(Articles!$C$2:$C$148,MATCH(A5,Articles!$A$2:$A$148,0)) -> Ardoise scolaire | C5: =INDEX(Articles!$G$2:$G$148,MATCH(A5,Articles!$A$2:$A$148,0)) -> 900 | D5: =INDEX(Articles!$H$2:$H$148,MATCH(A5,Articles!$A$2:$A$148,0))&" / "&INDEX(Articles!$F$2:$F$148,MATCH(A5,Articles!$A$2:$A$148,0)) -> Fixé / Estimé | E5: Ardoise (1) | F5: 500 | G5: =(C5-F5)/F5 -> 0.8 | H5: =IF(G5>=0.5,"Nous : beaucoup plus cher",IF(G5<=-0.35,"Nous : beaucoup moins cher",IF(ABS(G5)>=0.25,"Écart moyen","Aligné"))) -> Nous : beaucoup plus cher | I5: Oui
A6: LIT-013 | B6: =INDEX(Articles!$C$2:$C$148,MATCH(A6,Articles!$A$2:$A$148,0)) -> Sous l'orage (Seydou Badian) | C6: =INDEX(Articles!$G$2:$G$148,MATCH(A6,Articles!$A$2:$A$148,0)) -> 3500 | D6: =INDEX(Articles!$H$2:$H$148,MATCH(A6,Articles!$A$2:$A$148,0))&" / "&INDEX(Articles!$F$2:$F$148,MATCH(A6,Articles!$A$2:$A$148,0)) -> Fixé / Estimé | E6: Sous l'orage (95) | F6: 1800 | G6: =(C6-F6)/F6 -> 0.94444444 | H6: =IF(G6>=0.5,"Nous : beaucoup plus cher",IF(G6<=-0.35,"Nous : beaucoup moins cher",IF(ABS(G6)>=0.25,"Écart moyen","Aligné"))) -> Nous : beaucoup plus cher | I6: Oui : même titre. Nos autres romans africains à 3 500 F sont sans doute trop hauts aussi
A7: SAC-041 | B7: =INDEX(Articles!$C$2:$C$148,MATCH(A7,Articles!$A$2:$A$148,0)) -> Compas Maped | C7: =INDEX(Articles!$G$2:$G$148,MATCH(A7,Articles!$A$2:$A$148,0)) -> 2000 | D7: =INDEX(Articles!$H$2:$H$148,MATCH(A7,Articles!$A$2:$A$148,0))&" / "&INDEX(Articles!$F$2:$F$148,MATCH(A7,Articles!$A$2:$A$148,0)) -> Fixé / Confirmé | E7: Compas (81) | F7: 600 | G7: =(C7-F7)/F7 -> 2.3333333 | H7: =IF(G7>=0.5,"Nous : beaucoup plus cher",IF(G7<=-0.35,"Nous : beaucoup moins cher",IF(ABS(G7)>=0.25,"Écart moyen","Aligné"))) -> Nous : beaucoup plus cher | I7: Qualité différente : Maped chez nous
A8: SAC-069 | B8: =INDEX(Articles!$C$2:$C$148,MATCH(A8,Articles!$A$2:$A$148,0)) -> Correcteur souris ARK | C8: =INDEX(Articles!$G$2:$G$148,MATCH(A8,Articles!$A$2:$A$148,0)) -> 1000 | D8: =INDEX(Articles!$H$2:$H$148,MATCH(A8,Articles!$A$2:$A$148,0))&" / "&INDEX(Articles!$F$2:$F$148,MATCH(A8,Articles!$A$2:$A$148,0)) -> Fixé / Confirmé | E8: Blanco (119) | F8: 300 | G8: =(C8-F8)/F8 -> 2.3333333 | H8: =IF(G8>=0.5,"Nous : beaucoup plus cher",IF(G8<=-0.35,"Nous : beaucoup moins cher",IF(ABS(G8)>=0.25,"Écart moyen","Aligné"))) -> Nous : beaucoup plus cher | I8: Produit différent : souris chez nous, liquide chez eux
A9: S129 | B9: =INDEX(Articles!$C$2:$C$148,MATCH(A9,Articles!$A$2:$A$148,0)) -> Cahier de dessin TPG | C9: =INDEX(Articles!$G$2:$G$148,MATCH(A9,Articles!$A$2:$A$148,0)) -> 550 | D9: =INDEX(Articles!$H$2:$H$148,MATCH(A9,Articles!$A$2:$A$148,0))&" / "&INDEX(Articles!$F$2:$F$148,MATCH(A9,Articles!$A$2:$A$148,0)) -> Fixé / Inconnu | E9: Cahier dessin grand modèle (10) | F9: 450 | G9: =(C9-F9)/F9 -> 0.22222222 | H9: =IF(G9>=0.5,"Nous : beaucoup plus cher",IF(G9<=-0.35,"Nous : beaucoup moins cher",IF(ABS(G9)>=0.25,"Écart moyen","Aligné"))) -> Aligné | I9: Proche
A10: S009 | B10: =INDEX(Articles!$C$2:$C$148,MATCH(A10,Articles!$A$2:$A$148,0)) -> Gomme Staedtler Mars Plastic | C10: =INDEX(Articles!$G$2:$G$148,MATCH(A10,Articles!$A$2:$A$148,0)) -> 250 | D10: =INDEX(Articles!$H$2:$H$148,MATCH(A10,Articles!$A$2:$A$148,0))&" / "&INDEX(Articles!$F$2:$F$148,MATCH(A10,Articles!$A$2:$A$148,0)) -> Fixé / Estimé | E10: Gomme (122) | F10: 100 | G10: =(C10-F10)/F10 -> 1.5 | H10: =IF(G10>=0.5,"Nous : beaucoup plus cher",IF(G10<=-0.35,"Nous : beaucoup moins cher",IF(ABS(G10)>=0.25,"Écart moyen","Aligné"))) -> Nous : beaucoup plus cher | I10: Qualité différente : Staedtler chez nous
A11: SAC-017 | B11: =INDEX(Articles!$C$2:$C$148,MATCH(A11,Articles!$A$2:$A$148,0)) -> Taille-crayon avec réservoir Maped | C11: =INDEX(Articles!$G$2:$G$148,MATCH(A11,Articles!$A$2:$A$148,0)) -> 500 | D11: =INDEX(Articles!$H$2:$H$148,MATCH(A11,Articles!$A$2:$A$148,0))&" / "&INDEX(Articles!$F$2:$F$148,MATCH(A11,Articles!$A$2:$A$148,0)) -> Estimé / Estimé | E11: Taille-crayon (126) | F11: 200 | G11: =(C11-F11)/F11 -> 1.5 | H11: =IF(G11>=0.5,"Nous : beaucoup plus cher",IF(G11<=-0.35,"Nous : beaucoup moins cher",IF(ABS(G11)>=0.25,"Écart moyen","Aligné"))) -> Nous : beaucoup plus cher | I11: Qualité différente : réservoir Maped chez nous
A12: S069 | B12: =INDEX(Articles!$C$2:$C$148,MATCH(A12,Articles!$A$2:$A$148,0)) -> Règle métal 30 cm | C12: =INDEX(Articles!$G$2:$G$148,MATCH(A12,Articles!$A$2:$A$148,0)) -> 550 | D12: =INDEX(Articles!$H$2:$H$148,MATCH(A12,Articles!$A$2:$A$148,0))&" / "&INDEX(Articles!$F$2:$F$148,MATCH(A12,Articles!$A$2:$A$148,0)) -> Fixé / Estimé | E12: Règle 30 cm (84) | F12: 300 | G12: =(C12-F12)/F12 -> 0.83333333 | H12: =IF(G12>=0.5,"Nous : beaucoup plus cher",IF(G12<=-0.35,"Nous : beaucoup moins cher",IF(ABS(G12)>=0.25,"Écart moyen","Aligné"))) -> Nous : beaucoup plus cher | I12: Proche : métal chez nous
A13: SAC-016 | B13: =INDEX(Articles!$C$2:$C$148,MATCH(A13,Articles!$A$2:$A$148,0)) -> Ciseaux Maped 13 cm Security | C13: =INDEX(Articles!$G$2:$G$148,MATCH(A13,Articles!$A$2:$A$148,0)) -> 900 | D13: =INDEX(Articles!$H$2:$H$148,MATCH(A13,Articles!$A$2:$A$148,0))&" / "&INDEX(Articles!$F$2:$F$148,MATCH(A13,Articles!$A$2:$A$148,0)) -> Estimé / Estimé | E13: Ciseaux bouts ronds 13 cm (65) | F13: 500 | G13: =(C13-F13)/F13 -> 0.8 | H13: =IF(G13>=0.5,"Nous : beaucoup plus cher",IF(G13<=-0.35,"Nous : beaucoup moins cher",IF(ABS(G13)>=0.25,"Écart moyen","Aligné"))) -> Nous : beaucoup plus cher | I13: Oui, même taille ; Maped chez nous
... A42: S020 | B42: =INDEX(Articles!$C$2:$C$148,MATCH(A42,Articles!$A$2:$A$148,0)) -> Sac à dos bleu marine | C42: =INDEX(Articles!$G$2:$G$148,MATCH(A42,Articles!$A$2:$A$148,0)) -> 7000 | D42: =INDEX(Articles!$H$2:$H$148,MATCH(A42,Articles!$A$2:$A$148,0))&" / "&INDEX(Articles!$F$2:$F$148,MATCH(A42,Articles!$A$2:$A$148,0)) -> Fixé / Confirmé | E42: Sac à dos enfant (113) | F42: 10000 | G42: =(C42-F42)/F42 -> -0.3 | H42: =IF(G42>=0.5,"Nous : beaucoup plus cher",IF(G42<=-0.35,"Nous : beaucoup moins cher",IF(ABS(G42)>=0.25,"Écart moyen","Aligné"))) -> Écart moyen | I42: Proche
A44: Source : fichier produits Edushop envoyé par SacAdo le 25/09/2026. Prix Edushop en bleu. Les produits Edushop sont souvent sans marque : un écart peut venir de la qualité (Maped, Calligraphe, Staedtler chez nous).
A45: Hors kits mais au catalogue : Horizontes (espagnol) 3 550 F chez nous contre 2 500 à 3 000 F chez Edushop ; English for Success 4 000 F contre 3 000 F.
A46: Tous les packs Edushop sont affichés à 20 000 F, du CP à la Terminale, sans contenu détaillé : ce prix ne sert pas de repère.

Sheet Œuvres
A1: Classe | B1: Titre | C1: Cité par | D1: Place dans les kits | E1: Au catalogue ?
A2: 6e | B2: Le Pagne noir | C2: Ta liste, ISJA (et Sainte-Marie en 5e) | D2: Complet | E2: Oui (LIT-014)
A3: 6e | B3: Les Contes d'Amadou Koumba | C3: Ta liste (Sainte-Marie : Les Nouveaux Contes) | D3: Confort | E3: Oui (LIT-011)
A4: 6e | B4: Fables de La Fontaine | C4: Ta liste | D4: Confort | E4: Non
A5: 6e | B5: Les Fourberies de Scapin / Le Médecin malgré lui | C5: ISJA / Sainte-Marie | D5: Confort | E5: Non
A6: 5e | B6: La Belle Histoire de Leuk-le-Lièvre | C6: Ta liste | D6: Complet | E6: Oui (LIT-021)
A7: 5e | B7: Le Vieux Nègre et la Médaille | C7: Ta liste | D7: Complet | E7: Non
A8: 5e | B8: L'Os de Mor Lam | C8: Sainte-Marie | D8: Confort | E8: Oui (LIT-023), photo à refaire
A9: 5e | B9: Le Malade imaginaire | C9: ISJA | D9: Confort | E9: Oui (LIT-018)
A10: 5e | B10: Maïmouna | C10: ISJA | D10: Non retenu | E10: Oui (LIT-012)
A11: 4e | B11: Sous l'orage | C11: Ta liste, Sainte-Marie, ISJA | D11: Complet | E11: Oui (LIT-013)
A12: 4e | B12: Eugénie Grandet | C12: ISJA | D12: Confort | E12: Oui (NIO-2900)
... A37: Terminale | B37: L'Aventure ambiguë | C37: Ta liste | D37: Confort | E37: Oui (LIT-002)

Sheet Articles
A1: ID | B1: Fournisseur | C1: Désignation | D1: Unité de vente | E1: Prix achat (FCFA) | F1: Statut achat | G1: Prix vente (FCFA) | H1: Statut vente | I1: Remarque
A2: SAC-001 | B2: Papex | C2: Cahier de dessin L'écolier 32 pages | D2: pièce | E2: 150 | F2: Confirmé | G2: 250 | H2: Fixé
A3: SAC-004 | B3: Papex | C3: Cahier L'écolier 48 pages | D3: pièce | E3: 175 | F3: Confirmé | G3: 275 | H3: Estimé
A4: SAC-005 | B4: Papex | C4: Cahier L'écolier 192 pages | D4: pièce | E4: 400 | F4: Confirmé | G4: 500 | H4: Estimé | I4: Format (17x22 ou 24x32) non précisé : à confirmer
A5: SAC-048 | B5: Papex | C5: Cahier Calligraphe 96 pages 17x22 56 g seyès | D5: pièce | E5: 350 | F5: Confirmé | G5: 450 | H5: Fixé
A6: SAC-033 | B6: Papex | C6: Cahier Calligraphe 140 pages 17x22 90 g seyès | D6: pièce | E6: 650 | F6: Estimé | G6: 750 | H6: Fixé | I6: Achat interpolé
A7: SAC-046 | B7: Papex | C7: Cahier Calligraphe 192 pages 17x22 90 g seyès | D7: pièce | E7: 800 | F7: Confirmé | G7: 900 | H7: Fixé
A8: SAC-036 | B8: Papex | C8: Cahier Calligraphe 140 pages 24x32 90 g seyès | D8: pièce | E8: 1250 | F8: Estimé | G8: 1500 | H8: Fixé | I8: Achat interpolé
A9: A-CREER-01 | B9: Papex | C9: Cahier Calligraphe 192 pages 24x32 (grand format) | D9: pièce | E9: 1500 | F9: Confirmé | G9: 1650 | H9: Fixé | I9: Présent dans l'app selon toi : remplacer cet ID par celui de l'app et vérifier le prix (tarif Papex GF 192 p 1 500 / 1 650)
A10: A-CREER-02 | B10: Papex | C10: Cahier Calligraphe 96 pages 24x32 (grand format) | D10: pièce | E10: 1000 | F10: Confirmé | G10: 1350 | H10: Fixé | I10: Présent dans l'app selon toi : remplacer cet ID par celui de l'app et vérifier le prix (tarif Papex GF 96 p 1 000 / 1 350)
A11: A-CREER-03 | B11: À préciser | C11: Paquet de copies doubles grand format | D11: paquet | E11: 1300 | F11: Confirmé | G11: 1800 | H11: Fixé | I11: Prix donnés par SacAdo le 25/09/2026 (achat 1 300, vente 1 800)
A12: CDC-3M | B12: Korka Diallo | C12: MATHEMATIQUES TROISIEME (Korka Diallo, Le BFEM en poche) | D12: pièce | E12: 8000 | F12: Confirmé | G12: 10000 | H12: Fixé | I12: Catalogue Korka : prix public = prix de vente, achat -20 %
A13: CDC-3PC | B13: Korka Diallo | C13: PHYSIQUE CHIMIE TROISIEME (Korka Diallo, Le BFEM en poche) | D13: pièce | E13: 4000 | F13: Confirmé | G13: 5000 | H13: Fixé | I13: Catalogue Korka
A14: CDC-3ANG | B14: Korka Diallo | C14: ANNALE D'ANGLAIS TROISIEME (Korka Diallo, Club de l'Excellence) | D14: pièce | E14: 2400 | F14: Confirmé | G14: 3000 | H14: Fixé | I14: Catalogue Korka. Annales pour le BFEM
A15: CDC-2M | B15: Korka Diallo | C15: KAAMILE DE MATHS - SECONDE S (Korka Diallo, Collection Cracks) | D15: pièce | E15: 8000 | F15: Confirmé | G15: 10000 | H15: Fixé | I15: Catalogue Korka
A16: CDC-2PC | B16: Korka Diallo | C16: PHYSIQUE CHIMIE SECONDE S (Korka Diallo, Collection Cracks) | D16: pièce | E16: 8000 | F16: Confirmé | G16: 10000 | H16: Fixé | I16: Catalogue Korka
A17: CDC-2SVT | B17: Korka Diallo | C17: SVT SECONDE S | D17: pièce | E17: 12000 | F17: Confirmé | G17: 15000 | H17: Fixé | I17: Catalogue Korka. Auteur non indiqué
A18: CDC-1M-S1 | B18: Korka Diallo | C18: MATHS 1S1 (CRACKS EN MATHS) (Korka Diallo) | D18: pièce | E18: 12000 | F18: Confirmé | G18: 15000 | H18: Fixé | I18: Catalogue Korka. Édition S1
A19: CDC-1M-S2 | B19: Korka Diallo | C19: MATHS 1S2 - LA CLE DES CRACKS (Korka Diallo) | D19: pièce | E19: 4800 | F19: Confirmé | G19: 6000 | H19: Fixé | I19: Catalogue Korka. Édition S2
... A24: CDC-TPHILO | B24: Korka Diallo | C24: PHILOSOPHIE TERMINALES L ET S - L'ESSENTIEL (Korka Diallo, Club de l'Excellence) | D24: pièce | E24: 2400 | F24: Confirmé | G24: 3000 | H24: Fixé | I24: Catalogue Korka
A25: S109 | B25: LPD | C25: Protège-cahier couleur petit format (à l'unité) | D25: pièce | F25: Inconnu | G25: 150 | H25: Fixé | I25: PV corrigé par SacAdo le 26/09 (950 -> 150). Format supposé petit : à confirmer
A26: A-CREER-04 | B26: À préciser | C26: Protège-cahier grand format (à l'unité) | D26: pièce | F26: Inconnu | H26: À fournir | I26: À trouver dans l'app. Sans ce produit, les cahiers grand format des kits n'ont pas de protège-cahier
A27: SAC-007 | B27: Papex | C27: Kit de traçage 30 cm, 4 pièces L'écolier | D27: pièce | E27: 650 | F27: Confirmé | G27: 900 | H27: Estimé
A28: SAC-019 | B28: Papex | C28: Crayons de couleur Maped, boîte de 12 | D28: boîte | E28: 650 | F28: Estimé | G28: 900 | H28: Estimé
A29: SAC-024 | B29: Papex | C29: Crayons de couleur Maped Nightfall, boîte de 24 | D29: boîte | E29: 1300 | F29: Estimé | G29: 1600 | H29: Estimé
A30: SAC-065 | B30: Papex | C30: Stylo à bille Schneider Tops 505 M bleu | D30: pièce | F30: Inconnu | G30: 100 | H30: Fixé | I30: Achat supposé 50 à 80 F
A31: SAC-104 | B31: Papex | C31: Stylo à bille Schneider Tops 505 M vert | D31: pièce | F31: Inconnu | G31: 100 | H31: Fixé | I31: Achat supposé 50 à 80 F
A32: SAC-066 | B32: Papex | C32: Pack de 4 stylos Schneider Tops 505 M (bleu, noir, rouge, vert) | D32: pack de 4 | F32: Inconnu | G32: 400 | H32: Fixé | I32: Achat supposé 200 à 320 F
A33: SAC-062 | B33: Papex | C33: Stylo 4 couleurs Schneider | D33: pièce | E33: 1500 | F33: Confirmé | G33: 1750 | H33: Fixé
A34: SAC-017 | B34: Papex | C34: Taille-crayon avec réservoir Maped | D34: pièce | E34: 350 | F34: Estimé | G34: 500 | H34: Estimé
A35: SAC-031 | B35: Papex | C35: Bâton de colle Giotto 10 g | D35: pièce | E35: 350 | F35: Estimé | G35: 500 | H35: Estimé | I35: Achat en fourchette 300 à 400 F
A36: SAC-034 | B36: Papex | C36: Bâton de colle Giotto 20 g | D36: pièce | E36: 650 | F36: Estimé | G36: 900 | H36: Estimé | I36: Achat en fourchette 600 à 700 F
A37: SAC-016 | B37: Papex | C37: Ciseaux Maped 13 cm Security | D37: pièce | E37: 650 | F37: Estimé | G37: 900 | H37: Estimé
A38: SAC-041 | B38: Papex | C38: Compas Maped | D38: pièce | E38: 1750 | F38: Confirmé | G38: 2000 | H38: Fixé
A39: SAC-037 | B39: Papex | C39: Surligneurs Maped Fluo Peps, pochette de 4 | D39: pochette | E39: 2000 | F39: Confirmé | G39: 2500 | H39: Estimé
A40: SAC-069 | B40: Papex | C40: Correcteur souris ARK | D40: pièce | E40: 700 | F40: Confirmé | G40: 1000 | H40: Fixé
A41: SAC-055 | B41: Papex | C41: Chemise 3 rabats à élastique | D41: pièce | F41: Inconnu | G41: 500 | H41: Estimé | I41: PV calé sur le prix public Chez Monami, pas de prix fournisseur
A42: SAC-022 | B42: Papex | C42: Calculatrice Casio fx-92 Collège | D42: pièce | E42: 7000 | F42: Confirmé | G42: 8000 | H42: Fixé | I42: PV corrigé par SacAdo le 26/09 (9 000 -> 8 000)
A43: SAC-112 | B43: Papex | C43: Dictionnaire Le Robert de français, 65 000 mots | D43: pièce | E43: 3000 | F43: Confirmé | G43: 3500 | H43: Fixé
A44: S011 | B44: LPD | C44: Règle plastique transparente 20 cm | D44: pièce | F44: Inconnu | G44: 100 | H44: Fixé | I44: PV corrigé par SacAdo le 26/09 (300 -> 100). Achat à obtenir
A45: S069 | B45: LPD | C45: Règle métal 30 cm | D45: pièce | E45: 400 | F45: Estimé | G45: 550 | H45: Fixé
A46: S086 | B46: LPD | C46: Ardoise scolaire | D46: pièce | E46: 600 | F46: Estimé | G46: 900 | H46: Fixé
A47: S053 | B47: LPD | C47: Éponge | D47: pièce | F47: Inconnu | G47: 1500 | H47: Fixé | I47: Achat à obtenir. 1 500 F pour une éponge : à revoir
A48: S065 | B48: LPD | C48: Crayon papier (vendu à l'unité) | D48: pièce | F48: Inconnu | G48: 75 | H48: Fixé | I48: Achat à obtenir
A49: S009 | B49: LPD | C49: Gomme Staedtler Mars Plastic | D49: pièce | E49: 110 | F49: Estimé | G49: 250 | H49: Fixé
A50: S030 | B50: LPD | C50: Boîte à éponge (ex « taille-crayon rond ») | D50: pièce | E50: 100 | F50: Estimé | G50: 250 | H50: Fixé | I50: Renommé par SacAdo le 26/09 : ce n'est pas un taille-crayon. Retiré des kits
A51: S081 | B51: LPD | C51: Ciseaux scolaires bouts ronds | D51: pièce | E51: 100 | F51: Estimé | G51: 250 | H51: Fixé
A52: S033 | B52: LPD | C52: Compas de précision avec étui | D52: pièce | E52: 450 | F52: Estimé | G52: 600 | H52: Fixé
A53: S091 | B53: LPD | C53: Kit géométrie Maped 30 cm (réf. 1930) | D53: pièce | E53: 1500 | F53: Confirmé | G53: 1800 | H53: À trancher | I53: La grille LPD dit aussi « remonté de 1 800 à 1 900 »
A54: S015 | B54: LPD | C54: Calculatrice scientifique Parpn YH-2000 | D54: pièce | E54: 1100 | F54: Confirmé | G54: 1400 | H54: Fixé | I54: Générique : les listes demandent une Casio fx-92
A55: S100 | B55: LPD | C55: Protège-documents porte-vues | D55: pièce | E55: 850 | F55: Estimé | G55: 1150 | H55: Fixé
A56: S129 | B56: LPD | C56: Cahier de dessin TPG | D56: pièce | F56: Inconnu | G56: 550 | H56: Fixé | I56: PV corrigé par SacAdo le 26/09 (1 050 -> 550). Achat à obtenir
A57: CIS-ardoise | B57: Cissé & Frères | C57: Ardoise quadrillée avec poignée | D57: pièce | E57: 1500 | F57: Confirmé | G57: 2500 | H57: Fixé | I57: Couleur non choisie dans le kit
A58: LIT-014 | B58: LPD | C58: Le Pagne noir (Bernard Dadié) | D58: pièce | E58: 2500 | F58: Estimé | G58: 3500 | H58: Fixé | I58: Doublon à 3 900 dans l'app
A59: LIT-011 | B59: LPD | C59: Les Contes d'Amadou Koumba (Birago Diop) | D59: pièce | E59: 2500 | F59: Estimé | G59: 3500 | H59: Fixé
A60: LIT-021 | B60: LPD | C60: La Belle Histoire de Leuk-le-Lièvre (Senghor et Sadji) | D60: pièce | E60: 2500 | F60: Estimé | G60: 3500 | H60: Fixé
A61: LIT-023 | B61: LPD | C61: L'Os de Mor Lam (Birago Diop) | D61: pièce | E61: 2500 | F61: Estimé | G61: 3500 | H61: Fixé | I61: Photo LPD sous 400 px : non publiable, à remplacer
A62: LIT-018 | B62: LPD | C62: Le Malade imaginaire (Molière) | D62: pièce | E62: 1800 | F62: Estimé | G62: 2800 | H62: Fixé
A63: LIT-013 | B63: LPD | C63: Sous l'orage (Seydou Badian) | D63: pièce | E63: 2500 | F63: Estimé | G63: 3500 | H63: Fixé | I63: Doublon à 3 900 dans l'app
A64: NIO-2900 | B64: LPD | C64: Eugénie Grandet (Balzac) | D64: pièce | E64: 2900 | F64: Estimé | G64: 3900 | H64: Fixé
A65: LIT-001 | B65: LPD | C65: Une si longue lettre (Mariama Bâ) | D65: pièce | E65: 2500 | F65: Estimé | G65: 3500 | H65: Fixé | I65: Doublon à 3 900 dans l'app
A66: LIT-019 | B66: LPD | C66: Vol de nuit (Saint-Exupéry) | D66: pièce | E66: 1800 | F66: Estimé | G66: 2800 | H66: Fixé | I66: Doublon à 3 900 dans l'app
A67: NIO-6379 | B67: LPD | C67: Les Nouveaux Contes d'Amadou Koumba (Birago Diop) | D67: pièce | E67: 2900 | F67: Estimé | G67: 3900 | H67: Fixé
A68: S062 | B68: LPD | C68: Le Marabout de la sécheresse (Cheik Aliou Ndao) | D68: pièce | E68: 1800 | F68: Confirmé | G68: 2800 | H68: Fixé | I68: Prix LPD réel
A69: LIT-004 | B69: LPD | C69: L'Enfant noir (Camara Laye) | D69: pièce | E69: 1800 | F69: Estimé | G69: 2800 | H69: Fixé | I69: Doublon à 3 900 dans l'app
A70: LIT-024 | B70: LPD | C70: Une vie de boy (Ferdinand Oyono) | D70: pièce | E70: 1800 | F70: Estimé | G70: 2800 | H70: Fixé
A71: LIT-008 | B71: LPD | C71: Le Père Goriot (Balzac) | D71: pièce | E71: 1800 | F71: Estimé | G71: 2800 | H71: Fixé
A72: LIT-009 | B72: LPD | C72: Madame Bovary (Flaubert) | D72: pièce | E72: 1800 | F72: Estimé | G72: 2800 | H72: Fixé
A73: LIT-005 | B73: LPD | C73: Les Bouts de bois de Dieu (Ousmane Sembène) | D73: pièce | E73: 2500 | F73: Estimé | G73: 3500 | H73: Fixé
A74: LIT-003 | B74: LPD | C74: Nini, mulâtresse du Sénégal (Abdoulaye Sadji) | D74: pièce | E74: 2500 | F74: Estimé | G74: 3500 | H74: Fixé
A75: LIT-007 | B75: LPD | C75: L'Étranger (Albert Camus) | D75: pièce | E75: 1800 | F75: Estimé | G75: 2800 | H75: Fixé
A76: LIT-010 | B76: LPD | C76: Les Contemplations (Victor Hugo) | D76: pièce | E76: 1800 | F76: Confirmé | G76: 2800 | H76: Fixé | I76: Seul prix LPD confirmé du rayon livres
A77: LIT-002 | B77: LPD | C77: L'Aventure ambiguë (Cheikh Hamidou Kane) | D77: pièce | E77: 2500 | F77: Estimé | G77: 3500 | H77: Fixé
A78: LIT-020 | B78: LPD | C78: Apologie de Socrate (Platon) | D78: pièce | E78: 1800 | F78: Estimé | G78: 2800 | H78: Fixé
A79: DID-6913 | B79: LPD | C79: Langue et communication C.I. | D79: pièce | E79: 2890 | F79: Estimé | G79: 3890 | H79: Fixé | I79: PV du fichier livres, à vérifier dans l'app. Achat estimé
A80: DID-6936 | B80: LPD | C80: Mathématiques C.I. | D80: pièce | E80: 2890 | F80: Estimé | G80: 3890 | H80: Fixé | I80: PV du fichier livres, à vérifier dans l'app. Achat estimé
A81: DID-6949 | B81: LPD | C81: Découverte du monde C.I. | D81: pièce | E81: 2890 | F81: Estimé | G81: 3890 | H81: Fixé | I81: PV du fichier livres, à vérifier dans l'app. Achat estimé
A82: DID-6915 | B82: LPD | C82: Langue et communication C.P. | D82: pièce | E82: 2890 | F82: Estimé | G82: 3890 | H82: Fixé | I82: PV du fichier livres, à vérifier dans l'app. Achat estimé
A83: DID-6938 | B83: LPD | C83: Mathématiques C.P. | D83: pièce | E83: 2890 | F83: Estimé | G83: 3890 | H83: Fixé | I83: PV du fichier livres, à vérifier dans l'app. Achat estimé
A84: DID-6952 | B84: LPD | C84: Découverte du monde C.P. | D84: pièce | E84: 2890 | F84: Estimé | G84: 3890 | H84: Fixé | I84: PV du fichier livres, à vérifier dans l'app. Achat estimé
A85: DID-6917 | B85: LPD | C85: Langue et communication C.E.1 | D85: pièce | E85: 3000 | F85: Estimé | G85: 4000 | H85: Fixé | I85: PV du fichier livres, à vérifier dans l'app. Achat estimé
A86: DID-6941 | B86: LPD | C86: Mathématiques C.E.1 | D86: pièce | E86: 3000 | F86: Estimé | G86: 4000 | H86: Fixé | I86: PV du fichier livres, à vérifier dans l'app. Achat estimé
A87: DID-6954 | B87: LPD | C87: Découverte du monde C.E.1 | D87: pièce | E87: 3000 | F87: Estimé | G87: 4000 | H87: Fixé | I87: PV du fichier livres, à vérifier dans l'app. Achat estimé
A88: DID-6922 | B88: LPD | C88: Langue et communication C.E.2 | D88: pièce | E88: 3000 | F88: Estimé | G88: 4000 | H88: Fixé | I88: PV du fichier livres, à vérifier dans l'app. Achat estimé
A89: DID-6943 | B89: LPD | C89: Mathématiques C.E.2 | D89: pièce | E89: 3000 | F89: Estimé | G89: 4000 | H89: Fixé | I89: PV du fichier livres, à vérifier dans l'app. Achat estimé
A90: DID-6956 | B90: LPD | C90: Découverte du monde C.E.2 | D90: pièce | E90: 3000 | F90: Estimé | G90: 4000 | H90: Fixé | I90: PV du fichier livres, à vérifier dans l'app. Achat estimé
... A148: S020 | B148: LPD | C148: Sac à dos bleu marine | D148: pièce | E148: 5500 | F148: Confirmé | G148: 7000 | H148: Fixé | I148: Option collège et lycée (décochée)

Sheet CI
A1: Kit CI
A2: Liste réelle du Complexe Dar El-Hadith. Contrôle croisé avec la liste ISJA 2026-2027 (plus chargée, écoles privées).
A4: CI — Essentiel
A5: Groupe (app) | B5: Besoin (liste) | C5: ID | D5: Désignation | E5: Fournisseur | F5: Qté | G5: PV unit. (FCFA) | H5: Sous-total vente | I5: PA unit. (FCFA) | J5: Sous-total achat | K5: Statut vente | L5: Statut achat | M5: Remarque | N5: Coché par défaut
A6: Cahiers | B6: Cahier 32 pages | C6: SAC-004 | D6: =INDEX(Articles!$C$2:$C$148,MATCH(C6,Articles!$A$2:$A$148,0)) -> Cahier L'écolier 48 pages | E6: =INDEX(Articles!$B$2:$B$148,MATCH(C6,Articles!$A$2:$A$148,0)) -> Papex | F6: 2 | G6: =IF(INDEX(Articles!$G$2:$G$148,MATCH(C6,Articles!$A$2:$A$148,0))="","",INDEX(Articles!$G$2:$G$148,MATCH(C6,Articles!$A$2:$A$148,0))) -> 275 | H6: =IF(G6="",0,F6*G6) -> 550 | I6: =IF(INDEX(Articles!$E$2:$E$148,MATCH(C6,Articles!$A$2:$A$148,0))="","",INDEX(Articles!$E$2:$E$148,MATCH(C6,Articles!$A$2:$A$148,0))) -> 175 | J6: =IF(I6="","",F6*I6) -> 350 | K6: =INDEX(Articles!$H$2:$H$148,MATCH(C6,Articles!$A$2:$A$148,0)) -> Estimé | L6: =INDEX(Articles!$F$2:$F$148,MATCH(C6,Articles!$A$2:$A$148,0)) -> Confirmé | M6: 48 p (32 p absent) | N6: Oui
A7: Ardoise | B7: Ardoise | C7: S086 | D7: =INDEX(Articles!$C$2:$C$148,MATCH(C7,Articles!$A$2:$A$148,0)) -> Ardoise scolaire | E7: =INDEX(Articles!$B$2:$B$148,MATCH(C7,Articles!$A$2:$A$148,0)) -> LPD | F7: 1 | G7: =IF(INDEX(Articles!$G$2:$G$148,MATCH(C7,Articles!$A$2:$A$148,0))="","",INDEX(Articles!$G$2:$G$148,MATCH(C7,Articles!$A$2:$A$148,0))) -> 900 | H7: =IF(G7="",0,F7*G7) -> 900 | I7: =IF(INDEX(Articles!$E$2:$E$148,MATCH(C7,Articles!$A$2:$A$148,0))="","",INDEX(Articles!$E$2:$E$148,MATCH(C7,Articles!$A$2:$A$148,0))) -> 600 | J7: =IF(I7="","",F7*I7) -> 600 | K7: =INDEX(Articles!$H$2:$H$148,MATCH(C7,Articles!$A$2:$A$148,0)) -> Fixé | L7: =INDEX(Articles!$F$2:$F$148,MATCH(C7,Articles!$A$2:$A$148,0)) -> Estimé | N7: Oui
A8: Petit matériel | B8: Éponge | C8: S053 | D8: =INDEX(Articles!$C$2:$C$148,MATCH(C8,Articles!$A$2:$A$148,0)) -> Éponge | E8: =INDEX(Articles!$B$2:$B$148,MATCH(C8,Articles!$A$2:$A$148,0)) -> LPD | F8: 1 | G8: =IF(INDEX(Articles!$G$2:$G$148,MATCH(C8,Articles!$A$2:$A$148,0))="","",INDEX(Articles!$G$2:$G$148,MATCH(C8,Articles!$A$2:$A$148,0))) -> 1500 | H8: =IF(G8="",0,F8*G8) -> 1500 | I8: =IF(INDEX(Articles!$E$2:$E$148,MATCH(C8,Articles!$A$2:$A$148,0))="","",INDEX(Articles!$E$2:$E$148,MATCH(C8,Articles!$A$2:$A$148,0))) | J8: =IF(I8="","",F8*I8) | K8: =INDEX(Articles!$H$2:$H$148,MATCH(C8,Articles!$A$2:$A$148,0)) -> Fixé | L8: =INDEX(Articles!$F$2:$F$148,MATCH(C8,Articles!$A$2:$A$148,0)) -> Inconnu | N8: Oui
A9: Géométrie | B9: Règle | C9: S011 | D9: =INDEX(Articles!$C$2:$C$148,MATCH(C9,Articles!$A$2:$A$148,0)) -> Règle plastique transparente 20 cm | E9: =INDEX(Articles!$B$2:$B$148,MATCH(C9,Articles!$A$2:$A$148,0)) -> LPD | F9: 1 | G9: =IF(INDEX(Articles!$G$2:$G$148,MATCH(C9,Articles!$A$2:$A$148,0))="","",INDEX(Articles!$G$2:$G$148,MATCH(C9,Articles!$A$2:$A$148,0))) -> 100 | H9: =IF(G9="",0,F9*G9) -> 100 | I9: =IF(INDEX(Articles!$E$2:$E$148,MATCH(C9,Articles!$A$2:$A$148,0))="","",INDEX(Articles!$E$2:$E$148,MATCH(C9,Articles!$A$2:$A$148,0))) | J9: =IF(I9="","",F9*I9) | K9: =INDEX(Articles!$H$2:$H$148,MATCH(C9,Articles!$A$2:$A$148,0)) -> Fixé | L9: =INDEX(Articles!$F$2:$F$148,MATCH(C9,Articles!$A$2:$A$148,0)) -> Inconnu | N9: Oui
A10: Écriture | B10: Crayon noir | C10: S065 | D10: =INDEX(Articles!$C$2:$C$148,MATCH(C10,Articles!$A$2:$A$148,0)) -> Crayon papier (vendu à l'unité) | E10: =INDEX(Articles!$B$2:$B$148,MATCH(C10,Articles!$A$2:$A$148,0)) -> LPD | F10: 1 | G10: =IF(INDEX(Articles!$G$2:$G$148,MATCH(C10,Articles!$A$2:$A$148,0))="","",INDEX(Articles!$G$2:$G$148,MATCH(C10,Articles!$A$2:$A$148,0))) -> 75 | H10: =IF(G10="",0,F10*G10) -> 75 | I10: =IF(INDEX(Articles!$E$2:$E$148,MATCH(C10,Articles!$A$2:$A$148,0))="","",INDEX(Articles!$E$2:$E$148,MATCH(C10,Articles!$A$2:$A$148,0))) | J10: =IF(I10="","",F10*I10) | K10: =INDEX(Articles!$H$2:$H$148,MATCH(C10,Articles!$A$2:$A$148,0)) -> Fixé | L10: =INDEX(Articles!$F$2:$F$148,MATCH(C10,Articles!$A$2:$A$148,0)) -> Inconnu | N10: Oui
A11: Écriture | B11: Bic bleu | C11: SAC-065 | D11: =INDEX(Articles!$C$2:$C$148,MATCH(C11,Articles!$A$2:$A$148,0)) -> Stylo à bille Schneider Tops 505 M bleu | E11: =INDEX(Articles!$B$2:$B$148,MATCH(C11,Articles!$A$2:$A$148,0)) -> Papex | F11: 2 | G11: =IF(INDEX(Articles!$G$2:$G$148,MATCH(C11,Articles!$A$2:$A$148,0))="","",INDEX(Articles!$G$2:$G$148,MATCH(C11,Articles!$A$2:$A$148,0))) -> 100 | H11: =IF(G11="",0,F11*G11) -> 200 | I11: =IF(INDEX(Articles!$E$2:$E$148,MATCH(C11,Articles!$A$2:$A$148,0))="","",INDEX(Articles!$E$2:$E$148,MATCH(C11,Articles!$A$2:$A$148,0))) | J11: =IF(I11="","",F11*I11) | K11: =INDEX(Articles!$H$2:$H$148,MATCH(C11,Articles!$A$2:$A$148,0)) -> Fixé | L11: =INDEX(Articles!$F$2:$F$148,MATCH(C11,Articles!$A$2:$A$148,0)) -> Inconnu | N11: Oui
A12: Art & dessin | B12: Paquet de crayons de couleur | C12: SAC-019 | D12: =INDEX(Articles!$C$2:$C$148,MATCH(C12,Articles!$A$2:$A$148,0)) -> Crayons de couleur Maped, boîte de 12 | E12: =INDEX(Articles!$B$2:$B$148,MATCH(C12,Articles!$A$2:$A$148,0)) -> Papex | F12: 1 | G12: =IF(INDEX(Articles!$G$2:$G$148,MATCH(C12,Articles!$A$2:$A$148,0))="","",INDEX(Articles!$G$2:$G$148,MATCH(C12,Articles!$A$2:$A$148,0))) -> 900 | H12: =IF(G12="",0,F12*G12) -> 900 | I12: =IF(INDEX(Articles!$E$2:$E$148,MATCH(C12,Articles!$A$2:$A$148,0))="","",INDEX(Articles!$E$2:$E$148,MATCH(C12,Articles!$A$2:$A$148,0))) -> 650 | J12: =IF(I12="","",F12*I12) -> 650 | K12: =INDEX(Articles!$H$2:$H$148,MATCH(C12,Articles!$A$2:$A$148,0)) -> Estimé | L12: =INDEX(Articles!$F$2:$F$148,MATCH(C12,Articles!$A$2:$A$148,0)) -> Estimé | N12: Oui
D13: Lignes sans prix de vente (à fournir) | H13: =COUNTIF(G6:G12,"") -> 0
D14: Total vente du kit (FCFA) | H14: =SUM(H6:H12) -> 4225
D15: Coût de revient connu (FCFA) | H15: =SUM(J6:J12) -> 1600
D16: Lignes sans prix d'achat | H16: =COUNTIF(I6:I12,"") -> 4
D17: Marge sur les lignes au coût connu (FCFA) | H17: =SUMPRODUCT((I6:I12<>"")*H6:H12)-H15 -> 750
D18: Nombre de cahiers (ligne « X cahiers » dans l'app) | H18: =SUMIF(A6:A12,"Cahiers",F6:F12) -> 2
D19: Part du prix de vente reposant sur des PV estimés | H19: =IF(H14=0,0,SUMIF(K6:K12,"<>Fixé",H6:H12)/H14) -> 0.34319527
D20: Statut du coût | H20: =IF(H13>0,"Total incomplet : "&H13&" prix de vente à fournir",IF(H16>0,"Coût incomplet : "&H16&" ligne(s) sans prix d'achat","Complet")) -> Coût incomplet : 4 ligne(s) sans prix d'achat
D22: Proposés décochés : livres du Complet (non comptés, cochables par le client)
A23: Manuels au programme | B23: Didactikos Langue et communication | C23: DID-6913 | D23: =INDEX(Articles!$C$2:$C$148,MATCH(C23,Articles!$A$2:$A$148,0)) -> Langue et communication C.I. | G23: =INDEX(Articles!$G$2:$G$148,MATCH(C23,Articles!$A$2:$A$148,0)) -> 3890 | N23: Non
A24: Manuels au programme | B24: Didactikos Mathématiques | C24: DID-6936 | D24: =INDEX(Articles!$C$2:$C$148,MATCH(C24,Articles!$A$2:$A$148,0)) -> Mathématiques C.I. | G24: =INDEX(Articles!$G$2:$G$148,MATCH(C24,Articles!$A$2:$A$148,0)) -> 3890 | N24: Non
A25: Manuels au programme | B25: Didactikos Découverte du monde | C25: DID-6949 | D25: =INDEX(Articles!$C$2:$C$148,MATCH(C25,Articles!$A$2:$A$148,0)) -> Découverte du monde C.I. | G25: =INDEX(Articles!$G$2:$G$148,MATCH(C25,Articles!$A$2:$A$148,0)) -> 3890 | N25: Non
D26: Total si tous les livres sont cochés (FCFA) | H26: =H14+SUM(G23:G25) -> 15895
D27: Option décochée par défaut, non comptée : | E27: =INDEX(Articles!$C$2:$C$148,MATCH("S027",Articles!$A$2:$A$148,0)) -> Cartable rigide bleu marine | H27: =INDEX(Articles!$G$2:$G$148,MATCH("S027",Articles!$A$2:$A$148,0)) -> 7500
D28: Manquants : | E28: Cahier double ligne (1)
A31: CI — Complet
A32: Groupe (app) | B32: Besoin (liste) | C32: ID | D32: Désignation | E32: Fournisseur | F32: Qté | G32: PV unit. (FCFA) | H32: Sous-total vente | I32: PA unit. (FCFA) | J32: Sous-total achat | K32: Statut vente | L32: Statut achat | M32: Remarque | N32: Coché par défaut
A33: Cahiers | B33: Cahier 32 pages | C33: SAC-048 | D33: =INDEX(Articles!$C$2:$C$148,MATCH(C33,Articles!$A$2:$A$148,0)) -> Cahier Calligraphe 96 pages 17x22 56 g seyès | E33: =INDEX(Articles!$B$2:$B$148,MATCH(C33,Articles!$A$2:$A$148,0)) -> Papex | F33: 2 | G33: =IF(INDEX(Articles!$G$2:$G$148,MATCH(C33,Articles!$A$2:$A$148,0))="","",INDEX(Articles!$G$2:$G$148,MATCH(C33,Articles!$A$2:$A$148,0))) -> 450 | H33: =IF(G33="",0,F33*G33) -> 900 | I33: =IF(INDEX(Articles!$E$2:$E$148,MATCH(C33,Articles!$A$2:$A$148,0))="","",INDEX(Articles!$E$2:$E$148,MATCH(C33,Articles!$A$2:$A$148,0))) -> 350 | J33: =IF(I33="","",F33*I33) -> 700 | K33: =INDEX(Articles!$H$2:$H$148,MATCH(C33,Articles!$A$2:$A$148,0)) -> Fixé | L33: =INDEX(Articles!$F$2:$F$148,MATCH(C33,Articles!$A$2:$A$148,0)) -> Confirmé | M33: 96 p Calligraphe (32 p absent) | N33: Oui
A34: Ardoise | B34: Ardoise | C34: CIS-ardoise | D34: =INDEX(Articles!$C$2:$C$148,MATCH(C34,Articles!$A$2:$A$148,0)) -> Ardoise quadrillée avec poignée | E34: =INDEX(Articles!$B$2:$B$148,MATCH(C34,Articles!$A$2:$A$148,0)) -> Cissé & Frères | F34: 1 | G34: =IF(INDEX(Articles!$G$2:$G$148,MATCH(C34,Articles!$A$2:$A$148,0))="","",INDEX(Articles!$G$2:$G$148,MATCH(C34,Articles!$A$2:$A$148,0))) -> 2500 | H34: =IF(G34="",0,F34*G34) -> 2500 | I34: =IF(INDEX(Articles!$E$2:$E$148,MATCH(C34,Articles!$A$2:$A$148,0))="","",INDEX(Articles!$E$2:$E$148,MATCH(C34,Articles!$A$2:$A$148,0))) -> 1500 | J34: =IF(I34="","",F34*I34) -> 1500 | K34: =INDEX(Articles!$H$2:$H$148,MATCH(C34,Articles!$A$2:$A$148,0)) -> Fixé | L34: =INDEX(Articles!$F$2:$F$148,MATCH(C34,Articles!$A$2:$A$148,0)) -> Confirmé | N34: Oui
A35: Petit matériel | B35: Éponge | C35: S053 | D35: =INDEX(Articles!$C$2:$C$148,MATCH(C35,Articles!$A$2:$A$148,0)) -> Éponge | E35: =INDEX(Articles!$B$2:$B$148,MATCH(C35,Articles!$A$2:$A$148,0)) -> LPD | F35: 1 | G35: =IF(INDEX(Articles!$G$2:$G$148,MATCH(C35,Articles!$A$2:$A$148,0))="","",INDEX(Articles!$G$2:$G$148,MATCH(C35,Articles!$A$2:$A$148,0))) -> 1500 | H35: =IF(G35="",0,F35*G35) -> 1500 | I35: =IF(INDEX(Articles!$E$2:$E$148,MATCH(C35,Articles!$A$2:$A$148,0))="","",INDEX(Articles!$E$2:$E$148,MATCH(C35,Articles!$A$2:$A$148,0))) | J35: =IF(I35="","",F35*I35) | K35: =INDEX(Articles!$H$2:$H$148,MATCH(C35,Articles!$A$2:$A$148,0)) -> Fixé | L35: =INDEX(Articles!$F$2:$F$148,MATCH(C35,Articles!$A$2:$A$148,0)) -> Inconnu | N35: Oui
A36: Géométrie | B36: Règle | C36: S069 | D36: =INDEX(Articles!$C$2:$C$148,MATCH(C36,Articles!$A$2:$A$148,0)) -> Règle métal 30 cm | E36: =INDEX(Articles!$B$2:$B$148,MATCH(C36,Articles!$A$2:$A$148,0)) -> LPD | F36: 1 | G36: =IF(INDEX(Articles!$G$2:$G$148,MATCH(C36,Articles!$A$2:$A$148,0))="","",INDEX(Articles!$G$2:$G$148,MATCH(C36,Articles!$A$2:$A$148,0))) -> 550 | H36: =IF(G36="",0,F36*G36) -> 550 | I36: =IF(INDEX(Articles!$E$2:$E$148,MATCH(C36,Articles!$A$2:$A$148,0))="","",INDEX(Articles!$E$2:$E$148,MATCH(C36,Articles!$A$2:$A$148,0))) -> 400 | J36: =IF(I36="","",F36*I36) -> 400 | K36: =INDEX(Articles!$H$2:$H$148,MATCH(C36,Articles!$A$2:$A$148,0)) -> Fixé | L36: =INDEX(Articles!$F$2:$F$148,MATCH(C36,Articles!$A$2:$A$148,0)) -> Estimé | N36: Oui
A37: Écriture | B37: Crayon noir | C37: S065 | D37: =INDEX(Articles!$C$2:$C$148,MATCH(C37,Articles!$A$2:$A$148,0)) -> Crayon papier (vendu à l'unité) | E37: =INDEX(Articles!$B$2:$B$148,MATCH(C37,Articles!$A$2:$A$148,0)) -> LPD | F37: 1 | G37: =IF(INDEX(Articles!$G$2:$G$148,MATCH(C37,Articles!$A$2:$A$148,0))="","",INDEX(Articles!$G$2:$G$148,MATCH(C37,Articles!$A$2:$A$148,0))) -> 75 | H37: =IF(G37="",0,F37*G37) -> 75 | I37: =IF(INDEX(Articles!$E$2:$E$148,MATCH(C37,Articles!$A$2:$A$148,0))="","",INDEX(Articles!$E$2:$E$148,MATCH(C37,Articles!$A$2:$A$148,0))) | J37: =IF(I37="","",F37*I37) | K37: =INDEX(Articles!$H$2:$H$148,MATCH(C37,Articles!$A$2:$A$148,0)) -> Fixé | L37: =INDEX(Articles!$F$2:$F$148,MATCH(C37,Articles!$A$2:$A$148,0)) -> Inconnu | N37: Oui
A38: Écriture | B38: Bic bleu | C38: SAC-065 | D38: =INDEX(Articles!$C$2:$C$148,MATCH(C38,Articles!$A$2:$A$148,0)) -> Stylo à bille Schneider Tops 505 M bleu | E38: =INDEX(Articles!$B$2:$B$148,MATCH(C38,Articles!$A$2:$A$148,0)) -> Papex | F38: 2 | G38: =IF(INDEX(Articles!$G$2:$G$148,MATCH(C38,Articles!$A$2:$A$148,0))="","",INDEX(Articles!$G$2:$G$148,MATCH(C38,Articles!$A$2:$A$148,0))) -> 100 | H38: =IF(G38="",0,F38*G38) -> 200 | I38: =IF(INDEX(Articles!$E$2:$E$148,MATCH(C38,Articles!$A$2:$A$148,0))="","",INDEX(Articles!$E$2:$E$148,MATCH(C38,Articles!$A$2:$A$148,0))) | J38: =IF(I38="","",F38*I38) | K38: =INDEX(Articles!$H$2:$H$148,MATCH(C38,Articles!$A$2:$A$148,0)) -> Fixé | L38: =INDEX(Articles!$F$2:$F$148,MATCH(C38,Articles!$A$2:$A$148,0)) -> Inconnu | N38: Oui
A39: Art & dessin | B39: Paquet de crayons de couleur | C39: SAC-024 | D39: =INDEX(Articles!$C$2:$C$148,MATCH(C39,Articles!$A$2:$A$148,0)) -> Crayons de couleur Maped Nightfall, boîte de 24 | E39: =INDEX(Articles!$B$2:$B$148,MATCH(C39,Articles!$A$2:$A$148,0)) -> Papex | F39: 1 | G39: =IF(INDEX(Articles!$G$2:$G$148,MATCH(C39,Articles!$A$2:$A$148,0))="","",INDEX(Articles!$G$2:$G$148,MATCH(C39,Articles!$A$2:$A$148,0))) -> 1600 | H39: =IF(G39="",0,F39*G39) -> 1600 | I39: =IF(INDEX(Articles!$E$2:$E$148,MATCH(C39,Articles!$A$2:$A$148,0))="","",INDEX(Articles!$E$2:$E$148,MATCH(C39,Articles!$A$2:$A$148,0))) -> 1300 | J39: =IF(I39="","",F39*I39) -> 1300 | K39: =INDEX(Articles!$H$2:$H$148,MATCH(C39,Articles!$A$2:$A$148,0)) -> Estimé | L39: =INDEX(Articles!$F$2:$F$148,MATCH(C39,Articles!$A$2:$A$148,0)) -> Estimé | N39: Oui
A40: Manuels au programme | B40: Didactikos Langue et communication | C40: DID-6913 | D40: =INDEX(Articles!$C$2:$C$148,MATCH(C40,Articles!$A$2:$A$148,0)) -> Langue et communication C.I. | E40: =INDEX(Articles!$B$2:$B$148,MATCH(C40,Articles!$A$2:$A$148,0)) -> LPD | F40: 1 | G40: =IF(INDEX(Articles!$G$2:$G$148,MATCH(C40,Articles!$A$2:$A$148,0))="","",INDEX(Articles!$G$2:$G$148,MATCH(C40,Articles!$A$2:$A$148,0))) -> 3890 | H40: =IF(G40="",0,F40*G40) -> 3890 | I40: =IF(INDEX(Articles!$E$2:$E$148,MATCH(C40,Articles!$A$2:$A$148,0))="","",INDEX(Articles!$E$2:$E$148,MATCH(C40,Articles!$A$2:$A$148,0))) -> 2890 | J40: =IF(I40="","",F40*I40) -> 2890 | K40: =INDEX(Articles!$H$2:$H$148,MATCH(C40,Articles!$A$2:$A$148,0)) -> Fixé | L40: =INDEX(Articles!$F$2:$F$148,MATCH(C40,Articles!$A$2:$A$148,0)) -> Estimé | M40: « Didactikos langue, maths, DDM : 1 » lu comme 1 manuel par matière | N40: Oui
A41: Manuels au programme | B41: Didactikos Mathématiques | C41: DID-6936 | D41: =INDEX(Articles!$C$2:$C$148,MATCH(C41,Articles!$A$2:$A$148,0)) -> Mathématiques C.I. | E41: =INDEX(Articles!$B$2:$B$148,MATCH(C41,Articles!$A$2:$A$148,0)) -> LPD | F41: 1 | G41: =IF(INDEX(Articles!$G$2:$G$148,MATCH(C41,Articles!$A$2:$A$148,0))="","",INDEX(Articles!$G$2:$G$148,MATCH(C41,Articles!$A$2:$A$148,0))) -> 3890 | H41: =IF(G41="",0,F41*G41) -> 3890 | I41: =IF(INDEX(Articles!$E$2:$E$148,MATCH(C41,Articles!$A$2:$A$148,0))="","",INDEX(Articles!$E$2:$E$148,MATCH(C41,Articles!$A$2:$A$148,0))) -> 2890 | J41: =IF(I41="","",F41*I41) -> 2890 | K41: =INDEX(Articles!$H$2:$H$148,MATCH(C41,Articles!$A$2:$A$148,0)) -> Fixé | L41: =INDEX(Articles!$F$2:$F$148,MATCH(C41,Articles!$A$2:$A$148,0)) -> Estimé | M41: « Didactikos langue, maths, DDM : 1 » lu comme 1 manuel par matière | N41: Oui
A42: Manuels au programme | B42: Didactikos Découverte du monde | C42: DID-6949 | D42: =INDEX(Articles!$C$2:$C$148,MATCH(C42,Articles!$A$2:$A$148,0)) -> Découverte du monde C.I. | E42: =INDEX(Articles!$B$2:$B$148,MATCH(C42,Articles!$A$2:$A$148,0)) -> LPD | F42: 1 | G42: =IF(INDEX(Articles!$G$2:$G$148,MATCH(C42,Articles!$A$2:$A$148,0))="","",INDEX(Articles!$G$2:$G$148,MATCH(C42,Articles!$A$2:$A$148,0))) -> 3890 | H42: =IF(G42="",0,F42*G42) -> 3890 | I42: =IF(INDEX(Articles!$E$2:$E$148,MATCH(C42,Articles!$A$2:$A$148,0))="","",INDEX(Articles!$E$2:$E$148,MATCH(C42,Articles!$A$2:$A$148,0))) -> 2890 | J42: =IF(I42="","",F42*I42) -> 2890 | K42: =INDEX(Articles!$H$2:$H$148,MATCH(C42,Articles!$A$2:$A$148,0)) -> Fixé | L42: =INDEX(Articles!$F$2:$F$148,MATCH(C42,Articles!$A$2:$A$148,0)) -> Estimé | M42: « Didactikos langue, maths, DDM : 1 » lu comme 1 manuel par matière | N42: Oui
D43: Lignes sans prix de vente (à fournir) | H43: =COUNTIF(G33:G42,"") -> 0
D44: Total vente du kit (FCFA) | H44: =SUM(H33:H42) -> 18995
D45: Coût de revient connu (FCFA) | H45: =SUM(J33:J42) -> 12570
D46: Lignes sans prix d'achat | H46: =COUNTIF(I33:I42,"") -> 3
D47: Marge sur les lignes au coût connu (FCFA) | H47: =SUMPRODUCT((I33:I42<>"")*H33:H42)-H45 -> 4650
D48: Nombre de cahiers (ligne « X cahiers » dans l'app) | H48: =SUMIF(A33:A42,"Cahiers",F33:F42) -> 2
D49: Part du prix de vente reposant sur des PV estimés | H49: =IF(H44=0,0,SUMIF(K33:K42,"<>Fixé",H33:H42)/H44) -> 0.084232693
D50: Statut du coût | H50: =IF(H43>0,"Total incomplet : "&H43&" prix de vente à fournir",IF(H46>0,"Coût incomplet : "&H46&" ligne(s) sans prix d'achat","Complet")) -> Coût incomplet : 3 ligne(s) sans prix d'achat
D51: Option décochée par défaut, non comptée : | E51: =INDEX(Articles!$C$2:$C$148,MATCH("S027",Articles!$A$2:$A$148,0)) -> Cartable rigide bleu marine | H51: =INDEX(Articles!$G$2:$G$148,MATCH("S027",Articles!$A$2:$A$148,0)) -> 7500
D52: Manquants : | E52: Cahier double ligne (1)
A55: CI — Confort
A56: Groupe (app) | B56: Besoin (liste) | C56: ID | D56: Désignation | E56: Fournisseur | F56: Qté | G56: PV unit. (FCFA) | H56: Sous-total vente | I56: PA unit. (FCFA) | J56: Sous-total achat | K56: Statut vente | L56: Statut achat | M56: Remarque | N56: Coché par défaut
A57: Cahiers | B57: Cahier 32 pages | C57: SAC-048 | D57: =INDEX(Articles!$C$2:$C$148,MATCH(C57,Articles!$A$2:$A$148,0)) -> Cahier Calligraphe 96 pages 17x22 56 g seyès | E57: =INDEX(Articles!$B$2:$B$148,MATCH(C57,Articles!$A$2:$A$148,0)) -> Papex | F57: 2 | G57: =IF(INDEX(Articles!$G$2:$G$148,MATCH(C57,Articles!$A$2:$A$148,0))="","",INDEX(Articles!$G$2:$G$148,MATCH(C57,Articles!$A$2:$A$148,0))) -> 450 | H57: =IF(G57="",0,F57*G57) -> 900 | I57: =IF(INDEX(Articles!$E$2:$E$148,MATCH(C57,Articles!$A$2:$A$148,0))="","",INDEX(Articles!$E$2:$E$148,MATCH(C57,Articles!$A$2:$A$148,0))) -> 350 | J57: =IF(I57="","",F57*I57) -> 700 | K57: =INDEX(Articles!$H$2:$H$148,MATCH(C57,Articles!$A$2:$A$148,0)) -> Fixé | L57: =INDEX(Articles!$F$2:$F$148,MATCH(C57,Articles!$A$2:$A$148,0)) -> Confirmé | M57: 96 p Calligraphe (32 p absent) | N57: Oui
A58: Ardoise | B58: Ardoise | C58: CIS-ardoise | D58: =INDEX(Articles!$C$2:$C$148,MATCH(C58,Articles!$A$2:$A$148,0)) -> Ardoise quadrillée avec poignée | E58: =INDEX(Articles!$B$2:$B$148,MATCH(C58,Articles!$A$2:$A$148,0)) -> Cissé & Frères | F58: 1 | G58: =IF(INDEX(Articles!$G$2:$G$148,MATCH(C58,Articles!$A$2:$A$148,0))="","",INDEX(Articles!$G$2:$G$148,MATCH(C58,Articles!$A$2:$A$148,0))) -> 2500 | H58: =IF(G58="",0,F58*G58) -> 2500 | I58: =IF(INDEX(Articles!$E$2:$E$148,MATCH(C58,Articles!$A$2:$A$148,0))="","",INDEX(Articles!$E$2:$E$148,MATCH(C58,Articles!$A$2:$A$148,0))) -> 1500 | J58: =IF(I58="","",F58*I58) -> 1500 | K58: =INDEX(Articles!$H$2:$H$148,MATCH(C58,Articles!$A$2:$A$148,0)) -> Fixé | L58: =INDEX(Articles!$F$2:$F$148,MATCH(C58,Articles!$A$2:$A$148,0)) -> Confirmé | N58: Oui
A59: Petit matériel | B59: Éponge | C59: S053 | D59: =INDEX(Articles!$C$2:$C$148,MATCH(C59,Articles!$A$2:$A$148,0)) -> Éponge | E59: =INDEX(Articles!$B$2:$B$148,MATCH(C59,Articles!$A$2:$A$148,0)) -> LPD | F59: 1 | G59: =IF(INDEX(Articles!$G$2:$G$148,MATCH(C59,Articles!$A$2:$A$148,0))="","",INDEX(Articles!$G$2:$G$148,MATCH(C59,Articles!$A$2:$A$148,0))) -> 1500 | H59: =IF(G59="",0,F59*G59) -> 1500 | I59: =IF(INDEX(Articles!$E$2:$E$148,MATCH(C59,Articles!$A$2:$A$148,0))="","",INDEX(Articles!$E$2:$E$148,MATCH(C59,Articles!$A$2:$A$148,0))) | J59: =IF(I59="","",F59*I59) | K59: =INDEX(Articles!$H$2:$H$148,MATCH(C59,Articles!$A$2:$A$148,0)) -> Fixé | L59: =INDEX(Articles!$F$2:$F$148,MATCH(C59,Articles!$A$2:$A$148,0)) -> Inconnu | N59: Oui
A60: Géométrie | B60: Règle | C60: S069 | D60: =INDEX(Articles!$C$2:$C$148,MATCH(C60,Articles!$A$2:$A$148,0)) -> Règle métal 30 cm | E60: =INDEX(Articles!$B$2:$B$148,MATCH(C60,Articles!$A$2:$A$148,0)) -> LPD | F60: 1 | G60: =IF(INDEX(Articles!$G$2:$G$148,MATCH(C60,Articles!$A$2:$A$148,0))="","",INDEX(Articles!$G$2:$G$148,MATCH(C60,Articles!$A$2:$A$148,0))) -> 550 | H60: =IF(G60="",0,F60*G60) -> 550 | I60: =IF(INDEX(Articles!$E$2:$E$148,MATCH(C60,Articles!$A$2:$A$148,0))="","",INDEX(Articles!$E$2:$E$148,MATCH(C60,Articles!$A$2:$A$148,0))) -> 400 | J60: =IF(I60="","",F60*I60) -> 400 | K60: =INDEX(Articles!$H$2:$H$148,MATCH(C60,Articles!$A$2:$A$148,0)) -> Fixé | L60: =INDEX(Articles!$F$2:$F$148,MATCH(C60,Articles!$A$2:$A$148,0)) -> Estimé | N60: Oui
A61: Écriture | B61: Crayon noir | C61: S065 | D61: =INDEX(Articles!$C$2:$C$148,MATCH(C61,Articles!$A$2:$A$148,0)) -> Crayon papier (vendu à l'unité) | E61: =INDEX(Articles!$B$2:$B$148,MATCH(C61,Articles!$A$2:$A$148,0)) -> LPD | F61: 1 | G61: =IF(INDEX(Articles!$G$2:$G$148,MATCH(C61,Articles!$A$2:$A$148,0))="","",INDEX(Articles!$G$2:$G$148,MATCH(C61,Articles!$A$2:$A$148,0))) -> 75 | H61: =IF(G61="",0,F61*G61) -> 75 | I61: =IF(INDEX(Articles!$E$2:$E$148,MATCH(C61,Articles!$A$2:$A$148,0))="","",INDEX(Articles!$E$2:$E$148,MATCH(C61,Articles!$A$2:$A$148,0))) | J61: =IF(I61="","",F61*I61) | K61: =INDEX(Articles!$H$2:$H$148,MATCH(C61,Articles!$A$2:$A$148,0)) -> Fixé | L61: =INDEX(Articles!$F$2:$F$148,MATCH(C61,Articles!$A$2:$A$148,0)) -> Inconnu | N61: Oui
A62: Écriture | B62: Bic bleu | C62: SAC-065 | D62: =INDEX(Articles!$C$2:$C$148,MATCH(C62,Articles!$A$2:$A$148,0)) -> Stylo à bille Schneider Tops 505 M bleu | E62: =INDEX(Articles!$B$2:$B$148,MATCH(C62,Articles!$A$2:$A$148,0)) -> Papex | F62: 2 | G62: =IF(INDEX(Articles!$G$2:$G$148,MATCH(C62,Articles!$A$2:$A$148,0))="","",INDEX(Articles!$G$2:$G$148,MATCH(C62,Articles!$A$2:$A$148,0))) -> 100 | H62: =IF(G62="",0,F62*G62) -> 200 | I62: =IF(INDEX(Articles!$E$2:$E$148,MATCH(C62,Articles!$A$2:$A$148,0))="","",INDEX(Articles!$E$2:$E$148,MATCH(C62,Articles!$A$2:$A$148,0))) | J62: =IF(I62="","",F62*I62) | K62: =INDEX(Articles!$H$2:$H$148,MATCH(C62,Articles!$A$2:$A$148,0)) -> Fixé | L62: =INDEX(Articles!$F$2:$F$148,MATCH(C62,Articles!$A$2:$A$148,0)) -> Inconnu | N62: Oui
A63: Art & dessin | B63: Paquet de crayons de couleur | C63: SAC-024 | D63: =INDEX(Articles!$C$2:$C$148,MATCH(C63,Articles!$A$2:$A$148,0)) -> Crayons de couleur Maped Nightfall, boîte de 24 | E63: =INDEX(Articles!$B$2:$B$148,MATCH(C63,Articles!$A$2:$A$148,0)) -> Papex | F63: 1 | G63: =IF(INDEX(Articles!$G$2:$G$148,MATCH(C63,Articles!$A$2:$A$148,0))="","",INDEX(Articles!$G$2:$G$148,MATCH(C63,Articles!$A$2:$A$148,0))) -> 1600 | H63: =IF(G63="",0,F63*G63) -> 1600 | I63: =IF(INDEX(Articles!$E$2:$E$148,MATCH(C63,Articles!$A$2:$A$148,0))="","",INDEX(Articles!$E$2:$E$148,MATCH(C63,Articles!$A$2:$A$148,0))) -> 1300 | J63: =IF(I63="","",F63*I63) -> 1300 | K63: =INDEX(Articles!$H$2:$H$148,MATCH(C63,Articles!$A$2:$A$148,0)) -> Estimé | L63: =INDEX(Articles!$F$2:$F$148,MATCH(C63,Articles!$A$2:$A$148,0)) -> Estimé | N63: Oui
A64: Manuels au programme | B64: Didactikos Langue et communication | C64: DID-6913 | D64: =INDEX(Articles!$C$2:$C$148,MATCH(C64,Articles!$A$2:$A$148,0)) -> Langue et communication C.I. | E64: =INDEX(Articles!$B$2:$B$148,MATCH(C64,Articles!$A$2:$A$148,0)) -> LPD | F64: 1 | G64: =IF(INDEX(Articles!$G$2:$G$148,MATCH(C64,Articles!$A$2:$A$148,0))="","",INDEX(Articles!$G$2:$G$148,MATCH(C64,Articles!$A$2:$A$148,0))) -> 3890 | H64: =IF(G64="",0,F64*G64) -> 3890 | I64: =IF(INDEX(Articles!$E$2:$E$148,MATCH(C64,Articles!$A$2:$A$148,0))="","",INDEX(Articles!$E$2:$E$148,MATCH(C64,Articles!$A$2:$A$148,0))) -> 2890 | J64: =IF(I64="","",F64*I64) -> 2890 | K64: =INDEX(Articles!$H$2:$H$148,MATCH(C64,Articles!$A$2:$A$148,0)) -> Fixé | L64: =INDEX(Articles!$F$2:$F$148,MATCH(C64,Articles!$A$2:$A$148,0)) -> Estimé | M64: « Didactikos langue, maths, DDM : 1 » lu comme 1 manuel par matière | N64: Oui
A65: Manuels au programme | B65: Didactikos Mathématiques | C65: DID-6936 | D65: =INDEX(Articles!$C$2:$C$148,MATCH(C65,Articles!$A$2:$A$148,0)) -> Mathématiques C.I. | E65: =INDEX(Articles!$B$2:$B$148,MATCH(C65,Articles!$A$2:$A$148,0)) -> LPD | F65: 1 | G65: =IF(INDEX(Articles!$G$2:$G$148,MATCH(C65,Articles!$A$2:$A$148,0))="","",INDEX(Articles!$G$2:$G$148,MATCH(C65,Articles!$A$2:$A$148,0))) -> 3890 | H65: =IF(G65="",0,F65*G65) -> 3890 | I65: =IF(INDEX(Articles!$E$2:$E$148,MATCH(C65,Articles!$A$2:$A$148,0))="","",INDEX(Articles!$E$2:$E$148,MATCH(C65,Articles!$A$2:$A$148,0))) -> 2890 | J65: =IF(I65="","",F65*I65) -> 2890 | K65: =INDEX(Articles!$H$2:$H$148,MATCH(C65,Articles!$A$2:$A$148,0)) -> Fixé | L65: =INDEX(Articles!$F$2:$F$148,MATCH(C65,Articles!$A$2:$A$148,0)) -> Estimé | M65: « Didactikos langue, maths, DDM : 1 » lu comme 1 manuel par matière | N65: Oui
A66: Manuels au programme | B66: Didactikos Découverte du monde | C66: DID-6949 | D66: =INDEX(Articles!$C$2:$C$148,MATCH(C66,Articles!$A$2:$A$148,0)) -> Découverte du monde C.I. | E66: =INDEX(Articles!$B$2:$B$148,MATCH(C66,Articles!$A$2:$A$148,0)) -> LPD | F66: 1 | G66: =IF(INDEX(Articles!$G$2:$G$148,MATCH(C66,Articles!$A$2:$A$148,0))="","",INDEX(Articles!$G$2:$G$148,MATCH(C66,Articles!$A$2:$A$148,0))) -> 3890 | H66: =IF(G66="",0,F66*G66) -> 3890 | I66: =IF(INDEX(Articles!$E$2:$E$148,MATCH(C66,Articles!$A$2:$A$148,0))="","",INDEX(Articles!$E$2:$E$148,MATCH(C66,Articles!$A$2:$A$148,0))) -> 2890 | J66: =IF(I66="","",F66*I66) -> 2890 | K66: =INDEX(Articles!$H$2:$H$148,MATCH(C66,Articles!$A$2:$A$148,0)) -> Fixé | L66: =INDEX(Articles!$F$2:$F$148,MATCH(C66,Articles!$A$2:$A$148,0)) -> Estimé | M66: « Didactikos langue, maths, DDM : 1 » lu comme 1 manuel par matière | N66: Oui
A67: Parascolaire | B67: Cahier d'activités Langue et communication | C67: DID-7364 | D67: =INDEX(Articles!$C$2:$C$148,MATCH(C67,Articles!$A$2:$A$148,0)) -> Cahier d’activités fongible LC C.I. | E67: =INDEX(Articles!$B$2:$B$148,MATCH(C67,Articles!$A$2:$A$148,0)) -> LPD | F67: 1 | G67: =IF(INDEX(Articles!$G$2:$G$148,MATCH(C67,Articles!$A$2:$A$148,0))="","",INDEX(Articles!$G$2:$G$148,MATCH(C67,Articles!$A$2:$A$148,0))) -> 2790 | H67: =IF(G67="",0,F67*G67) -> 2790 | I67: =IF(INDEX(Articles!$E$2:$E$148,MATCH(C67,Articles!$A$2:$A$148,0))="","",INDEX(Articles!$E$2:$E$148,MATCH(C67,Articles!$A$2:$A$148,0))) -> 1790 | J67: =IF(I67="","",F67*I67) -> 1790 | K67: =INDEX(Articles!$H$2:$H$148,MATCH(C67,Articles!$A$2:$A$148,0)) -> Fixé | L67: =INDEX(Articles!$F$2:$F$148,MATCH(C67,Articles!$A$2:$A$148,0)) -> Estimé | N67: Oui
A68: Parascolaire | B68: Cahier d'activités Mathématiques | C68: DID-7253 | D68: =INDEX(Articles!$C$2:$C$148,MATCH(C68,Articles!$A$2:$A$148,0)) -> Cahier d’activités mathématiques C.I. | E68: =INDEX(Articles!$B$2:$B$148,MATCH(C68,Articles!$A$2:$A$148,0)) -> LPD | F68: 1 | G68: =IF(INDEX(Articles!$G$2:$G$148,MATCH(C68,Articles!$A$2:$A$148,0))="","",INDEX(Articles!$G$2:$G$148,MATCH(C68,Articles!$A$2:$A$148,0))) -> 2790 | H68: =IF(G68="",0,F68*G68) -> 2790 | I68: =IF(INDEX(Articles!$E$2:$E$148,MATCH(C68,Articles!$A$2:$A$148,0))="","",INDEX(Articles!$E$2:$E$148,MATCH(C68,Articles!$A$2:$A$148,0))) -> 1790 | J68: =IF(I68="","",F68*I68) -> 1790 | K68: =INDEX(Articles!$H$2:$H$148,MATCH(C68,Articles!$A$2:$A$148,0)) -> Fixé | L68: =INDEX(Articles!$F$2:$F$148,MATCH(C68,Articles!$A$2:$A$148,0)) -> Estimé | N68: Oui
D69: Lignes sans prix de vente (à fournir) | H69: =COUNTIF(G57:G68,"") -> 0
D70: Total vente du kit (FCFA) | H70: =SUM(H57:H68) -> 24575
D71: Coût de revient connu (FCFA) | H71: =SUM(J57:J68) -> 16150
D72: Lignes sans prix d'achat | H72: =COUNTIF(I57:I68,"") -> 3
D73: Marge sur les lignes au coût connu (FCFA) | H73: =SUMPRODUCT((I57:I68<>"")*H57:H68)-H71 -> 6650
D74: Nombre de cahiers (ligne « X cahiers » dans l'app) | H74: =SUMIF(A57:A68,"Cahiers",F57:F68) -> 2
D75: Part du prix de vente reposant sur des PV estimés | H75: =IF(H70=0,0,SUMIF(K57:K68,"<>Fixé",H57:H68)/H70) -> 0.065106816
D76: Statut du coût | H76: =IF(H69>0,"Total incomplet : "&H69&" prix de vente à fournir",IF(H72>0,"Coût incomplet : "&H72&" ligne(s) sans prix d'achat","Complet")) -> Coût incomplet : 3 ligne(s) sans prix d'achat
D77: Option décochée par défaut, non comptée : | E77: =INDEX(Articles!$C$2:$C$148,MATCH("S027",Articles!$A$2:$A$148,0)) -> Cartable rigide bleu marine | H77: =INDEX(Articles!$G$2:$G$148,MATCH("S027",Articles!$A$2:$A$148,0)) -> 7500
D78: Manquants : | E78: Cahier double ligne (1)

Sheet CP
A1: Kit CP
A2: Liste réelle du Complexe Dar El-Hadith. Contrôle croisé avec la liste ISJA 2026-2027 (plus chargée, écoles privées).
A4: CP — Essentiel
A5: Groupe (app) | B5: Besoin (liste) | C5: ID | D5: Désignation | E5: Fournisseur | F5: Qté | G5: PV unit. (FCFA) | H5: Sous-total vente | I5: PA unit. (FCFA) | J5: Sous-total achat | K5: Statut vente | L5: Statut achat | M5: Remarque | N5: Coché par défaut
A6: Cahiers | B6: Cahier 96 pages | C6: SAC-048 | D6: =INDEX(Articles!$C$2:$C$148,MATCH(C6,Articles!$A$2:$A$148,0)) -> Cahier Calligraphe 96 pages 17x22 56 g seyès | E6: =INDEX(Articles!$B$2:$B$148,MATCH(C6,Articles!$A$2:$A$148,0)) -> Papex | F6: 2 | G6: =IF(INDEX(Articles!$G$2:$G$148,MATCH(C6,Articles!$A$2:$A$148,0))="","",INDEX(Articles!$G$2:$G$148,MATCH(C6,Articles!$A$2:$A$148,0))) -> 450 | H6: =IF(G6="",0,F6*G6) -> 900 | I6: =IF(INDEX(Articles!$E$2:$E$148,MATCH(C6,Articles!$A$2:$A$148,0))="","",INDEX(Articles!$E$2:$E$148,MATCH(C6,Articles!$A$2:$A$148,0))) -> 350 | J6: =IF(I6="","",F6*I6) -> 700 | K6: =INDEX(Articles!$H$2:$H$148,MATCH(C6,Articles!$A$2:$A$148,0)) -> Fixé | L6: =INDEX(Articles!$F$2:$F$148,MATCH(C6,Articles!$A$2:$A$148,0)) -> Confirmé | N6: Oui
A7: Ardoise | B7: Ardoise | C7: S086 | D7: =INDEX(Articles!$C$2:$C$148,MATCH(C7,Articles!$A$2:$A$148,0)) -> Ardoise scolaire | E7: =INDEX(Articles!$B$2:$B$148,MATCH(C7,Articles!$A$2:$A$148,0)) -> LPD | F7: 1 | G7: =IF(INDEX(Articles!$G$2:$G$148,MATCH(C7,Articles!$A$2:$A$148,0))="","",INDEX(Articles!$G$2:$G$148,MATCH(C7,Articles!$A$2:$A$148,0))) -> 900 | H7: =IF(G7="",0,F7*G7) -> 900 | I7: =IF(INDEX(Articles!$E$2:$E$148,MATCH(C7,Articles!$A$2:$A$148,0))="","",INDEX(Articles!$E$2:$E$148,MATCH(C7,Articles!$A$2:$A$148,0))) -> 600 | J7: =IF(I7="","",F7*I7) -> 600 | K7: =INDEX(Articles!$H$2:$H$148,MATCH(C7,Articles!$A$2:$A$148,0)) -> Fixé | L7: =INDEX(Articles!$F$2:$F$148,MATCH(C7,Articles!$A$2:$A$148,0)) -> Estimé | N7: Oui
A8: Géométrie | B8: Règle | C8: S011 | D8: =INDEX(Articles!$C$2:$C$148,MATCH(C8,Articles!$A$2:$A$148,0)) -> Règle plastique transparente 20 cm | E8: =INDEX(Articles!$B$2:$B$148,MATCH(C8,Articles!$A$2:$A$148,0)) -> LPD | F8: 1 | G8: =IF(INDEX(Articles!$G$2:$G$148,MATCH(C8,Articles!$A$2:$A$148,0))="","",INDEX(Articles!$G$2:$G$148,MATCH(C8,Articles!$A$2:$A$148,0))) -> 100 | H8: =IF(G8="",0,F8*G8) -> 100 | I8: =IF(INDEX(Articles!$E$2:$E$148,MATCH(C8,Articles!$A$2:$A$148,0))="","",INDEX(Articles!$E$2:$E$148,MATCH(C8,Articles!$A$2:$A$148,0))) | J8: =IF(I8="","",F8*I8) | K8: =INDEX(Articles!$H$2:$H$148,MATCH(C8,Articles!$A$2:$A$148,0)) -> Fixé | L8: =INDEX(Articles!$F$2:$F$148,MATCH(C8,Articles!$A$2:$A$148,0)) -> Inconnu | N8: Oui
A9: Géométrie | B9: Matériel géométrique | C9: SAC-007 | D9: =INDEX(Articles!$C$2:$C$148,MATCH(C9,Articles!$A$2:$A$148,0)) -> Kit de traçage 30 cm, 4 pièces L'écolier | E9: =INDEX(Articles!$B$2:$B$148,MATCH(C9,Articles!$A$2:$A$148,0)) -> Papex | F9: 1 | G9: =IF(INDEX(Articles!$G$2:$G$148,MATCH(C9,Articles!$A$2:$A$148,0))="","",INDEX(Articles!$G$2:$G$148,MATCH(C9,Articles!$A$2:$A$148,0))) -> 900 | H9: =IF(G9="",0,F9*G9) -> 900 | I9: =IF(INDEX(Articles!$E$2:$E$148,MATCH(C9,Articles!$A$2:$A$148,0))="","",INDEX(Articles!$E$2:$E$148,MATCH(C9,Articles!$A$2:$A$148,0))) -> 650 | J9: =IF(I9="","",F9*I9) -> 650 | K9: =INDEX(Articles!$H$2:$H$148,MATCH(C9,Articles!$A$2:$A$148,0)) -> Estimé | L9: =INDEX(Articles!$F$2:$F$148,MATCH(C9,Articles!$A$2:$A$148,0)) -> Confirmé | N9: Oui
A10: Écriture | B10: Bic bleu | C10: SAC-065 | D10: =INDEX(Articles!$C$2:$C$148,MATCH(C10,Articles!$A$2:$A$148,0)) -> Stylo à bille Schneider Tops 505 M bleu | E10: =INDEX(Articles!$B$2:$B$148,MATCH(C10,Articles!$A$2:$A$148,0)) -> Papex | F10: 2 | G10: =IF(INDEX(Articles!$G$2:$G$148,MATCH(C10,Articles!$A$2:$A$148,0))="","",INDEX(Articles!$G$2:$G$148,MATCH(C10,Articles!$A$2:$A$148,0))) -> 100 | H10: =IF(G10="",0,F10*G10) -> 200 | I10: =IF(INDEX(Articles!$E$2:$E$148,MATCH(C10,Articles!$A$2:$A$148,0))="","",INDEX(Articles!$E$2:$E$148,MATCH(C10,Articles!$A$2:$A$148,0))) | J10: =IF(I10="","",F10*I10) | K10: =INDEX(Articles!$H$2:$H$148,MATCH(C10,Articles!$A$2:$A$148,0)) -> Fixé | L10: =INDEX(Articles!$F$2:$F$148,MATCH(C10,Articles!$A$2:$A$148,0)) -> Inconnu | N10: Oui
A11: Écriture | B11: Bic vert | C11: SAC-104 | D11: =INDEX(Articles!$C$2:$C$148,MATCH(C11,Articles!$A$2:$A$148,0)) -> Stylo à bille Schneider Tops 505 M vert | E11: =INDEX(Articles!$B$2:$B$148,MATCH(C11,Articles!$A$2:$A$148,0)) -> Papex | F11: 1 | G11: =IF(INDEX(Articles!$G$2:$G$148,MATCH(C11,Articles!$A$2:$A$148,0))="","",INDEX(Articles!$G$2:$G$148,MATCH(C11,Articles!$A$2:$A$148,0))) -> 100 | H11: =IF(G11="",0,F11*G11) -> 100 | I11: =IF(INDEX(Articles!$E$2:$E$148,MATCH(C11,Articles!$A$2:$A$148,0))="","",INDEX(Articles!$E$2:$E$148,MATCH(C11,Articles!$A$2:$A$148,0))) | J11: =IF(I11="","",F11*I11) | K11: =INDEX(Articles!$H$2:$H$148,MATCH(C11,Articles!$A$2:$A$148,0)) -> Fixé | L11: =INDEX(Articles!$F$2:$F$148,MATCH(C11,Articles!$A$2:$A$148,0)) -> Inconnu | N11: Oui
A12: Art & dessin | B12: Paquet de crayons de couleur | C12: SAC-019 | D12: =INDEX(Articles!$C$2:$C$148,MATCH(C12,Articles!$A$2:$A$148,0)) -> Crayons de couleur Maped, boîte de 12 | E12: =INDEX(Articles!$B$2:$B$148,MATCH(C12,Articles!$A$2:$A$148,0)) -> Papex | F12: 1 | G12: =IF(INDEX(Articles!$G$2:$G$148,MATCH(C12,Articles!$A$2:$A$148,0))="","",INDEX(Articles!$G$2:$G$148,MATCH(C12,Articles!$A$2:$A$148,0))) -> 900 | H12: =IF(G12="",0,F12*G12) -> 900 | I12: =IF(INDEX(Articles!$E$2:$E$148,MATCH(C12,Articles!$A$2:$A$148,0))="","",INDEX(Articles!$E$2:$E$148,MATCH(C12,Articles!$A$2:$A$148,0))) -> 650 | J12: =IF(I12="","",F12*I12) -> 650 | K12: =INDEX(Articles!$H$2:$H$148,MATCH(C12,Articles!$A$2:$A$148,0)) -> Estimé | L12: =INDEX(Articles!$F$2:$F$148,MATCH(C12,Articles!$A$2:$A$148,0)) -> Estimé | N12: Oui
D13: Lignes sans prix de vente (à fournir) | H13: =COUNTIF(G6:G12,"") -> 0
D14: Total vente du kit (FCFA) | H14: =SUM(H6:H12) -> 4000
D15: Coût de revient connu (FCFA) | H15: =SUM(J6:J12) -> 2600
D16: Lignes sans prix d'achat | H16: =COUNTIF(I6:I12,"") -> 3
D17: Marge sur les lignes au coût connu (FCFA) | H17: =SUMPRODUCT((I6:I12<>"")*H6:H12)-H15 -> 1000
D18: Nombre de cahiers (ligne « X cahiers » dans l'app) | H18: =SUMIF(A6:A12,"Cahiers",F6:F12) -> 2
D19: Part du prix de vente reposant sur des PV estimés | H19: =IF(H14=0,0,SUMIF(K6:K12,"<>Fixé",H6:H12)/H14) -> 0.45
D20: Statut du coût | H20: =IF(H13>0,"Total incomplet : "&H13&" prix de vente à fournir",IF(H16>0,"Coût incomplet : "&H16&" ligne(s) sans prix d'achat","Complet")) -> Coût incomplet : 3 ligne(s) sans prix d'achat
D22: Proposés décochés : livres du Complet (non comptés, cochables par le client)
A23: Manuels au programme | B23: Didactikos Langue et communication | C23: DID-6915 | D23: =INDEX(Articles!$C$2:$C$148,MATCH(C23,Articles!$A$2:$A$148,0)) -> Langue et communication C.P. | G23: =INDEX(Articles!$G$2:$G$148,MATCH(C23,Articles!$A$2:$A$148,0)) -> 3890 | N23: Non
A24: Manuels au programme | B24: Didactikos Mathématiques | C24: DID-6938 | D24: =INDEX(Articles!$C$2:$C$148,MATCH(C24,Articles!$A$2:$A$148,0)) -> Mathématiques C.P. | G24: =INDEX(Articles!$G$2:$G$148,MATCH(C24,Articles!$A$2:$A$148,0)) -> 3890 | N24: Non
A25: Manuels au programme | B25: Didactikos Découverte du monde | C25: DID-6952 | D25: =INDEX(Articles!$C$2:$C$148,MATCH(C25,Articles!$A$2:$A$148,0)) -> Découverte du monde C.P. | G25: =INDEX(Articles!$G$2:$G$148,MATCH(C25,Articles!$A$2:$A$148,0)) -> 3890 | N25: Non
D26: Total si tous les livres sont cochés (FCFA) | H26: =H14+SUM(G23:G25) -> 15670
D27: Option décochée par défaut, non comptée : | E27: =INDEX(Articles!$C$2:$C$148,MATCH("S027",Articles!$A$2:$A$148,0)) -> Cartable rigide bleu marine | H27: =INDEX(Articles!$G$2:$G$148,MATCH("S027",Articles!$A$2:$A$148,0)) -> 7500
D28: Manquants : | E28: aucun
A31: CP — Complet
A32: Groupe (app) | B32: Besoin (liste) | C32: ID | D32: Désignation | E32: Fournisseur | F32: Qté | G32: PV unit. (FCFA) | H32: Sous-total vente | I32: PA unit. (FCFA) | J32: Sous-total achat | K32: Statut vente | L32: Statut achat | M32: Remarque | N32: Coché par défaut
A33: Cahiers | B33: Cahier 96 pages | C33: SAC-033 | D33: =INDEX(Articles!$C$2:$C$148,MATCH(C33,Articles!$A$2:$A$148,0)) -> Cahier Calligraphe 140 pages 17x22 90 g seyès | E33: =INDEX(Articles!$B$2:$B$148,MATCH(C33,Articles!$A$2:$A$148,0)) -> Papex | F33: 2 | G33: =IF(INDEX(Articles!$G$2:$G$148,MATCH(C33,Articles!$A$2:$A$148,0))="","",INDEX(Articles!$G$2:$G$148,MATCH(C33,Articles!$A$2:$A$148,0))) -> 750 | H33: =IF(G33="",0,F33*G33) -> 1500 | I33: =IF(INDEX(Articles!$E$2:$E$148,MATCH(C33,Articles!$A$2:$A$148,0))="","",INDEX(Articles!$E$2:$E$148,MATCH(C33,Articles!$A$2:$A$148,0))) -> 650 | J33: =IF(I33="","",F33*I33) -> 1300 | K33: =INDEX(Articles!$H$2:$H$148,MATCH(C33,Articles!$A$2:$A$148,0)) -> Fixé | L33: =INDEX(Articles!$F$2:$F$148,MATCH(C33,Articles!$A$2:$A$148,0)) -> Estimé | M33: 140 p Calligraphe 90 g | N33: Oui
A34: Ardoise | B34: Ardoise | C34: CIS-ardoise | D34: =INDEX(Articles!$C$2:$C$148,MATCH(C34,Articles!$A$2:$A$148,0)) -> Ardoise quadrillée avec poignée | E34: =INDEX(Articles!$B$2:$B$148,MATCH(C34,Articles!$A$2:$A$148,0)) -> Cissé & Frères | F34: 1 | G34: =IF(INDEX(Articles!$G$2:$G$148,MATCH(C34,Articles!$A$2:$A$148,0))="","",INDEX(Articles!$G$2:$G$148,MATCH(C34,Articles!$A$2:$A$148,0))) -> 2500 | H34: =IF(G34="",0,F34*G34) -> 2500 | I34: =IF(INDEX(Articles!$E$2:$E$148,MATCH(C34,Articles!$A$2:$A$148,0))="","",INDEX(Articles!$E$2:$E$148,MATCH(C34,Articles!$A$2:$A$148,0))) -> 1500 | J34: =IF(I34="","",F34*I34) -> 1500 | K34: =INDEX(Articles!$H$2:$H$148,MATCH(C34,Articles!$A$2:$A$148,0)) -> Fixé | L34: =INDEX(Articles!$F$2:$F$148,MATCH(C34,Articles!$A$2:$A$148,0)) -> Confirmé | N34: Oui
A35: Géométrie | B35: Règle | C35: S069 | D35: =INDEX(Articles!$C$2:$C$148,MATCH(C35,Articles!$A$2:$A$148,0)) -> Règle métal 30 cm | E35: =INDEX(Articles!$B$2:$B$148,MATCH(C35,Articles!$A$2:$A$148,0)) -> LPD | F35: 1 | G35: =IF(INDEX(Articles!$G$2:$G$148,MATCH(C35,Articles!$A$2:$A$148,0))="","",INDEX(Articles!$G$2:$G$148,MATCH(C35,Articles!$A$2:$A$148,0))) -> 550 | H35: =IF(G35="",0,F35*G35) -> 550 | I35: =IF(INDEX(Articles!$E$2:$E$148,MATCH(C35,Articles!$A$2:$A$148,0))="","",INDEX(Articles!$E$2:$E$148,MATCH(C35,Articles!$A$2:$A$148,0))) -> 400 | J35: =IF(I35="","",F35*I35) -> 400 | K35: =INDEX(Articles!$H$2:$H$148,MATCH(C35,Articles!$A$2:$A$148,0)) -> Fixé | L35: =INDEX(Articles!$F$2:$F$148,MATCH(C35,Articles!$A$2:$A$148,0)) -> Estimé | N35: Oui
A36: Géométrie | B36: Matériel géométrique | C36: S091 | D36: =INDEX(Articles!$C$2:$C$148,MATCH(C36,Articles!$A$2:$A$148,0)) -> Kit géométrie Maped 30 cm (réf. 1930) | E36: =INDEX(Articles!$B$2:$B$148,MATCH(C36,Articles!$A$2:$A$148,0)) -> LPD | F36: 1 | G36: =IF(INDEX(Articles!$G$2:$G$148,MATCH(C36,Articles!$A$2:$A$148,0))="","",INDEX(Articles!$G$2:$G$148,MATCH(C36,Articles!$A$2:$A$148,0))) -> 1800 | H36: =IF(G36="",0,F36*G36) -> 1800 | I36: =IF(INDEX(Articles!$E$2:$E$148,MATCH(C36,Articles!$A$2:$A$148,0))="","",INDEX(Articles!$E$2:$E$148,MATCH(C36,Articles!$A$2:$A$148,0))) -> 1500 | J36: =IF(I36="","",F36*I36) -> 1500 | K36: =INDEX(Articles!$H$2:$H$148,MATCH(C36,Articles!$A$2:$A$148,0)) -> À trancher | L36: =INDEX(Articles!$F$2:$F$148,MATCH(C36,Articles!$A$2:$A$148,0)) -> Confirmé | N36: Oui
A37: Écriture | B37: Bic bleu | C37: SAC-065 | D37: =INDEX(Articles!$C$2:$C$148,MATCH(C37,Articles!$A$2:$A$148,0)) -> Stylo à bille Schneider Tops 505 M bleu | E37: =INDEX(Articles!$B$2:$B$148,MATCH(C37,Articles!$A$2:$A$148,0)) -> Papex | F37: 2 | G37: =IF(INDEX(Articles!$G$2:$G$148,MATCH(C37,Articles!$A$2:$A$148,0))="","",INDEX(Articles!$G$2:$G$148,MATCH(C37,Articles!$A$2:$A$148,0))) -> 100 | H37: =IF(G37="",0,F37*G37) -> 200 | I37: =IF(INDEX(Articles!$E$2:$E$148,MATCH(C37,Articles!$A$2:$A$148,0))="","",INDEX(Articles!$E$2:$E$148,MATCH(C37,Articles!$A$2:$A$148,0))) | J37: =IF(I37="","",F37*I37) | K37: =INDEX(Articles!$H$2:$H$148,MATCH(C37,Articles!$A$2:$A$148,0)) -> Fixé | L37: =INDEX(Articles!$F$2:$F$148,MATCH(C37,Articles!$A$2:$A$148,0)) -> Inconnu | N37: Oui
A38: Écriture | B38: Bic vert | C38: SAC-104 | D38: =INDEX(Articles!$C$2:$C$148,MATCH(C38,Articles!$A$2:$A$148,0)) -> Stylo à bille Schneider Tops 505 M vert | E38: =INDEX(Articles!$B$2:$B$148,MATCH(C38,Articles!$A$2:$A$148,0)) -> Papex | F38: 1 | G38: =IF(INDEX(Articles!$G$2:$G$148,MATCH(C38,Articles!$A$2:$A$148,0))="","",INDEX(Articles!$G$2:$G$148,MATCH(C38,Articles!$A$2:$A$148,0))) -> 100 | H38: =IF(G38="",0,F38*G38) -> 100 | I38: =IF(INDEX(Articles!$E$2:$E$148,MATCH(C38,Articles!$A$2:$A$148,0))="","",INDEX(Articles!$E$2:$E$148,MATCH(C38,Articles!$A$2:$A$148,0))) | J38: =IF(I38="","",F38*I38) | K38: =INDEX(Articles!$H$2:$H$148,MATCH(C38,Articles!$A$2:$A$148,0)) -> Fixé | L38: =INDEX(Articles!$F$2:$F$148,MATCH(C38,Articles!$A$2:$A$148,0)) -> Inconnu | N38: Oui
A39: Art & dessin | B39: Paquet de crayons de couleur | C39: SAC-024 | D39: =INDEX(Articles!$C$2:$C$148,MATCH(C39,Articles!$A$2:$A$148,0)) -> Crayons de couleur Maped Nightfall, boîte de 24 | E39: =INDEX(Articles!$B$2:$B$148,MATCH(C39,Articles!$A$2:$A$148,0)) -> Papex | F39: 1 | G39: =IF(INDEX(Articles!$G$2:$G$148,MATCH(C39,Articles!$A$2:$A$148,0))="","",INDEX(Articles!$G$2:$G$148,MATCH(C39,Articles!$A$2:$A$148,0))) -> 1600 | H39: =IF(G39="",0,F39*G39) -> 1600 | I39: =IF(INDEX(Articles!$E$2:$E$148,MATCH(C39,Articles!$A$2:$A$148,0))="","",INDEX(Articles!$E$2:$E$148,MATCH(C39,Articles!$A$2:$A$148,0))) -> 1300 | J39: =IF(I39="","",F39*I39) -> 1300 | K39: =INDEX(Articles!$H$2:$H$148,MATCH(C39,Articles!$A$2:$A$148,0)) -> Estimé | L39: =INDEX(Articles!$F$2:$F$148,MATCH(C39,Articles!$A$2:$A$148,0)) -> Estimé | N39: Oui
A40: Manuels au programme | B40: Didactikos Langue et communication | C40: DID-6915 | D40: =INDEX(Articles!$C$2:$C$148,MATCH(C40,Articles!$A$2:$A$148,0)) -> Langue et communication C.P. | E40: =INDEX(Articles!$B$2:$B$148,MATCH(C40,Articles!$A$2:$A$148,0)) -> LPD | F40: 1 | G40: =IF(INDEX(Articles!$G$2:$G$148,MATCH(C40,Articles!$A$2:$A$148,0))="","",INDEX(Articles!$G$2:$G$148,MATCH(C40,Articles!$A$2:$A$148,0))) -> 3890 | H40: =IF(G40="",0,F40*G40) -> 3890 | I40: =IF(INDEX(Articles!$E$2:$E$148,MATCH(C40,Articles!$A$2:$A$148,0))="","",INDEX(Articles!$E$2:$E$148,MATCH(C40,Articles!$A$2:$A$148,0))) -> 2890 | J40: =IF(I40="","",F40*I40) -> 2890 | K40: =INDEX(Articles!$H$2:$H$148,MATCH(C40,Articles!$A$2:$A$148,0)) -> Fixé | L40: =INDEX(Articles!$F$2:$F$148,MATCH(C40,Articles!$A$2:$A$148,0)) -> Estimé | M40: « Didactikos langue, maths, DDM : 1 » lu comme 1 manuel par matière | N40: Oui
A41: Manuels au programme | B41: Didactikos Mathématiques | C41: DID-6938 | D41: =INDEX(Articles!$C$2:$C$148,MATCH(C41,Articles!$A$2:$A$148,0)) -> Mathématiques C.P. | E41: =INDEX(Articles!$B$2:$B$148,MATCH(C41,Articles!$A$2:$A$148,0)) -> LPD | F41: 1 | G41: =IF(INDEX(Articles!$G$2:$G$148,MATCH(C41,Articles!$A$2:$A$148,0))="","",INDEX(Articles!$G$2:$G$148,MATCH(C41,Articles!$A$2:$A$148,0))) -> 3890 | H41: =IF(G41="",0,F41*G41) -> 3890 | I41: =IF(INDEX(Articles!$E$2:$E$148,MATCH(C41,Articles!$A$2:$A$148,0))="","",INDEX(Articles!$E$2:$E$148,MATCH(C41,Articles!$A$2:$A$148,0))) -> 2890 | J41: =IF(I41="","",F41*I41) -> 2890 | K41: =INDEX(Articles!$H$2:$H$148,MATCH(C41,Articles!$A$2:$A$148,0)) -> Fixé | L41: =INDEX(Articles!$F$2:$F$148,MATCH(C41,Articles!$A$2:$A$148,0)) -> Estimé | M41: « Didactikos langue, maths, DDM : 1 » lu comme 1 manuel par matière | N41: Oui
A42: Manuels au programme | B42: Didactikos Découverte du monde | C42: DID-6952 | D42: =INDEX(Articles!$C$2:$C$148,MATCH(C42,Articles!$A$2:$A$148,0)) -> Découverte du monde C.P. | E42: =INDEX(Articles!$B$2:$B$148,MATCH(C42,Articles!$A$2:$A$148,0)) -> LPD | F42: 1 | G42: =IF(INDEX(Articles!$G$2:$G$148,MATCH(C42,Articles!$A$2:$A$148,0))="","",INDEX(Articles!$G$2:$G$148,MATCH(C42,Articles!$A$2:$A$148,0))) -> 3890 | H42: =IF(G42="",0,F42*G42) -> 3890 | I42: =IF(INDEX(Articles!$E$2:$E$148,MATCH(C42,Articles!$A$2:$A$148,0))="","",INDEX(Articles!$E$2:$E$148,MATCH(C42,Articles!$A$2:$A$148,0))) -> 2890 | J42: =IF(I42="","",F42*I42) -> 2890 | K42: =INDEX(Articles!$H$2:$H$148,MATCH(C42,Articles!$A$2:$A$148,0)) -> Fixé | L42: =INDEX(Articles!$F$2:$F$148,MATCH(C42,Articles!$A$2:$A$148,0)) -> Estimé | M42: « Didactikos langue, maths, DDM : 1 » lu comme 1 manuel par matière | N42: Oui
D43: Lignes sans prix de vente (à fournir) | H43: =COUNTIF(G33:G42,"") -> 0
D44: Total vente du kit (FCFA) | H44: =SUM(H33:H42) -> 19920
D45: Coût de revient connu (FCFA) | H45: =SUM(J33:J42) -> 14670
D46: Lignes sans prix d'achat | H46: =COUNTIF(I33:I42,"") -> 2
D47: Marge sur les lignes au coût connu (FCFA) | H47: =SUMPRODUCT((I33:I42<>"")*H33:H42)-H45 -> 4950
D48: Nombre de cahiers (ligne « X cahiers » dans l'app) | H48: =SUMIF(A33:A42,"Cahiers",F33:F42) -> 2
D49: Part du prix de vente reposant sur des PV estimés | H49: =IF(H44=0,0,SUMIF(K33:K42,"<>Fixé",H33:H42)/H44) -> 0.17068273
D50: Statut du coût | H50: =IF(H43>0,"Total incomplet : "&H43&" prix de vente à fournir",IF(H46>0,"Coût incomplet : "&H46&" ligne(s) sans prix d'achat","Complet")) -> Coût incomplet : 2 ligne(s) sans prix d'achat
D51: Option décochée par défaut, non comptée : | E51: =INDEX(Articles!$C$2:$C$148,MATCH("S027",Articles!$A$2:$A$148,0)) -> Cartable rigide bleu marine | H51: =INDEX(Articles!$G$2:$G$148,MATCH("S027",Articles!$A$2:$A$148,0)) -> 7500
D52: Manquants : | E52: aucun
A55: CP — Confort
A56: Groupe (app) | B56: Besoin (liste) | C56: ID | D56: Désignation | E56: Fournisseur | F56: Qté | G56: PV unit. (FCFA) | H56: Sous-total vente | I56: PA unit. (FCFA) | J56: Sous-total achat | K56: Statut vente | L56: Statut achat | M56: Remarque | N56: Coché par défaut
A57: Cahiers | B57: Cahier 96 pages | C57: SAC-033 | D57: =INDEX(Articles!$C$2:$C$148,MATCH(C57,Articles!$A$2:$A$148,0)) -> Cahier Calligraphe 140 pages 17x22 90 g seyès | E57: =INDEX(Articles!$B$2:$B$148,MATCH(C57,Articles!$A$2:$A$148,0)) -> Papex | F57: 2 | G57: =IF(INDEX(Articles!$G$2:$G$148,MATCH(C57,Articles!$A$2:$A$148,0))="","",INDEX(Articles!$G$2:$G$148,MATCH(C57,Articles!$A$2:$A$148,0))) -> 750 | H57: =IF(G57="",0,F57*G57) -> 1500 | I57: =IF(INDEX(Articles!$E$2:$E$148,MATCH(C57,Articles!$A$2:$A$148,0))="","",INDEX(Articles!$E$2:$E$148,MATCH(C57,Articles!$A$2:$A$148,0))) -> 650 | J57: =IF(I57="","",F57*I57) -> 1300 | K57: =INDEX(Articles!$H$2:$H$148,MATCH(C57,Articles!$A$2:$A$148,0)) -> Fixé | L57: =INDEX(Articles!$F$2:$F$148,MATCH(C57,Articles!$A$2:$A$148,0)) -> Estimé | M57: 140 p Calligraphe 90 g | N57: Oui
A58: Ardoise | B58: Ardoise | C58: CIS-ardoise | D58: =INDEX(Articles!$C$2:$C$148,MATCH(C58,Articles!$A$2:$A$148,0)) -> Ardoise quadrillée avec poignée | E58: =INDEX(Articles!$B$2:$B$148,MATCH(C58,Articles!$A$2:$A$148,0)) -> Cissé & Frères | F58: 1 | G58: =IF(INDEX(Articles!$G$2:$G$148,MATCH(C58,Articles!$A$2:$A$148,0))="","",INDEX(Articles!$G$2:$G$148,MATCH(C58,Articles!$A$2:$A$148,0))) -> 2500 | H58: =IF(G58="",0,F58*G58) -> 2500 | I58: =IF(INDEX(Articles!$E$2:$E$148,MATCH(C58,Articles!$A$2:$A$148,0))="","",INDEX(Articles!$E$2:$E$148,MATCH(C58,Articles!$A$2:$A$148,0))) -> 1500 | J58: =IF(I58="","",F58*I58) -> 1500 | K58: =INDEX(Articles!$H$2:$H$148,MATCH(C58,Articles!$A$2:$A$148,0)) -> Fixé | L58: =INDEX(Articles!$F$2:$F$148,MATCH(C58,Articles!$A$2:$A$148,0)) -> Confirmé | N58: Oui
A59: Géométrie | B59: Règle | C59: S069 | D59: =INDEX(Articles!$C$2:$C$148,MATCH(C59,Articles!$A$2:$A$148,0)) -> Règle métal 30 cm | E59: =INDEX(Articles!$B$2:$B$148,MATCH(C59,Articles!$A$2:$A$148,0)) -> LPD | F59: 1 | G59: =IF(INDEX(Articles!$G$2:$G$148,MATCH(C59,Articles!$A$2:$A$148,0))="","",INDEX(Articles!$G$2:$G$148,MATCH(C59,Articles!$A$2:$A$148,0))) -> 550 | H59: =IF(G59="",0,F59*G59) -> 550 | I59: =IF(INDEX(Articles!$E$2:$E$148,MATCH(C59,Articles!$A$2:$A$148,0))="","",INDEX(Articles!$E$2:$E$148,MATCH(C59,Articles!$A$2:$A$148,0))) -> 400 | J59: =IF(I59="","",F59*I59) -> 400 | K59: =INDEX(Articles!$H$2:$H$148,MATCH(C59,Articles!$A$2:$A$148,0)) -> Fixé | L59: =INDEX(Articles!$F$2:$F$148,MATCH(C59,Articles!$A$2:$A$148,0)) -> Estimé | N59: Oui
A60: Géométrie | B60: Matériel géométrique | C60: S091 | D60: =INDEX(Articles!$C$2:$C$148,MATCH(C60,Articles!$A$2:$A$148,0)) -> Kit géométrie Maped 30 cm (réf. 1930) | E60: =INDEX(Articles!$B$2:$B$148,MATCH(C60,Articles!$A$2:$A$148,0)) -> LPD | F60: 1 | G60: =IF(INDEX(Articles!$G$2:$G$148,MATCH(C60,Articles!$A$2:$A$148,0))="","",INDEX(Articles!$G$2:$G$148,MATCH(C60,Articles!$A$2:$A$148,0))) -> 1800 | H60: =IF(G60="",0,F60*G60) -> 1800 | I60: =IF(INDEX(Articles!$E$2:$E$148,MATCH(C60,Articles!$A$2:$A$148,0))="","",INDEX(Articles!$E$2:$E$148,MATCH(C60,Articles!$A$2:$A$148,0))) -> 1500 | J60: =IF(I60="","",F60*I60) -> 1500 | K60: =INDEX(Articles!$H$2:$H$148,MATCH(C60,Articles!$A$2:$A$148,0)) -> À trancher | L60: =INDEX(Articles!$F$2:$F$148,MATCH(C60,Articles!$A$2:$A$148,0)) -> Confirmé | N60: Oui
A61: Écriture | B61: Bic bleu | C61: SAC-065 | D61: =INDEX(Articles!$C$2:$C$148,MATCH(C61,Articles!$A$2:$A$148,0)) -> Stylo à bille Schneider Tops 505 M bleu | E61: =INDEX(Articles!$B$2:$B$148,MATCH(C61,Articles!$A$2:$A$148,0)) -> Papex | F61: 2 | G61: =IF(INDEX(Articles!$G$2:$G$148,MATCH(C61,Articles!$A$2:$A$148,0))="","",INDEX(Articles!$G$2:$G$148,MATCH(C61,Articles!$A$2:$A$148,0))) -> 100 | H61: =IF(G61="",0,F61*G61) -> 200 | I61: =IF(INDEX(Articles!$E$2:$E$148,MATCH(C61,Articles!$A$2:$A$148,0))="","",INDEX(Articles!$E$2:$E$148,MATCH(C61,Articles!$A$2:$A$148,0))) | J61: =IF(I61="","",F61*I61) | K61: =INDEX(Articles!$H$2:$H$148,MATCH(C61,Articles!$A$2:$A$148,0)) -> Fixé | L61: =INDEX(Articles!$F$2:$F$148,MATCH(C61,Articles!$A$2:$A$148,0)) -> Inconnu | N61: Oui
A62: Écriture | B62: Bic vert | C62: SAC-104 | D62: =INDEX(Articles!$C$2:$C$148,MATCH(C62,Articles!$A$2:$A$148,0)) -> Stylo à bille Schneider Tops 505 M vert | E62: =INDEX(Articles!$B$2:$B$148,MATCH(C62,Articles!$A$2:$A$148,0)) -> Papex | F62: 1 | G62: =IF(INDEX(Articles!$G$2:$G$148,MATCH(C62,Articles!$A$2:$A$148,0))="","",INDEX(Articles!$G$2:$G$148,MATCH(C62,Articles!$A$2:$A$148,0))) -> 100 | H62: =IF(G62="",0,F62*G62) -> 100 | I62: =IF(INDEX(Articles!$E$2:$E$148,MATCH(C62,Articles!$A$2:$A$148,0))="","",INDEX(Articles!$E$2:$E$148,MATCH(C62,Articles!$A$2:$A$148,0))) | J62: =IF(I62="","",F62*I62) | K62: =INDEX(Articles!$H$2:$H$148,MATCH(C62,Articles!$A$2:$A$148,0)) -> Fixé | L62: =INDEX(Articles!$F$2:$F$148,MATCH(C62,Articles!$A$2:$A$148,0)) -> Inconnu | N62: Oui
A63: Art & dessin | B63: Paquet de crayons de couleur | C63: SAC-024 | D63: =INDEX(Articles!$C$2:$C$148,MATCH(C63,Articles!$A$2:$A$148,0)) -> Crayons de couleur Maped Nightfall, boîte de 24 | E63: =INDEX(Articles!$B$2:$B$148,MATCH(C63,Articles!$A$2:$A$148,0)) -> Papex | F63: 1 | G63: =IF(INDEX(Articles!$G$2:$G$148,MATCH(C63,Articles!$A$2:$A$148,0))="","",INDEX(Articles!$G$2:$G$148,MATCH(C63,Articles!$A$2:$A$148,0))) -> 1600 | H63: =IF(G63="",0,F63*G63) -> 1600 | I63: =IF(INDEX(Articles!$E$2:$E$148,MATCH(C63,Articles!$A$2:$A$148,0))="","",INDEX(Articles!$E$2:$E$148,MATCH(C63,Articles!$A$2:$A$148,0))) -> 1300 | J63: =IF(I63="","",F63*I63) -> 1300 | K63: =INDEX(Articles!$H$2:$H$148,MATCH(C63,Articles!$A$2:$A$148,0)) -> Estimé | L63: =INDEX(Articles!$F$2:$F$148,MATCH(C63,Articles!$A$2:$A$148,0)) -> Estimé | N63: Oui
A64: Manuels au programme | B64: Didactikos Langue et communication | C64: DID-6915 | D64: =INDEX(Articles!$C$2:$C$148,MATCH(C64,Articles!$A$2:$A$148,0)) -> Langue et communication C.P. | E64: =INDEX(Articles!$B$2:$B$148,MATCH(C64,Articles!$A$2:$A$148,0)) -> LPD | F64: 1 | G64: =IF(INDEX(Articles!$G$2:$G$148,MATCH(C64,Articles!$A$2:$A$148,0))="","",INDEX(Articles!$G$2:$G$148,MATCH(C64,Articles!$A$2:$A$148,0))) -> 3890 | H64: =IF(G64="",0,F64*G64) -> 3890 | I64: =IF(INDEX(Articles!$E$2:$E$148,MATCH(C64,Articles!$A$2:$A$148,0))="","",INDEX(Articles!$E$2:$E$148,MATCH(C64,Articles!$A$2:$A$148,0))) -> 2890 | J64: =IF(I64="","",F64*I64) -> 2890 | K64: =INDEX(Articles!$H$2:$H$148,MATCH(C64,Articles!$A$2:$A$148,0)) -> Fixé | L64: =INDEX(Articles!$F$2:$F$148,MATCH(C64,Articles!$A$2:$A$148,0)) -> Estimé | M64: « Didactikos langue, maths, DDM : 1 » lu comme 1 manuel par matière | N64: Oui
A65: Manuels au programme | B65: Didactikos Mathématiques | C65: DID-6938 | D65: =INDEX(Articles!$C$2:$C$148,MATCH(C65,Articles!$A$2:$A$148,0)) -> Mathématiques C.P. | E65: =INDEX(Articles!$B$2:$B$148,MATCH(C65,Articles!$A$2:$A$148,0)) -> LPD | F65: 1 | G65: =IF(INDEX(Articles!$G$2:$G$148,MATCH(C65,Articles!$A$2:$A$148,0))="","",INDEX(Articles!$G$2:$G$148,MATCH(C65,Articles!$A$2:$A$148,0))) -> 3890 | H65: =IF(G65="",0,F65*G65) -> 3890 | I65: =IF(INDEX(Articles!$E$2:$E$148,MATCH(C65,Articles!$A$2:$A$148,0))="","",INDEX(Articles!$E$2:$E$148,MATCH(C65,Articles!$A$2:$A$148,0))) -> 2890 | J65: =IF(I65="","",F65*I65) -> 2890 | K65: =INDEX(Articles!$H$2:$H$148,MATCH(C65,Articles!$A$2:$A$148,0)) -> Fixé | L65: =INDEX(Articles!$F$2:$F$148,MATCH(C65,Articles!$A$2:$A$148,0)) -> Estimé | M65: « Didactikos langue, maths, DDM : 1 » lu comme 1 manuel par matière | N65: Oui
A66: Manuels au programme | B66: Didactikos Découverte du monde | C66: DID-6952 | D66: =INDEX(Articles!$C$2:$C$148,MATCH(C66,Articles!$A$2:$A$148,0)) -> Découverte du monde C.P. | E66: =INDEX(Articles!$B$2:$B$148,MATCH(C66,Articles!$A$2:$A$148,0)) -> LPD | F66: 1 | G66: =IF(INDEX(Articles!$G$2:$G$148,MATCH(C66,Articles!$A$2:$A$148,0))="","",INDEX(Articles!$G$2:$G$148,MATCH(C66,Articles!$A$2:$A$148,0))) -> 3890 | H66: =IF(G66="",0,F66*G66) -> 3890 | I66: =IF(INDEX(Articles!$E$2:$E$148,MATCH(C66,Articles!$A$2:$A$148,0))="","",INDEX(Articles!$E$2:$E$148,MATCH(C66,Articles!$A$2:$A$148,0))) -> 2890 | J66: =IF(I66="","",F66*I66) -> 2890 | K66: =INDEX(Articles!$H$2:$H$148,MATCH(C66,Articles!$A$2:$A$148,0)) -> Fixé | L66: =INDEX(Articles!$F$2:$F$148,MATCH(C66,Articles!$A$2:$A$148,0)) -> Estimé | M66: « Didactikos langue, maths, DDM : 1 » lu comme 1 manuel par matière | N66: Oui
A67: Parascolaire | B67: Cahier d'activités Langue et communication | C67: DID-7404 | D67: =INDEX(Articles!$C$2:$C$148,MATCH(C67,Articles!$A$2:$A$148,0)) -> Cahier d’activités fongible LC C.P. | E67: =INDEX(Articles!$B$2:$B$148,MATCH(C67,Articles!$A$2:$A$148,0)) -> LPD | F67: 1 | G67: =IF(INDEX(Articles!$G$2:$G$148,MATCH(C67,Articles!$A$2:$A$148,0))="","",INDEX(Articles!$G$2:$G$148,MATCH(C67,Articles!$A$2:$A$148,0))) -> 2790 | H67: =IF(G67="",0,F67*G67) -> 2790 | I67: =IF(INDEX(Articles!$E$2:$E$148,MATCH(C67,Articles!$A$2:$A$148,0))="","",INDEX(Articles!$E$2:$E$148,MATCH(C67,Articles!$A$2:$A$148,0))) -> 1790 | J67: =IF(I67="","",F67*I67) -> 1790 | K67: =INDEX(Articles!$H$2:$H$148,MATCH(C67,Articles!$A$2:$A$148,0)) -> Fixé | L67: =INDEX(Articles!$F$2:$F$148,MATCH(C67,Articles!$A$2:$A$148,0)) -> Estimé | N67: Oui
A68: Parascolaire | B68: Cahier d'activités Mathématiques | C68: DID-7248 | D68: =INDEX(Articles!$C$2:$C$148,MATCH(C68,Articles!$A$2:$A$148,0)) -> Cahier d’activités mathématiques C.P. | E68: =INDEX(Articles!$B$2:$B$148,MATCH(C68,Articles!$A$2:$A$148,0)) -> LPD | F68: 1 | G68: =IF(INDEX(Articles!$G$2:$G$148,MATCH(C68,Articles!$A$2:$A$148,0))="","",INDEX(Articles!$G$2:$G$148,MATCH(C68,Articles!$A$2:$A$148,0))) -> 2790 | H68: =IF(G68="",0,F68*G68) -> 2790 | I68: =IF(INDEX(Articles!$E$2:$E$148,MATCH(C68,Articles!$A$2:$A$148,0))="","",INDEX(Articles!$E$2:$E$148,MATCH(C68,Articles!$A$2:$A$148,0))) -> 1790 | J68: =IF(I68="","",F68*I68) -> 1790 | K68: =INDEX(Articles!$H$2:$H$148,MATCH(C68,Articles!$A$2:$A$148,0)) -> Fixé | L68: =INDEX(Articles!$F$2:$F$148,MATCH(C68,Articles!$A$2:$A$148,0)) -> Estimé | N68: Oui
D69: Lignes sans prix de vente (à fournir) | H69: =COUNTIF(G57:G68,"") -> 0
D70: Total vente du kit (FCFA) | H70: =SUM(H57:H68) -> 25500
D71: Coût de revient connu (FCFA) | H71: =SUM(J57:J68) -> 18250
D72: Lignes sans prix d'achat | H72: =COUNTIF(I57:I68,"") -> 2
D73: Marge sur les lignes au coût connu (FCFA) | H73: =SUMPRODUCT((I57:I68<>"")*H57:H68)-H71 -> 6950
D74: Nombre de cahiers (ligne « X cahiers » dans l'app) | H74: =SUMIF(A57:A68,"Cahiers",F57:F68) -> 2
D75: Part du prix de vente reposant sur des PV estimés | H75: =IF(H70=0,0,SUMIF(K57:K68,"<>Fixé",H57:H68)/H70) -> 0.13333333
D76: Statut du coût | H76: =IF(H69>0,"Total incomplet : "&H69&" prix de vente à fournir",IF(H72>0,"Coût incomplet : "&H72&" ligne(s) sans prix d'achat","Complet")) -> Coût incomplet : 2 ligne(s) sans prix d'achat
D77: Option décochée par défaut, non comptée : | E77: =INDEX(Articles!$C$2:$C$148,MATCH("S027",Articles!$A$2:$A$148,0)) -> Cartable rigide bleu marine | H77: =INDEX(Articles!$G$2:$G$148,MATCH("S027",Articles!$A$2:$A$148,0)) -> 7500
D78: Manquants : | E78: aucun

Sheet CE1
A1: Kit CE1
A2: Liste réelle du Complexe Dar El-Hadith. Contrôle croisé avec la liste ISJA 2026-2027 (plus chargée, écoles privées).
A4: CE1 — Essentiel
A5: Groupe (app) | B5: Besoin (liste) | C5: ID | D5: Désignation | E5: Fournisseur | F5: Qté | G5: PV unit. (FCFA) | H5: Sous-total vente | I5: PA unit. (FCFA) | J5: Sous-total achat | K5: Statut vente | L5: Statut achat | M5: Remarque | N5: Coché par défaut
A6: Cahiers | B6: Cahier 96 pages | C6: SAC-048 | D6: =INDEX(Articles!$C$2:$C$148,MATCH(C6,Articles!$A$2:$A$148,0)) -> Cahier Calligraphe 96 pages 17x22 56 g seyès | E6: =INDEX(Articles!$B$2:$B$148,MATCH(C6,Articles!$A$2:$A$148,0)) -> Papex | F6: 4 | G6: =IF(INDEX(Articles!$G$2:$G$148,MATCH(C6,Articles!$A$2:$A$148,0))="","",INDEX(Articles!$G$2:$G$148,MATCH(C6,Articles!$A$2:$A$148,0))) -> 450 | H6: =IF(G6="",0,F6*G6) -> 1800 | I6: =IF(INDEX(Articles!$E$2:$E$148,MATCH(C6,Articles!$A$2:$A$148,0))="","",INDEX(Articles!$E$2:$E$148,MATCH(C6,Articles!$A$2:$A$148,0))) -> 350 | J6: =IF(I6="","",F6*I6) -> 1400 | K6: =INDEX(Articles!$H$2:$H$148,MATCH(C6,Articles!$A$2:$A$148,0)) -> Fixé | L6: =INDEX(Articles!$F$2:$F$148,MATCH(C6,Articles!$A$2:$A$148,0)) -> Confirmé | N6: Oui
A7: Géométrie | B7: Matériel géométrique | C7: SAC-007 | D7: =INDEX(Articles!$C$2:$C$148,MATCH(C7,Articles!$A$2:$A$148,0)) -> Kit de traçage 30 cm, 4 pièces L'écolier | E7: =INDEX(Articles!$B$2:$B$148,MATCH(C7,Articles!$A$2:$A$148,0)) -> Papex | F7: 1 | G7: =IF(INDEX(Articles!$G$2:$G$148,MATCH(C7,Articles!$A$2:$A$148,0))="","",INDEX(Articles!$G$2:$G$148,MATCH(C7,Articles!$A$2:$A$148,0))) -> 900 | H7: =IF(G7="",0,F7*G7) -> 900 | I7: =IF(INDEX(Articles!$E$2:$E$148,MATCH(C7,Articles!$A$2:$A$148,0))="","",INDEX(Articles!$E$2:$E$148,MATCH(C7,Articles!$A$2:$A$148,0))) -> 650 | J7: =IF(I7="","",F7*I7) -> 650 | K7: =INDEX(Articles!$H$2:$H$148,MATCH(C7,Articles!$A$2:$A$148,0)) -> Estimé | L7: =INDEX(Articles!$F$2:$F$148,MATCH(C7,Articles!$A$2:$A$148,0)) -> Confirmé | N7: Oui
A8: Ardoise | B8: Ardoise | C8: S086 | D8: =INDEX(Articles!$C$2:$C$148,MATCH(C8,Articles!$A$2:$A$148,0)) -> Ardoise scolaire | E8: =INDEX(Articles!$B$2:$B$148,MATCH(C8,Articles!$A$2:$A$148,0)) -> LPD | F8: 1 | G8: =IF(INDEX(Articles!$G$2:$G$148,MATCH(C8,Articles!$A$2:$A$148,0))="","",INDEX(Articles!$G$2:$G$148,MATCH(C8,Articles!$A$2:$A$148,0))) -> 900 | H8: =IF(G8="",0,F8*G8) -> 900 | I8: =IF(INDEX(Articles!$E$2:$E$148,MATCH(C8,Articles!$A$2:$A$148,0))="","",INDEX(Articles!$E$2:$E$148,MATCH(C8,Articles!$A$2:$A$148,0))) -> 600 | J8: =IF(I8="","",F8*I8) -> 600 | K8: =INDEX(Articles!$H$2:$H$148,MATCH(C8,Articles!$A$2:$A$148,0)) -> Fixé | L8: =INDEX(Articles!$F$2:$F$148,MATCH(C8,Articles!$A$2:$A$148,0)) -> Estimé | N8: Oui
A9: Art & dessin | B9: Paquet de crayons de couleur | C9: SAC-019 | D9: =INDEX(Articles!$C$2:$C$148,MATCH(C9,Articles!$A$2:$A$148,0)) -> Crayons de couleur Maped, boîte de 12 | E9: =INDEX(Articles!$B$2:$B$148,MATCH(C9,Articles!$A$2:$A$148,0)) -> Papex | F9: 1 | G9: =IF(INDEX(Articles!$G$2:$G$148,MATCH(C9,Articles!$A$2:$A$148,0))="","",INDEX(Articles!$G$2:$G$148,MATCH(C9,Articles!$A$2:$A$148,0))) -> 900 | H9: =IF(G9="",0,F9*G9) -> 900 | I9: =IF(INDEX(Articles!$E$2:$E$148,MATCH(C9,Articles!$A$2:$A$148,0))="","",INDEX(Articles!$E$2:$E$148,MATCH(C9,Articles!$A$2:$A$148,0))) -> 650 | J9: =IF(I9="","",F9*I9) -> 650 | K9: =INDEX(Articles!$H$2:$H$148,MATCH(C9,Articles!$A$2:$A$148,0)) -> Estimé | L9: =INDEX(Articles!$F$2:$F$148,MATCH(C9,Articles!$A$2:$A$148,0)) -> Estimé | N9: Oui
A10: Écriture | B10: Bic bleu | C10: SAC-065 | D10: =INDEX(Articles!$C$2:$C$148,MATCH(C10,Articles!$A$2:$A$148,0)) -> Stylo à bille Schneider Tops 505 M bleu | E10: =INDEX(Articles!$B$2:$B$148,MATCH(C10,Articles!$A$2:$A$148,0)) -> Papex | F10: 1 | G10: =IF(INDEX(Articles!$G$2:$G$148,MATCH(C10,Articles!$A$2:$A$148,0))="","",INDEX(Articles!$G$2:$G$148,MATCH(C10,Articles!$A$2:$A$148,0))) -> 100 | H10: =IF(G10="",0,F10*G10) -> 100 | I10: =IF(INDEX(Articles!$E$2:$E$148,MATCH(C10,Articles!$A$2:$A$148,0))="","",INDEX(Articles!$E$2:$E$148,MATCH(C10,Articles!$A$2:$A$148,0))) | J10: =IF(I10="","",F10*I10) | K10: =INDEX(Articles!$H$2:$H$148,MATCH(C10,Articles!$A$2:$A$148,0)) -> Fixé | L10: =INDEX(Articles!$F$2:$F$148,MATCH(C10,Articles!$A$2:$A$148,0)) -> Inconnu | N10: Oui
A11: Écriture | B11: Bic vert | C11: SAC-104 | D11: =INDEX(Articles!$C$2:$C$148,MATCH(C11,Articles!$A$2:$A$148,0)) -> Stylo à bille Schneider Tops 505 M vert | E11: =INDEX(Articles!$B$2:$B$148,MATCH(C11,Articles!$A$2:$A$148,0)) -> Papex | F11: 1 | G11: =IF(INDEX(Articles!$G$2:$G$148,MATCH(C11,Articles!$A$2:$A$148,0))="","",INDEX(Articles!$G$2:$G$148,MATCH(C11,Articles!$A$2:$A$148,0))) -> 100 | H11: =IF(G11="",0,F11*G11) -> 100 | I11: =IF(INDEX(Articles!$E$2:$E$148,MATCH(C11,Articles!$A$2:$A$148,0))="","",INDEX(Articles!$E$2:$E$148,MATCH(C11,Articles!$A$2:$A$148,0))) | J11: =IF(I11="","",F11*I11) | K11: =INDEX(Articles!$H$2:$H$148,MATCH(C11,Articles!$A$2:$A$148,0)) -> Fixé | L11: =INDEX(Articles!$F$2:$F$148,MATCH(C11,Articles!$A$2:$A$148,0)) -> Inconnu | N11: Oui
A12: Écriture | B12: Crayon noir | C12: S065 | D12: =INDEX(Articles!$C$2:$C$148,MATCH(C12,Articles!$A$2:$A$148,0)) -> Crayon papier (vendu à l'unité) | E12: =INDEX(Articles!$B$2:$B$148,MATCH(C12,Articles!$A$2:$A$148,0)) -> LPD | F12: 1 | G12: =IF(INDEX(Articles!$G$2:$G$148,MATCH(C12,Articles!$A$2:$A$148,0))="","",INDEX(Articles!$G$2:$G$148,MATCH(C12,Articles!$A$2:$A$148,0))) -> 75 | H12: =IF(G12="",0,F12*G12) -> 75 | I12: =IF(INDEX(Articles!$E$2:$E$148,MATCH(C12,Articles!$A$2:$A$148,0))="","",INDEX(Articles!$E$2:$E$148,MATCH(C12,Articles!$A$2:$A$148,0))) | J12: =IF(I12="","",F12*I12) | K12: =INDEX(Articles!$H$2:$H$148,MATCH(C12,Articles!$A$2:$A$148,0)) -> Fixé | L12: =INDEX(Articles!$F$2:$F$148,MATCH(C12,Articles!$A$2:$A$148,0)) -> Inconnu | N12: Oui
A13: Petit matériel | B13: Gomme | C13: S009 | D13: =INDEX(Articles!$C$2:$C$148,MATCH(C13,Articles!$A$2:$A$148,0)) -> Gomme Staedtler Mars Plastic | E13: =INDEX(Articles!$B$2:$B$148,MATCH(C13,Articles!$A$2:$A$148,0)) -> LPD | F13: 1 | G13: =IF(INDEX(Articles!$G$2:$G$148,MATCH(C13,Articles!$A$2:$A$148,0))="","",INDEX(Articles!$G$2:$G$148,MATCH(C13,Articles!$A$2:$A$148,0))) -> 250 | H13: =IF(G13="",0,F13*G13) -> 250 | I13: =IF(INDEX(Articles!$E$2:$E$148,MATCH(C13,Articles!$A$2:$A$148,0))="","",INDEX(Articles!$E$2:$E$148,MATCH(C13,Articles!$A$2:$A$148,0))) -> 110 | J13: =IF(I13="","",F13*I13) -> 110 | K13: =INDEX(Articles!$H$2:$H$148,MATCH(C13,Articles!$A$2:$A$148,0)) -> Fixé | L13: =INDEX(Articles!$F$2:$F$148,MATCH(C13,Articles!$A$2:$A$148,0)) -> Estimé | N13: Oui
D14: Lignes sans prix de vente (à fournir) | H14: =COUNTIF(G6:G13,"") -> 0
D15: Total vente du kit (FCFA) | H15: =SUM(H6:H13) -> 5025
D16: Coût de revient connu (FCFA) | H16: =SUM(J6:J13) -> 3410
D17: Lignes sans prix d'achat | H17: =COUNTIF(I6:I13,"") -> 3
D18: Marge sur les lignes au coût connu (FCFA) | H18: =SUMPRODUCT((I6:I13<>"")*H6:H13)-H16 -> 1340
D19: Nombre de cahiers (ligne « X cahiers » dans l'app) | H19: =SUMIF(A6:A13,"Cahiers",F6:F13) -> 4
D20: Part du prix de vente reposant sur des PV estimés | H20: =IF(H15=0,0,SUMIF(K6:K13,"<>Fixé",H6:H13)/H15) -> 0.35820896
D21: Statut du coût | H21: =IF(H14>0,"Total incomplet : "&H14&" prix de vente à fournir",IF(H17>0,"Coût incomplet : "&H17&" ligne(s) sans prix d'achat","Complet")) -> Coût incomplet : 3 ligne(s) sans prix d'achat
D23: Proposés décochés : livres du Complet (non comptés, cochables par le client)
A24: Manuels au programme | B24: Didactikos Langue et communication | C24: DID-6917 | D24: =INDEX(Articles!$C$2:$C$148,MATCH(C24,Articles!$A$2:$A$148,0)) -> Langue et communication C.E.1 | G24: =INDEX(Articles!$G$2:$G$148,MATCH(C24,Articles!$A$2:$A$148,0)) -> 4000 | N24: Non
A25: Manuels au programme | B25: Didactikos Mathématiques | C25: DID-6941 | D25: =INDEX(Articles!$C$2:$C$148,MATCH(C25,Articles!$A$2:$A$148,0)) -> Mathématiques C.E.1 | G25: =INDEX(Articles!$G$2:$G$148,MATCH(C25,Articles!$A$2:$A$148,0)) -> 4000 | N25: Non
A26: Manuels au programme | B26: Didactikos Découverte du monde | C26: DID-6954 | D26: =INDEX(Articles!$C$2:$C$148,MATCH(C26,Articles!$A$2:$A$148,0)) -> Découverte du monde C.E.1 | G26: =INDEX(Articles!$G$2:$G$148,MATCH(C26,Articles!$A$2:$A$148,0)) -> 4000 | N26: Non
D27: Total si tous les livres sont cochés (FCFA) | H27: =H15+SUM(G24:G26) -> 17025
D28: Option décochée par défaut, non comptée : | E28: =INDEX(Articles!$C$2:$C$148,MATCH("S027",Articles!$A$2:$A$148,0)) -> Cartable rigide bleu marine | H28: =INDEX(Articles!$G$2:$G$148,MATCH("S027",Articles!$A$2:$A$148,0)) -> 7500
D29: Manquants : | E29: aucun
A32: CE1 — Complet
A33: Groupe (app) | B33: Besoin (liste) | C33: ID | D33: Désignation | E33: Fournisseur | F33: Qté | G33: PV unit. (FCFA) | H33: Sous-total vente | I33: PA unit. (FCFA) | J33: Sous-total achat | K33: Statut vente | L33: Statut achat | M33: Remarque | N33: Coché par défaut
A34: Cahiers | B34: Cahier 96 pages | C34: SAC-033 | D34: =INDEX(Articles!$C$2:$C$148,MATCH(C34,Articles!$A$2:$A$148,0)) -> Cahier Calligraphe 140 pages 17x22 90 g seyès | E34: =INDEX(Articles!$B$2:$B$148,MATCH(C34,Articles!$A$2:$A$148,0)) -> Papex | F34: 4 | G34: =IF(INDEX(Articles!$G$2:$G$148,MATCH(C34,Articles!$A$2:$A$148,0))="","",INDEX(Articles!$G$2:$G$148,MATCH(C34,Articles!$A$2:$A$148,0))) -> 750 | H34: =IF(G34="",0,F34*G34) -> 3000 | I34: =IF(INDEX(Articles!$E$2:$E$148,MATCH(C34,Articles!$A$2:$A$148,0))="","",INDEX(Articles!$E$2:$E$148,MATCH(C34,Articles!$A$2:$A$148,0))) -> 650 | J34: =IF(I34="","",F34*I34) -> 2600 | K34: =INDEX(Articles!$H$2:$H$148,MATCH(C34,Articles!$A$2:$A$148,0)) -> Fixé | L34: =INDEX(Articles!$F$2:$F$148,MATCH(C34,Articles!$A$2:$A$148,0)) -> Estimé | M34: 140 p Calligraphe 90 g | N34: Oui
A35: Géométrie | B35: Matériel géométrique | C35: S091 | D35: =INDEX(Articles!$C$2:$C$148,MATCH(C35,Articles!$A$2:$A$148,0)) -> Kit géométrie Maped 30 cm (réf. 1930) | E35: =INDEX(Articles!$B$2:$B$148,MATCH(C35,Articles!$A$2:$A$148,0)) -> LPD | F35: 1 | G35: =IF(INDEX(Articles!$G$2:$G$148,MATCH(C35,Articles!$A$2:$A$148,0))="","",INDEX(Articles!$G$2:$G$148,MATCH(C35,Articles!$A$2:$A$148,0))) -> 1800 | H35: =IF(G35="",0,F35*G35) -> 1800 | I35: =IF(INDEX(Articles!$E$2:$E$148,MATCH(C35,Articles!$A$2:$A$148,0))="","",INDEX(Articles!$E$2:$E$148,MATCH(C35,Articles!$A$2:$A$148,0))) -> 1500 | J35: =IF(I35="","",F35*I35) -> 1500 | K35: =INDEX(Articles!$H$2:$H$148,MATCH(C35,Articles!$A$2:$A$148,0)) -> À trancher | L35: =INDEX(Articles!$F$2:$F$148,MATCH(C35,Articles!$A$2:$A$148,0)) -> Confirmé | N35: Oui
A36: Ardoise | B36: Ardoise | C36: CIS-ardoise | D36: =INDEX(Articles!$C$2:$C$148,MATCH(C36,Articles!$A$2:$A$148,0)) -> Ardoise quadrillée avec poignée | E36: =INDEX(Articles!$B$2:$B$148,MATCH(C36,Articles!$A$2:$A$148,0)) -> Cissé & Frères | F36: 1 | G36: =IF(INDEX(Articles!$G$2:$G$148,MATCH(C36,Articles!$A$2:$A$148,0))="","",INDEX(Articles!$G$2:$G$148,MATCH(C36,Articles!$A$2:$A$148,0))) -> 2500 | H36: =IF(G36="",0,F36*G36) -> 2500 | I36: =IF(INDEX(Articles!$E$2:$E$148,MATCH(C36,Articles!$A$2:$A$148,0))="","",INDEX(Articles!$E$2:$E$148,MATCH(C36,Articles!$A$2:$A$148,0))) -> 1500 | J36: =IF(I36="","",F36*I36) -> 1500 | K36: =INDEX(Articles!$H$2:$H$148,MATCH(C36,Articles!$A$2:$A$148,0)) -> Fixé | L36: =INDEX(Articles!$F$2:$F$148,MATCH(C36,Articles!$A$2:$A$148,0)) -> Confirmé | N36: Oui
A37: Art & dessin | B37: Paquet de crayons de couleur | C37: SAC-024 | D37: =INDEX(Articles!$C$2:$C$148,MATCH(C37,Articles!$A$2:$A$148,0)) -> Crayons de couleur Maped Nightfall, boîte de 24 | E37: =INDEX(Articles!$B$2:$B$148,MATCH(C37,Articles!$A$2:$A$148,0)) -> Papex | F37: 1 | G37: =IF(INDEX(Articles!$G$2:$G$148,MATCH(C37,Articles!$A$2:$A$148,0))="","",INDEX(Articles!$G$2:$G$148,MATCH(C37,Articles!$A$2:$A$148,0))) -> 1600 | H37: =IF(G37="",0,F37*G37) -> 1600 | I37: =IF(INDEX(Articles!$E$2:$E$148,MATCH(C37,Articles!$A$2:$A$148,0))="","",INDEX(Articles!$E$2:$E$148,MATCH(C37,Articles!$A$2:$A$148,0))) -> 1300 | J37: =IF(I37="","",F37*I37) -> 1300 | K37: =INDEX(Articles!$H$2:$H$148,MATCH(C37,Articles!$A$2:$A$148,0)) -> Estimé | L37: =INDEX(Articles!$F$2:$F$148,MATCH(C37,Articles!$A$2:$A$148,0)) -> Estimé | N37: Oui
A38: Écriture | B38: Bic bleu | C38: SAC-065 | D38: =INDEX(Articles!$C$2:$C$148,MATCH(C38,Articles!$A$2:$A$148,0)) -> Stylo à bille Schneider Tops 505 M bleu | E38: =INDEX(Articles!$B$2:$B$148,MATCH(C38,Articles!$A$2:$A$148,0)) -> Papex | F38: 1 | G38: =IF(INDEX(Articles!$G$2:$G$148,MATCH(C38,Articles!$A$2:$A$148,0))="","",INDEX(Articles!$G$2:$G$148,MATCH(C38,Articles!$A$2:$A$148,0))) -> 100 | H38: =IF(G38="",0,F38*G38) -> 100 | I38: =IF(INDEX(Articles!$E$2:$E$148,MATCH(C38,Articles!$A$2:$A$148,0))="","",INDEX(Articles!$E$2:$E$148,MATCH(C38,Articles!$A$2:$A$148,0))) | J38: =IF(I38="","",F38*I38) | K38: =INDEX(Articles!$H$2:$H$148,MATCH(C38,Articles!$A$2:$A$148,0)) -> Fixé | L38: =INDEX(Articles!$F$2:$F$148,MATCH(C38,Articles!$A$2:$A$148,0)) -> Inconnu | N38: Oui
A39: Écriture | B39: Bic vert | C39: SAC-104 | D39: =INDEX(Articles!$C$2:$C$148,MATCH(C39,Articles!$A$2:$A$148,0)) -> Stylo à bille Schneider Tops 505 M vert | E39: =INDEX(Articles!$B$2:$B$148,MATCH(C39,Articles!$A$2:$A$148,0)) -> Papex | F39: 1 | G39: =IF(INDEX(Articles!$G$2:$G$148,MATCH(C39,Articles!$A$2:$A$148,0))="","",INDEX(Articles!$G$2:$G$148,MATCH(C39,Articles!$A$2:$A$148,0))) -> 100 | H39: =IF(G39="",0,F39*G39) -> 100 | I39: =IF(INDEX(Articles!$E$2:$E$148,MATCH(C39,Articles!$A$2:$A$148,0))="","",INDEX(Articles!$E$2:$E$148,MATCH(C39,Articles!$A$2:$A$148,0))) | J39: =IF(I39="","",F39*I39) | K39: =INDEX(Articles!$H$2:$H$148,MATCH(C39,Articles!$A$2:$A$148,0)) -> Fixé | L39: =INDEX(Articles!$F$2:$F$148,MATCH(C39,Articles!$A$2:$A$148,0)) -> Inconnu | N39: Oui
A40: Écriture | B40: Crayon noir | C40: S065 | D40: =INDEX(Articles!$C$2:$C$148,MATCH(C40,Articles!$A$2:$A$148,0)) -> Crayon papier (vendu à l'unité) | E40: =INDEX(Articles!$B$2:$B$148,MATCH(C40,Articles!$A$2:$A$148,0)) -> LPD | F40: 1 | G40: =IF(INDEX(Articles!$G$2:$G$148,MATCH(C40,Articles!$A$2:$A$148,0))="","",INDEX(Articles!$G$2:$G$148,MATCH(C40,Articles!$A$2:$A$148,0))) -> 75 | H40: =IF(G40="",0,F40*G40) -> 75 | I40: =IF(INDEX(Articles!$E$2:$E$148,MATCH(C40,Articles!$A$2:$A$148,0))="","",INDEX(Articles!$E$2:$E$148,MATCH(C40,Articles!$A$2:$A$148,0))) | J40: =IF(I40="","",F40*I40) | K40: =INDEX(Articles!$H$2:$H$148,MATCH(C40,Articles!$A$2:$A$148,0)) -> Fixé | L40: =INDEX(Articles!$F$2:$F$148,MATCH(C40,Articles!$A$2:$A$148,0)) -> Inconnu | N40: Oui
A41: Petit matériel | B41: Gomme | C41: S009 | D41: =INDEX(Articles!$C$2:$C$148,MATCH(C41,Articles!$A$2:$A$148,0)) -> Gomme Staedtler Mars Plastic | E41: =INDEX(Articles!$B$2:$B$148,MATCH(C41,Articles!$A$2:$A$148,0)) -> LPD | F41: 1 | G41: =IF(INDEX(Articles!$G$2:$G$148,MATCH(C41,Articles!$A$2:$A$148,0))="","",INDEX(Articles!$G$2:$G$148,MATCH(C41,Articles!$A$2:$A$148,0))) -> 250 | H41: =IF(G41="",0,F41*G41) -> 250 | I41: =IF(INDEX(Articles!$E$2:$E$148,MATCH(C41,Articles!$A$2:$A$148,0))="","",INDEX(Articles!$E$2:$E$148,MATCH(C41,Articles!$A$2:$A$148,0))) -> 110 | J41: =IF(I41="","",F41*I41) -> 110 | K41: =INDEX(Articles!$H$2:$H$148,MATCH(C41,Articles!$A$2:$A$148,0)) -> Fixé | L41: =INDEX(Articles!$F$2:$F$148,MATCH(C41,Articles!$A$2:$A$148,0)) -> Estimé | N41: Oui
A42: Manuels au programme | B42: Didactikos Langue et communication | C42: DID-6917 | D42: =INDEX(Articles!$C$2:$C$148,MATCH(C42,Articles!$A$2:$A$148,0)) -> Langue et communication C.E.1 | E42: =INDEX(Articles!$B$2:$B$148,MATCH(C42,Articles!$A$2:$A$148,0)) -> LPD | F42: 1 | G42: =IF(INDEX(Articles!$G$2:$G$148,MATCH(C42,Articles!$A$2:$A$148,0))="","",INDEX(Articles!$G$2:$G$148,MATCH(C42,Articles!$A$2:$A$148,0))) -> 4000 | H42: =IF(G42="",0,F42*G42) -> 4000 | I42: =IF(INDEX(Articles!$E$2:$E$148,MATCH(C42,Articles!$A$2:$A$148,0))="","",INDEX(Articles!$E$2:$E$148,MATCH(C42,Articles!$A$2:$A$148,0))) -> 3000 | J42: =IF(I42="","",F42*I42) -> 3000 | K42: =INDEX(Articles!$H$2:$H$148,MATCH(C42,Articles!$A$2:$A$148,0)) -> Fixé | L42: =INDEX(Articles!$F$2:$F$148,MATCH(C42,Articles!$A$2:$A$148,0)) -> Estimé | M42: « Didactikos langue, maths, DDM : 1 » lu comme 1 manuel par matière | N42: Oui
A43: Manuels au programme | B43: Didactikos Mathématiques | C43: DID-6941 | D43: =INDEX(Articles!$C$2:$C$148,MATCH(C43,Articles!$A$2:$A$148,0)) -> Mathématiques C.E.1 | E43: =INDEX(Articles!$B$2:$B$148,MATCH(C43,Articles!$A$2:$A$148,0)) -> LPD | F43: 1 | G43: =IF(INDEX(Articles!$G$2:$G$148,MATCH(C43,Articles!$A$2:$A$148,0))="","",INDEX(Articles!$G$2:$G$148,MATCH(C43,Articles!$A$2:$A$148,0))) -> 4000 | H43: =IF(G43="",0,F43*G43) -> 4000 | I43: =IF(INDEX(Articles!$E$2:$E$148,MATCH(C43,Articles!$A$2:$A$148,0))="","",INDEX(Articles!$E$2:$E$148,MATCH(C43,Articles!$A$2:$A$148,0))) -> 3000 | J43: =IF(I43="","",F43*I43) -> 3000 | K43: =INDEX(Articles!$H$2:$H$148,MATCH(C43,Articles!$A$2:$A$148,0)) -> Fixé | L43: =INDEX(Articles!$F$2:$F$148,MATCH(C43,Articles!$A$2:$A$148,0)) -> Estimé | M43: « Didactikos langue, maths, DDM : 1 » lu comme 1 manuel par matière | N43: Oui
A44: Manuels au programme | B44: Didactikos Découverte du monde | C44: DID-6954 | D44: =INDEX(Articles!$C$2:$C$148,MATCH(C44,Articles!$A$2:$A$148,0)) -> Découverte du monde C.E.1 | E44: =INDEX(Articles!$B$2:$B$148,MATCH(C44,Articles!$A$2:$A$148,0)) -> LPD | F44: 1 | G44: =IF(INDEX(Articles!$G$2:$G$148,MATCH(C44,Articles!$A$2:$A$148,0))="","",INDEX(Articles!$G$2:$G$148,MATCH(C44,Articles!$A$2:$A$148,0))) -> 4000 | H44: =IF(G44="",0,F44*G44) -> 4000 | I44: =IF(INDEX(Articles!$E$2:$E$148,MATCH(C44,Articles!$A$2:$A$148,0))="","",INDEX(Articles!$E$2:$E$148,MATCH(C44,Articles!$A$2:$A$148,0))) -> 3000 | J44: =IF(I44="","",F44*I44) -> 3000 | K44: =INDEX(Articles!$H$2:$H$148,MATCH(C44,Articles!$A$2:$A$148,0)) -> Fixé | L44: =INDEX(Articles!$F$2:$F$148,MATCH(C44,Articles!$A$2:$A$148,0)) -> Estimé | M44: « Didactikos langue, maths, DDM : 1 » lu comme 1 manuel par matière | N44: Oui
D45: Lignes sans prix de vente (à fournir) | H45: =COUNTIF(G34:G44,"") -> 0
D46: Total vente du kit (FCFA) | H46: =SUM(H34:H44) -> 21425
D47: Coût de revient connu (FCFA) | H47: =SUM(J34:J44) -> 16010
D48: Lignes sans prix d'achat | H48: =COUNTIF(I34:I44,"") -> 3
D49: Marge sur les lignes au coût connu (FCFA) | H49: =SUMPRODUCT((I34:I44<>"")*H34:H44)-H47 -> 5140
D50: Nombre de cahiers (ligne « X cahiers » dans l'app) | H50: =SUMIF(A34:A44,"Cahiers",F34:F44) -> 4
D51: Part du prix de vente reposant sur des PV estimés | H51: =IF(H46=0,0,SUMIF(K34:K44,"<>Fixé",H34:H44)/H46) -> 0.15869312
D52: Statut du coût | H52: =IF(H45>0,"Total incomplet : "&H45&" prix de vente à fournir",IF(H48>0,"Coût incomplet : "&H48&" ligne(s) sans prix d'achat","Complet")) -> Coût incomplet : 3 ligne(s) sans prix d'achat
D53: Option décochée par défaut, non comptée : | E53: =INDEX(Articles!$C$2:$C$148,MATCH("S027",Articles!$A$2:$A$148,0)) -> Cartable rigide bleu marine | H53: =INDEX(Articles!$G$2:$G$148,MATCH("S027",Articles!$A$2:$A$148,0)) -> 7500
D54: Manquants : | E54: aucun
A57: CE1 — Confort
A58: Groupe (app) | B58: Besoin (liste) | C58: ID | D58: Désignation | E58: Fournisseur | F58: Qté | G58: PV unit. (FCFA) | H58: Sous-total vente | I58: PA unit. (FCFA) | J58: Sous-total achat | K58: Statut vente | L58: Statut achat | M58: Remarque | N58: Coché par défaut
A59: Cahiers | B59: Cahier 96 pages | C59: SAC-033 | D59: =INDEX(Articles!$C$2:$C$148,MATCH(C59,Articles!$A$2:$A$148,0)) -> Cahier Calligraphe 140 pages 17x22 90 g seyès | E59: =INDEX(Articles!$B$2:$B$148,MATCH(C59,Articles!$A$2:$A$148,0)) -> Papex | F59: 4 | G59: =IF(INDEX(Articles!$G$2:$G$148,MATCH(C59,Articles!$A$2:$A$148,0))="","",INDEX(Articles!$G$2:$G$148,MATCH(C59,Articles!$A$2:$A$148,0))) -> 750 | H59: =IF(G59="",0,F59*G59) -> 3000 | I59: =IF(INDEX(Articles!$E$2:$E$148,MATCH(C59,Articles!$A$2:$A$148,0))="","",INDEX(Articles!$E$2:$E$148,MATCH(C59,Articles!$A$2:$A$148,0))) -> 650 | J59: =IF(I59="","",F59*I59) -> 2600 | K59: =INDEX(Articles!$H$2:$H$148,MATCH(C59,Articles!$A$2:$A$148,0)) -> Fixé | L59: =INDEX(Articles!$F$2:$F$148,MATCH(C59,Articles!$A$2:$A$148,0)) -> Estimé | M59: 140 p Calligraphe 90 g | N59: Oui
A60: Géométrie | B60: Matériel géométrique | C60: S091 | D60: =INDEX(Articles!$C$2:$C$148,MATCH(C60,Articles!$A$2:$A$148,0)) -> Kit géométrie Maped 30 cm (réf. 1930) | E60: =INDEX(Articles!$B$2:$B$148,MATCH(C60,Articles!$A$2:$A$148,0)) -> LPD | F60: 1 | G60: =IF(INDEX(Articles!$G$2:$G$148,MATCH(C60,Articles!$A$2:$A$148,0))="","",INDEX(Articles!$G$2:$G$148,MATCH(C60,Articles!$A$2:$A$148,0))) -> 1800 | H60: =IF(G60="",0,F60*G60) -> 1800 | I60: =IF(INDEX(Articles!$E$2:$E$148,MATCH(C60,Articles!$A$2:$A$148,0))="","",INDEX(Articles!$E$2:$E$148,MATCH(C60,Articles!$A$2:$A$148,0))) -> 1500 | J60: =IF(I60="","",F60*I60) -> 1500 | K60: =INDEX(Articles!$H$2:$H$148,MATCH(C60,Articles!$A$2:$A$148,0)) -> À trancher | L60: =INDEX(Articles!$F$2:$F$148,MATCH(C60,Articles!$A$2:$A$148,0)) -> Confirmé | N60: Oui
A61: Ardoise | B61: Ardoise | C61: CIS-ardoise | D61: =INDEX(Articles!$C$2:$C$148,MATCH(C61,Articles!$A$2:$A$148,0)) -> Ardoise quadrillée avec poignée | E61: =INDEX(Articles!$B$2:$B$148,MATCH(C61,Articles!$A$2:$A$148,0)) -> Cissé & Frères | F61: 1 | G61: =IF(INDEX(Articles!$G$2:$G$148,MATCH(C61,Articles!$A$2:$A$148,0))="","",INDEX(Articles!$G$2:$G$148,MATCH(C61,Articles!$A$2:$A$148,0))) -> 2500 | H61: =IF(G61="",0,F61*G61) -> 2500 | I61: =IF(INDEX(Articles!$E$2:$E$148,MATCH(C61,Articles!$A$2:$A$148,0))="","",INDEX(Articles!$E$2:$E$148,MATCH(C61,Articles!$A$2:$A$148,0))) -> 1500 | J61: =IF(I61="","",F61*I61) -> 1500 | K61: =INDEX(Articles!$H$2:$H$148,MATCH(C61,Articles!$A$2:$A$148,0)) -> Fixé | L61: =INDEX(Articles!$F$2:$F$148,MATCH(C61,Articles!$A$2:$A$148,0)) -> Confirmé | N61: Oui
A62: Art & dessin | B62: Paquet de crayons de couleur | C62: SAC-024 | D62: =INDEX(Articles!$C$2:$C$148,MATCH(C62,Articles!$A$2:$A$148,0)) -> Crayons de couleur Maped Nightfall, boîte de 24 | E62: =INDEX(Articles!$B$2:$B$148,MATCH(C62,Articles!$A$2:$A$148,0)) -> Papex | F62: 1 | G62: =IF(INDEX(Articles!$G$2:$G$148,MATCH(C62,Articles!$A$2:$A$148,0))="","",INDEX(Articles!$G$2:$G$148,MATCH(C62,Articles!$A$2:$A$148,0))) -> 1600 | H62: =IF(G62="",0,F62*G62) -> 1600 | I62: =IF(INDEX(Articles!$E$2:$E$148,MATCH(C62,Articles!$A$2:$A$148,0))="","",INDEX(Articles!$E$2:$E$148,MATCH(C62,Articles!$A$2:$A$148,0))) -> 1300 | J62: =IF(I62="","",F62*I62) -> 1300 | K62: =INDEX(Articles!$H$2:$H$148,MATCH(C62,Articles!$A$2:$A$148,0)) -> Estimé | L62: =INDEX(Articles!$F$2:$F$148,MATCH(C62,Articles!$A$2:$A$148,0)) -> Estimé | N62: Oui
A63: Écriture | B63: Bic bleu | C63: SAC-065 | D63: =INDEX(Articles!$C$2:$C$148,MATCH(C63,Articles!$A$2:$A$148,0)) -> Stylo à bille Schneider Tops 505 M bleu | E63: =INDEX(Articles!$B$2:$B$148,MATCH(C63,Articles!$A$2:$A$148,0)) -> Papex | F63: 1 | G63: =IF(INDEX(Articles!$G$2:$G$148,MATCH(C63,Articles!$A$2:$A$148,0))="","",INDEX(Articles!$G$2:$G$148,MATCH(C63,Articles!$A$2:$A$148,0))) -> 100 | H63: =IF(G63="",0,F63*G63) -> 100 | I63: =IF(INDEX(Articles!$E$2:$E$148,MATCH(C63,Articles!$A$2:$A$148,0))="","",INDEX(Articles!$E$2:$E$148,MATCH(C63,Articles!$A$2:$A$148,0))) | J63: =IF(I63="","",F63*I63) | K63: =INDEX(Articles!$H$2:$H$148,MATCH(C63,Articles!$A$2:$A$148,0)) -> Fixé | L63: =INDEX(Articles!$F$2:$F$148,MATCH(C63,Articles!$A$2:$A$148,0)) -> Inconnu | N63: Oui
A64: Écriture | B64: Bic vert | C64: SAC-104 | D64: =INDEX(Articles!$C$2:$C$148,MATCH(C64,Articles!$A$2:$A$148,0)) -> Stylo à bille Schneider Tops 505 M vert | E64: =INDEX(Articles!$B$2:$B$148,MATCH(C64,Articles!$A$2:$A$148,0)) -> Papex | F64: 1 | G64: =IF(INDEX(Articles!$G$2:$G$148,MATCH(C64,Articles!$A$2:$A$148,0))="","",INDEX(Articles!$G$2:$G$148,MATCH(C64,Articles!$A$2:$A$148,0))) -> 100 | H64: =IF(G64="",0,F64*G64) -> 100 | I64: =IF(INDEX(Articles!$E$2:$E$148,MATCH(C64,Articles!$A$2:$A$148,0))="","",INDEX(Articles!$E$2:$E$148,MATCH(C64,Articles!$A$2:$A$148,0))) | J64: =IF(I64="","",F64*I64) | K64: =INDEX(Articles!$H$2:$H$148,MATCH(C64,Articles!$A$2:$A$148,0)) -> Fixé | L64: =INDEX(Articles!$F$2:$F$148,MATCH(C64,Articles!$A$2:$A$148,0)) -> Inconnu | N64: Oui
A65: Écriture | B65: Crayon noir | C65: S065 | D65: =INDEX(Articles!$C$2:$C$148,MATCH(C65,Articles!$A$2:$A$148,0)) -> Crayon papier (vendu à l'unité) | E65: =INDEX(Articles!$B$2:$B$148,MATCH(C65,Articles!$A$2:$A$148,0)) -> LPD | F65: 1 | G65: =IF(INDEX(Articles!$G$2:$G$148,MATCH(C65,Articles!$A$2:$A$148,0))="","",INDEX(Articles!$G$2:$G$148,MATCH(C65,Articles!$A$2:$A$148,0))) -> 75 | H65: =IF(G65="",0,F65*G65) -> 75 | I65: =IF(INDEX(Articles!$E$2:$E$148,MATCH(C65,Articles!$A$2:$A$148,0))="","",INDEX(Articles!$E$2:$E$148,MATCH(C65,Articles!$A$2:$A$148,0))) | J65: =IF(I65="","",F65*I65) | K65: =INDEX(Articles!$H$2:$H$148,MATCH(C65,Articles!$A$2:$A$148,0)) -> Fixé | L65: =INDEX(Articles!$F$2:$F$148,MATCH(C65,Articles!$A$2:$A$148,0)) -> Inconnu | N65: Oui
A66: Petit matériel | B66: Gomme | C66: S009 | D66: =INDEX(Articles!$C$2:$C$148,MATCH(C66,Articles!$A$2:$A$148,0)) -> Gomme Staedtler Mars Plastic | E66: =INDEX(Articles!$B$2:$B$148,MATCH(C66,Articles!$A$2:$A$148,0)) -> LPD | F66: 1 | G66: =IF(INDEX(Articles!$G$2:$G$148,MATCH(C66,Articles!$A$2:$A$148,0))="","",INDEX(Articles!$G$2:$G$148,MATCH(C66,Articles!$A$2:$A$148,0))) -> 250 | H66: =IF(G66="",0,F66*G66) -> 250 | I66: =IF(INDEX(Articles!$E$2:$E$148,MATCH(C66,Articles!$A$2:$A$148,0))="","",INDEX(Articles!$E$2:$E$148,MATCH(C66,Articles!$A$2:$A$148,0))) -> 110 | J66: =IF(I66="","",F66*I66) -> 110 | K66: =INDEX(Articles!$H$2:$H$148,MATCH(C66,Articles!$A$2:$A$148,0)) -> Fixé | L66: =INDEX(Articles!$F$2:$F$148,MATCH(C66,Articles!$A$2:$A$148,0)) -> Estimé | N66: Oui
A67: Manuels au programme | B67: Didactikos Langue et communication | C67: DID-6917 | D67: =INDEX(Articles!$C$2:$C$148,MATCH(C67,Articles!$A$2:$A$148,0)) -> Langue et communication C.E.1 | E67: =INDEX(Articles!$B$2:$B$148,MATCH(C67,Articles!$A$2:$A$148,0)) -> LPD | F67: 1 | G67: =IF(INDEX(Articles!$G$2:$G$148,MATCH(C67,Articles!$A$2:$A$148,0))="","",INDEX(Articles!$G$2:$G$148,MATCH(C67,Articles!$A$2:$A$148,0))) -> 4000 | H67: =IF(G67="",0,F67*G67) -> 4000 | I67: =IF(INDEX(Articles!$E$2:$E$148,MATCH(C67,Articles!$A$2:$A$148,0))="","",INDEX(Articles!$E$2:$E$148,MATCH(C67,Articles!$A$2:$A$148,0))) -> 3000 | J67: =IF(I67="","",F67*I67) -> 3000 | K67: =INDEX(Articles!$H$2:$H$148,MATCH(C67,Articles!$A$2:$A$148,0)) -> Fixé | L67: =INDEX(Articles!$F$2:$F$148,MATCH(C67,Articles!$A$2:$A$148,0)) -> Estimé | M67: « Didactikos langue, maths, DDM : 1 » lu comme 1 manuel par matière | N67: Oui
A68: Manuels au programme | B68: Didactikos Mathématiques | C68: DID-6941 | D68: =INDEX(Articles!$C$2:$C$148,MATCH(C68,Articles!$A$2:$A$148,0)) -> Mathématiques C.E.1 | E68: =INDEX(Articles!$B$2:$B$148,MATCH(C68,Articles!$A$2:$A$148,0)) -> LPD | F68: 1 | G68: =IF(INDEX(Articles!$G$2:$G$148,MATCH(C68,Articles!$A$2:$A$148,0))="","",INDEX(Articles!$G$2:$G$148,MATCH(C68,Articles!$A$2:$A$148,0))) -> 4000 | H68: =IF(G68="",0,F68*G68) -> 4000 | I68: =IF(INDEX(Articles!$E$2:$E$148,MATCH(C68,Articles!$A$2:$A$148,0))="","",INDEX(Articles!$E$2:$E$148,MATCH(C68,Articles!$A$2:$A$148,0))) -> 3000 | J68: =IF(I68="","",F68*I68) -> 3000 | K68: =INDEX(Articles!$H$2:$H$148,MATCH(C68,Articles!$A$2:$A$148,0)) -> Fixé | L68: =INDEX(Articles!$F$2:$F$148,MATCH(C68,Articles!$A$2:$A$148,0)) -> Estimé | M68: « Didactikos langue, maths, DDM : 1 » lu comme 1 manuel par matière | N68: Oui
A69: Manuels au programme | B69: Didactikos Découverte du monde | C69: DID-6954 | D69: =INDEX(Articles!$C$2:$C$148,MATCH(C69,Articles!$A$2:$A$148,0)) -> Découverte du monde C.E.1 | E69: =INDEX(Articles!$B$2:$B$148,MATCH(C69,Articles!$A$2:$A$148,0)) -> LPD | F69: 1 | G69: =IF(INDEX(Articles!$G$2:$G$148,MATCH(C69,Articles!$A$2:$A$148,0))="","",INDEX(Articles!$G$2:$G$148,MATCH(C69,Articles!$A$2:$A$148,0))) -> 4000 | H69: =IF(G69="",0,F69*G69) -> 4000 | I69: =IF(INDEX(Articles!$E$2:$E$148,MATCH(C69,Articles!$A$2:$A$148,0))="","",INDEX(Articles!$E$2:$E$148,MATCH(C69,Articles!$A$2:$A$148,0))) -> 3000 | J69: =IF(I69="","",F69*I69) -> 3000 | K69: =INDEX(Articles!$H$2:$H$148,MATCH(C69,Articles!$A$2:$A$148,0)) -> Fixé | L69: =INDEX(Articles!$F$2:$F$148,MATCH(C69,Articles!$A$2:$A$148,0)) -> Estimé | M69: « Didactikos langue, maths, DDM : 1 » lu comme 1 manuel par matière | N69: Oui
A70: Parascolaire | B70: Cahier d'activités Langue et communication | C70: DID-7403 | D70: =INDEX(Articles!$C$2:$C$148,MATCH(C70,Articles!$A$2:$A$148,0)) -> Cahier d’activités fongible LC C.E.1 | E70: =INDEX(Articles!$B$2:$B$148,MATCH(C70,Articles!$A$2:$A$148,0)) -> LPD | F70: 1 | G70: =IF(INDEX(Articles!$G$2:$G$148,MATCH(C70,Articles!$A$2:$A$148,0))="","",INDEX(Articles!$G$2:$G$148,MATCH(C70,Articles!$A$2:$A$148,0))) -> 3010 | H70: =IF(G70="",0,F70*G70) -> 3010 | I70: =IF(INDEX(Articles!$E$2:$E$148,MATCH(C70,Articles!$A$2:$A$148,0))="","",INDEX(Articles!$E$2:$E$148,MATCH(C70,Articles!$A$2:$A$148,0))) -> 2010 | J70: =IF(I70="","",F70*I70) -> 2010 | K70: =INDEX(Articles!$H$2:$H$148,MATCH(C70,Articles!$A$2:$A$148,0)) -> Fixé | L70: =INDEX(Articles!$F$2:$F$148,MATCH(C70,Articles!$A$2:$A$148,0)) -> Estimé | N70: Oui
A71: Parascolaire | B71: Cahier d'activités Mathématiques | C71: DID-7246 | D71: =INDEX(Articles!$C$2:$C$148,MATCH(C71,Articles!$A$2:$A$148,0)) -> Cahier d’activités mathématiques C.E.1 | E71: =INDEX(Articles!$B$2:$B$148,MATCH(C71,Articles!$A$2:$A$148,0)) -> LPD | F71: 1 | G71: =IF(INDEX(Articles!$G$2:$G$148,MATCH(C71,Articles!$A$2:$A$148,0))="","",INDEX(Articles!$G$2:$G$148,MATCH(C71,Articles!$A$2:$A$148,0))) -> 3010 | H71: =IF(G71="",0,F71*G71) -> 3010 | I71: =IF(INDEX(Articles!$E$2:$E$148,MATCH(C71,Articles!$A$2:$A$148,0))="","",INDEX(Articles!$E$2:$E$148,MATCH(C71,Articles!$A$2:$A$148,0))) -> 2010 | J71: =IF(I71="","",F71*I71) -> 2010 | K71: =INDEX(Articles!$H$2:$H$148,MATCH(C71,Articles!$A$2:$A$148,0)) -> Fixé | L71: =INDEX(Articles!$F$2:$F$148,MATCH(C71,Articles!$A$2:$A$148,0)) -> Estimé | N71: Oui
D72: Lignes sans prix de vente (à fournir) | H72: =COUNTIF(G59:G71,"") -> 0
D73: Total vente du kit (FCFA) | H73: =SUM(H59:H71) -> 27445
D74: Coût de revient connu (FCFA) | H74: =SUM(J59:J71) -> 20030
D75: Lignes sans prix d'achat | H75: =COUNTIF(I59:I71,"") -> 3
D76: Marge sur les lignes au coût connu (FCFA) | H76: =SUMPRODUCT((I59:I71<>"")*H59:H71)-H74 -> 7140
D77: Nombre de cahiers (ligne « X cahiers » dans l'app) | H77: =SUMIF(A59:A71,"Cahiers",F59:F71) -> 4
D78: Part du prix de vente reposant sur des PV estimés | H78: =IF(H73=0,0,SUMIF(K59:K71,"<>Fixé",H59:H71)/H73) -> 0.12388413
D79: Statut du coût | H79: =IF(H72>0,"Total incomplet : "&H72&" prix de vente à fournir",IF(H75>0,"Coût incomplet : "&H75&" ligne(s) sans prix d'achat","Complet")) -> Coût incomplet : 3 ligne(s) sans prix d'achat
D80: Option décochée par défaut, non comptée : | E80: =INDEX(Articles!$C$2:$C$148,MATCH("S027",Articles!$A$2:$A$148,0)) -> Cartable rigide bleu marine | H80: =INDEX(Articles!$G$2:$G$148,MATCH("S027",Articles!$A$2:$A$148,0)) -> 7500
D81: Manquants : | E81: aucun

Sheet CE2
A1: Kit CE2
A2: Liste réelle du Complexe Dar El-Hadith. Contrôle croisé avec la liste ISJA 2026-2027 (plus chargée, écoles privées).
A4: CE2 — Essentiel
A5: Groupe (app) | B5: Besoin (liste) | C5: ID | D5: Désignation | E5: Fournisseur | F5: Qté | G5: PV unit. (FCFA) | H5: Sous-total vente | I5: PA unit. (FCFA) | J5: Sous-total achat | K5: Statut vente | L5: Statut achat | M5: Remarque | N5: Coché par défaut
A6: Cahiers | B6: Cahier 96 pages | C6: SAC-048 | D6: =INDEX(Articles!$C$2:$C$148,MATCH(C6,Articles!$A$2:$A$148,0)) -> Cahier Calligraphe 96 pages 17x22 56 g seyès | E6: =INDEX(Articles!$B$2:$B$148,MATCH(C6,Articles!$A$2:$A$148,0)) -> Papex | F6: 4 | G6: =IF(INDEX(Articles!$G$2:$G$148,MATCH(C6,Articles!$A$2:$A$148,0))="","",INDEX(Articles!$G$2:$G$148,MATCH(C6,Articles!$A$2:$A$148,0))) -> 450 | H6: =IF(G6="",0,F6*G6) -> 1800 | I6: =IF(INDEX(Articles!$E$2:$E$148,MATCH(C6,Articles!$A$2:$A$148,0))="","",INDEX(Articles!$E$2:$E$148,MATCH(C6,Articles!$A$2:$A$148,0))) -> 350 | J6: =IF(I6="","",F6*I6) -> 1400 | K6: =INDEX(Articles!$H$2:$H$148,MATCH(C6,Articles!$A$2:$A$148,0)) -> Fixé | L6: =INDEX(Articles!$F$2:$F$148,MATCH(C6,Articles!$A$2:$A$148,0)) -> Confirmé | N6: Oui
A7: Géométrie | B7: Matériel géométrique | C7: SAC-007 | D7: =INDEX(Articles!$C$2:$C$148,MATCH(C7,Articles!$A$2:$A$148,0)) -> Kit de traçage 30 cm, 4 pièces L'écolier | E7: =INDEX(Articles!$B$2:$B$148,MATCH(C7,Articles!$A$2:$A$148,0)) -> Papex | F7: 1 | G7: =IF(INDEX(Articles!$G$2:$G$148,MATCH(C7,Articles!$A$2:$A$148,0))="","",INDEX(Articles!$G$2:$G$148,MATCH(C7,Articles!$A$2:$A$148,0))) -> 900 | H7: =IF(G7="",0,F7*G7) -> 900 | I7: =IF(INDEX(Articles!$E$2:$E$148,MATCH(C7,Articles!$A$2:$A$148,0))="","",INDEX(Articles!$E$2:$E$148,MATCH(C7,Articles!$A$2:$A$148,0))) -> 650 | J7: =IF(I7="","",F7*I7) -> 650 | K7: =INDEX(Articles!$H$2:$H$148,MATCH(C7,Articles!$A$2:$A$148,0)) -> Estimé | L7: =INDEX(Articles!$F$2:$F$148,MATCH(C7,Articles!$A$2:$A$148,0)) -> Confirmé | N7: Oui
A8: Ardoise | B8: Ardoise | C8: S086 | D8: =INDEX(Articles!$C$2:$C$148,MATCH(C8,Articles!$A$2:$A$148,0)) -> Ardoise scolaire | E8: =INDEX(Articles!$B$2:$B$148,MATCH(C8,Articles!$A$2:$A$148,0)) -> LPD | F8: 1 | G8: =IF(INDEX(Articles!$G$2:$G$148,MATCH(C8,Articles!$A$2:$A$148,0))="","",INDEX(Articles!$G$2:$G$148,MATCH(C8,Articles!$A$2:$A$148,0))) -> 900 | H8: =IF(G8="",0,F8*G8) -> 900 | I8: =IF(INDEX(Articles!$E$2:$E$148,MATCH(C8,Articles!$A$2:$A$148,0))="","",INDEX(Articles!$E$2:$E$148,MATCH(C8,Articles!$A$2:$A$148,0))) -> 600 | J8: =IF(I8="","",F8*I8) -> 600 | K8: =INDEX(Articles!$H$2:$H$148,MATCH(C8,Articles!$A$2:$A$148,0)) -> Fixé | L8: =INDEX(Articles!$F$2:$F$148,MATCH(C8,Articles!$A$2:$A$148,0)) -> Estimé | N8: Oui
A9: Art & dessin | B9: Paquet de crayons de couleur | C9: SAC-019 | D9: =INDEX(Articles!$C$2:$C$148,MATCH(C9,Articles!$A$2:$A$148,0)) -> Crayons de couleur Maped, boîte de 12 | E9: =INDEX(Articles!$B$2:$B$148,MATCH(C9,Articles!$A$2:$A$148,0)) -> Papex | F9: 1 | G9: =IF(INDEX(Articles!$G$2:$G$148,MATCH(C9,Articles!$A$2:$A$148,0))="","",INDEX(Articles!$G$2:$G$148,MATCH(C9,Articles!$A$2:$A$148,0))) -> 900 | H9: =IF(G9="",0,F9*G9) -> 900 | I9: =IF(INDEX(Articles!$E$2:$E$148,MATCH(C9,Articles!$A$2:$A$148,0))="","",INDEX(Articles!$E$2:$E$148,MATCH(C9,Articles!$A$2:$A$148,0))) -> 650 | J9: =IF(I9="","",F9*I9) -> 650 | K9: =INDEX(Articles!$H$2:$H$148,MATCH(C9,Articles!$A$2:$A$148,0)) -> Estimé | L9: =INDEX(Articles!$F$2:$F$148,MATCH(C9,Articles!$A$2:$A$148,0)) -> Estimé | N9: Oui
A10: Écriture | B10: Bic bleu | C10: SAC-065 | D10: =INDEX(Articles!$C$2:$C$148,MATCH(C10,Articles!$A$2:$A$148,0)) -> Stylo à bille Schneider Tops 505 M bleu | E10: =INDEX(Articles!$B$2:$B$148,MATCH(C10,Articles!$A$2:$A$148,0)) -> Papex | F10: 1 | G10: =IF(INDEX(Articles!$G$2:$G$148,MATCH(C10,Articles!$A$2:$A$148,0))="","",INDEX(Articles!$G$2:$G$148,MATCH(C10,Articles!$A$2:$A$148,0))) -> 100 | H10: =IF(G10="",0,F10*G10) -> 100 | I10: =IF(INDEX(Articles!$E$2:$E$148,MATCH(C10,Articles!$A$2:$A$148,0))="","",INDEX(Articles!$E$2:$E$148,MATCH(C10,Articles!$A$2:$A$148,0))) | J10: =IF(I10="","",F10*I10) | K10: =INDEX(Articles!$H$2:$H$148,MATCH(C10,Articles!$A$2:$A$148,0)) -> Fixé | L10: =INDEX(Articles!$F$2:$F$148,MATCH(C10,Articles!$A$2:$A$148,0)) -> Inconnu | N10: Oui
A11: Écriture | B11: Bic vert | C11: SAC-104 | D11: =INDEX(Articles!$C$2:$C$148,MATCH(C11,Articles!$A$2:$A$148,0)) -> Stylo à bille Schneider Tops 505 M vert | E11: =INDEX(Articles!$B$2:$B$148,MATCH(C11,Articles!$A$2:$A$148,0)) -> Papex | F11: 1 | G11: =IF(INDEX(Articles!$G$2:$G$148,MATCH(C11,Articles!$A$2:$A$148,0))="","",INDEX(Articles!$G$2:$G$148,MATCH(C11,Articles!$A$2:$A$148,0))) -> 100 | H11: =IF(G11="",0,F11*G11) -> 100 | I11: =IF(INDEX(Articles!$E$2:$E$148,MATCH(C11,Articles!$A$2:$A$148,0))="","",INDEX(Articles!$E$2:$E$148,MATCH(C11,Articles!$A$2:$A$148,0))) | J11: =IF(I11="","",F11*I11) | K11: =INDEX(Articles!$H$2:$H$148,MATCH(C11,Articles!$A$2:$A$148,0)) -> Fixé | L11: =INDEX(Articles!$F$2:$F$148,MATCH(C11,Articles!$A$2:$A$148,0)) -> Inconnu | N11: Oui
A12: Écriture | B12: Crayon noir | C12: S065 | D12: =INDEX(Articles!$C$2:$C$148,MATCH(C12,Articles!$A$2:$A$148,0)) -> Crayon papier (vendu à l'unité) | E12: =INDEX(Articles!$B$2:$B$148,MATCH(C12,Articles!$A$2:$A$148,0)) -> LPD | F12: 1 | G12: =IF(INDEX(Articles!$G$2:$G$148,MATCH(C12,Articles!$A$2:$A$148,0))="","",INDEX(Articles!$G$2:$G$148,MATCH(C12,Articles!$A$2:$A$148,0))) -> 75 | H12: =IF(G12="",0,F12*G12) -> 75 | I12: =IF(INDEX(Articles!$E$2:$E$148,MATCH(C12,Articles!$A$2:$A$148,0))="","",INDEX(Articles!$E$2:$E$148,MATCH(C12,Articles!$A$2:$A$148,0))) | J12: =IF(I12="","",F12*I12) | K12: =INDEX(Articles!$H$2:$H$148,MATCH(C12,Articles!$A$2:$A$148,0)) -> Fixé | L12: =INDEX(Articles!$F$2:$F$148,MATCH(C12,Articles!$A$2:$A$148,0)) -> Inconnu | N12: Oui
A13: Petit matériel | B13: Gomme | C13: S009 | D13: =INDEX(Articles!$C$2:$C$148,MATCH(C13,Articles!$A$2:$A$148,0)) -> Gomme Staedtler Mars Plastic | E13: =INDEX(Articles!$B$2:$B$148,MATCH(C13,Articles!$A$2:$A$148,0)) -> LPD | F13: 1 | G13: =IF(INDEX(Articles!$G$2:$G$148,MATCH(C13,Articles!$A$2:$A$148,0))="","",INDEX(Articles!$G$2:$G$148,MATCH(C13,Articles!$A$2:$A$148,0))) -> 250 | H13: =IF(G13="",0,F13*G13) -> 250 | I13: =IF(INDEX(Articles!$E$2:$E$148,MATCH(C13,Articles!$A$2:$A$148,0))="","",INDEX(Articles!$E$2:$E$148,MATCH(C13,Articles!$A$2:$A$148,0))) -> 110 | J13: =IF(I13="","",F13*I13) -> 110 | K13: =INDEX(Articles!$H$2:$H$148,MATCH(C13,Articles!$A$2:$A$148,0)) -> Fixé | L13: =INDEX(Articles!$F$2:$F$148,MATCH(C13,Articles!$A$2:$A$148,0)) -> Estimé | N13: Oui
D14: Lignes sans prix de vente (à fournir) | H14: =COUNTIF(G6:G13,"") -> 0
D15: Total vente du kit (FCFA) | H15: =SUM(H6:H13) -> 5025
D16: Coût de revient connu (FCFA) | H16: =SUM(J6:J13) -> 3410
D17: Lignes sans prix d'achat | H17: =COUNTIF(I6:I13,"") -> 3
D18: Marge sur les lignes au coût connu (FCFA) | H18: =SUMPRODUCT((I6:I13<>"")*H6:H13)-H16 -> 1340
D19: Nombre de cahiers (ligne « X cahiers » dans l'app) | H19: =SUMIF(A6:A13,"Cahiers",F6:F13) -> 4
D20: Part du prix de vente reposant sur des PV estimés | H20: =IF(H15=0,0,SUMIF(K6:K13,"<>Fixé",H6:H13)/H15) -> 0.35820896
D21: Statut du coût | H21: =IF(H14>0,"Total incomplet : "&H14&" prix de vente à fournir",IF(H17>0,"Coût incomplet : "&H17&" ligne(s) sans prix d'achat","Complet")) -> Coût incomplet : 3 ligne(s) sans prix d'achat
D23: Proposés décochés : livres du Complet (non comptés, cochables par le client)
A24: Manuels au programme | B24: Didactikos Langue et communication | C24: DID-6922 | D24: =INDEX(Articles!$C$2:$C$148,MATCH(C24,Articles!$A$2:$A$148,0)) -> Langue et communication C.E.2 | G24: =INDEX(Articles!$G$2:$G$148,MATCH(C24,Articles!$A$2:$A$148,0)) -> 4000 | N24: Non
A25: Manuels au programme | B25: Didactikos Mathématiques | C25: DID-6943 | D25: =INDEX(Articles!$C$2:$C$148,MATCH(C25,Articles!$A$2:$A$148,0)) -> Mathématiques C.E.2 | G25: =INDEX(Articles!$G$2:$G$148,MATCH(C25,Articles!$A$2:$A$148,0)) -> 4000 | N25: Non
A26: Manuels au programme | B26: Didactikos Découverte du monde | C26: DID-6956 | D26: =INDEX(Articles!$C$2:$C$148,MATCH(C26,Articles!$A$2:$A$148,0)) -> Découverte du monde C.E.2 | G26: =INDEX(Articles!$G$2:$G$148,MATCH(C26,Articles!$A$2:$A$148,0)) -> 4000 | N26: Non
D27: Total si tous les livres sont cochés (FCFA) | H27: =H15+SUM(G24:G26) -> 17025
D28: Option décochée par défaut, non comptée : | E28: =INDEX(Articles!$C$2:$C$148,MATCH("S027",Articles!$A$2:$A$148,0)) -> Cartable rigide bleu marine | H28: =INDEX(Articles!$G$2:$G$148,MATCH("S027",Articles!$A$2:$A$148,0)) -> 7500
D29: Manquants : | E29: aucun
A32: CE2 — Complet
A33: Groupe (app) | B33: Besoin (liste) | C33: ID | D33: Désignation | E33: Fournisseur | F33: Qté | G33: PV unit. (FCFA) | H33: Sous-total vente | I33: PA unit. (FCFA) | J33: Sous-total achat | K33: Statut vente | L33: Statut achat | M33: Remarque | N33: Coché par défaut
A34: Cahiers | B34: Cahier 96 pages | C34: SAC-033 | D34: =INDEX(Articles!$C$2:$C$148,MATCH(C34,Articles!$A$2:$A$148,0)) -> Cahier Calligraphe 140 pages 17x22 90 g seyès | E34: =INDEX(Articles!$B$2:$B$148,MATCH(C34,Articles!$A$2:$A$148,0)) -> Papex | F34: 4 | G34: =IF(INDEX(Articles!$G$2:$G$148,MATCH(C34,Articles!$A$2:$A$148,0))="","",INDEX(Articles!$G$2:$G$148,MATCH(C34,Articles!$A$2:$A$148,0))) -> 750 | H34: =IF(G34="",0,F34*G34) -> 3000 | I34: =IF(INDEX(Articles!$E$2:$E$148,MATCH(C34,Articles!$A$2:$A$148,0))="","",INDEX(Articles!$E$2:$E$148,MATCH(C34,Articles!$A$2:$A$148,0))) -> 650 | J34: =IF(I34="","",F34*I34) -> 2600 | K34: =INDEX(Articles!$H$2:$H$148,MATCH(C34,Articles!$A$2:$A$148,0)) -> Fixé | L34: =INDEX(Articles!$F$2:$F$148,MATCH(C34,Articles!$A$2:$A$148,0)) -> Estimé | M34: 140 p Calligraphe 90 g | N34: Oui
A35: Géométrie | B35: Matériel géométrique | C35: S091 | D35: =INDEX(Articles!$C$2:$C$148,MATCH(C35,Articles!$A$2:$A$148,0)) -> Kit géométrie Maped 30 cm (réf. 1930) | E35: =INDEX(Articles!$B$2:$B$148,MATCH(C35,Articles!$A$2:$A$148,0)) -> LPD | F35: 1 | G35: =IF(INDEX(Articles!$G$2:$G$148,MATCH(C35,Articles!$A$2:$A$148,0))="","",INDEX(Articles!$G$2:$G$148,MATCH(C35,Articles!$A$2:$A$148,0))) -> 1800 | H35: =IF(G35="",0,F35*G35) -> 1800 | I35: =IF(INDEX(Articles!$E$2:$E$148,MATCH(C35,Articles!$A$2:$A$148,0))="","",INDEX(Articles!$E$2:$E$148,MATCH(C35,Articles!$A$2:$A$148,0))) -> 1500 | J35: =IF(I35="","",F35*I35) -> 1500 | K35: =INDEX(Articles!$H$2:$H$148,MATCH(C35,Articles!$A$2:$A$148,0)) -> À trancher | L35: =INDEX(Articles!$F$2:$F$148,MATCH(C35,Articles!$A$2:$A$148,0)) -> Confirmé | N35: Oui
A36: Ardoise | B36: Ardoise | C36: CIS-ardoise | D36: =INDEX(Articles!$C$2:$C$148,MATCH(C36,Articles!$A$2:$A$148,0)) -> Ardoise quadrillée avec poignée | E36: =INDEX(Articles!$B$2:$B$148,MATCH(C36,Articles!$A$2:$A$148,0)) -> Cissé & Frères | F36: 1 | G36: =IF(INDEX(Articles!$G$2:$G$148,MATCH(C36,Articles!$A$2:$A$148,0))="","",INDEX(Articles!$G$2:$G$148,MATCH(C36,Articles!$A$2:$A$148,0))) -> 2500 | H36: =IF(G36="",0,F36*G36) -> 2500 | I36: =IF(INDEX(Articles!$E$2:$E$148,MATCH(C36,Articles!$A$2:$A$148,0))="","",INDEX(Articles!$E$2:$E$148,MATCH(C36,Articles!$A$2:$A$148,0))) -> 1500 | J36: =IF(I36="","",F36*I36) -> 1500 | K36: =INDEX(Articles!$H$2:$H$148,MATCH(C36,Articles!$A$2:$A$148,0)) -> Fixé | L36: =INDEX(Articles!$F$2:$F$148,MATCH(C36,Articles!$A$2:$A$148,0)) -> Confirmé | N36: Oui
A37: Art & dessin | B37: Paquet de crayons de couleur | C37: SAC-024 | D37: =INDEX(Articles!$C$2:$C$148,MATCH(C37,Articles!$A$2:$A$148,0)) -> Crayons de couleur Maped Nightfall, boîte de 24 | E37: =INDEX(Articles!$B$2:$B$148,MATCH(C37,Articles!$A$2:$A$148,0)) -> Papex | F37: 1 | G37: =IF(INDEX(Articles!$G$2:$G$148,MATCH(C37,Articles!$A$2:$A$148,0))="","",INDEX(Articles!$G$2:$G$148,MATCH(C37,Articles!$A$2:$A$148,0))) -> 1600 | H37: =IF(G37="",0,F37*G37) -> 1600 | I37: =IF(INDEX(Articles!$E$2:$E$148,MATCH(C37,Articles!$A$2:$A$148,0))="","",INDEX(Articles!$E$2:$E$148,MATCH(C37,Articles!$A$2:$A$148,0))) -> 1300 | J37: =IF(I37="","",F37*I37) -> 1300 | K37: =INDEX(Articles!$H$2:$H$148,MATCH(C37,Articles!$A$2:$A$148,0)) -> Estimé | L37: =INDEX(Articles!$F$2:$F$148,MATCH(C37,Articles!$A$2:$A$148,0)) -> Estimé | N37: Oui
A38: Écriture | B38: Bic bleu | C38: SAC-065 | D38: =INDEX(Articles!$C$2:$C$148,MATCH(C38,Articles!$A$2:$A$148,0)) -> Stylo à bille Schneider Tops 505 M bleu | E38: =INDEX(Articles!$B$2:$B$148,MATCH(C38,Articles!$A$2:$A$148,0)) -> Papex | F38: 1 | G38: =IF(INDEX(Articles!$G$2:$G$148,MATCH(C38,Articles!$A$2:$A$148,0))="","",INDEX(Articles!$G$2:$G$148,MATCH(C38,Articles!$A$2:$A$148,0))) -> 100 | H38: =IF(G38="",0,F38*G38) -> 100 | I38: =IF(INDEX(Articles!$E$2:$E$148,MATCH(C38,Articles!$A$2:$A$148,0))="","",INDEX(Articles!$E$2:$E$148,MATCH(C38,Articles!$A$2:$A$148,0))) | J38: =IF(I38="","",F38*I38) | K38: =INDEX(Articles!$H$2:$H$148,MATCH(C38,Articles!$A$2:$A$148,0)) -> Fixé | L38: =INDEX(Articles!$F$2:$F$148,MATCH(C38,Articles!$A$2:$A$148,0)) -> Inconnu | N38: Oui
A39: Écriture | B39: Bic vert | C39: SAC-104 | D39: =INDEX(Articles!$C$2:$C$148,MATCH(C39,Articles!$A$2:$A$148,0)) -> Stylo à bille Schneider Tops 505 M vert | E39: =INDEX(Articles!$B$2:$B$148,MATCH(C39,Articles!$A$2:$A$148,0)) -> Papex | F39: 1 | G39: =IF(INDEX(Articles!$G$2:$G$148,MATCH(C39,Articles!$A$2:$A$148,0))="","",INDEX(Articles!$G$2:$G$148,MATCH(C39,Articles!$A$2:$A$148,0))) -> 100 | H39: =IF(G39="",0,F39*G39) -> 100 | I39: =IF(INDEX(Articles!$E$2:$E$148,MATCH(C39,Articles!$A$2:$A$148,0))="","",INDEX(Articles!$E$2:$E$148,MATCH(C39,Articles!$A$2:$A$148,0))) | J39: =IF(I39="","",F39*I39) | K39: =INDEX(Articles!$H$2:$H$148,MATCH(C39,Articles!$A$2:$A$148,0)) -> Fixé | L39: =INDEX(Articles!$F$2:$F$148,MATCH(C39,Articles!$A$2:$A$148,0)) -> Inconnu | N39: Oui
A40: Écriture | B40: Crayon noir | C40: S065 | D40: =INDEX(Articles!$C$2:$C$148,MATCH(C40,Articles!$A$2:$A$148,0)) -> Crayon papier (vendu à l'unité) | E40: =INDEX(Articles!$B$2:$B$148,MATCH(C40,Articles!$A$2:$A$148,0)) -> LPD | F40: 1 | G40: =IF(INDEX(Articles!$G$2:$G$148,MATCH(C40,Articles!$A$2:$A$148,0))="","",INDEX(Articles!$G$2:$G$148,MATCH(C40,Articles!$A$2:$A$148,0))) -> 75 | H40: =IF(G40="",0,F40*G40) -> 75 | I40: =IF(INDEX(Articles!$E$2:$E$148,MATCH(C40,Articles!$A$2:$A$148,0))="","",INDEX(Articles!$E$2:$E$148,MATCH(C40,Articles!$A$2:$A$148,0))) | J40: =IF(I40="","",F40*I40) | K40: =INDEX(Articles!$H$2:$H$148,MATCH(C40,Articles!$A$2:$A$148,0)) -> Fixé | L40: =INDEX(Articles!$F$2:$F$148,MATCH(C40,Articles!$A$2:$A$148,0)) -> Inconnu | N40: Oui
A41: Petit matériel | B41: Gomme | C41: S009 | D41: =INDEX(Articles!$C$2:$C$148,MATCH(C41,Articles!$A$2:$A$148,0)) -> Gomme Staedtler Mars Plastic | E41: =INDEX(Articles!$B$2:$B$148,MATCH(C41,Articles!$A$2:$A$148,0)) -> LPD | F41: 1 | G41: =IF(INDEX(Articles!$G$2:$G$148,MATCH(C41,Articles!$A$2:$A$148,0))="","",INDEX(Articles!$G$2:$G$148,MATCH(C41,Articles!$A$2:$A$148,0))) -> 250 | H41: =IF(G41="",0,F41*G41) -> 250 | I41: =IF(INDEX(Articles!$E$2:$E$148,MATCH(C41,Articles!$A$2:$A$148,0))="","",INDEX(Articles!$E$2:$E$148,MATCH(C41,Articles!$A$2:$A$148,0))) -> 110 | J41: =IF(I41="","",F41*I41) -> 110 | K41: =INDEX(Articles!$H$2:$H$148,MATCH(C41,Articles!$A$2:$A$148,0)) -> Fixé | L41: =INDEX(Articles!$F$2:$F$148,MATCH(C41,Articles!$A$2:$A$148,0)) -> Estimé | N41: Oui
A42: Manuels au programme | B42: Didactikos Langue et communication | C42: DID-6922 | D42: =INDEX(Articles!$C$2:$C$148,MATCH(C42,Articles!$A$2:$A$148,0)) -> Langue et communication C.E.2 | E42: =INDEX(Articles!$B$2:$B$148,MATCH(C42,Articles!$A$2:$A$148,0)) -> LPD | F42: 1 | G42: =IF(INDEX(Articles!$G$2:$G$148,MATCH(C42,Articles!$A$2:$A$148,0))="","",INDEX(Articles!$G$2:$G$148,MATCH(C42,Articles!$A$2:$A$148,0))) -> 4000 | H42: =IF(G42="",0,F42*G42) -> 4000 | I42: =IF(INDEX(Articles!$E$2:$E$148,MATCH(C42,Articles!$A$2:$A$148,0))="","",INDEX(Articles!$E$2:$E$148,MATCH(C42,Articles!$A$2:$A$148,0))) -> 3000 | J42: =IF(I42="","",F42*I42) -> 3000 | K42: =INDEX(Articles!$H$2:$H$148,MATCH(C42,Articles!$A$2:$A$148,0)) -> Fixé | L42: =INDEX(Articles!$F$2:$F$148,MATCH(C42,Articles!$A$2:$A$148,0)) -> Estimé | M42: « Didactikos langue, maths, DDM : 1 » lu comme 1 manuel par matière | N42: Oui
A43: Manuels au programme | B43: Didactikos Mathématiques | C43: DID-6943 | D43: =INDEX(Articles!$C$2:$C$148,MATCH(C43,Articles!$A$2:$A$148,0)) -> Mathématiques C.E.2 | E43: =INDEX(Articles!$B$2:$B$148,MATCH(C43,Articles!$A$2:$A$148,0)) -> LPD | F43: 1 | G43: =IF(INDEX(Articles!$G$2:$G$148,MATCH(C43,Articles!$A$2:$A$148,0))="","",INDEX(Articles!$G$2:$G$148,MATCH(C43,Articles!$A$2:$A$148,0))) -> 4000 | H43: =IF(G43="",0,F43*G43) -> 4000 | I43: =IF(INDEX(Articles!$E$2:$E$148,MATCH(C43,Articles!$A$2:$A$148,0))="","",INDEX(Articles!$E$2:$E$148,MATCH(C43,Articles!$A$2:$A$148,0))) -> 3000 | J43: =IF(I43="","",F43*I43) -> 3000 | K43: =INDEX(Articles!$H$2:$H$148,MATCH(C43,Articles!$A$2:$A$148,0)) -> Fixé | L43: =INDEX(Articles!$F$2:$F$148,MATCH(C43,Articles!$A$2:$A$148,0)) -> Estimé | M43: « Didactikos langue, maths, DDM : 1 » lu comme 1 manuel par matière | N43: Oui
A44: Manuels au programme | B44: Didactikos Découverte du monde | C44: DID-6956 | D44: =INDEX(Articles!$C$2:$C$148,MATCH(C44,Articles!$A$2:$A$148,0)) -> Découverte du monde C.E.2 | E44: =INDEX(Articles!$B$2:$B$148,MATCH(C44,Articles!$A$2:$A$148,0)) -> LPD | F44: 1 | G44: =IF(INDEX(Articles!$G$2:$G$148,MATCH(C44,Articles!$A$2:$A$148,0))="","",INDEX(Articles!$G$2:$G$148,MATCH(C44,Articles!$A$2:$A$148,0))) -> 4000 | H44: =IF(G44="",0,F44*G44) -> 4000 | I44: =IF(INDEX(Articles!$E$2:$E$148,MATCH(C44,Articles!$A$2:$A$148,0))="","",INDEX(Articles!$E$2:$E$148,MATCH(C44,Articles!$A$2:$A$148,0))) -> 3000 | J44: =IF(I44="","",F44*I44) -> 3000 | K44: =INDEX(Articles!$H$2:$H$148,MATCH(C44,Articles!$A$2:$A$148,0)) -> Fixé | L44: =INDEX(Articles!$F$2:$F$148,MATCH(C44,Articles!$A$2:$A$148,0)) -> Estimé | M44: « Didactikos langue, maths, DDM : 1 » lu comme 1 manuel par matière | N44: Oui
D45: Lignes sans prix de vente (à fournir) | H45: =COUNTIF(G34:G44,"") -> 0
D46: Total vente du kit (FCFA) | H46: =SUM(H34:H44) -> 21425
D47: Coût de revient connu (FCFA) | H47: =SUM(J34:J44) -> 16010
D48: Lignes sans prix d'achat | H48: =COUNTIF(I34:I44,"") -> 3
D49: Marge sur les lignes au coût connu (FCFA) | H49: =SUMPRODUCT((I34:I44<>"")*H34:H44)-H47 -> 5140
D50: Nombre de cahiers (ligne « X cahiers » dans l'app) | H50: =SUMIF(A34:A44,"Cahiers",F34:F44) -> 4
D51: Part du prix de vente reposant sur des PV estimés | H51: =IF(H46=0,0,SUMIF(K34:K44,"<>Fixé",H34:H44)/H46) -> 0.15869312
D52: Statut du coût | H52: =IF(H45>0,"Total incomplet : "&H45&" prix de vente à fournir",IF(H48>0,"Coût incomplet : "&H48&" ligne(s) sans prix d'achat","Complet")) -> Coût incomplet : 3 ligne(s) sans prix d'achat
D53: Option décochée par défaut, non comptée : | E53: =INDEX(Articles!$C$2:$C$148,MATCH("S027",Articles!$A$2:$A$148,0)) -> Cartable rigide bleu marine | H53: =INDEX(Articles!$G$2:$G$148,MATCH("S027",Articles!$A$2:$A$148,0)) -> 7500
D54: Manquants : | E54: aucun
A57: CE2 — Confort
A58: Groupe (app) | B58: Besoin (liste) | C58: ID | D58: Désignation | E58: Fournisseur | F58: Qté | G58: PV unit. (FCFA) | H58: Sous-total vente | I58: PA unit. (FCFA) | J58: Sous-total achat | K58: Statut vente | L58: Statut achat | M58: Remarque | N58: Coché par défaut
A59: Cahiers | B59: Cahier 96 pages | C59: SAC-033 | D59: =INDEX(Articles!$C$2:$C$148,MATCH(C59,Articles!$A$2:$A$148,0)) -> Cahier Calligraphe 140 pages 17x22 90 g seyès | E59: =INDEX(Articles!$B$2:$B$148,MATCH(C59,Articles!$A$2:$A$148,0)) -> Papex | F59: 4 | G59: =IF(INDEX(Articles!$G$2:$G$148,MATCH(C59,Articles!$A$2:$A$148,0))="","",INDEX(Articles!$G$2:$G$148,MATCH(C59,Articles!$A$2:$A$148,0))) -> 750 | H59: =IF(G59="",0,F59*G59) -> 3000 | I59: =IF(INDEX(Articles!$E$2:$E$148,MATCH(C59,Articles!$A$2:$A$148,0))="","",INDEX(Articles!$E$2:$E$148,MATCH(C59,Articles!$A$2:$A$148,0))) -> 650 | J59: =IF(I59="","",F59*I59) -> 2600 | K59: =INDEX(Articles!$H$2:$H$148,MATCH(C59,Articles!$A$2:$A$148,0)) -> Fixé | L59: =INDEX(Articles!$F$2:$F$148,MATCH(C59,Articles!$A$2:$A$148,0)) -> Estimé | M59: 140 p Calligraphe 90 g | N59: Oui
A60: Géométrie | B60: Matériel géométrique | C60: S091 | D60: =INDEX(Articles!$C$2:$C$148,MATCH(C60,Articles!$A$2:$A$148,0)) -> Kit géométrie Maped 30 cm (réf. 1930) | E60: =INDEX(Articles!$B$2:$B$148,MATCH(C60,Articles!$A$2:$A$148,0)) -> LPD | F60: 1 | G60: =IF(INDEX(Articles!$G$2:$G$148,MATCH(C60,Articles!$A$2:$A$148,0))="","",INDEX(Articles!$G$2:$G$148,MATCH(C60,Articles!$A$2:$A$148,0))) -> 1800 | H60: =IF(G60="",0,F60*G60) -> 1800 | I60: =IF(INDEX(Articles!$E$2:$E$148,MATCH(C60,Articles!$A$2:$A$148,0))="","",INDEX(Articles!$E$2:$E$148,MATCH(C60,Articles!$A$2:$A$148,0))) -> 1500 | J60: =IF(I60="","",F60*I60) -> 1500 | K60: =INDEX(Articles!$H$2:$H$148,MATCH(C60,Articles!$A$2:$A$148,0)) -> À trancher | L60: =INDEX(Articles!$F$2:$F$148,MATCH(C60,Articles!$A$2:$A$148,0)) -> Confirmé | N60: Oui
A61: Ardoise | B61: Ardoise | C61: CIS-ardoise | D61: =INDEX(Articles!$C$2:$C$148,MATCH(C61,Articles!$A$2:$A$148,0)) -> Ardoise quadrillée avec poignée | E61: =INDEX(Articles!$B$2:$B$148,MATCH(C61,Articles!$A$2:$A$148,0)) -> Cissé & Frères | F61: 1 | G61: =IF(INDEX(Articles!$G$2:$G$148,MATCH(C61,Articles!$A$2:$A$148,0))="","",INDEX(Articles!$G$2:$G$148,MATCH(C61,Articles!$A$2:$A$148,0))) -> 2500 | H61: =IF(G61="",0,F61*G61) -> 2500 | I61: =IF(INDEX(Articles!$E$2:$E$148,MATCH(C61,Articles!$A$2:$A$148,0))="","",INDEX(Articles!$E$2:$E$148,MATCH(C61,Articles!$A$2:$A$148,0))) -> 1500 | J61: =IF(I61="","",F61*I61) -> 1500 | K61: =INDEX(Articles!$H$2:$H$148,MATCH(C61,Articles!$A$2:$A$148,0)) -> Fixé | L61: =INDEX(Articles!$F$2:$F$148,MATCH(C61,Articles!$A$2:$A$148,0)) -> Confirmé | N61: Oui
A62: Art & dessin | B62: Paquet de crayons de couleur | C62: SAC-024 | D62: =INDEX(Articles!$C$2:$C$148,MATCH(C62,Articles!$A$2:$A$148,0)) -> Crayons de couleur Maped Nightfall, boîte de 24 | E62: =INDEX(Articles!$B$2:$B$148,MATCH(C62,Articles!$A$2:$A$148,0)) -> Papex | F62: 1 | G62: =IF(INDEX(Articles!$G$2:$G$148,MATCH(C62,Articles!$A$2:$A$148,0))="","",INDEX(Articles!$G$2:$G$148,MATCH(C62,Articles!$A$2:$A$148,0))) -> 1600 | H62: =IF(G62="",0,F62*G62) -> 1600 | I62: =IF(INDEX(Articles!$E$2:$E$148,MATCH(C62,Articles!$A$2:$A$148,0))="","",INDEX(Articles!$E$2:$E$148,MATCH(C62,Articles!$A$2:$A$148,0))) -> 1300 | J62: =IF(I62="","",F62*I62) -> 1300 | K62: =INDEX(Articles!$H$2:$H$148,MATCH(C62,Articles!$A$2:$A$148,0)) -> Estimé | L62: =INDEX(Articles!$F$2:$F$148,MATCH(C62,Articles!$A$2:$A$148,0)) -> Estimé | N62: Oui
A63: Écriture | B63: Bic bleu | C63: SAC-065 | D63: =INDEX(Articles!$C$2:$C$148,MATCH(C63,Articles!$A$2:$A$148,0)) -> Stylo à bille Schneider Tops 505 M bleu | E63: =INDEX(Articles!$B$2:$B$148,MATCH(C63,Articles!$A$2:$A$148,0)) -> Papex | F63: 1 | G63: =IF(INDEX(Articles!$G$2:$G$148,MATCH(C63,Articles!$A$2:$A$148,0))="","",INDEX(Articles!$G$2:$G$148,MATCH(C63,Articles!$A$2:$A$148,0))) -> 100 | H63: =IF(G63="",0,F63*G63) -> 100 | I63: =IF(INDEX(Articles!$E$2:$E$148,MATCH(C63,Articles!$A$2:$A$148,0))="","",INDEX(Articles!$E$2:$E$148,MATCH(C63,Articles!$A$2:$A$148,0))) | J63: =IF(I63="","",F63*I63) | K63: =INDEX(Articles!$H$2:$H$148,MATCH(C63,Articles!$A$2:$A$148,0)) -> Fixé | L63: =INDEX(Articles!$F$2:$F$148,MATCH(C63,Articles!$A$2:$A$148,0)) -> Inconnu | N63: Oui
A64: Écriture | B64: Bic vert | C64: SAC-104 | D64: =INDEX(Articles!$C$2:$C$148,MATCH(C64,Articles!$A$2:$A$148,0)) -> Stylo à bille Schneider Tops 505 M vert | E64: =INDEX(Articles!$B$2:$B$148,MATCH(C64,Articles!$A$2:$A$148,0)) -> Papex | F64: 1 | G64: =IF(INDEX(Articles!$G$2:$G$148,MATCH(C64,Articles!$A$2:$A$148,0))="","",INDEX(Articles!$G$2:$G$148,MATCH(C64,Articles!$A$2:$A$148,0))) -> 100 | H64: =IF(G64="",0,F64*G64) -> 100 | I64: =IF(INDEX(Articles!$E$2:$E$148,MATCH(C64,Articles!$A$2:$A$148,0))="","",INDEX(Articles!$E$2:$E$148,MATCH(C64,Articles!$A$2:$A$148,0))) | J64: =IF(I64="","",F64*I64) | K64: =INDEX(Articles!$H$2:$H$148,MATCH(C64,Articles!$A$2:$A$148,0)) -> Fixé | L64: =INDEX(Articles!$F$2:$F$148,MATCH(C64,Articles!$A$2:$A$148,0)) -> Inconnu | N64: Oui
A65: Écriture | B65: Crayon noir | C65: S065 | D65: =INDEX(Articles!$C$2:$C$148,MATCH(C65,Articles!$A$2:$A$148,0)) -> Crayon papier (vendu à l'unité) | E65: =INDEX(Articles!$B$2:$B$148,MATCH(C65,Articles!$A$2:$A$148,0)) -> LPD | F65: 1 | G65: =IF(INDEX(Articles!$G$2:$G$148,MATCH(C65,Articles!$A$2:$A$148,0))="","",INDEX(Articles!$G$2:$G$148,MATCH(C65,Articles!$A$2:$A$148,0))) -> 75 | H65: =IF(G65="",0,F65*G65) -> 75 | I65: =IF(INDEX(Articles!$E$2:$E$148,MATCH(C65,Articles!$A$2:$A$148,0))="","",INDEX(Articles!$E$2:$E$148,MATCH(C65,Articles!$A$2:$A$148,0))) | J65: =IF(I65="","",F65*I65) | K65: =INDEX(Articles!$H$2:$H$148,MATCH(C65,Articles!$A$2:$A$148,0)) -> Fixé | L65: =INDEX(Articles!$F$2:$F$148,MATCH(C65,Articles!$A$2:$A$148,0)) -> Inconnu | N65: Oui
A66: Petit matériel | B66: Gomme | C66: S009 | D66: =INDEX(Articles!$C$2:$C$148,MATCH(C66,Articles!$A$2:$A$148,0)) -> Gomme Staedtler Mars Plastic | E66: =INDEX(Articles!$B$2:$B$148,MATCH(C66,Articles!$A$2:$A$148,0)) -> LPD | F66: 1 | G66: =IF(INDEX(Articles!$G$2:$G$148,MATCH(C66,Articles!$A$2:$A$148,0))="","",INDEX(Articles!$G$2:$G$148,MATCH(C66,Articles!$A$2:$A$148,0))) -> 250 | H66: =IF(G66="",0,F66*G66) -> 250 | I66: =IF(INDEX(Articles!$E$2:$E$148,MATCH(C66,Articles!$A$2:$A$148,0))="","",INDEX(Articles!$E$2:$E$148,MATCH(C66,Articles!$A$2:$A$148,0))) -> 110 | J66: =IF(I66="","",F66*I66) -> 110 | K66: =INDEX(Articles!$H$2:$H$148,MATCH(C66,Articles!$A$2:$A$148,0)) -> Fixé | L66: =INDEX(Articles!$F$2:$F$148,MATCH(C66,Articles!$A$2:$A$148,0)) -> Estimé | N66: Oui
A67: Manuels au programme | B67: Didactikos Langue et communication | C67: DID-6922 | D67: =INDEX(Articles!$C$2:$C$148,MATCH(C67,Articles!$A$2:$A$148,0)) -> Langue et communication C.E.2 | E67: =INDEX(Articles!$B$2:$B$148,MATCH(C67,Articles!$A$2:$A$148,0)) -> LPD | F67: 1 | G67: =IF(INDEX(Articles!$G$2:$G$148,MATCH(C67,Articles!$A$2:$A$148,0))="","",INDEX(Articles!$G$2:$G$148,MATCH(C67,Articles!$A$2:$A$148,0))) -> 4000 | H67: =IF(G67="",0,F67*G67) -> 4000 | I67: =IF(INDEX(Articles!$E$2:$E$148,MATCH(C67,Articles!$A$2:$A$148,0))="","",INDEX(Articles!$E$2:$E$148,MATCH(C67,Articles!$A$2:$A$148,0))) -> 3000 | J67: =IF(I67="","",F67*I67) -> 3000 | K67: =INDEX(Articles!$H$2:$H$148,MATCH(C67,Articles!$A$2:$A$148,0)) -> Fixé | L67: =INDEX(Articles!$F$2:$F$148,MATCH(C67,Articles!$A$2:$A$148,0)) -> Estimé | M67: « Didactikos langue, maths, DDM : 1 » lu comme 1 manuel par matière | N67: Oui
A68: Manuels au programme | B68: Didactikos Mathématiques | C68: DID-6943 | D68: =INDEX(Articles!$C$2:$C$148,MATCH(C68,Articles!$A$2:$A$148,0)) -> Mathématiques C.E.2 | E68: =INDEX(Articles!$B$2:$B$148,MATCH(C68,Articles!$A$2:$A$148,0)) -> LPD | F68: 1 | G68: =IF(INDEX(Articles!$G$2:$G$148,MATCH(C68,Articles!$A$2:$A$148,0))="","",INDEX(Articles!$G$2:$G$148,MATCH(C68,Articles!$A$2:$A$148,0))) -> 4000 | H68: =IF(G68="",0,F68*G68) -> 4000 | I68: =IF(INDEX(Articles!$E$2:$E$148,MATCH(C68,Articles!$A$2:$A$148,0))="","",INDEX(Articles!$E$2:$E$148,MATCH(C68,Articles!$A$2:$A$148,0))) -> 3000 | J68: =IF(I68="","",F68*I68) -> 3000 | K68: =INDEX(Articles!$H$2:$H$148,MATCH(C68,Articles!$A$2:$A$148,0)) -> Fixé | L68: =INDEX(Articles!$F$2:$F$148,MATCH(C68,Articles!$A$2:$A$148,0)) -> Estimé | M68: « Didactikos langue, maths, DDM : 1 » lu comme 1 manuel par matière | N68: Oui
A69: Manuels au programme | B69: Didactikos Découverte du monde | C69: DID-6956 | D69: =INDEX(Articles!$C$2:$C$148,MATCH(C69,Articles!$A$2:$A$148,0)) -> Découverte du monde C.E.2 | E69: =INDEX(Articles!$B$2:$B$148,MATCH(C69,Articles!$A$2:$A$148,0)) -> LPD | F69: 1 | G69: =IF(INDEX(Articles!$G$2:$G$148,MATCH(C69,Articles!$A$2:$A$148,0))="","",INDEX(Articles!$G$2:$G$148,MATCH(C69,Articles!$A$2:$A$148,0))) -> 4000 | H69: =IF(G69="",0,F69*G69) -> 4000 | I69: =IF(INDEX(Articles!$E$2:$E$148,MATCH(C69,Articles!$A$2:$A$148,0))="","",INDEX(Articles!$E$2:$E$148,MATCH(C69,Articles!$A$2:$A$148,0))) -> 3000 | J69: =IF(I69="","",F69*I69) -> 3000 | K69: =INDEX(Articles!$H$2:$H$148,MATCH(C69,Articles!$A$2:$A$148,0)) -> Fixé | L69: =INDEX(Articles!$F$2:$F$148,MATCH(C69,Articles!$A$2:$A$148,0)) -> Estimé | M69: « Didactikos langue, maths, DDM : 1 » lu comme 1 manuel par matière | N69: Oui
A70: Parascolaire | B70: Cahier d'activités Langue et communication | C70: DID-7256 | D70: =INDEX(Articles!$C$2:$C$148,MATCH(C70,Articles!$A$2:$A$148,0)) -> Cahier d’activités fongible LC C.E.2 | E70: =INDEX(Articles!$B$2:$B$148,MATCH(C70,Articles!$A$2:$A$148,0)) -> LPD | F70: 1 | G70: =IF(INDEX(Articles!$G$2:$G$148,MATCH(C70,Articles!$A$2:$A$148,0))="","",INDEX(Articles!$G$2:$G$148,MATCH(C70,Articles!$A$2:$A$148,0))) -> 3010 | H70: =IF(G70="",0,F70*G70) -> 3010 | I70: =IF(INDEX(Articles!$E$2:$E$148,MATCH(C70,Articles!$A$2:$A$148,0))="","",INDEX(Articles!$E$2:$E$148,MATCH(C70,Articles!$A$2:$A$148,0))) -> 2010 | J70: =IF(I70="","",F70*I70) -> 2010 | K70: =INDEX(Articles!$H$2:$H$148,MATCH(C70,Articles!$A$2:$A$148,0)) -> Fixé | L70: =INDEX(Articles!$F$2:$F$148,MATCH(C70,Articles!$A$2:$A$148,0)) -> Estimé | N70: Oui
A71: Parascolaire | B71: Cahier d'activités Mathématiques | C71: DID-7241 | D71: =INDEX(Articles!$C$2:$C$148,MATCH(C71,Articles!$A$2:$A$148,0)) -> Cahier d’activités mathématiques C.E.2 | E71: =INDEX(Articles!$B$2:$B$148,MATCH(C71,Articles!$A$2:$A$148,0)) -> LPD | F71: 1 | G71: =IF(INDEX(Articles!$G$2:$G$148,MATCH(C71,Articles!$A$2:$A$148,0))="","",INDEX(Articles!$G$2:$G$148,MATCH(C71,Articles!$A$2:$A$148,0))) -> 3010 | H71: =IF(G71="",0,F71*G71) -> 3010 | I71: =IF(INDEX(Articles!$E$2:$E$148,MATCH(C71,Articles!$A$2:$A$148,0))="","",INDEX(Articles!$E$2:$E$148,MATCH(C71,Articles!$A$2:$A$148,0))) -> 2010 | J71: =IF(I71="","",F71*I71) -> 2010 | K71: =INDEX(Articles!$H$2:$H$148,MATCH(C71,Articles!$A$2:$A$148,0)) -> Fixé | L71: =INDEX(Articles!$F$2:$F$148,MATCH(C71,Articles!$A$2:$A$148,0)) -> Estimé | N71: Oui
D72: Lignes sans prix de vente (à fournir) | H72: =COUNTIF(G59:G71,"") -> 0
D73: Total vente du kit (FCFA) | H73: =SUM(H59:H71) -> 27445
D74: Coût de revient connu (FCFA) | H74: =SUM(J59:J71) -> 20030
D75: Lignes sans prix d'achat | H75: =COUNTIF(I59:I71,"") -> 3
D76: Marge sur les lignes au coût connu (FCFA) | H76: =SUMPRODUCT((I59:I71<>"")*H59:H71)-H74 -> 7140
D77: Nombre de cahiers (ligne « X cahiers » dans l'app) | H77: =SUMIF(A59:A71,"Cahiers",F59:F71) -> 4
D78: Part du prix de vente reposant sur des PV estimés | H78: =IF(H73=0,0,SUMIF(K59:K71,"<>Fixé",H59:H71)/H73) -> 0.12388413
D79: Statut du coût | H79: =IF(H72>0,"Total incomplet : "&H72&" prix de vente à fournir",IF(H75>0,"Coût incomplet : "&H75&" ligne(s) sans prix d'achat","Complet")) -> Coût incomplet : 3 ligne(s) sans prix d'achat
D80: Option décochée par défaut, non comptée : | E80: =INDEX(Articles!$C$2:$C$148,MATCH("S027",Articles!$A$2:$A$148,0)) -> Cartable rigide bleu marine | H80: =INDEX(Articles!$G$2:$G$148,MATCH("S027",Articles!$A$2:$A$148,0)) -> 7500
D81: Manquants : | E81: aucun

Sheet CM1
A1: Kit CM1
A2: Liste réelle du Complexe Dar El-Hadith. Contrôle croisé avec la liste ISJA 2026-2027 (plus chargée, écoles privées).
A4: CM1 — Essentiel
A5: Groupe (app) | B5: Besoin (liste) | C5: ID | D5: Désignation | E5: Fournisseur | F5: Qté | G5: PV unit. (FCFA) | H5: Sous-total vente | I5: PA unit. (FCFA) | J5: Sous-total achat | K5: Statut vente | L5: Statut achat | M5: Remarque | N5: Coché par défaut
A6: Cahiers | B6: Cahier 96 pages | C6: SAC-048 | D6: =INDEX(Articles!$C$2:$C$148,MATCH(C6,Articles!$A$2:$A$148,0)) -> Cahier Calligraphe 96 pages 17x22 56 g seyès | E6: =INDEX(Articles!$B$2:$B$148,MATCH(C6,Articles!$A$2:$A$148,0)) -> Papex | F6: 4 | G6: =IF(INDEX(Articles!$G$2:$G$148,MATCH(C6,Articles!$A$2:$A$148,0))="","",INDEX(Articles!$G$2:$G$148,MATCH(C6,Articles!$A$2:$A$148,0))) -> 450 | H6: =IF(G6="",0,F6*G6) -> 1800 | I6: =IF(INDEX(Articles!$E$2:$E$148,MATCH(C6,Articles!$A$2:$A$148,0))="","",INDEX(Articles!$E$2:$E$148,MATCH(C6,Articles!$A$2:$A$148,0))) -> 350 | J6: =IF(I6="","",F6*I6) -> 1400 | K6: =INDEX(Articles!$H$2:$H$148,MATCH(C6,Articles!$A$2:$A$148,0)) -> Fixé | L6: =INDEX(Articles!$F$2:$F$148,MATCH(C6,Articles!$A$2:$A$148,0)) -> Confirmé | N6: Oui
A7: Géométrie | B7: Matériel géométrique | C7: SAC-007 | D7: =INDEX(Articles!$C$2:$C$148,MATCH(C7,Articles!$A$2:$A$148,0)) -> Kit de traçage 30 cm, 4 pièces L'écolier | E7: =INDEX(Articles!$B$2:$B$148,MATCH(C7,Articles!$A$2:$A$148,0)) -> Papex | F7: 1 | G7: =IF(INDEX(Articles!$G$2:$G$148,MATCH(C7,Articles!$A$2:$A$148,0))="","",INDEX(Articles!$G$2:$G$148,MATCH(C7,Articles!$A$2:$A$148,0))) -> 900 | H7: =IF(G7="",0,F7*G7) -> 900 | I7: =IF(INDEX(Articles!$E$2:$E$148,MATCH(C7,Articles!$A$2:$A$148,0))="","",INDEX(Articles!$E$2:$E$148,MATCH(C7,Articles!$A$2:$A$148,0))) -> 650 | J7: =IF(I7="","",F7*I7) -> 650 | K7: =INDEX(Articles!$H$2:$H$148,MATCH(C7,Articles!$A$2:$A$148,0)) -> Estimé | L7: =INDEX(Articles!$F$2:$F$148,MATCH(C7,Articles!$A$2:$A$148,0)) -> Confirmé | N7: Oui
A8: Ardoise | B8: Ardoise | C8: S086 | D8: =INDEX(Articles!$C$2:$C$148,MATCH(C8,Articles!$A$2:$A$148,0)) -> Ardoise scolaire | E8: =INDEX(Articles!$B$2:$B$148,MATCH(C8,Articles!$A$2:$A$148,0)) -> LPD | F8: 1 | G8: =IF(INDEX(Articles!$G$2:$G$148,MATCH(C8,Articles!$A$2:$A$148,0))="","",INDEX(Articles!$G$2:$G$148,MATCH(C8,Articles!$A$2:$A$148,0))) -> 900 | H8: =IF(G8="",0,F8*G8) -> 900 | I8: =IF(INDEX(Articles!$E$2:$E$148,MATCH(C8,Articles!$A$2:$A$148,0))="","",INDEX(Articles!$E$2:$E$148,MATCH(C8,Articles!$A$2:$A$148,0))) -> 600 | J8: =IF(I8="","",F8*I8) -> 600 | K8: =INDEX(Articles!$H$2:$H$148,MATCH(C8,Articles!$A$2:$A$148,0)) -> Fixé | L8: =INDEX(Articles!$F$2:$F$148,MATCH(C8,Articles!$A$2:$A$148,0)) -> Estimé | N8: Oui
A9: Art & dessin | B9: Paquet de crayons de couleur | C9: SAC-019 | D9: =INDEX(Articles!$C$2:$C$148,MATCH(C9,Articles!$A$2:$A$148,0)) -> Crayons de couleur Maped, boîte de 12 | E9: =INDEX(Articles!$B$2:$B$148,MATCH(C9,Articles!$A$2:$A$148,0)) -> Papex | F9: 1 | G9: =IF(INDEX(Articles!$G$2:$G$148,MATCH(C9,Articles!$A$2:$A$148,0))="","",INDEX(Articles!$G$2:$G$148,MATCH(C9,Articles!$A$2:$A$148,0))) -> 900 | H9: =IF(G9="",0,F9*G9) -> 900 | I9: =IF(INDEX(Articles!$E$2:$E$148,MATCH(C9,Articles!$A$2:$A$148,0))="","",INDEX(Articles!$E$2:$E$148,MATCH(C9,Articles!$A$2:$A$148,0))) -> 650 | J9: =IF(I9="","",F9*I9) -> 650 | K9: =INDEX(Articles!$H$2:$H$148,MATCH(C9,Articles!$A$2:$A$148,0)) -> Estimé | L9: =INDEX(Articles!$F$2:$F$148,MATCH(C9,Articles!$A$2:$A$148,0)) -> Estimé | N9: Oui
A10: Écriture | B10: Bic bleu | C10: SAC-065 | D10: =INDEX(Articles!$C$2:$C$148,MATCH(C10,Articles!$A$2:$A$148,0)) -> Stylo à bille Schneider Tops 505 M bleu | E10: =INDEX(Articles!$B$2:$B$148,MATCH(C10,Articles!$A$2:$A$148,0)) -> Papex | F10: 1 | G10: =IF(INDEX(Articles!$G$2:$G$148,MATCH(C10,Articles!$A$2:$A$148,0))="","",INDEX(Articles!$G$2:$G$148,MATCH(C10,Articles!$A$2:$A$148,0))) -> 100 | H10: =IF(G10="",0,F10*G10) -> 100 | I10: =IF(INDEX(Articles!$E$2:$E$148,MATCH(C10,Articles!$A$2:$A$148,0))="","",INDEX(Articles!$E$2:$E$148,MATCH(C10,Articles!$A$2:$A$148,0))) | J10: =IF(I10="","",F10*I10) | K10: =INDEX(Articles!$H$2:$H$148,MATCH(C10,Articles!$A$2:$A$148,0)) -> Fixé | L10: =INDEX(Articles!$F$2:$F$148,MATCH(C10,Articles!$A$2:$A$148,0)) -> Inconnu | N10: Oui
A11: Écriture | B11: Bic vert | C11: SAC-104 | D11: =INDEX(Articles!$C$2:$C$148,MATCH(C11,Articles!$A$2:$A$148,0)) -> Stylo à bille Schneider Tops 505 M vert | E11: =INDEX(Articles!$B$2:$B$148,MATCH(C11,Articles!$A$2:$A$148,0)) -> Papex | F11: 1 | G11: =IF(INDEX(Articles!$G$2:$G$148,MATCH(C11,Articles!$A$2:$A$148,0))="","",INDEX(Articles!$G$2:$G$148,MATCH(C11,Articles!$A$2:$A$148,0))) -> 100 | H11: =IF(G11="",0,F11*G11) -> 100 | I11: =IF(INDEX(Articles!$E$2:$E$148,MATCH(C11,Articles!$A$2:$A$148,0))="","",INDEX(Articles!$E$2:$E$148,MATCH(C11,Articles!$A$2:$A$148,0))) | J11: =IF(I11="","",F11*I11) | K11: =INDEX(Articles!$H$2:$H$148,MATCH(C11,Articles!$A$2:$A$148,0)) -> Fixé | L11: =INDEX(Articles!$F$2:$F$148,MATCH(C11,Articles!$A$2:$A$148,0)) -> Inconnu | N11: Oui
A12: Écriture | B12: Crayon noir | C12: S065 | D12: =INDEX(Articles!$C$2:$C$148,MATCH(C12,Articles!$A$2:$A$148,0)) -> Crayon papier (vendu à l'unité) | E12: =INDEX(Articles!$B$2:$B$148,MATCH(C12,Articles!$A$2:$A$148,0)) -> LPD | F12: 1 | G12: =IF(INDEX(Articles!$G$2:$G$148,MATCH(C12,Articles!$A$2:$A$148,0))="","",INDEX(Articles!$G$2:$G$148,MATCH(C12,Articles!$A$2:$A$148,0))) -> 75 | H12: =IF(G12="",0,F12*G12) -> 75 | I12: =IF(INDEX(Articles!$E$2:$E$148,MATCH(C12,Articles!$A$2:$A$148,0))="","",INDEX(Articles!$E$2:$E$148,MATCH(C12,Articles!$A$2:$A$148,0))) | J12: =IF(I12="","",F12*I12) | K12: =INDEX(Articles!$H$2:$H$148,MATCH(C12,Articles!$A$2:$A$148,0)) -> Fixé | L12: =INDEX(Articles!$F$2:$F$148,MATCH(C12,Articles!$A$2:$A$148,0)) -> Inconnu | N12: Oui
A13: Petit matériel | B13: Gomme | C13: S009 | D13: =INDEX(Articles!$C$2:$C$148,MATCH(C13,Articles!$A$2:$A$148,0)) -> Gomme Staedtler Mars Plastic | E13: =INDEX(Articles!$B$2:$B$148,MATCH(C13,Articles!$A$2:$A$148,0)) -> LPD | F13: 1 | G13: =IF(INDEX(Articles!$G$2:$G$148,MATCH(C13,Articles!$A$2:$A$148,0))="","",INDEX(Articles!$G$2:$G$148,MATCH(C13,Articles!$A$2:$A$148,0))) -> 250 | H13: =IF(G13="",0,F13*G13) -> 250 | I13: =IF(INDEX(Articles!$E$2:$E$148,MATCH(C13,Articles!$A$2:$A$148,0))="","",INDEX(Articles!$E$2:$E$148,MATCH(C13,Articles!$A$2:$A$148,0))) -> 110 | J13: =IF(I13="","",F13*I13) -> 110 | K13: =INDEX(Articles!$H$2:$H$148,MATCH(C13,Articles!$A$2:$A$148,0)) -> Fixé | L13: =INDEX(Articles!$F$2:$F$148,MATCH(C13,Articles!$A$2:$A$148,0)) -> Estimé | N13: Oui
D14: Lignes sans prix de vente (à fournir) | H14: =COUNTIF(G6:G13,"") -> 0
D15: Total vente du kit (FCFA) | H15: =SUM(H6:H13) -> 5025
D16: Coût de revient connu (FCFA) | H16: =SUM(J6:J13) -> 3410
D17: Lignes sans prix d'achat | H17: =COUNTIF(I6:I13,"") -> 3
D18: Marge sur les lignes au coût connu (FCFA) | H18: =SUMPRODUCT((I6:I13<>"")*H6:H13)-H16 -> 1340
D19: Nombre de cahiers (ligne « X cahiers » dans l'app) | H19: =SUMIF(A6:A13,"Cahiers",F6:F13) -> 4
D20: Part du prix de vente reposant sur des PV estimés | H20: =IF(H15=0,0,SUMIF(K6:K13,"<>Fixé",H6:H13)/H15) -> 0.35820896
D21: Statut du coût | H21: =IF(H14>0,"Total incomplet : "&H14&" prix de vente à fournir",IF(H17>0,"Coût incomplet : "&H17&" ligne(s) sans prix d'achat","Complet")) -> Coût incomplet : 3 ligne(s) sans prix d'achat
D23: Proposés décochés : livres du Complet (non comptés, cochables par le client)
A24: Manuels au programme | B24: Didactikos Langue et communication | C24: DID-6924 | D24: =INDEX(Articles!$C$2:$C$148,MATCH(C24,Articles!$A$2:$A$148,0)) -> Langue et communication C.M.1 | G24: =INDEX(Articles!$G$2:$G$148,MATCH(C24,Articles!$A$2:$A$148,0)) -> 4000 | N24: Non
A25: Manuels au programme | B25: Didactikos Mathématiques | C25: DID-6945 | D25: =INDEX(Articles!$C$2:$C$148,MATCH(C25,Articles!$A$2:$A$148,0)) -> Mathématiques C.M.1 | G25: =INDEX(Articles!$G$2:$G$148,MATCH(C25,Articles!$A$2:$A$148,0)) -> 4000 | N25: Non
A26: Manuels au programme | B26: Didactikos Découverte du monde | C26: DID-6958 | D26: =INDEX(Articles!$C$2:$C$148,MATCH(C26,Articles!$A$2:$A$148,0)) -> Découverte du monde C.M.1 | G26: =INDEX(Articles!$G$2:$G$148,MATCH(C26,Articles!$A$2:$A$148,0)) -> 4000 | N26: Non
D27: Total si tous les livres sont cochés (FCFA) | H27: =H15+SUM(G24:G26) -> 17025
D28: Option décochée par défaut, non comptée : | E28: =INDEX(Articles!$C$2:$C$148,MATCH("S027",Articles!$A$2:$A$148,0)) -> Cartable rigide bleu marine | H28: =INDEX(Articles!$G$2:$G$148,MATCH("S027",Articles!$A$2:$A$148,0)) -> 7500
D29: Manquants : | E29: aucun
A32: CM1 — Complet
A33: Groupe (app) | B33: Besoin (liste) | C33: ID | D33: Désignation | E33: Fournisseur | F33: Qté | G33: PV unit. (FCFA) | H33: Sous-total vente | I33: PA unit. (FCFA) | J33: Sous-total achat | K33: Statut vente | L33: Statut achat | M33: Remarque | N33: Coché par défaut
A34: Cahiers | B34: Cahier 96 pages | C34: SAC-033 | D34: =INDEX(Articles!$C$2:$C$148,MATCH(C34,Articles!$A$2:$A$148,0)) -> Cahier Calligraphe 140 pages 17x22 90 g seyès | E34: =INDEX(Articles!$B$2:$B$148,MATCH(C34,Articles!$A$2:$A$148,0)) -> Papex | F34: 4 | G34: =IF(INDEX(Articles!$G$2:$G$148,MATCH(C34,Articles!$A$2:$A$148,0))="","",INDEX(Articles!$G$2:$G$148,MATCH(C34,Articles!$A$2:$A$148,0))) -> 750 | H34: =IF(G34="",0,F34*G34) -> 3000 | I34: =IF(INDEX(Articles!$E$2:$E$148,MATCH(C34,Articles!$A$2:$A$148,0))="","",INDEX(Articles!$E$2:$E$148,MATCH(C34,Articles!$A$2:$A$148,0))) -> 650 | J34: =IF(I34="","",F34*I34) -> 2600 | K34: =INDEX(Articles!$H$2:$H$148,MATCH(C34,Articles!$A$2:$A$148,0)) -> Fixé | L34: =INDEX(Articles!$F$2:$F$148,MATCH(C34,Articles!$A$2:$A$148,0)) -> Estimé | M34: 140 p Calligraphe 90 g | N34: Oui
A35: Géométrie | B35: Matériel géométrique | C35: S091 | D35: =INDEX(Articles!$C$2:$C$148,MATCH(C35,Articles!$A$2:$A$148,0)) -> Kit géométrie Maped 30 cm (réf. 1930) | E35: =INDEX(Articles!$B$2:$B$148,MATCH(C35,Articles!$A$2:$A$148,0)) -> LPD | F35: 1 | G35: =IF(INDEX(Articles!$G$2:$G$148,MATCH(C35,Articles!$A$2:$A$148,0))="","",INDEX(Articles!$G$2:$G$148,MATCH(C35,Articles!$A$2:$A$148,0))) -> 1800 | H35: =IF(G35="",0,F35*G35) -> 1800 | I35: =IF(INDEX(Articles!$E$2:$E$148,MATCH(C35,Articles!$A$2:$A$148,0))="","",INDEX(Articles!$E$2:$E$148,MATCH(C35,Articles!$A$2:$A$148,0))) -> 1500 | J35: =IF(I35="","",F35*I35) -> 1500 | K35: =INDEX(Articles!$H$2:$H$148,MATCH(C35,Articles!$A$2:$A$148,0)) -> À trancher | L35: =INDEX(Articles!$F$2:$F$148,MATCH(C35,Articles!$A$2:$A$148,0)) -> Confirmé | N35: Oui
A36: Ardoise | B36: Ardoise | C36: CIS-ardoise | D36: =INDEX(Articles!$C$2:$C$148,MATCH(C36,Articles!$A$2:$A$148,0)) -> Ardoise quadrillée avec poignée | E36: =INDEX(Articles!$B$2:$B$148,MATCH(C36,Articles!$A$2:$A$148,0)) -> Cissé & Frères | F36: 1 | G36: =IF(INDEX(Articles!$G$2:$G$148,MATCH(C36,Articles!$A$2:$A$148,0))="","",INDEX(Articles!$G$2:$G$148,MATCH(C36,Articles!$A$2:$A$148,0))) -> 2500 | H36: =IF(G36="",0,F36*G36) -> 2500 | I36: =IF(INDEX(Articles!$E$2:$E$148,MATCH(C36,Articles!$A$2:$A$148,0))="","",INDEX(Articles!$E$2:$E$148,MATCH(C36,Articles!$A$2:$A$148,0))) -> 1500 | J36: =IF(I36="","",F36*I36) -> 1500 | K36: =INDEX(Articles!$H$2:$H$148,MATCH(C36,Articles!$A$2:$A$148,0)) -> Fixé | L36: =INDEX(Articles!$F$2:$F$148,MATCH(C36,Articles!$A$2:$A$148,0)) -> Confirmé | N36: Oui
A37: Art & dessin | B37: Paquet de crayons de couleur | C37: SAC-024 | D37: =INDEX(Articles!$C$2:$C$148,MATCH(C37,Articles!$A$2:$A$148,0)) -> Crayons de couleur Maped Nightfall, boîte de 24 | E37: =INDEX(Articles!$B$2:$B$148,MATCH(C37,Articles!$A$2:$A$148,0)) -> Papex | F37: 1 | G37: =IF(INDEX(Articles!$G$2:$G$148,MATCH(C37,Articles!$A$2:$A$148,0))="","",INDEX(Articles!$G$2:$G$148,MATCH(C37,Articles!$A$2:$A$148,0))) -> 1600 | H37: =IF(G37="",0,F37*G37) -> 1600 | I37: =IF(INDEX(Articles!$E$2:$E$148,MATCH(C37,Articles!$A$2:$A$148,0))="","",INDEX(Articles!$E$2:$E$148,MATCH(C37,Articles!$A$2:$A$148,0))) -> 1300 | J37: =IF(I37="","",F37*I37) -> 1300 | K37: =INDEX(Articles!$H$2:$H$148,MATCH(C37,Articles!$A$2:$A$148,0)) -> Estimé | L37: =INDEX(Articles!$F$2:$F$148,MATCH(C37,Articles!$A$2:$A$148,0)) -> Estimé | N37: Oui
A38: Écriture | B38: Bic bleu | C38: SAC-065 | D38: =INDEX(Articles!$C$2:$C$148,MATCH(C38,Articles!$A$2:$A$148,0)) -> Stylo à bille Schneider Tops 505 M bleu | E38: =INDEX(Articles!$B$2:$B$148,MATCH(C38,Articles!$A$2:$A$148,0)) -> Papex | F38: 1 | G38: =IF(INDEX(Articles!$G$2:$G$148,MATCH(C38,Articles!$A$2:$A$148,0))="","",INDEX(Articles!$G$2:$G$148,MATCH(C38,Articles!$A$2:$A$148,0))) -> 100 | H38: =IF(G38="",0,F38*G38) -> 100 | I38: =IF(INDEX(Articles!$E$2:$E$148,MATCH(C38,Articles!$A$2:$A$148,0))="","",INDEX(Articles!$E$2:$E$148,MATCH(C38,Articles!$A$2:$A$148,0))) | J38: =IF(I38="","",F38*I38) | K38: =INDEX(Articles!$H$2:$H$148,MATCH(C38,Articles!$A$2:$A$148,0)) -> Fixé | L38: =INDEX(Articles!$F$2:$F$148,MATCH(C38,Articles!$A$2:$A$148,0)) -> Inconnu | N38: Oui
A39: Écriture | B39: Bic vert | C39: SAC-104 | D39: =INDEX(Articles!$C$2:$C$148,MATCH(C39,Articles!$A$2:$A$148,0)) -> Stylo à bille Schneider Tops 505 M vert | E39: =INDEX(Articles!$B$2:$B$148,MATCH(C39,Articles!$A$2:$A$148,0)) -> Papex | F39: 1 | G39: =IF(INDEX(Articles!$G$2:$G$148,MATCH(C39,Articles!$A$2:$A$148,0))="","",INDEX(Articles!$G$2:$G$148,MATCH(C39,Articles!$A$2:$A$148,0))) -> 100 | H39: =IF(G39="",0,F39*G39) -> 100 | I39: =IF(INDEX(Articles!$E$2:$E$148,MATCH(C39,Articles!$A$2:$A$148,0))="","",INDEX(Articles!$E$2:$E$148,MATCH(C39,Articles!$A$2:$A$148,0))) | J39: =IF(I39="","",F39*I39) | K39: =INDEX(Articles!$H$2:$H$148,MATCH(C39,Articles!$A$2:$A$148,0)) -> Fixé | L39: =INDEX(Articles!$F$2:$F$148,MATCH(C39,Articles!$A$2:$A$148,0)) -> Inconnu | N39: Oui
A40: Écriture | B40: Crayon noir | C40: S065 | D40: =INDEX(Articles!$C$2:$C$148,MATCH(C40,Articles!$A$2:$A$148,0)) -> Crayon papier (vendu à l'unité) | E40: =INDEX(Articles!$B$2:$B$148,MATCH(C40,Articles!$A$2:$A$148,0)) -> LPD | F40: 1 | G40: =IF(INDEX(Articles!$G$2:$G$148,MATCH(C40,Articles!$A$2:$A$148,0))="","",INDEX(Articles!$G$2:$G$148,MATCH(C40,Articles!$A$2:$A$148,0))) -> 75 | H40: =IF(G40="",0,F40*G40) -> 75 | I40: =IF(INDEX(Articles!$E$2:$E$148,MATCH(C40,Articles!$A$2:$A$148,0))="","",INDEX(Articles!$E$2:$E$148,MATCH(C40,Articles!$A$2:$A$148,0))) | J40: =IF(I40="","",F40*I40) | K40: =INDEX(Articles!$H$2:$H$148,MATCH(C40,Articles!$A$2:$A$148,0)) -> Fixé | L40: =INDEX(Articles!$F$2:$F$148,MATCH(C40,Articles!$A$2:$A$148,0)) -> Inconnu | N40: Oui
A41: Petit matériel | B41: Gomme | C41: S009 | D41: =INDEX(Articles!$C$2:$C$148,MATCH(C41,Articles!$A$2:$A$148,0)) -> Gomme Staedtler Mars Plastic | E41: =INDEX(Articles!$B$2:$B$148,MATCH(C41,Articles!$A$2:$A$148,0)) -> LPD | F41: 1 | G41: =IF(INDEX(Articles!$G$2:$G$148,MATCH(C41,Articles!$A$2:$A$148,0))="","",INDEX(Articles!$G$2:$G$148,MATCH(C41,Articles!$A$2:$A$148,0))) -> 250 | H41: =IF(G41="",0,F41*G41) -> 250 | I41: =IF(INDEX(Articles!$E$2:$E$148,MATCH(C41,Articles!$A$2:$A$148,0))="","",INDEX(Articles!$E$2:$E$148,MATCH(C41,Articles!$A$2:$A$148,0))) -> 110 | J41: =IF(I41="","",F41*I41) -> 110 | K41: =INDEX(Articles!$H$2:$H$148,MATCH(C41,Articles!$A$2:$A$148,0)) -> Fixé | L41: =INDEX(Articles!$F$2:$F$148,MATCH(C41,Articles!$A$2:$A$148,0)) -> Estimé | N41: Oui
A42: Manuels au programme | B42: Didactikos Langue et communication | C42: DID-6924 | D42: =INDEX(Articles!$C$2:$C$148,MATCH(C42,Articles!$A$2:$A$148,0)) -> Langue et communication C.M.1 | E42: =INDEX(Articles!$B$2:$B$148,MATCH(C42,Articles!$A$2:$A$148,0)) -> LPD | F42: 1 | G42: =IF(INDEX(Articles!$G$2:$G$148,MATCH(C42,Articles!$A$2:$A$148,0))="","",INDEX(Articles!$G$2:$G$148,MATCH(C42,Articles!$A$2:$A$148,0))) -> 4000 | H42: =IF(G42="",0,F42*G42) -> 4000 | I42: =IF(INDEX(Articles!$E$2:$E$148,MATCH(C42,Articles!$A$2:$A$148,0))="","",INDEX(Articles!$E$2:$E$148,MATCH(C42,Articles!$A$2:$A$148,0))) -> 3000 | J42: =IF(I42="","",F42*I42) -> 3000 | K42: =INDEX(Articles!$H$2:$H$148,MATCH(C42,Articles!$A$2:$A$148,0)) -> Fixé | L42: =INDEX(Articles!$F$2:$F$148,MATCH(C42,Articles!$A$2:$A$148,0)) -> Estimé | M42: « Didactikos langue, maths, DDM : 1 » lu comme 1 manuel par matière | N42: Oui
A43: Manuels au programme | B43: Didactikos Mathématiques | C43: DID-6945 | D43: =INDEX(Articles!$C$2:$C$148,MATCH(C43,Articles!$A$2:$A$148,0)) -> Mathématiques C.M.1 | E43: =INDEX(Articles!$B$2:$B$148,MATCH(C43,Articles!$A$2:$A$148,0)) -> LPD | F43: 1 | G43: =IF(INDEX(Articles!$G$2:$G$148,MATCH(C43,Articles!$A$2:$A$148,0))="","",INDEX(Articles!$G$2:$G$148,MATCH(C43,Articles!$A$2:$A$148,0))) -> 4000 | H43: =IF(G43="",0,F43*G43) -> 4000 | I43: =IF(INDEX(Articles!$E$2:$E$148,MATCH(C43,Articles!$A$2:$A$148,0))="","",INDEX(Articles!$E$2:$E$148,MATCH(C43,Articles!$A$2:$A$148,0))) -> 3000 | J43: =IF(I43="","",F43*I43) -> 3000 | K43: =INDEX(Articles!$H$2:$H$148,MATCH(C43,Articles!$A$2:$A$148,0)) -> Fixé | L43: =INDEX(Articles!$F$2:$F$148,MATCH(C43,Articles!$A$2:$A$148,0)) -> Estimé | M43: « Didactikos langue, maths, DDM : 1 » lu comme 1 manuel par matière | N43: Oui
A44: Manuels au programme | B44: Didactikos Découverte du monde | C44: DID-6958 | D44: =INDEX(Articles!$C$2:$C$148,MATCH(C44,Articles!$A$2:$A$148,0)) -> Découverte du monde C.M.1 | E44: =INDEX(Articles!$B$2:$B$148,MATCH(C44,Articles!$A$2:$A$148,0)) -> LPD | F44: 1 | G44: =IF(INDEX(Articles!$G$2:$G$148,MATCH(C44,Articles!$A$2:$A$148,0))="","",INDEX(Articles!$G$2:$G$148,MATCH(C44,Articles!$A$2:$A$148,0))) -> 4000 | H44: =IF(G44="",0,F44*G44) -> 4000 | I44: =IF(INDEX(Articles!$E$2:$E$148,MATCH(C44,Articles!$A$2:$A$148,0))="","",INDEX(Articles!$E$2:$E$148,MATCH(C44,Articles!$A$2:$A$148,0))) -> 3000 | J44: =IF(I44="","",F44*I44) -> 3000 | K44: =INDEX(Articles!$H$2:$H$148,MATCH(C44,Articles!$A$2:$A$148,0)) -> Fixé | L44: =INDEX(Articles!$F$2:$F$148,MATCH(C44,Articles!$A$2:$A$148,0)) -> Estimé | M44: « Didactikos langue, maths, DDM : 1 » lu comme 1 manuel par matière | N44: Oui
D45: Lignes sans prix de vente (à fournir) | H45: =COUNTIF(G34:G44,"") -> 0
D46: Total vente du kit (FCFA) | H46: =SUM(H34:H44) -> 21425
D47: Coût de revient connu (FCFA) | H47: =SUM(J34:J44) -> 16010
D48: Lignes sans prix d'achat | H48: =COUNTIF(I34:I44,"") -> 3
D49: Marge sur les lignes au coût connu (FCFA) | H49: =SUMPRODUCT((I34:I44<>"")*H34:H44)-H47 -> 5140
D50: Nombre de cahiers (ligne « X cahiers » dans l'app) | H50: =SUMIF(A34:A44,"Cahiers",F34:F44) -> 4
D51: Part du prix de vente reposant sur des PV estimés | H51: =IF(H46=0,0,SUMIF(K34:K44,"<>Fixé",H34:H44)/H46) -> 0.15869312
D52: Statut du coût | H52: =IF(H45>0,"Total incomplet : "&H45&" prix de vente à fournir",IF(H48>0,"Coût incomplet : "&H48&" ligne(s) sans prix d'achat","Complet")) -> Coût incomplet : 3 ligne(s) sans prix d'achat
D53: Option décochée par défaut, non comptée : | E53: =INDEX(Articles!$C$2:$C$148,MATCH("S027",Articles!$A$2:$A$148,0)) -> Cartable rigide bleu marine | H53: =INDEX(Articles!$G$2:$G$148,MATCH("S027",Articles!$A$2:$A$148,0)) -> 7500
D54: Manquants : | E54: aucun
A57: CM1 — Confort
A58: Groupe (app) | B58: Besoin (liste) | C58: ID | D58: Désignation | E58: Fournisseur | F58: Qté | G58: PV unit. (FCFA) | H58: Sous-total vente | I58: PA unit. (FCFA) | J58: Sous-total achat | K58: Statut vente | L58: Statut achat | M58: Remarque | N58: Coché par défaut
A59: Cahiers | B59: Cahier 96 pages | C59: SAC-033 | D59: =INDEX(Articles!$C$2:$C$148,MATCH(C59,Articles!$A$2:$A$148,0)) -> Cahier Calligraphe 140 pages 17x22 90 g seyès | E59: =INDEX(Articles!$B$2:$B$148,MATCH(C59,Articles!$A$2:$A$148,0)) -> Papex | F59: 4 | G59: =IF(INDEX(Articles!$G$2:$G$148,MATCH(C59,Articles!$A$2:$A$148,0))="","",INDEX(Articles!$G$2:$G$148,MATCH(C59,Articles!$A$2:$A$148,0))) -> 750 | H59: =IF(G59="",0,F59*G59) -> 3000 | I59: =IF(INDEX(Articles!$E$2:$E$148,MATCH(C59,Articles!$A$2:$A$148,0))="","",INDEX(Articles!$E$2:$E$148,MATCH(C59,Articles!$A$2:$A$148,0))) -> 650 | J59: =IF(I59="","",F59*I59) -> 2600 | K59: =INDEX(Articles!$H$2:$H$148,MATCH(C59,Articles!$A$2:$A$148,0)) -> Fixé | L59: =INDEX(Articles!$F$2:$F$148,MATCH(C59,Articles!$A$2:$A$148,0)) -> Estimé | M59: 140 p Calligraphe 90 g | N59: Oui
A60: Géométrie | B60: Matériel géométrique | C60: S091 | D60: =INDEX(Articles!$C$2:$C$148,MATCH(C60,Articles!$A$2:$A$148,0)) -> Kit géométrie Maped 30 cm (réf. 1930) | E60: =INDEX(Articles!$B$2:$B$148,MATCH(C60,Articles!$A$2:$A$148,0)) -> LPD | F60: 1 | G60: =IF(INDEX(Articles!$G$2:$G$148,MATCH(C60,Articles!$A$2:$A$148,0))="","",INDEX(Articles!$G$2:$G$148,MATCH(C60,Articles!$A$2:$A$148,0))) -> 1800 | H60: =IF(G60="",0,F60*G60) -> 1800 | I60: =IF(INDEX(Articles!$E$2:$E$148,MATCH(C60,Articles!$A$2:$A$148,0))="","",INDEX(Articles!$E$2:$E$148,MATCH(C60,Articles!$A$2:$A$148,0))) -> 1500 | J60: =IF(I60="","",F60*I60) -> 1500 | K60: =INDEX(Articles!$H$2:$H$148,MATCH(C60,Articles!$A$2:$A$148,0)) -> À trancher | L60: =INDEX(Articles!$F$2:$F$148,MATCH(C60,Articles!$A$2:$A$148,0)) -> Confirmé | N60: Oui
A61: Ardoise | B61: Ardoise | C61: CIS-ardoise | D61: =INDEX(Articles!$C$2:$C$148,MATCH(C61,Articles!$A$2:$A$148,0)) -> Ardoise quadrillée avec poignée | E61: =INDEX(Articles!$B$2:$B$148,MATCH(C61,Articles!$A$2:$A$148,0)) -> Cissé & Frères | F61: 1 | G61: =IF(INDEX(Articles!$G$2:$G$148,MATCH(C61,Articles!$A$2:$A$148,0))="","",INDEX(Articles!$G$2:$G$148,MATCH(C61,Articles!$A$2:$A$148,0))) -> 2500 | H61: =IF(G61="",0,F61*G61) -> 2500 | I61: =IF(INDEX(Articles!$E$2:$E$148,MATCH(C61,Articles!$A$2:$A$148,0))="","",INDEX(Articles!$E$2:$E$148,MATCH(C61,Articles!$A$2:$A$148,0))) -> 1500 | J61: =IF(I61="","",F61*I61) -> 1500 | K61: =INDEX(Articles!$H$2:$H$148,MATCH(C61,Articles!$A$2:$A$148,0)) -> Fixé | L61: =INDEX(Articles!$F$2:$F$148,MATCH(C61,Articles!$A$2:$A$148,0)) -> Confirmé | N61: Oui
A62: Art & dessin | B62: Paquet de crayons de couleur | C62: SAC-024 | D62: =INDEX(Articles!$C$2:$C$148,MATCH(C62,Articles!$A$2:$A$148,0)) -> Crayons de couleur Maped Nightfall, boîte de 24 | E62: =INDEX(Articles!$B$2:$B$148,MATCH(C62,Articles!$A$2:$A$148,0)) -> Papex | F62: 1 | G62: =IF(INDEX(Articles!$G$2:$G$148,MATCH(C62,Articles!$A$2:$A$148,0))="","",INDEX(Articles!$G$2:$G$148,MATCH(C62,Articles!$A$2:$A$148,0))) -> 1600 | H62: =IF(G62="",0,F62*G62) -> 1600 | I62: =IF(INDEX(Articles!$E$2:$E$148,MATCH(C62,Articles!$A$2:$A$148,0))="","",INDEX(Articles!$E$2:$E$148,MATCH(C62,Articles!$A$2:$A$148,0))) -> 1300 | J62: =IF(I62="","",F62*I62) -> 1300 | K62: =INDEX(Articles!$H$2:$H$148,MATCH(C62,Articles!$A$2:$A$148,0)) -> Estimé | L62: =INDEX(Articles!$F$2:$F$148,MATCH(C62,Articles!$A$2:$A$148,0)) -> Estimé | N62: Oui
A63: Écriture | B63: Bic bleu | C63: SAC-065 | D63: =INDEX(Articles!$C$2:$C$148,MATCH(C63,Articles!$A$2:$A$148,0)) -> Stylo à bille Schneider Tops 505 M bleu | E63: =INDEX(Articles!$B$2:$B$148,MATCH(C63,Articles!$A$2:$A$148,0)) -> Papex | F63: 1 | G63: =IF(INDEX(Articles!$G$2:$G$148,MATCH(C63,Articles!$A$2:$A$148,0))="","",INDEX(Articles!$G$2:$G$148,MATCH(C63,Articles!$A$2:$A$148,0))) -> 100 | H63: =IF(G63="",0,F63*G63) -> 100 | I63: =IF(INDEX(Articles!$E$2:$E$148,MATCH(C63,Articles!$A$2:$A$148,0))="","",INDEX(Articles!$E$2:$E$148,MATCH(C63,Articles!$A$2:$A$148,0))) | J63: =IF(I63="","",F63*I63) | K63: =INDEX(Articles!$H$2:$H$148,MATCH(C63,Articles!$A$2:$A$148,0)) -> Fixé | L63: =INDEX(Articles!$F$2:$F$148,MATCH(C63,Articles!$A$2:$A$148,0)) -> Inconnu | N63: Oui
A64: Écriture | B64: Bic vert | C64: SAC-104 | D64: =INDEX(Articles!$C$2:$C$148,MATCH(C64,Articles!$A$2:$A$148,0)) -> Stylo à bille Schneider Tops 505 M vert | E64: =INDEX(Articles!$B$2:$B$148,MATCH(C64,Articles!$A$2:$A$148,0)) -> Papex | F64: 1 | G64: =IF(INDEX(Articles!$G$2:$G$148,MATCH(C64,Articles!$A$2:$A$148,0))="","",INDEX(Articles!$G$2:$G$148,MATCH(C64,Articles!$A$2:$A$148,0))) -> 100 | H64: =IF(G64="",0,F64*G64) -> 100 | I64: =IF(INDEX(Articles!$E$2:$E$148,MATCH(C64,Articles!$A$2:$A$148,0))="","",INDEX(Articles!$E$2:$E$148,MATCH(C64,Articles!$A$2:$A$148,0))) | J64: =IF(I64="","",F64*I64) | K64: =INDEX(Articles!$H$2:$H$148,MATCH(C64,Articles!$A$2:$A$148,0)) -> Fixé | L64: =INDEX(Articles!$F$2:$F$148,MATCH(C64,Articles!$A$2:$A$148,0)) -> Inconnu | N64: Oui
A65: Écriture | B65: Crayon noir | C65: S065 | D65: =INDEX(Articles!$C$2:$C$148,MATCH(C65,Articles!$A$2:$A$148,0)) -> Crayon papier (vendu à l'unité) | E65: =INDEX(Articles!$B$2:$B$148,MATCH(C65,Articles!$A$2:$A$148,0)) -> LPD | F65: 1 | G65: =IF(INDEX(Articles!$G$2:$G$148,MATCH(C65,Articles!$A$2:$A$148,0))="","",INDEX(Articles!$G$2:$G$148,MATCH(C65,Articles!$A$2:$A$148,0))) -> 75 | H65: =IF(G65="",0,F65*G65) -> 75 | I65: =IF(INDEX(Articles!$E$2:$E$148,MATCH(C65,Articles!$A$2:$A$148,0))="","",INDEX(Articles!$E$2:$E$148,MATCH(C65,Articles!$A$2:$A$148,0))) | J65: =IF(I65="","",F65*I65) | K65: =INDEX(Articles!$H$2:$H$148,MATCH(C65,Articles!$A$2:$A$148,0)) -> Fixé | L65: =INDEX(Articles!$F$2:$F$148,MATCH(C65,Articles!$A$2:$A$148,0)) -> Inconnu | N65: Oui
A66: Petit matériel | B66: Gomme | C66: S009 | D66: =INDEX(Articles!$C$2:$C$148,MATCH(C66,Articles!$A$2:$A$148,0)) -> Gomme Staedtler Mars Plastic | E66: =INDEX(Articles!$B$2:$B$148,MATCH(C66,Articles!$A$2:$A$148,0)) -> LPD | F66: 1 | G66: =IF(INDEX(Articles!$G$2:$G$148,MATCH(C66,Articles!$A$2:$A$148,0))="","",INDEX(Articles!$G$2:$G$148,MATCH(C66,Articles!$A$2:$A$148,0))) -> 250 | H66: =IF(G66="",0,F66*G66) -> 250 | I66: =IF(INDEX(Articles!$E$2:$E$148,MATCH(C66,Articles!$A$2:$A$148,0))="","",INDEX(Articles!$E$2:$E$148,MATCH(C66,Articles!$A$2:$A$148,0))) -> 110 | J66: =IF(I66="","",F66*I66) -> 110 | K66: =INDEX(Articles!$H$2:$H$148,MATCH(C66,Articles!$A$2:$A$148,0)) -> Fixé | L66: =INDEX(Articles!$F$2:$F$148,MATCH(C66,Articles!$A$2:$A$148,0)) -> Estimé | N66: Oui
A67: Manuels au programme | B67: Didactikos Langue et communication | C67: DID-6924 | D67: =INDEX(Articles!$C$2:$C$148,MATCH(C67,Articles!$A$2:$A$148,0)) -> Langue et communication C.M.1 | E67: =INDEX(Articles!$B$2:$B$148,MATCH(C67,Articles!$A$2:$A$148,0)) -> LPD | F67: 1 | G67: =IF(INDEX(Articles!$G$2:$G$148,MATCH(C67,Articles!$A$2:$A$148,0))="","",INDEX(Articles!$G$2:$G$148,MATCH(C67,Articles!$A$2:$A$148,0))) -> 4000 | H67: =IF(G67="",0,F67*G67) -> 4000 | I67: =IF(INDEX(Articles!$E$2:$E$148,MATCH(C67,Articles!$A$2:$A$148,0))="","",INDEX(Articles!$E$2:$E$148,MATCH(C67,Articles!$A$2:$A$148,0))) -> 3000 | J67: =IF(I67="","",F67*I67) -> 3000 | K67: =INDEX(Articles!$H$2:$H$148,MATCH(C67,Articles!$A$2:$A$148,0)) -> Fixé | L67: =INDEX(Articles!$F$2:$F$148,MATCH(C67,Articles!$A$2:$A$148,0)) -> Estimé | M67: « Didactikos langue, maths, DDM : 1 » lu comme 1 manuel par matière | N67: Oui
A68: Manuels au programme | B68: Didactikos Mathématiques | C68: DID-6945 | D68: =INDEX(Articles!$C$2:$C$148,MATCH(C68,Articles!$A$2:$A$148,0)) -> Mathématiques C.M.1 | E68: =INDEX(Articles!$B$2:$B$148,MATCH(C68,Articles!$A$2:$A$148,0)) -> LPD | F68: 1 | G68: =IF(INDEX(Articles!$G$2:$G$148,MATCH(C68,Articles!$A$2:$A$148,0))="","",INDEX(Articles!$G$2:$G$148,MATCH(C68,Articles!$A$2:$A$148,0))) -> 4000 | H68: =IF(G68="",0,F68*G68) -> 4000 | I68: =IF(INDEX(Articles!$E$2:$E$148,MATCH(C68,Articles!$A$2:$A$148,0))="","",INDEX(Articles!$E$2:$E$148,MATCH(C68,Articles!$A$2:$A$148,0))) -> 3000 | J68: =IF(I68="","",F68*I68) -> 3000 | K68: =INDEX(Articles!$H$2:$H$148,MATCH(C68,Articles!$A$2:$A$148,0)) -> Fixé | L68: =INDEX(Articles!$F$2:$F$148,MATCH(C68,Articles!$A$2:$A$148,0)) -> Estimé | M68: « Didactikos langue, maths, DDM : 1 » lu comme 1 manuel par matière | N68: Oui
A69: Manuels au programme | B69: Didactikos Découverte du monde | C69: DID-6958 | D69: =INDEX(Articles!$C$2:$C$148,MATCH(C69,Articles!$A$2:$A$148,0)) -> Découverte du monde C.M.1 | E69: =INDEX(Articles!$B$2:$B$148,MATCH(C69,Articles!$A$2:$A$148,0)) -> LPD | F69: 1 | G69: =IF(INDEX(Articles!$G$2:$G$148,MATCH(C69,Articles!$A$2:$A$148,0))="","",INDEX(Articles!$G$2:$G$148,MATCH(C69,Articles!$A$2:$A$148,0))) -> 4000 | H69: =IF(G69="",0,F69*G69) -> 4000 | I69: =IF(INDEX(Articles!$E$2:$E$148,MATCH(C69,Articles!$A$2:$A$148,0))="","",INDEX(Articles!$E$2:$E$148,MATCH(C69,Articles!$A$2:$A$148,0))) -> 3000 | J69: =IF(I69="","",F69*I69) -> 3000 | K69: =INDEX(Articles!$H$2:$H$148,MATCH(C69,Articles!$A$2:$A$148,0)) -> Fixé | L69: =INDEX(Articles!$F$2:$F$148,MATCH(C69,Articles!$A$2:$A$148,0)) -> Estimé | M69: « Didactikos langue, maths, DDM : 1 » lu comme 1 manuel par matière | N69: Oui
A70: Parascolaire | B70: Cahier d'activités Langue et communication | C70: DID-7259 | D70: =INDEX(Articles!$C$2:$C$148,MATCH(C70,Articles!$A$2:$A$148,0)) -> Cahier d’activités fongible LC C.M.1 | E70: =INDEX(Articles!$B$2:$B$148,MATCH(C70,Articles!$A$2:$A$148,0)) -> LPD | F70: 1 | G70: =IF(INDEX(Articles!$G$2:$G$148,MATCH(C70,Articles!$A$2:$A$148,0))="","",INDEX(Articles!$G$2:$G$148,MATCH(C70,Articles!$A$2:$A$148,0))) -> 3240 | H70: =IF(G70="",0,F70*G70) -> 3240 | I70: =IF(INDEX(Articles!$E$2:$E$148,MATCH(C70,Articles!$A$2:$A$148,0))="","",INDEX(Articles!$E$2:$E$148,MATCH(C70,Articles!$A$2:$A$148,0))) -> 2240 | J70: =IF(I70="","",F70*I70) -> 2240 | K70: =INDEX(Articles!$H$2:$H$148,MATCH(C70,Articles!$A$2:$A$148,0)) -> Fixé | L70: =INDEX(Articles!$F$2:$F$148,MATCH(C70,Articles!$A$2:$A$148,0)) -> Estimé | N70: Oui
A71: Parascolaire | B71: Cahier d'activités Mathématiques | C71: DID-7239 | D71: =INDEX(Articles!$C$2:$C$148,MATCH(C71,Articles!$A$2:$A$148,0)) -> Cahier d’activités mathématiques C.M.1 | E71: =INDEX(Articles!$B$2:$B$148,MATCH(C71,Articles!$A$2:$A$148,0)) -> LPD | F71: 1 | G71: =IF(INDEX(Articles!$G$2:$G$148,MATCH(C71,Articles!$A$2:$A$148,0))="","",INDEX(Articles!$G$2:$G$148,MATCH(C71,Articles!$A$2:$A$148,0))) -> 3240 | H71: =IF(G71="",0,F71*G71) -> 3240 | I71: =IF(INDEX(Articles!$E$2:$E$148,MATCH(C71,Articles!$A$2:$A$148,0))="","",INDEX(Articles!$E$2:$E$148,MATCH(C71,Articles!$A$2:$A$148,0))) -> 2240 | J71: =IF(I71="","",F71*I71) -> 2240 | K71: =INDEX(Articles!$H$2:$H$148,MATCH(C71,Articles!$A$2:$A$148,0)) -> Fixé | L71: =INDEX(Articles!$F$2:$F$148,MATCH(C71,Articles!$A$2:$A$148,0)) -> Estimé | N71: Oui
D72: Lignes sans prix de vente (à fournir) | H72: =COUNTIF(G59:G71,"") -> 0
D73: Total vente du kit (FCFA) | H73: =SUM(H59:H71) -> 27905
D74: Coût de revient connu (FCFA) | H74: =SUM(J59:J71) -> 20490
D75: Lignes sans prix d'achat | H75: =COUNTIF(I59:I71,"") -> 3
D76: Marge sur les lignes au coût connu (FCFA) | H76: =SUMPRODUCT((I59:I71<>"")*H59:H71)-H74 -> 7140
D77: Nombre de cahiers (ligne « X cahiers » dans l'app) | H77: =SUMIF(A59:A71,"Cahiers",F59:F71) -> 4
D78: Part du prix de vente reposant sur des PV estimés | H78: =IF(H73=0,0,SUMIF(K59:K71,"<>Fixé",H59:H71)/H73) -> 0.12184196
D79: Statut du coût | H79: =IF(H72>0,"Total incomplet : "&H72&" prix de vente à fournir",IF(H75>0,"Coût incomplet : "&H75&" ligne(s) sans prix d'achat","Complet")) -> Coût incomplet : 3 ligne(s) sans prix d'achat
D80: Option décochée par défaut, non comptée : | E80: =INDEX(Articles!$C$2:$C$148,MATCH("S027",Articles!$A$2:$A$148,0)) -> Cartable rigide bleu marine | H80: =INDEX(Articles!$G$2:$G$148,MATCH("S027",Articles!$A$2:$A$148,0)) -> 7500
D81: Manquants : | E81: aucun

Sheet CM2
A1: Kit CM2
A2: Liste réelle du Complexe Dar El-Hadith. Contrôle croisé avec la liste ISJA 2026-2027 (plus chargée, écoles privées).
A4: CM2 — Essentiel
A5: Groupe (app) | B5: Besoin (liste) | C5: ID | D5: Désignation | E5: Fournisseur | F5: Qté | G5: PV unit. (FCFA) | H5: Sous-total vente | I5: PA unit. (FCFA) | J5: Sous-total achat | K5: Statut vente | L5: Statut achat | M5: Remarque | N5: Coché par défaut
A6: Cahiers | B6: Cahier 96 pages | C6: SAC-048 | D6: =INDEX(Articles!$C$2:$C$148,MATCH(C6,Articles!$A$2:$A$148,0)) -> Cahier Calligraphe 96 pages 17x22 56 g seyès | E6: =INDEX(Articles!$B$2:$B$148,MATCH(C6,Articles!$A$2:$A$148,0)) -> Papex | F6: 4 | G6: =IF(INDEX(Articles!$G$2:$G$148,MATCH(C6,Articles!$A$2:$A$148,0))="","",INDEX(Articles!$G$2:$G$148,MATCH(C6,Articles!$A$2:$A$148,0))) -> 450 | H6: =IF(G6="",0,F6*G6) -> 1800 | I6: =IF(INDEX(Articles!$E$2:$E$148,MATCH(C6,Articles!$A$2:$A$148,0))="","",INDEX(Articles!$E$2:$E$148,MATCH(C6,Articles!$A$2:$A$148,0))) -> 350 | J6: =IF(I6="","",F6*I6) -> 1400 | K6: =INDEX(Articles!$H$2:$H$148,MATCH(C6,Articles!$A$2:$A$148,0)) -> Fixé | L6: =INDEX(Articles!$F$2:$F$148,MATCH(C6,Articles!$A$2:$A$148,0)) -> Confirmé | N6: Oui
A7: Géométrie | B7: Matériel géométrique | C7: SAC-007 | D7: =INDEX(Articles!$C$2:$C$148,MATCH(C7,Articles!$A$2:$A$148,0)) -> Kit de traçage 30 cm, 4 pièces L'écolier | E7: =INDEX(Articles!$B$2:$B$148,MATCH(C7,Articles!$A$2:$A$148,0)) -> Papex | F7: 1 | G7: =IF(INDEX(Articles!$G$2:$G$148,MATCH(C7,Articles!$A$2:$A$148,0))="","",INDEX(Articles!$G$2:$G$148,MATCH(C7,Articles!$A$2:$A$148,0))) -> 900 | H7: =IF(G7="",0,F7*G7) -> 900 | I7: =IF(INDEX(Articles!$E$2:$E$148,MATCH(C7,Articles!$A$2:$A$148,0))="","",INDEX(Articles!$E$2:$E$148,MATCH(C7,Articles!$A$2:$A$148,0))) -> 650 | J7: =IF(I7="","",F7*I7) -> 650 | K7: =INDEX(Articles!$H$2:$H$148,MATCH(C7,Articles!$A$2:$A$148,0)) -> Estimé | L7: =INDEX(Articles!$F$2:$F$148,MATCH(C7,Articles!$A$2:$A$148,0)) -> Confirmé | N7: Oui
A8: Ardoise | B8: Ardoise | C8: S086 | D8: =INDEX(Articles!$C$2:$C$148,MATCH(C8,Articles!$A$2:$A$148,0)) -> Ardoise scolaire | E8: =INDEX(Articles!$B$2:$B$148,MATCH(C8,Articles!$A$2:$A$148,0)) -> LPD | F8: 1 | G8: =IF(INDEX(Articles!$G$2:$G$148,MATCH(C8,Articles!$A$2:$A$148,0))="","",INDEX(Articles!$G$2:$G$148,MATCH(C8,Articles!$A$2:$A$148,0))) -> 900 | H8: =IF(G8="",0,F8*G8) -> 900 | I8: =IF(INDEX(Articles!$E$2:$E$148,MATCH(C8,Articles!$A$2:$A$148,0))="","",INDEX(Articles!$E$2:$E$148,MATCH(C8,Articles!$A$2:$A$148,0))) -> 600 | J8: =IF(I8="","",F8*I8) -> 600 | K8: =INDEX(Articles!$H$2:$H$148,MATCH(C8,Articles!$A$2:$A$148,0)) -> Fixé | L8: =INDEX(Articles!$F$2:$F$148,MATCH(C8,Articles!$A$2:$A$148,0)) -> Estimé | N8: Oui
